Workbook

Sheet 1° Encuesta Filtrada
L1: Eje economico | AD1: Eje social
A2: Marca temporal | B2: Número de Trámite DNI | C2: Año de nacimiento | D2: Año de cursado. La mayoría de las materias obligatorias que cursaste en 2024 son de: | E2: ¿Con qué identidad de género se identifica? | F2: ¿Cuál fue el último nivel educativo alcanzado por su padre o tutor? | G2: ¿Cuál fue el último nivel educativo alcanzado por su madre o tutora? | H2: Ubíquese en la pirámide en base a su ingreso total familiar aproximado | I2: ¿De dónde provienen tus ingresos? | J2: ¿Dónde vivías antes de venir a estudiar a Córdoba? | K2: , | L2: El Estado debe intervenir en el mercado laboral para reducir la brecha salarial entre hombres y mujeres | M2: puntaje | N2: Los países con Estados más “pequeños” (menor gasto público) son más exitosos y sus habitantes gozan de una mejor calidad de vida. | O2: puntaje | P2: Los ricos deben pagar relativamente más impuestos que los pobres | Q2: puntaje | R2: El país sólo puede crecer a largo plazo si reorienta sus políticas hacia una economía de mercado y libre comercio | S2: puntaje | T2: El gobierno siempre debe intervenir en el mercado cuando lo crea necesario | U2: puntaje | V2: Aquellos que puedan trabajar, y rechacen la oportunidad, no deberían esperar ayuda social | W2: puntaje | X2: El gasto público en planes y asistencia social debe reducirse a un mínimo y en su lugar debe gastarse el dinero público en planes de empleo e inversión | Y2: puntaje | Z2: La única responsabilidad social de una empresa debería ser proporcionar utilidades a sus accionistas | AA2: puntaje | AB2: Suma eje economico | AC2: Eje Econ reescalado | AD2: Altos salarios para funcionarios estatales (en los 3 poderes) son beneficiosos por disminuir las posibilidades de que estos cometan actos de corrupción | AE2: puntaje | AF2: Las medidas de restricción de la circulación y aislamiento obligatorio durante la pandemia fueron excesivas y un atropello a la libertad individual de los ciudadanos | AG2: puntaje | AH2: El movimiento feminista carece de sentido ya que actualmente mujeres y hombres se encuentran en pie de igualdad | AI2: puntaje | AJ2: El aborto, cuando no esté amenazada la vida de la madre, siempre debería ser ilegal | AK2: puntaje | AL2: El cambio climático es una problemática alarmante y a la que todos los Estados deberían prestar atención | AM2: puntaje | AN2: Los contribuyentes deberían financiar con impuestos aquellos teatros o museos que no fuesen rentables por sí mismos | AO2: puntaje | AP2: En la justicia penal la rehabilitación debería ser más importante que el castigo | AQ2: puntaje | AR2: Los extranjeros no deberían acceder a educación y salud gratuita | AS2: puntaje | AT2: El Estado no debería obligar a vacunar a los niños | AU2: puntaje | AV2: Eje social | AW2: El peronismo es el responsable de arruinar nuestro país en los últimos años | AX2: La política tradicional es responsable de la crisis económica y social del país | AY2: El FMI es partícipe del fracaso económico de los últimos años | AZ2: La falta de dólares es uno de los principales problemas de la argentina | BA2: Se puede pagar el precio de cierto grado de corrupción, siempre que se solucionen los problemas del país | BB2: Estoy dispuesto a sacrificar derechos políticos por más seguridad | BC2: Estoy dispuesto a sacrificar derechos políticos por más bienestar económico | BD2: Si me asegura 30 años de estabilidad económica y crecimiento, estoy dispuesto a sacrificar derechos políticos | BE2: La vida en los barrios cerrados ("countries") es de mejor calidad que en barrios abiertos, incluso si estos son seguros | BF2: Suponiendo un transporte público eficiente, de calidad y bajo costo, estaría dispuesto a disminuir el uso del automóvil particular | BG2: La educación secundaria privada prepara mejor a los ciudadanos que la escuela pública | BH2: ¿Con cuáles de los siguientes términos se identifica? (Puede elegir más de uno) [De derecha] | BI2: ¿Con cuáles de los siguientes términos se identifica? (Puede elegir más de uno) [De izquierda] | BJ2: ¿Con cuáles de los siguientes términos se identifica? (Puede elegir más de uno) [De centro] | BK2: ¿Con cuáles de los siguientes términos se identifica? (Puede elegir más de uno) [Progresista] | BL2: ¿Con cuáles de los siguientes términos se identifica? (Puede elegir más de uno) [Conservador] | BM2: ¿Con cuáles de los siguientes términos se identifica? (Puede elegir más de uno) [Liberal] | BN2: ¿Con cuáles de los siguientes términos se identifica? (Puede elegir más de uno) [Socialista] | BO2: ¿Con cuáles de los siguientes términos se identifica? (Puede elegir más de uno) [Del PRO] | BP2: ¿Con cuáles de los siguientes términos se identifica? (Puede elegir más de uno) [Peronista] | BQ2: ¿Con cuáles de los siguientes términos se identifica? (Puede elegir más de uno) [Kirchnerista] | BR2: ¿Con cuáles de los siguientes términos se identifica? (Puede elegir más de uno) [Libertario] | BS2: ¿Con cuáles de los siguientes términos se identifica? (Puede elegir más de uno) [Radical] | BT2: ¿Con cuáles de los siguientes términos se identifica? (Puede elegir más de uno) [Macrista] | BU2: ¿Con cuáles de los siguientes términos se identifica? (Puede elegir más de uno) [Feminista] | BV2: ¿Con cuáles de los siguientes términos se identifica? (Puede elegir más de uno) [Ecologista] | BW2: ¿Con cuáles de los siguientes términos se identifica? (Puede elegir más de uno) [Anarquista] | BX2: ¿Cómo votó para Presidente en las elecciones PASO de agosto de 2023? | BY2: ¿Cómo votó para Presidente en las elecciones generales de octubre de 2023? | BZ2: ¿Cómo votó para Presidente en el ballotage de noviembre de 2023? | CA2: ¿Cuál es tu sexo registrado al nacer?
A3: 45553.854 | B3: 00157138797 | C3: 1997 | D3: Quinto año | E3: Varón | F3: Universitario completo | G3: Universitario completo | H3: Clase Media Baja (C3): entre $850.001 mensuales y $1.350.000 mensuales | I3: Trabajo propio | J3: Ciudad de Córdoba | K3: , | L3: Levemente de Acuerdo | M3: =IF(L3="Totalmente de Acuerdo",-1,IF(L3="Muy de Acuerdo",-0.66,IF(L3="Levemente de Acuerdo",-0.33,IF(L3="Levemente en Desacuerdo",0.33,IF(L3="Muy en Desacuerdo",0.66,IF(L3="Totalmente en Desacuerdo",1,"error")))))) -> -0.33 | N3: Levemente en Desacuerdo | O3: =IF(N3="Totalmente de Acuerdo",1,IF(N3="Muy de Acuerdo",0.66,IF(N3="Levemente de Acuerdo",0.33,IF(N3="Levemente en Desacuerdo",-0.33,IF(N3="Muy en Desacuerdo",-0.66,IF(N3="Totalmente en Desacuerdo",-1,"error")))))) -> -0.33 | P3: Muy de Acuerdo | Q3: =IF(P3="Totalmente de Acuerdo",-1,IF(P3="Muy de Acuerdo",-0.66,IF(P3="Levemente de Acuerdo",-0.33,IF(P3="Levemente en Desacuerdo",0.33,IF(P3="Muy en Desacuerdo",0.66,IF(P3="Totalmente en Desacuerdo",1,"error")))))) -> -0.66 | R3: Muy de Acuerdo | S3: =IF(R3="Totalmente de Acuerdo",1,IF(R3="Muy de Acuerdo",0.66,IF(R3="Levemente de Acuerdo",0.33,IF(R3="Levemente en Desacuerdo",-0.33,IF(R3="Muy en Desacuerdo",-0.66,IF(R3="Totalmente en Desacuerdo",-1,"error")))))) -> 0.66 | T3: Levemente de Acuerdo | U3: =IF(T3="Totalmente de Acuerdo",-1,IF(T3="Muy de Acuerdo",-0.66,IF(T3="Levemente de Acuerdo",-0.33,IF(T3="Levemente en Desacuerdo",0.33,IF(T3="Muy en Desacuerdo",0.66,IF(T3="Totalmente en Desacuerdo",1,"error")))))) -> -0.33 | V3: Levemente en Desacuerdo | W3: =IF(V3="Totalmente de Acuerdo",1,IF(V3="Muy de Acuerdo",0.66,IF(V3="Levemente de Acuerdo",0.33,IF(V3="Levemente en Desacuerdo",-0.33,IF(V3="Muy en Desacuerdo",-0.66,IF(V3="Totalmente en Desacuerdo",-1,"error")))))) -> -0.33 | X3: Levemente en Desacuerdo | Y3: =IF(X3="Totalmente de Acuerdo",1,IF(X3="Muy de Acuerdo",0.66,IF(X3="Levemente de Acuerdo",0.33,IF(X3="Levemente en Desacuerdo",-0.33,IF(X3="Muy en Desacuerdo",-0.66,IF(X3="Totalmente en Desacuerdo",-1,"error")))))) -> -0.33 | Z3: Levemente en Desacuerdo | AA3: =IF(Z3="Totalmente de Acuerdo",1,IF(Z3="Muy de Acuerdo",0.66,IF(Z3="Levemente en Acuerdo",0.33,IF(Z3="Levemente en Desacuerdo",-0.33,IF(Z3="Muy en Desacuerdo",-0.66,IF(Z3="Totalmente en Desacuerdo",-1,"error")))))) -> -0.33 | AB3: =+AA3+Y3+W3+U3+S3+Q3+O3+M3 -> -1.98 | AC3: =+AB3*AB$29 -> -2.2275 | AD3: Muy de Acuerdo | AE3: =IF(AD3="Totalmente de Acuerdo",1,IF(AD3="Muy de Acuerdo",0.66,IF(AD3="Levemente de Acuerdo",0.33,IF(AD3="Levemente en Desacuerdo",-0.33,IF(AD3="Muy en Desacuerdo",-0.66,IF(AD3="Totalmente en Desacuerdo",-1,"error")))))) -> 0.66 | AF3: Levemente en Desacuerdo | AG3: =IF(AF3="Totalmente de Acuerdo",-1,IF(AF3="Muy de Acuerdo",-0.66,IF(AF3="Levemente de Acuerdo",-0.33,IF(AF3="Levemente en Desacuerdo",0.33,IF(AF3="Muy en Desacuerdo",0.66,IF(AF3="Totalmente en Desacuerdo",1,"error")))))) -> 0.33 | AH3: Totalmente en Desacuerdo | AI3: =IF(AH3="Totalmente de Acuerdo",1,IF(AH3="Muy de Acuerdo",0.66,IF(AH3="Levemente de Acuerdo",0.33,IF(AH3="Levemente en Desacuerdo",-0.33,IF(AH3="Muy en Desacuerdo",-0.66,IF(AH3="Totalmente en Desacuerdo",-1,"error")))))) -> -1 | AJ3: Totalmente en Desacuerdo | AK3: =IF(AJ3="Totalmente de Acuerdo",1,IF(AJ3="Muy de Acuerdo",0.66,IF(AJ3="Levemente de Acuerdo",0.33,IF(AJ3="Levemente en Desacuerdo",-0.33,IF(AJ3="Muy en Desacuerdo",-0.66,IF(AJ3="Totalmente en Desacuerdo",-1,"error")))))) -> -1 | AL3: Muy en Desacuerdo | AM3: =IF(AL3="Totalmente de Acuerdo",-1,IF(AL3="Muy de Acuerdo",-0.66,IF(AL3="Levemente de Acuerdo",-0.33,IF(AL3="Levemente en Desacuerdo",0.33,IF(AL3="Muy en Desacuerdo",0.66,IF(AL3="Totalmente en Desacuerdo",1,"error")))))) -> 0.66 | AN3: Levemente de Acuerdo | AO3: =IF(AN3="Totalmente de Acuerdo",-1,IF(AN3="Muy de Acuerdo",-0.66,IF(AN3="Levemente de Acuerdo",-0.33,IF(AN3="Levemente en Desacuerdo",0.33,IF(AN3="Muy en Desacuerdo",0.66,IF(AN3="Totalmente en Desacuerdo",1,"error")))))) -> -0.33 | AP3: Levemente en Desacuerdo | AQ3: =IF(AP3="Totalmente de Acuerdo",-1,IF(AP3="Muy de Acuerdo",-0.66,IF(AP3="Levemente de Acuerdo",-0.33,IF(AP3="Levemente en Desacuerdo",0.33,IF(AP3="Muy en Desacuerdo",0.66,IF(AP3="Totalmente en Desacuerdo",1,"error")))))) -> 0.33 | AR3: Levemente en Desacuerdo | AS3: =IF(AR3="Totalmente de Acuerdo",1,IF(AR3="Muy de Acuerdo",0.66,IF(AR3="Levemente de Acuerdo",0.33,IF(AR3="Levemente en Desacuerdo",-0.33,IF(AR3="Muy en Desacuerdo",-0.66,IF(AR3="Totalmente en Desacuerdo",-1,"error")))))) -> -0.33 | AT3: Totalmente en Desacuerdo | AU3: =IF(AT3="Totalmente de Acuerdo",-1,IF(AT3="Muy de Acuerdo",-0.66,IF(AT3="Levemente de Acuerdo",-0.33,IF(AT3="Levemente en Desacuerdo",0.33,IF(AT3="Muy en Desacuerdo",0.66,IF(AT3="Totalmente en Desacuerdo",1,"error")))))) -> 1 | AV3: =+AU3+AS3+AQ3+AO3+AM3+AK3+AI3+AG3+AE3 -> 0.32 | AW3: Totalmente en Desacuerdo | AX3: Levemente de Acuerdo | AY3: Levemente de Acuerdo | AZ3: Levemente de Acuerdo | BA3: Totalmente de Acuerdo | BB3: Totalmente en Desacuerdo | BC3: Muy en Desacuerdo | BD3: Levemente en Desacuerdo | BE3: Totalmente en Desacuerdo | BF3: Levemente de Acuerdo | BG3: Totalmente de Acuerdo | BM3: Me identifico | BP3: Me identifico | BX3: Sergio Massa (Unión por la Patria) | BY3: Sergio Massa (Unión por la Patria) | BZ3: Sergio Massa (Unión por la Patria)
A4: 45547.898 | B4: 00164890275 | C4: 1998 | D4: Quinto año | E4: Varón | F4: Universitario completo | G4: Universitario incompleto | H4: Clase Alta (ABC1): más de $2.850.000 mensuales | I4: Familia | J4: Otra localidad en otra Provincia | K4: , | L4: Levemente de Acuerdo | M4: =IF(L4="Totalmente de Acuerdo",-1,IF(L4="Muy de Acuerdo",-0.66,IF(L4="Levemente de Acuerdo",-0.33,IF(L4="Levemente en Desacuerdo",0.33,IF(L4="Muy en Desacuerdo",0.66,IF(L4="Totalmente en Desacuerdo",1,"error")))))) -> -0.33 | N4: Muy en Desacuerdo | O4: =IF(N4="Totalmente de Acuerdo",1,IF(N4="Muy de Acuerdo",0.66,IF(N4="Levemente de Acuerdo",0.33,IF(N4="Levemente en Desacuerdo",-0.33,IF(N4="Muy en Desacuerdo",-0.66,IF(N4="Totalmente en Desacuerdo",-1,"error")))))) -> -0.66 | P4: Totalmente de Acuerdo | Q4: =IF(P4="Totalmente de Acuerdo",-1,IF(P4="Muy de Acuerdo",-0.66,IF(P4="Levemente de Acuerdo",-0.33,IF(P4="Levemente en Desacuerdo",0.33,IF(P4="Muy en Desacuerdo",0.66,IF(P4="Totalmente en Desacuerdo",1,"error")))))) -> -1 | R4: Levemente de Acuerdo | S4: =IF(R4="Totalmente de Acuerdo",1,IF(R4="Muy de Acuerdo",0.66,IF(R4="Levemente de Acuerdo",0.33,IF(R4="Levemente en Desacuerdo",-0.33,IF(R4="Muy en Desacuerdo",-0.66,IF(R4="Totalmente en Desacuerdo",-1,"error")))))) -> 0.33 | T4: Levemente en Desacuerdo | U4: =IF(T4="Totalmente de Acuerdo",-1,IF(T4="Muy de Acuerdo",-0.66,IF(T4="Levemente de Acuerdo",-0.33,IF(T4="Levemente en Desacuerdo",0.33,IF(T4="Muy en Desacuerdo",0.66,IF(T4="Totalmente en Desacuerdo",1,"error")))))) -> 0.33 | V4: Levemente en Desacuerdo | W4: =IF(V4="Totalmente de Acuerdo",1,IF(V4="Muy de Acuerdo",0.66,IF(V4="Levemente de Acuerdo",0.33,IF(V4="Levemente en Desacuerdo",-0.33,IF(V4="Muy en Desacuerdo",-0.66,IF(V4="Totalmente en Desacuerdo",-1,"error")))))) -> -0.33 | X4: Levemente en Desacuerdo | Y4: =IF(X4="Totalmente de Acuerdo",1,IF(X4="Muy de Acuerdo",0.66,IF(X4="Levemente de Acuerdo",0.33,IF(X4="Levemente en Desacuerdo",-0.33,IF(X4="Muy en Desacuerdo",-0.66,IF(X4="Totalmente en Desacuerdo",-1,"error")))))) -> -0.33 | Z4: Muy en Desacuerdo | AA4: =IF(Z4="Totalmente de Acuerdo",1,IF(Z4="Muy de Acuerdo",0.66,IF(Z4="Levemente en Acuerdo",0.33,IF(Z4="Levemente en Desacuerdo",-0.33,IF(Z4="Muy en Desacuerdo",-0.66,IF(Z4="Totalmente en Desacuerdo",-1,"error")))))) -> -0.66 | AB4: =+AA4+Y4+W4+U4+S4+Q4+O4+M4 -> -2.65 | AC4: =+AB4*AB$29 -> -2.98125 | AD4: Levemente de Acuerdo | AE4: =IF(AD4="Totalmente de Acuerdo",1,IF(AD4="Muy de Acuerdo",0.66,IF(AD4="Levemente de Acuerdo",0.33,IF(AD4="Levemente en Desacuerdo",-0.33,IF(AD4="Muy en Desacuerdo",-0.66,IF(AD4="Totalmente en Desacuerdo",-1,"error")))))) -> 0.33 | AF4: Levemente de Acuerdo | AG4: =IF(AF4="Totalmente de Acuerdo",-1,IF(AF4="Muy de Acuerdo",-0.66,IF(AF4="Levemente de Acuerdo",-0.33,IF(AF4="Levemente en Desacuerdo",0.33,IF(AF4="Muy en Desacuerdo",0.66,IF(AF4="Totalmente en Desacuerdo",1,"error")))))) -> -0.33 | AH4: Totalmente en Desacuerdo | AI4: =IF(AH4="Totalmente de Acuerdo",1,IF(AH4="Muy de Acuerdo",0.66,IF(AH4="Levemente de Acuerdo",0.33,IF(AH4="Levemente en Desacuerdo",-0.33,IF(AH4="Muy en Desacuerdo",-0.66,IF(AH4="Totalmente en Desacuerdo",-1,"error")))))) -> -1 | AJ4: Totalmente en Desacuerdo | AK4: =IF(AJ4="Totalmente de Acuerdo",1,IF(AJ4="Muy de Acuerdo",0.66,IF(AJ4="Levemente de Acuerdo",0.33,IF(AJ4="Levemente en Desacuerdo",-0.33,IF(AJ4="Muy en Desacuerdo",-0.66,IF(AJ4="Totalmente en Desacuerdo",-1,"error")))))) -> -1 | AL4: Muy de Acuerdo | AM4: =IF(AL4="Totalmente de Acuerdo",-1,IF(AL4="Muy de Acuerdo",-0.66,IF(AL4="Levemente de Acuerdo",-0.33,IF(AL4="Levemente en Desacuerdo",0.33,IF(AL4="Muy en Desacuerdo",0.66,IF(AL4="Totalmente en Desacuerdo",1,"error")))))) -> -0.66 | AN4: Muy de Acuerdo | AO4: =IF(AN4="Totalmente de Acuerdo",-1,IF(AN4="Muy de Acuerdo",-0.66,IF(AN4="Levemente de Acuerdo",-0.33,IF(AN4="Levemente en Desacuerdo",0.33,IF(AN4="Muy en Desacuerdo",0.66,IF(AN4="Totalmente en Desacuerdo",1,"error")))))) -> -0.66 | AP4: Muy de Acuerdo | AQ4: =IF(AP4="Totalmente de Acuerdo",-1,IF(AP4="Muy de Acuerdo",-0.66,IF(AP4="Levemente de Acuerdo",-0.33,IF(AP4="Levemente en Desacuerdo",0.33,IF(AP4="Muy en Desacuerdo",0.66,IF(AP4="Totalmente en Desacuerdo",1,"error")))))) -> -0.66 | AR4: Totalmente en Desacuerdo | AS4: =IF(AR4="Totalmente de Acuerdo",1,IF(AR4="Muy de Acuerdo",0.66,IF(AR4="Levemente de Acuerdo",0.33,IF(AR4="Levemente en Desacuerdo",-0.33,IF(AR4="Muy en Desacuerdo",-0.66,IF(AR4="Totalmente en Desacuerdo",-1,"error")))))) -> -1 | AT4: Totalmente en Desacuerdo | AU4: =IF(AT4="Totalmente de Acuerdo",-1,IF(AT4="Muy de Acuerdo",-0.66,IF(AT4="Levemente de Acuerdo",-0.33,IF(AT4="Levemente en Desacuerdo",0.33,IF(AT4="Muy en Desacuerdo",0.66,IF(AT4="Totalmente en Desacuerdo",1,"error")))))) -> 1 | AV4: =+AU4+AS4+AQ4+AO4+AM4+AK4+AI4+AG4+AE4 -> -3.98 | AW4: Totalmente en Desacuerdo | AX4: Levemente de Acuerdo | AY4: Levemente de Acuerdo | AZ4: Levemente de Acuerdo | BA4: Levemente en Desacuerdo | BB4: Muy en Desacuerdo | BC4: Muy en Desacuerdo | BD4: Levemente en Desacuerdo | BE4: Levemente en Desacuerdo | BF4: Muy de Acuerdo | BG4: Levemente de Acuerdo | BJ4: Me identifico | BK4: Me identifico | BX4: Horacio Rodríguez Larreta (Juntos por el Cambio) | BY4: Sergio Massa (Unión por la Patria) | BZ4: Sergio Massa (Unión por la Patria)
A5: 45560.553 | B5: 00284397411 | C5: 1999 | D5: Cuarto año | E5: Otra | F5: Universitario completo | G5: Posgrado completo | H5: Clase Media Alta (C2): entre $1.350.001 mensuales y $2.850.000 mensuales | I5: Trabajo propio | J5: Otra localidad en otra Provincia | K5: , | L5: Muy de Acuerdo | M5: =IF(L5="Totalmente de Acuerdo",-1,IF(L5="Muy de Acuerdo",-0.66,IF(L5="Levemente de Acuerdo",-0.33,IF(L5="Levemente en Desacuerdo",0.33,IF(L5="Muy en Desacuerdo",0.66,IF(L5="Totalmente en Desacuerdo",1,"error")))))) -> -0.66 | N5: Muy en Desacuerdo | O5: =IF(N5="Totalmente de Acuerdo",1,IF(N5="Muy de Acuerdo",0.66,IF(N5="Levemente de Acuerdo",0.33,IF(N5="Levemente en Desacuerdo",-0.33,IF(N5="Muy en Desacuerdo",-0.66,IF(N5="Totalmente en Desacuerdo",-1,"error")))))) -> -0.66 | P5: Totalmente de Acuerdo | Q5: =IF(P5="Totalmente de Acuerdo",-1,IF(P5="Muy de Acuerdo",-0.66,IF(P5="Levemente de Acuerdo",-0.33,IF(P5="Levemente en Desacuerdo",0.33,IF(P5="Muy en Desacuerdo",0.66,IF(P5="Totalmente en Desacuerdo",1,"error")))))) -> -1 | R5: Totalmente en Desacuerdo | S5: =IF(R5="Totalmente de Acuerdo",1,IF(R5="Muy de Acuerdo",0.66,IF(R5="Levemente de Acuerdo",0.33,IF(R5="Levemente en Desacuerdo",-0.33,IF(R5="Muy en Desacuerdo",-0.66,IF(R5="Totalmente en Desacuerdo",-1,"error")))))) -> -1 | T5: Muy de Acuerdo | U5: =IF(T5="Totalmente de Acuerdo",-1,IF(T5="Muy de Acuerdo",-0.66,IF(T5="Levemente de Acuerdo",-0.33,IF(T5="Levemente en Desacuerdo",0.33,IF(T5="Muy en Desacuerdo",0.66,IF(T5="Totalmente en Desacuerdo",1,"error")))))) -> -0.66 | V5: Levemente de Acuerdo | W5: =IF(V5="Totalmente de Acuerdo",1,IF(V5="Muy de Acuerdo",0.66,IF(V5="Levemente de Acuerdo",0.33,IF(V5="Levemente en Desacuerdo",-0.33,IF(V5="Muy en Desacuerdo",-0.66,IF(V5="Totalmente en Desacuerdo",-1,"error")))))) -> 0.33 | X5: Levemente en Desacuerdo | Y5: =IF(X5="Totalmente de Acuerdo",1,IF(X5="Muy de Acuerdo",0.66,IF(X5="Levemente de Acuerdo",0.33,IF(X5="Levemente en Desacuerdo",-0.33,IF(X5="Muy en Desacuerdo",-0.66,IF(X5="Totalmente en Desacuerdo",-1,"error")))))) -> -0.33 | Z5: Totalmente en Desacuerdo | AA5: =IF(Z5="Totalmente de Acuerdo",1,IF(Z5="Muy de Acuerdo",0.66,IF(Z5="Levemente en Acuerdo",0.33,IF(Z5="Levemente en Desacuerdo",-0.33,IF(Z5="Muy en Desacuerdo",-0.66,IF(Z5="Totalmente en Desacuerdo",-1,"error")))))) -> -1 | AB5: =+AA5+Y5+W5+U5+S5+Q5+O5+M5 -> -4.98 | AC5: =+AB5*AB$29 -> -5.6025 | AD5: Muy en Desacuerdo | AE5: =IF(AD5="Totalmente de Acuerdo",1,IF(AD5="Muy de Acuerdo",0.66,IF(AD5="Levemente de Acuerdo",0.33,IF(AD5="Levemente en Desacuerdo",-0.33,IF(AD5="Muy en Desacuerdo",-0.66,IF(AD5="Totalmente en Desacuerdo",-1,"error")))))) -> -0.66 | AF5: Muy en Desacuerdo | AG5: =IF(AF5="Totalmente de Acuerdo",-1,IF(AF5="Muy de Acuerdo",-0.66,IF(AF5="Levemente de Acuerdo",-0.33,IF(AF5="Levemente en Desacuerdo",0.33,IF(AF5="Muy en Desacuerdo",0.66,IF(AF5="Totalmente en Desacuerdo",1,"error")))))) -> 0.66 | AH5: Totalmente en Desacuerdo | AI5: =IF(AH5="Totalmente de Acuerdo",1,IF(AH5="Muy de Acuerdo",0.66,IF(AH5="Levemente de Acuerdo",0.33,IF(AH5="Levemente en Desacuerdo",-0.33,IF(AH5="Muy en Desacuerdo",-0.66,IF(AH5="Totalmente en Desacuerdo",-1,"error")))))) -> -1 | AJ5: Totalmente en Desacuerdo | AK5: =IF(AJ5="Totalmente de Acuerdo",1,IF(AJ5="Muy de Acuerdo",0.66,IF(AJ5="Levemente de Acuerdo",0.33,IF(AJ5="Levemente en Desacuerdo",-0.33,IF(AJ5="Muy en Desacuerdo",-0.66,IF(AJ5="Totalmente en Desacuerdo",-1,"error")))))) -> -1 | AL5: Totalmente de Acuerdo | AM5: =IF(AL5="Totalmente de Acuerdo",-1,IF(AL5="Muy de Acuerdo",-0.66,IF(AL5="Levemente de Acuerdo",-0.33,IF(AL5="Levemente en Desacuerdo",0.33,IF(AL5="Muy en Desacuerdo",0.66,IF(AL5="Totalmente en Desacuerdo",1,"error")))))) -> -1 | AN5: Levemente de Acuerdo | AO5: =IF(AN5="Totalmente de Acuerdo",-1,IF(AN5="Muy de Acuerdo",-0.66,IF(AN5="Levemente de Acuerdo",-0.33,IF(AN5="Levemente en Desacuerdo",0.33,IF(AN5="Muy en Desacuerdo",0.66,IF(AN5="Totalmente en Desacuerdo",1,"error")))))) -> -0.33 | AP5: Muy de Acuerdo | AQ5: =IF(AP5="Totalmente de Acuerdo",-1,IF(AP5="Muy de Acuerdo",-0.66,IF(AP5="Levemente de Acuerdo",-0.33,IF(AP5="Levemente en Desacuerdo",0.33,IF(AP5="Muy en Desacuerdo",0.66,IF(AP5="Totalmente en Desacuerdo",1,"error")))))) -> -0.66 | AR5: Totalmente en Desacuerdo | AS5: =IF(AR5="Totalmente de Acuerdo",1,IF(AR5="Muy de Acuerdo",0.66,IF(AR5="Levemente de Acuerdo",0.33,IF(AR5="Levemente en Desacuerdo",-0.33,IF(AR5="Muy en Desacuerdo",-0.66,IF(AR5="Totalmente en Desacuerdo",-1,"error")))))) -> -1 | AT5: Levemente en Desacuerdo | AU5: =IF(AT5="Totalmente de Acuerdo",-1,IF(AT5="Muy de Acuerdo",-0.66,IF(AT5="Levemente de Acuerdo",-0.33,IF(AT5="Levemente en Desacuerdo",0.33,IF(AT5="Muy en Desacuerdo",0.66,IF(AT5="Totalmente en Desacuerdo",1,"error")))))) -> 0.33 | AV5: =+AU5+AS5+AQ5+AO5+AM5+AK5+AI5+AG5+AE5 -> -4.66 | AW5: Totalmente en Desacuerdo | AX5: Levemente en Desacuerdo | AY5: Muy de Acuerdo | AZ5: Levemente de Acuerdo | BA5: Muy en Desacuerdo | BB5: Totalmente en Desacuerdo | BC5: Totalmente en Desacuerdo | BD5: Totalmente en Desacuerdo | BE5: Totalmente en Desacuerdo | BF5: Muy de Acuerdo | BG5: Totalmente en Desacuerdo | BP5: Me identifico | BQ5: Me identifico | BU5: Me identifico | BX5: Sergio Massa (Unión por la Patria) | BY5: Sergio Massa (Unión por la Patria) | BZ5: Sergio Massa (Unión por la Patria)
A6: 45547.9 | B6: 00305830361 | C6: 2000 | D6: Cuarto año | E6: Mujer | F6: Universitario completo | G6: Posgrado completo | H6: Clase Media Alta (C2): entre $1.350.001 mensuales y $2.850.000 mensuales | I6: Trabajo propio | J6: Ciudad de Córdoba | K6: , | L6: Muy de Acuerdo | M6: =IF(L6="Totalmente de Acuerdo",-1,IF(L6="Muy de Acuerdo",-0.66,IF(L6="Levemente de Acuerdo",-0.33,IF(L6="Levemente en Desacuerdo",0.33,IF(L6="Muy en Desacuerdo",0.66,IF(L6="Totalmente en Desacuerdo",1,"error")))))) -> -0.66 | N6: Levemente en Desacuerdo | O6: =IF(N6="Totalmente de Acuerdo",1,IF(N6="Muy de Acuerdo",0.66,IF(N6="Levemente de Acuerdo",0.33,IF(N6="Levemente en Desacuerdo",-0.33,IF(N6="Muy en Desacuerdo",-0.66,IF(N6="Totalmente en Desacuerdo",-1,"error")))))) -> -0.33 | P6: Muy de Acuerdo | Q6: =IF(P6="Totalmente de Acuerdo",-1,IF(P6="Muy de Acuerdo",-0.66,IF(P6="Levemente de Acuerdo",-0.33,IF(P6="Levemente en Desacuerdo",0.33,IF(P6="Muy en Desacuerdo",0.66,IF(P6="Totalmente en Desacuerdo",1,"error")))))) -> -0.66 | R6: Muy de Acuerdo | S6: =IF(R6="Totalmente de Acuerdo",1,IF(R6="Muy de Acuerdo",0.66,IF(R6="Levemente de Acuerdo",0.33,IF(R6="Levemente en Desacuerdo",-0.33,IF(R6="Muy en Desacuerdo",-0.66,IF(R6="Totalmente en Desacuerdo",-1,"error")))))) -> 0.66 | T6: Muy en Desacuerdo | U6: =IF(T6="Totalmente de Acuerdo",-1,IF(T6="Muy de Acuerdo",-0.66,IF(T6="Levemente de Acuerdo",-0.33,IF(T6="Levemente en Desacuerdo",0.33,IF(T6="Muy en Desacuerdo",0.66,IF(T6="Totalmente en Desacuerdo",1,"error")))))) -> 0.66 | V6: Muy de Acuerdo | W6: =IF(V6="Totalmente de Acuerdo",1,IF(V6="Muy de Acuerdo",0.66,IF(V6="Levemente de Acuerdo",0.33,IF(V6="Levemente en Desacuerdo",-0.33,IF(V6="Muy en Desacuerdo",-0.66,IF(V6="Totalmente en Desacuerdo",-1,"error")))))) -> 0.66 | X6: Levemente en Desacuerdo | Y6: =IF(X6="Totalmente de Acuerdo",1,IF(X6="Muy de Acuerdo",0.66,IF(X6="Levemente de Acuerdo",0.33,IF(X6="Levemente en Desacuerdo",-0.33,IF(X6="Muy en Desacuerdo",-0.66,IF(X6="Totalmente en Desacuerdo",-1,"error")))))) -> -0.33 | Z6: Muy en Desacuerdo | AA6: =IF(Z6="Totalmente de Acuerdo",1,IF(Z6="Muy de Acuerdo",0.66,IF(Z6="Levemente en Acuerdo",0.33,IF(Z6="Levemente en Desacuerdo",-0.33,IF(Z6="Muy en Desacuerdo",-0.66,IF(Z6="Totalmente en Desacuerdo",-1,"error")))))) -> -0.66 | AB6: =+AA6+Y6+W6+U6+S6+Q6+O6+M6 -> -0.66 | AC6: =+AB6*AB$29 -> -0.7425 | AD6: Muy en Desacuerdo | AE6: =IF(AD6="Totalmente de Acuerdo",1,IF(AD6="Muy de Acuerdo",0.66,IF(AD6="Levemente de Acuerdo",0.33,IF(AD6="Levemente en Desacuerdo",-0.33,IF(AD6="Muy en Desacuerdo",-0.66,IF(AD6="Totalmente en Desacuerdo",-1,"error")))))) -> -0.66 | AF6: Muy de Acuerdo | AG6: =IF(AF6="Totalmente de Acuerdo",-1,IF(AF6="Muy de Acuerdo",-0.66,IF(AF6="Levemente de Acuerdo",-0.33,IF(AF6="Levemente en Desacuerdo",0.33,IF(AF6="Muy en Desacuerdo",0.66,IF(AF6="Totalmente en Desacuerdo",1,"error")))))) -> -0.66 | AH6: Levemente en Desacuerdo | AI6: =IF(AH6="Totalmente de Acuerdo",1,IF(AH6="Muy de Acuerdo",0.66,IF(AH6="Levemente de Acuerdo",0.33,IF(AH6="Levemente en Desacuerdo",-0.33,IF(AH6="Muy en Desacuerdo",-0.66,IF(AH6="Totalmente en Desacuerdo",-1,"error")))))) -> -0.33 | AJ6: Levemente de Acuerdo | AK6: =IF(AJ6="Totalmente de Acuerdo",1,IF(AJ6="Muy de Acuerdo",0.66,IF(AJ6="Levemente de Acuerdo",0.33,IF(AJ6="Levemente en Desacuerdo",-0.33,IF(AJ6="Muy en Desacuerdo",-0.66,IF(AJ6="Totalmente en Desacuerdo",-1,"error")))))) -> 0.33 | AL6: Totalmente de Acuerdo | AM6: =IF(AL6="Totalmente de Acuerdo",-1,IF(AL6="Muy de Acuerdo",-0.66,IF(AL6="Levemente de Acuerdo",-0.33,IF(AL6="Levemente en Desacuerdo",0.33,IF(AL6="Muy en Desacuerdo",0.66,IF(AL6="Totalmente en Desacuerdo",1,"error")))))) -> -1 | AN6: Levemente de Acuerdo | AO6: =IF(AN6="Totalmente de Acuerdo",-1,IF(AN6="Muy de Acuerdo",-0.66,IF(AN6="Levemente de Acuerdo",-0.33,IF(AN6="Levemente en Desacuerdo",0.33,IF(AN6="Muy en Desacuerdo",0.66,IF(AN6="Totalmente en Desacuerdo",1,"error")))))) -> -0.33 | AP6: Muy de Acuerdo | AQ6: =IF(AP6="Totalmente de Acuerdo",-1,IF(AP6="Muy de Acuerdo",-0.66,IF(AP6="Levemente de Acuerdo",-0.33,IF(AP6="Levemente en Desacuerdo",0.33,IF(AP6="Muy en Desacuerdo",0.66,IF(AP6="Totalmente en Desacuerdo",1,"error")))))) -> -0.66 | AR6: Totalmente de Acuerdo | AS6: =IF(AR6="Totalmente de Acuerdo",1,IF(AR6="Muy de Acuerdo",0.66,IF(AR6="Levemente de Acuerdo",0.33,IF(AR6="Levemente en Desacuerdo",-0.33,IF(AR6="Muy en Desacuerdo",-0.66,IF(AR6="Totalmente en Desacuerdo",-1,"error")))))) -> 1 | AT6: Muy en Desacuerdo | AU6: =IF(AT6="Totalmente de Acuerdo",-1,IF(AT6="Muy de Acuerdo",-0.66,IF(AT6="Levemente de Acuerdo",-0.33,IF(AT6="Levemente en Desacuerdo",0.33,IF(AT6="Muy en Desacuerdo",0.66,IF(AT6="Totalmente en Desacuerdo",1,"error")))))) -> 0.66 | AV6: =+AU6+AS6+AQ6+AO6+AM6+AK6+AI6+AG6+AE6 -> -1.65 | AW6: Levemente de Acuerdo | AX6: Levemente en Desacuerdo | AY6: Levemente en Desacuerdo | AZ6: Muy de Acuerdo | BA6: Muy de Acuerdo | BB6: Levemente de Acuerdo | BC6: Levemente de Acuerdo | BD6: Muy de Acuerdo | BE6: Muy en Desacuerdo | BF6: Totalmente de Acuerdo | BG6: Muy de Acuerdo | BJ6: Me identifico | BV6: Me identifico | BX6: Juan Schiaretti (Hacemos por Nuestro País) | BY6: Juan Schiaretti (Hacemos por Nuestro País) | BZ6: En blanco
A7: 45547.9 | B7: 00338374873 | C7: 2000 | D7: Quinto año | E7: Mujer | F7: Posgrado completo | G7: Posgrado completo | H7: Clase Alta (ABC1): más de $2.850.000 mensuales | I7: Familia | J7: Otra localidad en la Provincia de Córdoba | K7: , | L7: Levemente de Acuerdo | M7: =IF(L7="Totalmente de Acuerdo",-1,IF(L7="Muy de Acuerdo",-0.66,IF(L7="Levemente de Acuerdo",-0.33,IF(L7="Levemente en Desacuerdo",0.33,IF(L7="Muy en Desacuerdo",0.66,IF(L7="Totalmente en Desacuerdo",1,"error")))))) -> -0.33 | N7: Levemente en Desacuerdo | O7: =IF(N7="Totalmente de Acuerdo",1,IF(N7="Muy de Acuerdo",0.66,IF(N7="Levemente de Acuerdo",0.33,IF(N7="Levemente en Desacuerdo",-0.33,IF(N7="Muy en Desacuerdo",-0.66,IF(N7="Totalmente en Desacuerdo",-1,"error")))))) -> -0.33 | P7: Muy de Acuerdo | Q7: =IF(P7="Totalmente de Acuerdo",-1,IF(P7="Muy de Acuerdo",-0.66,IF(P7="Levemente de Acuerdo",-0.33,IF(P7="Levemente en Desacuerdo",0.33,IF(P7="Muy en Desacuerdo",0.66,IF(P7="Totalmente en Desacuerdo",1,"error")))))) -> -0.66 | R7: Levemente de Acuerdo | S7: =IF(R7="Totalmente de Acuerdo",1,IF(R7="Muy de Acuerdo",0.66,IF(R7="Levemente de Acuerdo",0.33,IF(R7="Levemente en Desacuerdo",-0.33,IF(R7="Muy en Desacuerdo",-0.66,IF(R7="Totalmente en Desacuerdo",-1,"error")))))) -> 0.33 | T7: Levemente de Acuerdo | U7: =IF(T7="Totalmente de Acuerdo",-1,IF(T7="Muy de Acuerdo",-0.66,IF(T7="Levemente de Acuerdo",-0.33,IF(T7="Levemente en Desacuerdo",0.33,IF(T7="Muy en Desacuerdo",0.66,IF(T7="Totalmente en Desacuerdo",1,"error")))))) -> -0.33 | V7: Muy de Acuerdo | W7: =IF(V7="Totalmente de Acuerdo",1,IF(V7="Muy de Acuerdo",0.66,IF(V7="Levemente de Acuerdo",0.33,IF(V7="Levemente en Desacuerdo",-0.33,IF(V7="Muy en Desacuerdo",-0.66,IF(V7="Totalmente en Desacuerdo",-1,"error")))))) -> 0.66 | X7: Levemente en Desacuerdo | Y7: =IF(X7="Totalmente de Acuerdo",1,IF(X7="Muy de Acuerdo",0.66,IF(X7="Levemente de Acuerdo",0.33,IF(X7="Levemente en Desacuerdo",-0.33,IF(X7="Muy en Desacuerdo",-0.66,IF(X7="Totalmente en Desacuerdo",-1,"error")))))) -> -0.33 | Z7: Levemente en Desacuerdo | AA7: =IF(Z7="Totalmente de Acuerdo",1,IF(Z7="Muy de Acuerdo",0.66,IF(Z7="Levemente en Acuerdo",0.33,IF(Z7="Levemente en Desacuerdo",-0.33,IF(Z7="Muy en Desacuerdo",-0.66,IF(Z7="Totalmente en Desacuerdo",-1,"error")))))) -> -0.33 | AB7: =+AA7+Y7+W7+U7+S7+Q7+O7+M7 -> -1.32 | AC7: =+AB7*AB$29 -> -1.485 | AD7: Levemente de Acuerdo | AE7: =IF(AD7="Totalmente de Acuerdo",1,IF(AD7="Muy de Acuerdo",0.66,IF(AD7="Levemente de Acuerdo",0.33,IF(AD7="Levemente en Desacuerdo",-0.33,IF(AD7="Muy en Desacuerdo",-0.66,IF(AD7="Totalmente en Desacuerdo",-1,"error")))))) -> 0.33 | AF7: Muy de Acuerdo | AG7: =IF(AF7="Totalmente de Acuerdo",-1,IF(AF7="Muy de Acuerdo",-0.66,IF(AF7="Levemente de Acuerdo",-0.33,IF(AF7="Levemente en Desacuerdo",0.33,IF(AF7="Muy en Desacuerdo",0.66,IF(AF7="Totalmente en Desacuerdo",1,"error")))))) -> -0.66 | AH7: Totalmente en Desacuerdo | AI7: =IF(AH7="Totalmente de Acuerdo",1,IF(AH7="Muy de Acuerdo",0.66,IF(AH7="Levemente de Acuerdo",0.33,IF(AH7="Levemente en Desacuerdo",-0.33,IF(AH7="Muy en Desacuerdo",-0.66,IF(AH7="Totalmente en Desacuerdo",-1,"error")))))) -> -1 | AJ7: Totalmente en Desacuerdo | AK7: =IF(AJ7="Totalmente de Acuerdo",1,IF(AJ7="Muy de Acuerdo",0.66,IF(AJ7="Levemente de Acuerdo",0.33,IF(AJ7="Levemente en Desacuerdo",-0.33,IF(AJ7="Muy en Desacuerdo",-0.66,IF(AJ7="Totalmente en Desacuerdo",-1,"error")))))) -> -1 | AL7: Levemente de Acuerdo | AM7: =IF(AL7="Totalmente de Acuerdo",-1,IF(AL7="Muy de Acuerdo",-0.66,IF(AL7="Levemente de Acuerdo",-0.33,IF(AL7="Levemente en Desacuerdo",0.33,IF(AL7="Muy en Desacuerdo",0.66,IF(AL7="Totalmente en Desacuerdo",1,"error")))))) -> -0.33 | AN7: Levemente en Desacuerdo | AO7: =IF(AN7="Totalmente de Acuerdo",-1,IF(AN7="Muy de Acuerdo",-0.66,IF(AN7="Levemente de Acuerdo",-0.33,IF(AN7="Levemente en Desacuerdo",0.33,IF(AN7="Muy en Desacuerdo",0.66,IF(AN7="Totalmente en Desacuerdo",1,"error")))))) -> 0.33 | AP7: Levemente de Acuerdo | AQ7: =IF(AP7="Totalmente de Acuerdo",-1,IF(AP7="Muy de Acuerdo",-0.66,IF(AP7="Levemente de Acuerdo",-0.33,IF(AP7="Levemente en Desacuerdo",0.33,IF(AP7="Muy en Desacuerdo",0.66,IF(AP7="Totalmente en Desacuerdo",1,"error")))))) -> -0.33 | AR7: Muy de Acuerdo | AS7: =IF(AR7="Totalmente de Acuerdo",1,IF(AR7="Muy de Acuerdo",0.66,IF(AR7="Levemente de Acuerdo",0.33,IF(AR7="Levemente en Desacuerdo",-0.33,IF(AR7="Muy en Desacuerdo",-0.66,IF(AR7="Totalmente en Desacuerdo",-1,"error")))))) -> 0.66 | AT7: Muy en Desacuerdo | AU7: =IF(AT7="Totalmente de Acuerdo",-1,IF(AT7="Muy de Acuerdo",-0.66,IF(AT7="Levemente de Acuerdo",-0.33,IF(AT7="Levemente en Desacuerdo",0.33,IF(AT7="Muy en Desacuerdo",0.66,IF(AT7="Totalmente en Desacuerdo",1,"error")))))) -> 0.66 | AV7: =+AU7+AS7+AQ7+AO7+AM7+AK7+AI7+AG7+AE7 -> -1.34 | AW7: Levemente de Acuerdo | AX7: Levemente de Acuerdo | AY7: Muy en Desacuerdo | AZ7: Levemente en Desacuerdo | BA7: Muy de Acuerdo | BB7: Levemente en Desacuerdo | BC7: Levemente en Desacuerdo | BD7: Levemente de Acuerdo | BE7: Muy en Desacuerdo | BF7: Muy de Acuerdo | BG7: Muy de Acuerdo | BJ7: Me identifico | BK7: Me identifico | BU7: Me identifico | BX7: No vote | BY7: Javier Milei (La Libertad Avanza) | BZ7: Javier Milei (La Libertad Avanza)
A8: 45553.88 | B8: 003420609968086 | C8: 2000 | D8: Quinto año | E8: Varón | F8: Secundario completo | G8: Terciario completo | H8: Clase Media Baja (C3): entre $850.001 mensuales y $1.350.000 mensuales | I8: Beca|Pasantia|Familia | J8: Otra localidad en la Provincia de Córdoba | K8: , | L8: Muy de Acuerdo | M8: =IF(L8="Totalmente de Acuerdo",-1,IF(L8="Muy de Acuerdo",-0.66,IF(L8="Levemente de Acuerdo",-0.33,IF(L8="Levemente en Desacuerdo",0.33,IF(L8="Muy en Desacuerdo",0.66,IF(L8="Totalmente en Desacuerdo",1,"error")))))) -> -0.66 | N8: Levemente en Desacuerdo | O8: =IF(N8="Totalmente de Acuerdo",1,IF(N8="Muy de Acuerdo",0.66,IF(N8="Levemente de Acuerdo",0.33,IF(N8="Levemente en Desacuerdo",-0.33,IF(N8="Muy en Desacuerdo",-0.66,IF(N8="Totalmente en Desacuerdo",-1,"error")))))) -> -0.33 | P8: Muy de Acuerdo | Q8: =IF(P8="Totalmente de Acuerdo",-1,IF(P8="Muy de Acuerdo",-0.66,IF(P8="Levemente de Acuerdo",-0.33,IF(P8="Levemente en Desacuerdo",0.33,IF(P8="Muy en Desacuerdo",0.66,IF(P8="Totalmente en Desacuerdo",1,"error")))))) -> -0.66 | R8: Levemente de Acuerdo | S8: =IF(R8="Totalmente de Acuerdo",1,IF(R8="Muy de Acuerdo",0.66,IF(R8="Levemente de Acuerdo",0.33,IF(R8="Levemente en Desacuerdo",-0.33,IF(R8="Muy en Desacuerdo",-0.66,IF(R8="Totalmente en Desacuerdo",-1,"error")))))) -> 0.33 | T8: Muy de Acuerdo | U8: =IF(T8="Totalmente de Acuerdo",-1,IF(T8="Muy de Acuerdo",-0.66,IF(T8="Levemente de Acuerdo",-0.33,IF(T8="Levemente en Desacuerdo",0.33,IF(T8="Muy en Desacuerdo",0.66,IF(T8="Totalmente en Desacuerdo",1,"error")))))) -> -0.66 | V8: Muy de Acuerdo | W8: =IF(V8="Totalmente de Acuerdo",1,IF(V8="Muy de Acuerdo",0.66,IF(V8="Levemente de Acuerdo",0.33,IF(V8="Levemente en Desacuerdo",-0.33,IF(V8="Muy en Desacuerdo",-0.66,IF(V8="Totalmente en Desacuerdo",-1,"error")))))) -> 0.66 | X8: Levemente en Desacuerdo | Y8: =IF(X8="Totalmente de Acuerdo",1,IF(X8="Muy de Acuerdo",0.66,IF(X8="Levemente de Acuerdo",0.33,IF(X8="Levemente en Desacuerdo",-0.33,IF(X8="Muy en Desacuerdo",-0.66,IF(X8="Totalmente en Desacuerdo",-1,"error")))))) -> -0.33 | Z8: Muy en Desacuerdo | AA8: =IF(Z8="Totalmente de Acuerdo",1,IF(Z8="Muy de Acuerdo",0.66,IF(Z8="Levemente en Acuerdo",0.33,IF(Z8="Levemente en Desacuerdo",-0.33,IF(Z8="Muy en Desacuerdo",-0.66,IF(Z8="Totalmente en Desacuerdo",-1,"error")))))) -> -0.66 | AB8: =+AA8+Y8+W8+U8+S8+Q8+O8+M8 -> -2.31 | AC8: =+AB8*AB$29 -> -2.59875 | AD8: Levemente en Desacuerdo | AE8: =IF(AD8="Totalmente de Acuerdo",1,IF(AD8="Muy de Acuerdo",0.66,IF(AD8="Levemente de Acuerdo",0.33,IF(AD8="Levemente en Desacuerdo",-0.33,IF(AD8="Muy en Desacuerdo",-0.66,IF(AD8="Totalmente en Desacuerdo",-1,"error")))))) -> -0.33 | AF8: Muy de Acuerdo | AG8: =IF(AF8="Totalmente de Acuerdo",-1,IF(AF8="Muy de Acuerdo",-0.66,IF(AF8="Levemente de Acuerdo",-0.33,IF(AF8="Levemente en Desacuerdo",0.33,IF(AF8="Muy en Desacuerdo",0.66,IF(AF8="Totalmente en Desacuerdo",1,"error")))))) -> -0.66 | AH8: Muy en Desacuerdo | AI8: =IF(AH8="Totalmente de Acuerdo",1,IF(AH8="Muy de Acuerdo",0.66,IF(AH8="Levemente de Acuerdo",0.33,IF(AH8="Levemente en Desacuerdo",-0.33,IF(AH8="Muy en Desacuerdo",-0.66,IF(AH8="Totalmente en Desacuerdo",-1,"error")))))) -> -0.66 | AJ8: Muy en Desacuerdo | AK8: =IF(AJ8="Totalmente de Acuerdo",1,IF(AJ8="Muy de Acuerdo",0.66,IF(AJ8="Levemente de Acuerdo",0.33,IF(AJ8="Levemente en Desacuerdo",-0.33,IF(AJ8="Muy en Desacuerdo",-0.66,IF(AJ8="Totalmente en Desacuerdo",-1,"error")))))) -> -0.66 | AL8: Totalmente de Acuerdo | AM8: =IF(AL8="Totalmente de Acuerdo",-1,IF(AL8="Muy de Acuerdo",-0.66,IF(AL8="Levemente de Acuerdo",-0.33,IF(AL8="Levemente en Desacuerdo",0.33,IF(AL8="Muy en Desacuerdo",0.66,IF(AL8="Totalmente en Desacuerdo",1,"error")))))) -> -1 | AN8: Muy en Desacuerdo | AO8: =IF(AN8="Totalmente de Acuerdo",-1,IF(AN8="Muy de Acuerdo",-0.66,IF(AN8="Levemente de Acuerdo",-0.33,IF(AN8="Levemente en Desacuerdo",0.33,IF(AN8="Muy en Desacuerdo",0.66,IF(AN8="Totalmente en Desacuerdo",1,"error")))))) -> 0.66 | AP8: Muy de Acuerdo | AQ8: =IF(AP8="Totalmente de Acuerdo",-1,IF(AP8="Muy de Acuerdo",-0.66,IF(AP8="Levemente de Acuerdo",-0.33,IF(AP8="Levemente en Desacuerdo",0.33,IF(AP8="Muy en Desacuerdo",0.66,IF(AP8="Totalmente en Desacuerdo",1,"error")))))) -> -0.66 | AR8: Muy de Acuerdo | AS8: =IF(AR8="Totalmente de Acuerdo",1,IF(AR8="Muy de Acuerdo",0.66,IF(AR8="Levemente de Acuerdo",0.33,IF(AR8="Levemente en Desacuerdo",-0.33,IF(AR8="Muy en Desacuerdo",-0.66,IF(AR8="Totalmente en Desacuerdo",-1,"error")))))) -> 0.66 | AT8: Muy en Desacuerdo | AU8: =IF(AT8="Totalmente de Acuerdo",-1,IF(AT8="Muy de Acuerdo",-0.66,IF(AT8="Levemente de Acuerdo",-0.33,IF(AT8="Levemente en Desacuerdo",0.33,IF(AT8="Muy en Desacuerdo",0.66,IF(AT8="Totalmente en Desacuerdo",1,"error")))))) -> 0.66 | AV8: =+AU8+AS8+AQ8+AO8+AM8+AK8+AI8+AG8+AE8 -> -1.99 | AW8: Muy de Acuerdo | AX8: Muy de Acuerdo | AY8: Muy en Desacuerdo | AZ8: Levemente en Desacuerdo | BA8: Levemente en Desacuerdo | BB8: Levemente en Desacuerdo | BC8: Levemente en Desacuerdo | BD8: Levemente en Desacuerdo | BE8: Muy de Acuerdo | BF8: Muy de Acuerdo | BG8: Muy de Acuerdo | BH8: Me identifico | BI8: Me identifico | BJ8: Me identifico | BK8: Me identifico | BL8: Me identifico | BM8: Me identifico | BN8: Me identifico | BO8: Me identifico | BP8: Me identifico | BQ8: Me identifico | BR8: Me identifico | BS8: Me identifico | BT8: Me identifico | BU8: Me identifico | BV8: Me identifico | BW8: Me identifico | BX8: No asistí | BY8: En blanco | BZ8: En blanco
A9: 45547.903 | B9: 00344474148 | C9: 1999 | D9: Tercer año | E9: Varón | F9: Terciario completo | G9: Terciario completo | H9: Clase Media Alta (C2): entre $1.350.001 mensuales y $2.850.000 mensuales | I9: Trabajo propio | J9: Otra localidad en la Provincia de Córdoba | K9: , | L9: Muy en Desacuerdo | M9: =IF(L9="Totalmente de Acuerdo",-1,IF(L9="Muy de Acuerdo",-0.66,IF(L9="Levemente de Acuerdo",-0.33,IF(L9="Levemente en Desacuerdo",0.33,IF(L9="Muy en Desacuerdo",0.66,IF(L9="Totalmente en Desacuerdo",1,"error")))))) -> 0.66 | N9: Levemente de Acuerdo | O9: =IF(N9="Totalmente de Acuerdo",1,IF(N9="Muy de Acuerdo",0.66,IF(N9="Levemente de Acuerdo",0.33,IF(N9="Levemente en Desacuerdo",-0.33,IF(N9="Muy en Desacuerdo",-0.66,IF(N9="Totalmente en Desacuerdo",-1,"error")))))) -> 0.33 | P9: Levemente en Desacuerdo | Q9: =IF(P9="Totalmente de Acuerdo",-1,IF(P9="Muy de Acuerdo",-0.66,IF(P9="Levemente de Acuerdo",-0.33,IF(P9="Levemente en Desacuerdo",0.33,IF(P9="Muy en Desacuerdo",0.66,IF(P9="Totalmente en Desacuerdo",1,"error")))))) -> 0.33 | R9: Muy de Acuerdo | S9: =IF(R9="Totalmente de Acuerdo",1,IF(R9="Muy de Acuerdo",0.66,IF(R9="Levemente de Acuerdo",0.33,IF(R9="Levemente en Desacuerdo",-0.33,IF(R9="Muy en Desacuerdo",-0.66,IF(R9="Totalmente en Desacuerdo",-1,"error")))))) -> 0.66 | T9: Levemente de Acuerdo | U9: =IF(T9="Totalmente de Acuerdo",-1,IF(T9="Muy de Acuerdo",-0.66,IF(T9="Levemente de Acuerdo",-0.33,IF(T9="Levemente en Desacuerdo",0.33,IF(T9="Muy en Desacuerdo",0.66,IF(T9="Totalmente en Desacuerdo",1,"error")))))) -> -0.33 | V9: Totalmente de Acuerdo | W9: =IF(V9="Totalmente de Acuerdo",1,IF(V9="Muy de Acuerdo",0.66,IF(V9="Levemente de Acuerdo",0.33,IF(V9="Levemente en Desacuerdo",-0.33,IF(V9="Muy en Desacuerdo",-0.66,IF(V9="Totalmente en Desacuerdo",-1,"error")))))) -> 1 | X9: Muy de Acuerdo | Y9: =IF(X9="Totalmente de Acuerdo",1,IF(X9="Muy de Acuerdo",0.66,IF(X9="Levemente de Acuerdo",0.33,IF(X9="Levemente en Desacuerdo",-0.33,IF(X9="Muy en Desacuerdo",-0.66,IF(X9="Totalmente en Desacuerdo",-1,"error")))))) -> 0.66 | Z9: Levemente en Acuerdo | AA9: =IF(Z9="Totalmente de Acuerdo",1,IF(Z9="Muy de Acuerdo",0.66,IF(Z9="Levemente en Acuerdo",0.33,IF(Z9="Levemente en Desacuerdo",-0.33,IF(Z9="Muy en Desacuerdo",-0.66,IF(Z9="Totalmente en Desacuerdo",-1,"error")))))) -> 0.33 | AB9: =+AA9+Y9+W9+U9+S9+Q9+O9+M9 -> 3.64 | AC9: =+AB9*AB$29 -> 4.095 | AD9: Totalmente en Desacuerdo | AE9: =IF(AD9="Totalmente de Acuerdo",1,IF(AD9="Muy de Acuerdo",0.66,IF(AD9="Levemente de Acuerdo",0.33,IF(AD9="Levemente en Desacuerdo",-0.33,IF(AD9="Muy en Desacuerdo",-0.66,IF(AD9="Totalmente en Desacuerdo",-1,"error")))))) -> -1 | AF9: Muy de Acuerdo | AG9: =IF(AF9="Totalmente de Acuerdo",-1,IF(AF9="Muy de Acuerdo",-0.66,IF(AF9="Levemente de Acuerdo",-0.33,IF(AF9="Levemente en Desacuerdo",0.33,IF(AF9="Muy en Desacuerdo",0.66,IF(AF9="Totalmente en Desacuerdo",1,"error")))))) -> -0.66 | AH9: Levemente de Acuerdo | AI9: =IF(AH9="Totalmente de Acuerdo",1,IF(AH9="Muy de Acuerdo",0.66,IF(AH9="Levemente de Acuerdo",0.33,IF(AH9="Levemente en Desacuerdo",-0.33,IF(AH9="Muy en Desacuerdo",-0.66,IF(AH9="Totalmente en Desacuerdo",-1,"error")))))) -> 0.33 | AJ9: Muy en Desacuerdo | AK9: =IF(AJ9="Totalmente de Acuerdo",1,IF(AJ9="Muy de Acuerdo",0.66,IF(AJ9="Levemente de Acuerdo",0.33,IF(AJ9="Levemente en Desacuerdo",-0.33,IF(AJ9="Muy en Desacuerdo",-0.66,IF(AJ9="Totalmente en Desacuerdo",-1,"error")))))) -> -0.66 | AL9: Levemente de Acuerdo | AM9: =IF(AL9="Totalmente de Acuerdo",-1,IF(AL9="Muy de Acuerdo",-0.66,IF(AL9="Levemente de Acuerdo",-0.33,IF(AL9="Levemente en Desacuerdo",0.33,IF(AL9="Muy en Desacuerdo",0.66,IF(AL9="Totalmente en Desacuerdo",1,"error")))))) -> -0.33 | AN9: Muy en Desacuerdo | AO9: =IF(AN9="Totalmente de Acuerdo",-1,IF(AN9="Muy de Acuerdo",-0.66,IF(AN9="Levemente de Acuerdo",-0.33,IF(AN9="Levemente en Desacuerdo",0.33,IF(AN9="Muy en Desacuerdo",0.66,IF(AN9="Totalmente en Desacuerdo",1,"error")))))) -> 0.66 | AP9: Levemente de Acuerdo | AQ9: =IF(AP9="Totalmente de Acuerdo",-1,IF(AP9="Muy de Acuerdo",-0.66,IF(AP9="Levemente de Acuerdo",-0.33,IF(AP9="Levemente en Desacuerdo",0.33,IF(AP9="Muy en Desacuerdo",0.66,IF(AP9="Totalmente en Desacuerdo",1,"error")))))) -> -0.33 | AR9: Totalmente de Acuerdo | AS9: =IF(AR9="Totalmente de Acuerdo",1,IF(AR9="Muy de Acuerdo",0.66,IF(AR9="Levemente de Acuerdo",0.33,IF(AR9="Levemente en Desacuerdo",-0.33,IF(AR9="Muy en Desacuerdo",-0.66,IF(AR9="Totalmente en Desacuerdo",-1,"error")))))) -> 1 | AT9: Totalmente en Desacuerdo | AU9: =IF(AT9="Totalmente de Acuerdo",-1,IF(AT9="Muy de Acuerdo",-0.66,IF(AT9="Levemente de Acuerdo",-0.33,IF(AT9="Levemente en Desacuerdo",0.33,IF(AT9="Muy en Desacuerdo",0.66,IF(AT9="Totalmente en Desacuerdo",1,"error")))))) -> 1 | AV9: =+AU9+AS9+AQ9+AO9+AM9+AK9+AI9+AG9+AE9 -> 0.01 | AW9: Levemente de Acuerdo | AX9: Muy de Acuerdo | AY9: Levemente en Desacuerdo | AZ9: Totalmente en Desacuerdo | BA9: Totalmente en Desacuerdo | BB9: Totalmente de Acuerdo | BC9: Totalmente de Acuerdo | BD9: Totalmente de Acuerdo | BE9: Levemente en Desacuerdo | BF9: Muy en Desacuerdo | BG9: Muy en Desacuerdo | BH9: Me identifico | BX9: Javier Milei (La Libertad Avanza) | BY9: En blanco | BZ9: En blanco
A10: 45547.901 | B10: 004551455698171 | C10: 2001 | D10: Cuarto año | E10: Mujer | F10: Secundario incompleto | G10: Universitario completo | H10: Clase Alta (ABC1): más de $2.850.000 mensuales | I10: Familia | J10: Otra localidad en otra Provincia | K10: , | L10: Levemente de Acuerdo | M10: =IF(L10="Totalmente de Acuerdo",-1,IF(L10="Muy de Acuerdo",-0.66,IF(L10="Levemente de Acuerdo",-0.33,IF(L10="Levemente en Desacuerdo",0.33,IF(L10="Muy en Desacuerdo",0.66,IF(L10="Totalmente en Desacuerdo",1,"error")))))) -> -0.33 | N10: Levemente de Acuerdo | O10: =IF(N10="Totalmente de Acuerdo",1,IF(N10="Muy de Acuerdo",0.66,IF(N10="Levemente de Acuerdo",0.33,IF(N10="Levemente en Desacuerdo",-0.33,IF(N10="Muy en Desacuerdo",-0.66,IF(N10="Totalmente en Desacuerdo",-1,"error")))))) -> 0.33 | P10: Levemente de Acuerdo | Q10: =IF(P10="Totalmente de Acuerdo",-1,IF(P10="Muy de Acuerdo",-0.66,IF(P10="Levemente de Acuerdo",-0.33,IF(P10="Levemente en Desacuerdo",0.33,IF(P10="Muy en Desacuerdo",0.66,IF(P10="Totalmente en Desacuerdo",1,"error")))))) -> -0.33 | R10: Levemente de Acuerdo | S10: =IF(R10="Totalmente de Acuerdo",1,IF(R10="Muy de Acuerdo",0.66,IF(R10="Levemente de Acuerdo",0.33,IF(R10="Levemente en Desacuerdo",-0.33,IF(R10="Muy en Desacuerdo",-0.66,IF(R10="Totalmente en Desacuerdo",-1,"error")))))) -> 0.33 | T10: Levemente de Acuerdo | U10: =IF(T10="Totalmente de Acuerdo",-1,IF(T10="Muy de Acuerdo",-0.66,IF(T10="Levemente de Acuerdo",-0.33,IF(T10="Levemente en Desacuerdo",0.33,IF(T10="Muy en Desacuerdo",0.66,IF(T10="Totalmente en Desacuerdo",1,"error")))))) -> -0.33 | V10: Muy de Acuerdo | W10: =IF(V10="Totalmente de Acuerdo",1,IF(V10="Muy de Acuerdo",0.66,IF(V10="Levemente de Acuerdo",0.33,IF(V10="Levemente en Desacuerdo",-0.33,IF(V10="Muy en Desacuerdo",-0.66,IF(V10="Totalmente en Desacuerdo",-1,"error")))))) -> 0.66 | X10: Levemente de Acuerdo | Y10: =IF(X10="Totalmente de Acuerdo",1,IF(X10="Muy de Acuerdo",0.66,IF(X10="Levemente de Acuerdo",0.33,IF(X10="Levemente en Desacuerdo",-0.33,IF(X10="Muy en Desacuerdo",-0.66,IF(X10="Totalmente en Desacuerdo",-1,"error")))))) -> 0.33 | Z10: Levemente en Desacuerdo | AA10: =IF(Z10="Totalmente de Acuerdo",1,IF(Z10="Muy de Acuerdo",0.66,IF(Z10="Levemente en Acuerdo",0.33,IF(Z10="Levemente en Desacuerdo",-0.33,IF(Z10="Muy en Desacuerdo",-0.66,IF(Z10="Totalmente en Desacuerdo",-1,"error")))))) -> -0.33 | AB10: =+AA10+Y10+W10+U10+S10+Q10+O10+M10 -> 0.33 | AC10: =+AB10*AB$29 -> 0.37125 | AD10: Levemente en Desacuerdo | AE10: =IF(AD10="Totalmente de Acuerdo",1,IF(AD10="Muy de Acuerdo",0.66,IF(AD10="Levemente de Acuerdo",0.33,IF(AD10="Levemente en Desacuerdo",-0.33,IF(AD10="Muy en Desacuerdo",-0.66,IF(AD10="Totalmente en Desacuerdo",-1,"error")))))) -> -0.33 | AF10: Muy de Acuerdo | AG10: =IF(AF10="Totalmente de Acuerdo",-1,IF(AF10="Muy de Acuerdo",-0.66,IF(AF10="Levemente de Acuerdo",-0.33,IF(AF10="Levemente en Desacuerdo",0.33,IF(AF10="Muy en Desacuerdo",0.66,IF(AF10="Totalmente en Desacuerdo",1,"error")))))) -> -0.66 | AH10: Levemente en Desacuerdo | AI10: =IF(AH10="Totalmente de Acuerdo",1,IF(AH10="Muy de Acuerdo",0.66,IF(AH10="Levemente de Acuerdo",0.33,IF(AH10="Levemente en Desacuerdo",-0.33,IF(AH10="Muy en Desacuerdo",-0.66,IF(AH10="Totalmente en Desacuerdo",-1,"error")))))) -> -0.33 | AJ10: Levemente en Desacuerdo | AK10: =IF(AJ10="Totalmente de Acuerdo",1,IF(AJ10="Muy de Acuerdo",0.66,IF(AJ10="Levemente de Acuerdo",0.33,IF(AJ10="Levemente en Desacuerdo",-0.33,IF(AJ10="Muy en Desacuerdo",-0.66,IF(AJ10="Totalmente en Desacuerdo",-1,"error")))))) -> -0.33 | AL10: Muy de Acuerdo | AM10: =IF(AL10="Totalmente de Acuerdo",-1,IF(AL10="Muy de Acuerdo",-0.66,IF(AL10="Levemente de Acuerdo",-0.33,IF(AL10="Levemente en Desacuerdo",0.33,IF(AL10="Muy en Desacuerdo",0.66,IF(AL10="Totalmente en Desacuerdo",1,"error")))))) -> -0.66 | AN10: Totalmente en Desacuerdo | AO10: =IF(AN10="Totalmente de Acuerdo",-1,IF(AN10="Muy de Acuerdo",-0.66,IF(AN10="Levemente de Acuerdo",-0.33,IF(AN10="Levemente en Desacuerdo",0.33,IF(AN10="Muy en Desacuerdo",0.66,IF(AN10="Totalmente en Desacuerdo",1,"error")))))) -> 1 | AP10: Levemente de Acuerdo | AQ10: =IF(AP10="Totalmente de Acuerdo",-1,IF(AP10="Muy de Acuerdo",-0.66,IF(AP10="Levemente de Acuerdo",-0.33,IF(AP10="Levemente en Desacuerdo",0.33,IF(AP10="Muy en Desacuerdo",0.66,IF(AP10="Totalmente en Desacuerdo",1,"error")))))) -> -0.33 | AR10: Muy de Acuerdo | AS10: =IF(AR10="Totalmente de Acuerdo",1,IF(AR10="Muy de Acuerdo",0.66,IF(AR10="Levemente de Acuerdo",0.33,IF(AR10="Levemente en Desacuerdo",-0.33,IF(AR10="Muy en Desacuerdo",-0.66,IF(AR10="Totalmente en Desacuerdo",-1,"error")))))) -> 0.66 | AT10: Totalmente en Desacuerdo | AU10: =IF(AT10="Totalmente de Acuerdo",-1,IF(AT10="Muy de Acuerdo",-0.66,IF(AT10="Levemente de Acuerdo",-0.33,IF(AT10="Levemente en Desacuerdo",0.33,IF(AT10="Muy en Desacuerdo",0.66,IF(AT10="Totalmente en Desacuerdo",1,"error")))))) -> 1 | AV10: =+AU10+AS10+AQ10+AO10+AM10+AK10+AI10+AG10+AE10 -> 0.02 | AW10: Muy de Acuerdo | AX10: Levemente de Acuerdo | AY10: Muy en Desacuerdo | AZ10: Muy en Desacuerdo | BA10: Totalmente en Desacuerdo | BB10: Totalmente en Desacuerdo | BC10: Totalmente en Desacuerdo | BD10: Muy en Desacuerdo | BE10: Muy de Acuerdo | BF10: Levemente en Desacuerdo | BG10: Muy de Acuerdo | BO10: Me identifico | BX10: No vote | BY10: En blanco | BZ10: En blanco
A11: 45554.363 | B11: 00506717796 | C11: 2001 | D11: Cuarto año | E11: Mujer | F11: Universitario completo | G11: Universitario completo | H11: Clase Alta (ABC1): más de $2.850.000 mensuales | I11: Familia | J11: Ciudad de Córdoba | K11: , | L11: Levemente en Desacuerdo | M11: =IF(L11="Totalmente de Acuerdo",-1,IF(L11="Muy de Acuerdo",-0.66,IF(L11="Levemente de Acuerdo",-0.33,IF(L11="Levemente en Desacuerdo",0.33,IF(L11="Muy en Desacuerdo",0.66,IF(L11="Totalmente en Desacuerdo",1,"error")))))) -> 0.33 | N11: Levemente de Acuerdo | O11: =IF(N11="Totalmente de Acuerdo",1,IF(N11="Muy de Acuerdo",0.66,IF(N11="Levemente de Acuerdo",0.33,IF(N11="Levemente en Desacuerdo",-0.33,IF(N11="Muy en Desacuerdo",-0.66,IF(N11="Totalmente en Desacuerdo",-1,"error")))))) -> 0.33 | P11: Muy de Acuerdo | Q11: =IF(P11="Totalmente de Acuerdo",-1,IF(P11="Muy de Acuerdo",-0.66,IF(P11="Levemente de Acuerdo",-0.33,IF(P11="Levemente en Desacuerdo",0.33,IF(P11="Muy en Desacuerdo",0.66,IF(P11="Totalmente en Desacuerdo",1,"error")))))) -> -0.66 | R11: Levemente de Acuerdo | S11: =IF(R11="Totalmente de Acuerdo",1,IF(R11="Muy de Acuerdo",0.66,IF(R11="Levemente de Acuerdo",0.33,IF(R11="Levemente en Desacuerdo",-0.33,IF(R11="Muy en Desacuerdo",-0.66,IF(R11="Totalmente en Desacuerdo",-1,"error")))))) -> 0.33 | T11: Levemente en Desacuerdo | U11: =IF(T11="Totalmente de Acuerdo",-1,IF(T11="Muy de Acuerdo",-0.66,IF(T11="Levemente de Acuerdo",-0.33,IF(T11="Levemente en Desacuerdo",0.33,IF(T11="Muy en Desacuerdo",0.66,IF(T11="Totalmente en Desacuerdo",1,"error")))))) -> 0.33 | V11: Levemente en Desacuerdo | W11: =IF(V11="Totalmente de Acuerdo",1,IF(V11="Muy de Acuerdo",0.66,IF(V11="Levemente de Acuerdo",0.33,IF(V11="Levemente en Desacuerdo",-0.33,IF(V11="Muy en Desacuerdo",-0.66,IF(V11="Totalmente en Desacuerdo",-1,"error")))))) -> -0.33 | X11: Muy de Acuerdo | Y11: =IF(X11="Totalmente de Acuerdo",1,IF(X11="Muy de Acuerdo",0.66,IF(X11="Levemente de Acuerdo",0.33,IF(X11="Levemente en Desacuerdo",-0.33,IF(X11="Muy en Desacuerdo",-0.66,IF(X11="Totalmente en Desacuerdo",-1,"error")))))) -> 0.66 | Z11: Muy en Desacuerdo | AA11: =IF(Z11="Totalmente de Acuerdo",1,IF(Z11="Muy de Acuerdo",0.66,IF(Z11="Levemente en Acuerdo",0.33,IF(Z11="Levemente en Desacuerdo",-0.33,IF(Z11="Muy en Desacuerdo",-0.66,IF(Z11="Totalmente en Desacuerdo",-1,"error")))))) -> -0.66 | AB11: =+AA11+Y11+W11+U11+S11+Q11+O11+M11 -> 0.33 | AC11: =+AB11*AB$29 -> 0.37125 | AD11: Levemente en Desacuerdo | AE11: =IF(AD11="Totalmente de Acuerdo",1,IF(AD11="Muy de Acuerdo",0.66,IF(AD11="Levemente de Acuerdo",0.33,IF(AD11="Levemente en Desacuerdo",-0.33,IF(AD11="Muy en Desacuerdo",-0.66,IF(AD11="Totalmente en Desacuerdo",-1,"error")))))) -> -0.33 | AF11: Muy de Acuerdo | AG11: =IF(AF11="Totalmente de Acuerdo",-1,IF(AF11="Muy de Acuerdo",-0.66,IF(AF11="Levemente de Acuerdo",-0.33,IF(AF11="Levemente en Desacuerdo",0.33,IF(AF11="Muy en Desacuerdo",0.66,IF(AF11="Totalmente en Desacuerdo",1,"error")))))) -> -0.66 | AH11: Muy en Desacuerdo | AI11: =IF(AH11="Totalmente de Acuerdo",1,IF(AH11="Muy de Acuerdo",0.66,IF(AH11="Levemente de Acuerdo",0.33,IF(AH11="Levemente en Desacuerdo",-0.33,IF(AH11="Muy en Desacuerdo",-0.66,IF(AH11="Totalmente en Desacuerdo",-1,"error")))))) -> -0.66 | AJ11: Totalmente en Desacuerdo | AK11: =IF(AJ11="Totalmente de Acuerdo",1,IF(AJ11="Muy de Acuerdo",0.66,IF(AJ11="Levemente de Acuerdo",0.33,IF(AJ11="Levemente en Desacuerdo",-0.33,IF(AJ11="Muy en Desacuerdo",-0.66,IF(AJ11="Totalmente en Desacuerdo",-1,"error")))))) -> -1 | AL11: Levemente de Acuerdo | AM11: =IF(AL11="Totalmente de Acuerdo",-1,IF(AL11="Muy de Acuerdo",-0.66,IF(AL11="Levemente de Acuerdo",-0.33,IF(AL11="Levemente en Desacuerdo",0.33,IF(AL11="Muy en Desacuerdo",0.66,IF(AL11="Totalmente en Desacuerdo",1,"error")))))) -> -0.33 | AN11: Muy en Desacuerdo | AO11: =IF(AN11="Totalmente de Acuerdo",-1,IF(AN11="Muy de Acuerdo",-0.66,IF(AN11="Levemente de Acuerdo",-0.33,IF(AN11="Levemente en Desacuerdo",0.33,IF(AN11="Muy en Desacuerdo",0.66,IF(AN11="Totalmente en Desacuerdo",1,"error")))))) -> 0.66 | AP11: Levemente de Acuerdo | AQ11: =IF(AP11="Totalmente de Acuerdo",-1,IF(AP11="Muy de Acuerdo",-0.66,IF(AP11="Levemente de Acuerdo",-0.33,IF(AP11="Levemente en Desacuerdo",0.33,IF(AP11="Muy en Desacuerdo",0.66,IF(AP11="Totalmente en Desacuerdo",1,"error")))))) -> -0.33 | AR11: Muy de Acuerdo | AS11: =IF(AR11="Totalmente de Acuerdo",1,IF(AR11="Muy de Acuerdo",0.66,IF(AR11="Levemente de Acuerdo",0.33,IF(AR11="Levemente en Desacuerdo",-0.33,IF(AR11="Muy en Desacuerdo",-0.66,IF(AR11="Totalmente en Desacuerdo",-1,"error")))))) -> 0.66 | AT11: Totalmente en Desacuerdo | AU11: =IF(AT11="Totalmente de Acuerdo",-1,IF(AT11="Muy de Acuerdo",-0.66,IF(AT11="Levemente de Acuerdo",-0.33,IF(AT11="Levemente en Desacuerdo",0.33,IF(AT11="Muy en Desacuerdo",0.66,IF(AT11="Totalmente en Desacuerdo",1,"error")))))) -> 1 | AV11: =+AU11+AS11+AQ11+AO11+AM11+AK11+AI11+AG11+AE11 -> -0.99 | AW11: Muy de Acuerdo | AX11: Levemente de Acuerdo | AY11: Totalmente en Desacuerdo | AZ11: Muy en Desacuerdo | BA11: Totalmente en Desacuerdo | BB11: Levemente de Acuerdo | BC11: Levemente en Desacuerdo | BD11: Muy de Acuerdo | BE11: Totalmente de Acuerdo | BF11: Levemente en Desacuerdo | BG11: Levemente en Desacuerdo | BH11: Me identifico | BL11: Me identifico | BM11: Me identifico | BO11: Me identifico | BR11: Me identifico | BX11: Patricia Bullrich (Juntos por el Cambio) | BY11: Javier Milei (La Libertad Avanza) | BZ11: Javier Milei (La Libertad Avanza)
A12: 45551.791 | B12: 00513759005 | C12: 2002 | D12: Cuarto año | E12: Varón | F12: Posgrado completo | G12: Posgrado completo | H12: Clase Media Alta (C2): entre $1.350.001 mensuales y $2.850.000 mensuales | I12: Familia | J12: Ciudad de Córdoba | K12: , | L12: Muy en Desacuerdo | M12: =IF(L12="Totalmente de Acuerdo",-1,IF(L12="Muy de Acuerdo",-0.66,IF(L12="Levemente de Acuerdo",-0.33,IF(L12="Levemente en Desacuerdo",0.33,IF(L12="Muy en Desacuerdo",0.66,IF(L12="Totalmente en Desacuerdo",1,"error")))))) -> 0.66 | N12: Levemente en Desacuerdo | O12: =IF(N12="Totalmente de Acuerdo",1,IF(N12="Muy de Acuerdo",0.66,IF(N12="Levemente de Acuerdo",0.33,IF(N12="Levemente en Desacuerdo",-0.33,IF(N12="Muy en Desacuerdo",-0.66,IF(N12="Totalmente en Desacuerdo",-1,"error")))))) -> -0.33 | P12: Totalmente de Acuerdo | Q12: =IF(P12="Totalmente de Acuerdo",-1,IF(P12="Muy de Acuerdo",-0.66,IF(P12="Levemente de Acuerdo",-0.33,IF(P12="Levemente en Desacuerdo",0.33,IF(P12="Muy en Desacuerdo",0.66,IF(P12="Totalmente en Desacuerdo",1,"error")))))) -> -1 | R12: Muy de Acuerdo | S12: =IF(R12="Totalmente de Acuerdo",1,IF(R12="Muy de Acuerdo",0.66,IF(R12="Levemente de Acuerdo",0.33,IF(R12="Levemente en Desacuerdo",-0.33,IF(R12="Muy en Desacuerdo",-0.66,IF(R12="Totalmente en Desacuerdo",-1,"error")))))) -> 0.66 | T12: Levemente de Acuerdo | U12: =IF(T12="Totalmente de Acuerdo",-1,IF(T12="Muy de Acuerdo",-0.66,IF(T12="Levemente de Acuerdo",-0.33,IF(T12="Levemente en Desacuerdo",0.33,IF(T12="Muy en Desacuerdo",0.66,IF(T12="Totalmente en Desacuerdo",1,"error")))))) -> -0.33 | V12: Levemente de Acuerdo | W12: =IF(V12="Totalmente de Acuerdo",1,IF(V12="Muy de Acuerdo",0.66,IF(V12="Levemente de Acuerdo",0.33,IF(V12="Levemente en Desacuerdo",-0.33,IF(V12="Muy en Desacuerdo",-0.66,IF(V12="Totalmente en Desacuerdo",-1,"error")))))) -> 0.33 | X12: Levemente en Desacuerdo | Y12: =IF(X12="Totalmente de Acuerdo",1,IF(X12="Muy de Acuerdo",0.66,IF(X12="Levemente de Acuerdo",0.33,IF(X12="Levemente en Desacuerdo",-0.33,IF(X12="Muy en Desacuerdo",-0.66,IF(X12="Totalmente en Desacuerdo",-1,"error")))))) -> -0.33 | Z12: Totalmente en Desacuerdo | AA12: =IF(Z12="Totalmente de Acuerdo",1,IF(Z12="Muy de Acuerdo",0.66,IF(Z12="Levemente en Acuerdo",0.33,IF(Z12="Levemente en Desacuerdo",-0.33,IF(Z12="Muy en Desacuerdo",-0.66,IF(Z12="Totalmente en Desacuerdo",-1,"error")))))) -> -1 | AB12: =+AA12+Y12+W12+U12+S12+Q12+O12+M12 -> -1.34 | AC12: =+AB12*AB$29 -> -1.5075 | AD12: Levemente de Acuerdo | AE12: =IF(AD12="Totalmente de Acuerdo",1,IF(AD12="Muy de Acuerdo",0.66,IF(AD12="Levemente de Acuerdo",0.33,IF(AD12="Levemente en Desacuerdo",-0.33,IF(AD12="Muy en Desacuerdo",-0.66,IF(AD12="Totalmente en Desacuerdo",-1,"error")))))) -> 0.33 | AF12: Muy de Acuerdo | AG12: =IF(AF12="Totalmente de Acuerdo",-1,IF(AF12="Muy de Acuerdo",-0.66,IF(AF12="Levemente de Acuerdo",-0.33,IF(AF12="Levemente en Desacuerdo",0.33,IF(AF12="Muy en Desacuerdo",0.66,IF(AF12="Totalmente en Desacuerdo",1,"error")))))) -> -0.66 | AH12: Muy de Acuerdo | AI12: =IF(AH12="Totalmente de Acuerdo",1,IF(AH12="Muy de Acuerdo",0.66,IF(AH12="Levemente de Acuerdo",0.33,IF(AH12="Levemente en Desacuerdo",-0.33,IF(AH12="Muy en Desacuerdo",-0.66,IF(AH12="Totalmente en Desacuerdo",-1,"error")))))) -> 0.66 | AJ12: Totalmente de Acuerdo | AK12: =IF(AJ12="Totalmente de Acuerdo",1,IF(AJ12="Muy de Acuerdo",0.66,IF(AJ12="Levemente de Acuerdo",0.33,IF(AJ12="Levemente en Desacuerdo",-0.33,IF(AJ12="Muy en Desacuerdo",-0.66,IF(AJ12="Totalmente en Desacuerdo",-1,"error")))))) -> 1 | AL12: Muy de Acuerdo | AM12: =IF(AL12="Totalmente de Acuerdo",-1,IF(AL12="Muy de Acuerdo",-0.66,IF(AL12="Levemente de Acuerdo",-0.33,IF(AL12="Levemente en Desacuerdo",0.33,IF(AL12="Muy en Desacuerdo",0.66,IF(AL12="Totalmente en Desacuerdo",1,"error")))))) -> -0.66 | AN12: Muy de Acuerdo | AO12: =IF(AN12="Totalmente de Acuerdo",-1,IF(AN12="Muy de Acuerdo",-0.66,IF(AN12="Levemente de Acuerdo",-0.33,IF(AN12="Levemente en Desacuerdo",0.33,IF(AN12="Muy en Desacuerdo",0.66,IF(AN12="Totalmente en Desacuerdo",1,"error")))))) -> -0.66 | AP12: Totalmente de Acuerdo | AQ12: =IF(AP12="Totalmente de Acuerdo",-1,IF(AP12="Muy de Acuerdo",-0.66,IF(AP12="Levemente de Acuerdo",-0.33,IF(AP12="Levemente en Desacuerdo",0.33,IF(AP12="Muy en Desacuerdo",0.66,IF(AP12="Totalmente en Desacuerdo",1,"error")))))) -> -1 | AR12: Muy de Acuerdo | AS12: =IF(AR12="Totalmente de Acuerdo",1,IF(AR12="Muy de Acuerdo",0.66,IF(AR12="Levemente de Acuerdo",0.33,IF(AR12="Levemente en Desacuerdo",-0.33,IF(AR12="Muy en Desacuerdo",-0.66,IF(AR12="Totalmente en Desacuerdo",-1,"error")))))) -> 0.66 | AT12: Muy en Desacuerdo | AU12: =IF(AT12="Totalmente de Acuerdo",-1,IF(AT12="Muy de Acuerdo",-0.66,IF(AT12="Levemente de Acuerdo",-0.33,IF(AT12="Levemente en Desacuerdo",0.33,IF(AT12="Muy en Desacuerdo",0.66,IF(AT12="Totalmente en Desacuerdo",1,"error")))))) -> 0.66 | AV12: =+AU12+AS12+AQ12+AO12+AM12+AK12+AI12+AG12+AE12 -> 0.33 | AW12: Muy de Acuerdo | AX12: Muy de Acuerdo | AY12: Levemente de Acuerdo | AZ12: Levemente de Acuerdo | BA12: Muy en Desacuerdo | BB12: Levemente de Acuerdo | BC12: Levemente de Acuerdo | BD12: Levemente de Acuerdo | BE12: Muy en Desacuerdo | BF12: Muy de Acuerdo | BG12: Muy de Acuerdo | BL12: Me identifico | BX12: Javier Milei (La Libertad Avanza) | BY12: Patricia Bullrich (Juntos por el Cambio) | BZ12: Javier Milei (La Libertad Avanza)
A13: 45554.668 | B13: 00516733809 | C13: 2002 | D13: Cuarto año | E13: Mujer | F13: Universitario incompleto | G13: Universitario incompleto | H13: Clase Media Alta (C2): entre $1.350.001 mensuales y $2.850.000 mensuales | I13: Familia | J13: Otra localidad en la Provincia de Córdoba | K13: , | L13: Muy en Desacuerdo | M13: =IF(L13="Totalmente de Acuerdo",-1,IF(L13="Muy de Acuerdo",-0.66,IF(L13="Levemente de Acuerdo",-0.33,IF(L13="Levemente en Desacuerdo",0.33,IF(L13="Muy en Desacuerdo",0.66,IF(L13="Totalmente en Desacuerdo",1,"error")))))) -> 0.66 | N13: Totalmente de Acuerdo | O13: =IF(N13="Totalmente de Acuerdo",1,IF(N13="Muy de Acuerdo",0.66,IF(N13="Levemente de Acuerdo",0.33,IF(N13="Levemente en Desacuerdo",-0.33,IF(N13="Muy en Desacuerdo",-0.66,IF(N13="Totalmente en Desacuerdo",-1,"error")))))) -> 1 | P13: Totalmente en Desacuerdo | Q13: =IF(P13="Totalmente de Acuerdo",-1,IF(P13="Muy de Acuerdo",-0.66,IF(P13="Levemente de Acuerdo",-0.33,IF(P13="Levemente en Desacuerdo",0.33,IF(P13="Muy en Desacuerdo",0.66,IF(P13="Totalmente en Desacuerdo",1,"error")))))) -> 1 | R13: Muy de Acuerdo | S13: =IF(R13="Totalmente de Acuerdo",1,IF(R13="Muy de Acuerdo",0.66,IF(R13="Levemente de Acuerdo",0.33,IF(R13="Levemente en Desacuerdo",-0.33,IF(R13="Muy en Desacuerdo",-0.66,IF(R13="Totalmente en Desacuerdo",-1,"error")))))) -> 0.66 | T13: Muy en Desacuerdo | U13: =IF(T13="Totalmente de Acuerdo",-1,IF(T13="Muy de Acuerdo",-0.66,IF(T13="Levemente de Acuerdo",-0.33,IF(T13="Levemente en Desacuerdo",0.33,IF(T13="Muy en Desacuerdo",0.66,IF(T13="Totalmente en Desacuerdo",1,"error")))))) -> 0.66 | V13: Muy en Desacuerdo | W13: =IF(V13="Totalmente de Acuerdo",1,IF(V13="Muy de Acuerdo",0.66,IF(V13="Levemente de Acuerdo",0.33,IF(V13="Levemente en Desacuerdo",-0.33,IF(V13="Muy en Desacuerdo",-0.66,IF(V13="Totalmente en Desacuerdo",-1,"error")))))) -> -0.66 | X13: Muy de Acuerdo | Y13: =IF(X13="Totalmente de Acuerdo",1,IF(X13="Muy de Acuerdo",0.66,IF(X13="Levemente de Acuerdo",0.33,IF(X13="Levemente en Desacuerdo",-0.33,IF(X13="Muy en Desacuerdo",-0.66,IF(X13="Totalmente en Desacuerdo",-1,"error")))))) -> 0.66 | Z13: Muy en Desacuerdo | AA13: =IF(Z13="Totalmente de Acuerdo",1,IF(Z13="Muy de Acuerdo",0.66,IF(Z13="Levemente en Acuerdo",0.33,IF(Z13="Levemente en Desacuerdo",-0.33,IF(Z13="Muy en Desacuerdo",-0.66,IF(Z13="Totalmente en Desacuerdo",-1,"error")))))) -> -0.66 | AB13: =+AA13+Y13+W13+U13+S13+Q13+O13+M13 -> 3.32 | AC13: =+AB13*AB$29 -> 3.735 | AD13: Muy en Desacuerdo | AE13: =IF(AD13="Totalmente de Acuerdo",1,IF(AD13="Muy de Acuerdo",0.66,IF(AD13="Levemente de Acuerdo",0.33,IF(AD13="Levemente en Desacuerdo",-0.33,IF(AD13="Muy en Desacuerdo",-0.66,IF(AD13="Totalmente en Desacuerdo",-1,"error")))))) -> -0.66 | AF13: Totalmente de Acuerdo | AG13: =IF(AF13="Totalmente de Acuerdo",-1,IF(AF13="Muy de Acuerdo",-0.66,IF(AF13="Levemente de Acuerdo",-0.33,IF(AF13="Levemente en Desacuerdo",0.33,IF(AF13="Muy en Desacuerdo",0.66,IF(AF13="Totalmente en Desacuerdo",1,"error")))))) -> -1 | AH13: Levemente de Acuerdo | AI13: =IF(AH13="Totalmente de Acuerdo",1,IF(AH13="Muy de Acuerdo",0.66,IF(AH13="Levemente de Acuerdo",0.33,IF(AH13="Levemente en Desacuerdo",-0.33,IF(AH13="Muy en Desacuerdo",-0.66,IF(AH13="Totalmente en Desacuerdo",-1,"error")))))) -> 0.33 | AJ13: Levemente de Acuerdo | AK13: =IF(AJ13="Totalmente de Acuerdo",1,IF(AJ13="Muy de Acuerdo",0.66,IF(AJ13="Levemente de Acuerdo",0.33,IF(AJ13="Levemente en Desacuerdo",-0.33,IF(AJ13="Muy en Desacuerdo",-0.66,IF(AJ13="Totalmente en Desacuerdo",-1,"error")))))) -> 0.33 | AL13: Totalmente de Acuerdo | AM13: =IF(AL13="Totalmente de Acuerdo",-1,IF(AL13="Muy de Acuerdo",-0.66,IF(AL13="Levemente de Acuerdo",-0.33,IF(AL13="Levemente en Desacuerdo",0.33,IF(AL13="Muy en Desacuerdo",0.66,IF(AL13="Totalmente en Desacuerdo",1,"error")))))) -> -1 | AN13: Totalmente en Desacuerdo | AO13: =IF(AN13="Totalmente de Acuerdo",-1,IF(AN13="Muy de Acuerdo",-0.66,IF(AN13="Levemente de Acuerdo",-0.33,IF(AN13="Levemente en Desacuerdo",0.33,IF(AN13="Muy en Desacuerdo",0.66,IF(AN13="Totalmente en Desacuerdo",1,"error")))))) -> 1 | AP13: Muy en Desacuerdo | AQ13: =IF(AP13="Totalmente de Acuerdo",-1,IF(AP13="Muy de Acuerdo",-0.66,IF(AP13="Levemente de Acuerdo",-0.33,IF(AP13="Levemente en Desacuerdo",0.33,IF(AP13="Muy en Desacuerdo",0.66,IF(AP13="Totalmente en Desacuerdo",1,"error")))))) -> 0.66 | AR13: Totalmente de Acuerdo | AS13: =IF(AR13="Totalmente de Acuerdo",1,IF(AR13="Muy de Acuerdo",0.66,IF(AR13="Levemente de Acuerdo",0.33,IF(AR13="Levemente en Desacuerdo",-0.33,IF(AR13="Muy en Desacuerdo",-0.66,IF(AR13="Totalmente en Desacuerdo",-1,"error")))))) -> 1 | AT13: Muy de Acuerdo | AU13: =IF(AT13="Totalmente de Acuerdo",-1,IF(AT13="Muy de Acuerdo",-0.66,IF(AT13="Levemente de Acuerdo",-0.33,IF(AT13="Levemente en Desacuerdo",0.33,IF(AT13="Muy en Desacuerdo",0.66,IF(AT13="Totalmente en Desacuerdo",1,"error")))))) -> -0.66 | AV13: =+AU13+AS13+AQ13+AO13+AM13+AK13+AI13+AG13+AE13 -> 0 | AW13: Muy de Acuerdo | AX13: Levemente de Acuerdo | AY13: Levemente en Desacuerdo | AZ13: Levemente en Desacuerdo | BA13: Levemente de Acuerdo | BB13: Levemente en Desacuerdo | BC13: Levemente en Desacuerdo | BD13: Muy en Desacuerdo | BE13: Muy en Desacuerdo | BF13: Muy de Acuerdo | BG13: Levemente en Desacuerdo | BH13: Me identifico | BM13: Me identifico | BR13: Me identifico | BX13: Patricia Bullrich (Juntos por el Cambio) | BY13: Javier Milei (La Libertad Avanza) | BZ13: Javier Milei (La Libertad Avanza)
A14: 45554.826 | B14: 00531671249 | C14: 2002 | D14: Tercer año | E14: Varón | F14: Terciario completo | G14: Terciario completo | H14: Clase Media Baja (C3): entre $850.001 mensuales y $1.350.000 mensuales | I14: Trabajo propio | J14: Ciudad de Córdoba | K14: , | L14: Levemente en Desacuerdo | M14: =IF(L14="Totalmente de Acuerdo",-1,IF(L14="Muy de Acuerdo",-0.66,IF(L14="Levemente de Acuerdo",-0.33,IF(L14="Levemente en Desacuerdo",0.33,IF(L14="Muy en Desacuerdo",0.66,IF(L14="Totalmente en Desacuerdo",1,"error")))))) -> 0.33 | N14: Levemente en Desacuerdo | O14: =IF(N14="Totalmente de Acuerdo",1,IF(N14="Muy de Acuerdo",0.66,IF(N14="Levemente de Acuerdo",0.33,IF(N14="Levemente en Desacuerdo",-0.33,IF(N14="Muy en Desacuerdo",-0.66,IF(N14="Totalmente en Desacuerdo",-1,"error")))))) -> -0.33 | P14: Totalmente de Acuerdo | Q14: =IF(P14="Totalmente de Acuerdo",-1,IF(P14="Muy de Acuerdo",-0.66,IF(P14="Levemente de Acuerdo",-0.33,IF(P14="Levemente en Desacuerdo",0.33,IF(P14="Muy en Desacuerdo",0.66,IF(P14="Totalmente en Desacuerdo",1,"error")))))) -> -1 | R14: Muy de Acuerdo | S14: =IF(R14="Totalmente de Acuerdo",1,IF(R14="Muy de Acuerdo",0.66,IF(R14="Levemente de Acuerdo",0.33,IF(R14="Levemente en Desacuerdo",-0.33,IF(R14="Muy en Desacuerdo",-0.66,IF(R14="Totalmente en Desacuerdo",-1,"error")))))) -> 0.66 | T14: Levemente en Desacuerdo | U14: =IF(T14="Totalmente de Acuerdo",-1,IF(T14="Muy de Acuerdo",-0.66,IF(T14="Levemente de Acuerdo",-0.33,IF(T14="Levemente en Desacuerdo",0.33,IF(T14="Muy en Desacuerdo",0.66,IF(T14="Totalmente en Desacuerdo",1,"error")))))) -> 0.33 | V14: Levemente en Desacuerdo | W14: =IF(V14="Totalmente de Acuerdo",1,IF(V14="Muy de Acuerdo",0.66,IF(V14="Levemente de Acuerdo",0.33,IF(V14="Levemente en Desacuerdo",-0.33,IF(V14="Muy en Desacuerdo",-0.66,IF(V14="Totalmente en Desacuerdo",-1,"error")))))) -> -0.33 | X14: Levemente de Acuerdo | Y14: =IF(X14="Totalmente de Acuerdo",1,IF(X14="Muy de Acuerdo",0.66,IF(X14="Levemente de Acuerdo",0.33,IF(X14="Levemente en Desacuerdo",-0.33,IF(X14="Muy en Desacuerdo",-0.66,IF(X14="Totalmente en Desacuerdo",-1,"error")))))) -> 0.33 | Z14: Muy en Desacuerdo | AA14: =IF(Z14="Totalmente de Acuerdo",1,IF(Z14="Muy de Acuerdo",0.66,IF(Z14="Levemente en Acuerdo",0.33,IF(Z14="Levemente en Desacuerdo",-0.33,IF(Z14="Muy en Desacuerdo",-0.66,IF(Z14="Totalmente en Desacuerdo",-1,"error")))))) -> -0.66 | AB14: =+AA14+Y14+W14+U14+S14+Q14+O14+M14 -> -0.67 | AC14: =+AB14*AB$29 -> -0.75375 | AD14: Levemente de Acuerdo | AE14: =IF(AD14="Totalmente de Acuerdo",1,IF(AD14="Muy de Acuerdo",0.66,IF(AD14="Levemente de Acuerdo",0.33,IF(AD14="Levemente en Desacuerdo",-0.33,IF(AD14="Muy en Desacuerdo",-0.66,IF(AD14="Totalmente en Desacuerdo",-1,"error")))))) -> 0.33 | AF14: Muy de Acuerdo | AG14: =IF(AF14="Totalmente de Acuerdo",-1,IF(AF14="Muy de Acuerdo",-0.66,IF(AF14="Levemente de Acuerdo",-0.33,IF(AF14="Levemente en Desacuerdo",0.33,IF(AF14="Muy en Desacuerdo",0.66,IF(AF14="Totalmente en Desacuerdo",1,"error")))))) -> -0.66 | AH14: Totalmente en Desacuerdo | AI14: =IF(AH14="Totalmente de Acuerdo",1,IF(AH14="Muy de Acuerdo",0.66,IF(AH14="Levemente de Acuerdo",0.33,IF(AH14="Levemente en Desacuerdo",-0.33,IF(AH14="Muy en Desacuerdo",-0.66,IF(AH14="Totalmente en Desacuerdo",-1,"error")))))) -> -1 | AJ14: Totalmente en Desacuerdo | AK14: =IF(AJ14="Totalmente de Acuerdo",1,IF(AJ14="Muy de Acuerdo",0.66,IF(AJ14="Levemente de Acuerdo",0.33,IF(AJ14="Levemente en Desacuerdo",-0.33,IF(AJ14="Muy en Desacuerdo",-0.66,IF(AJ14="Totalmente en Desacuerdo",-1,"error")))))) -> -1 | AL14: Levemente en Desacuerdo | AM14: =IF(AL14="Totalmente de Acuerdo",-1,IF(AL14="Muy de Acuerdo",-0.66,IF(AL14="Levemente de Acuerdo",-0.33,IF(AL14="Levemente en Desacuerdo",0.33,IF(AL14="Muy en Desacuerdo",0.66,IF(AL14="Totalmente en Desacuerdo",1,"error")))))) -> 0.33 | AN14: Levemente en Desacuerdo | AO14: =IF(AN14="Totalmente de Acuerdo",-1,IF(AN14="Muy de Acuerdo",-0.66,IF(AN14="Levemente de Acuerdo",-0.33,IF(AN14="Levemente en Desacuerdo",0.33,IF(AN14="Muy en Desacuerdo",0.66,IF(AN14="Totalmente en Desacuerdo",1,"error")))))) -> 0.33 | AP14: Levemente de Acuerdo | AQ14: =IF(AP14="Totalmente de Acuerdo",-1,IF(AP14="Muy de Acuerdo",-0.66,IF(AP14="Levemente de Acuerdo",-0.33,IF(AP14="Levemente en Desacuerdo",0.33,IF(AP14="Muy en Desacuerdo",0.66,IF(AP14="Totalmente en Desacuerdo",1,"error")))))) -> -0.33 | AR14: Levemente en Desacuerdo | AS14: =IF(AR14="Totalmente de Acuerdo",1,IF(AR14="Muy de Acuerdo",0.66,IF(AR14="Levemente de Acuerdo",0.33,IF(AR14="Levemente en Desacuerdo",-0.33,IF(AR14="Muy en Desacuerdo",-0.66,IF(AR14="Totalmente en Desacuerdo",-1,"error")))))) -> -0.33 | AT14: Totalmente en Desacuerdo | AU14: =IF(AT14="Totalmente de Acuerdo",-1,IF(AT14="Muy de Acuerdo",-0.66,IF(AT14="Levemente de Acuerdo",-0.33,IF(AT14="Levemente en Desacuerdo",0.33,IF(AT14="Muy en Desacuerdo",0.66,IF(AT14="Totalmente en Desacuerdo",1,"error")))))) -> 1 | AV14: =+AU14+AS14+AQ14+AO14+AM14+AK14+AI14+AG14+AE14 -> -1.33 | AW14: Muy de Acuerdo | AX14: Muy de Acuerdo | AY14: Levemente en Desacuerdo | AZ14: Levemente en Desacuerdo | BA14: Totalmente en Desacuerdo | BB14: Levemente en Desacuerdo | BC14: Muy en Desacuerdo | BD14: Levemente en Desacuerdo | BE14: Muy en Desacuerdo | BF14: Muy de Acuerdo | BG14: Levemente de Acuerdo | BK14: Me identifico | BM14: Me identifico | BX14: Patricia Bullrich (Juntos por el Cambio) | BY14: Patricia Bullrich (Juntos por el Cambio) | BZ14: Javier Milei (La Libertad Avanza)
A15: 45547.9 | B15: 00544287188 | C15: 2003 | D15: Cuarto año | E15: Varón | F15: NS/NC | G15: Terciario completo | H15: Clase Baja Superior (D1): entre $773.501 y $850.000 mensuales | I15: Familia | J15: Otra localidad en la Provincia de Córdoba | K15: , | L15: Levemente de Acuerdo | M15: =IF(L15="Totalmente de Acuerdo",-1,IF(L15="Muy de Acuerdo",-0.66,IF(L15="Levemente de Acuerdo",-0.33,IF(L15="Levemente en Desacuerdo",0.33,IF(L15="Muy en Desacuerdo",0.66,IF(L15="Totalmente en Desacuerdo",1,"error")))))) -> -0.33 | N15: Levemente de Acuerdo | O15: =IF(N15="Totalmente de Acuerdo",1,IF(N15="Muy de Acuerdo",0.66,IF(N15="Levemente de Acuerdo",0.33,IF(N15="Levemente en Desacuerdo",-0.33,IF(N15="Muy en Desacuerdo",-0.66,IF(N15="Totalmente en Desacuerdo",-1,"error")))))) -> 0.33 | P15: Muy de Acuerdo | Q15: =IF(P15="Totalmente de Acuerdo",-1,IF(P15="Muy de Acuerdo",-0.66,IF(P15="Levemente de Acuerdo",-0.33,IF(P15="Levemente en Desacuerdo",0.33,IF(P15="Muy en Desacuerdo",0.66,IF(P15="Totalmente en Desacuerdo",1,"error")))))) -> -0.66 | R15: Levemente de Acuerdo | S15: =IF(R15="Totalmente de Acuerdo",1,IF(R15="Muy de Acuerdo",0.66,IF(R15="Levemente de Acuerdo",0.33,IF(R15="Levemente en Desacuerdo",-0.33,IF(R15="Muy en Desacuerdo",-0.66,IF(R15="Totalmente en Desacuerdo",-1,"error")))))) -> 0.33 | T15: Levemente de Acuerdo | U15: =IF(T15="Totalmente de Acuerdo",-1,IF(T15="Muy de Acuerdo",-0.66,IF(T15="Levemente de Acuerdo",-0.33,IF(T15="Levemente en Desacuerdo",0.33,IF(T15="Muy en Desacuerdo",0.66,IF(T15="Totalmente en Desacuerdo",1,"error")))))) -> -0.33 | V15: Totalmente de Acuerdo | W15: =IF(V15="Totalmente de Acuerdo",1,IF(V15="Muy de Acuerdo",0.66,IF(V15="Levemente de Acuerdo",0.33,IF(V15="Levemente en Desacuerdo",-0.33,IF(V15="Muy en Desacuerdo",-0.66,IF(V15="Totalmente en Desacuerdo",-1,"error")))))) -> 1 | X15: Levemente de Acuerdo | Y15: =IF(X15="Totalmente de Acuerdo",1,IF(X15="Muy de Acuerdo",0.66,IF(X15="Levemente de Acuerdo",0.33,IF(X15="Levemente en Desacuerdo",-0.33,IF(X15="Muy en Desacuerdo",-0.66,IF(X15="Totalmente en Desacuerdo",-1,"error")))))) -> 0.33 | Z15: Muy en Desacuerdo | AA15: =IF(Z15="Totalmente de Acuerdo",1,IF(Z15="Muy de Acuerdo",0.66,IF(Z15="Levemente en Acuerdo",0.33,IF(Z15="Levemente en Desacuerdo",-0.33,IF(Z15="Muy en Desacuerdo",-0.66,IF(Z15="Totalmente en Desacuerdo",-1,"error")))))) -> -0.66 | AB15: =+AA15+Y15+W15+U15+S15+Q15+O15+M15 -> 0.01 | AC15: =+AB15*AB$29 -> 0.01125 | AD15: Muy en Desacuerdo | AE15: =IF(AD15="Totalmente de Acuerdo",1,IF(AD15="Muy de Acuerdo",0.66,IF(AD15="Levemente de Acuerdo",0.33,IF(AD15="Levemente en Desacuerdo",-0.33,IF(AD15="Muy en Desacuerdo",-0.66,IF(AD15="Totalmente en Desacuerdo",-1,"error")))))) -> -0.66 | AF15: Muy de Acuerdo | AG15: =IF(AF15="Totalmente de Acuerdo",-1,IF(AF15="Muy de Acuerdo",-0.66,IF(AF15="Levemente de Acuerdo",-0.33,IF(AF15="Levemente en Desacuerdo",0.33,IF(AF15="Muy en Desacuerdo",0.66,IF(AF15="Totalmente en Desacuerdo",1,"error")))))) -> -0.66 | AH15: Levemente de Acuerdo | AI15: =IF(AH15="Totalmente de Acuerdo",1,IF(AH15="Muy de Acuerdo",0.66,IF(AH15="Levemente de Acuerdo",0.33,IF(AH15="Levemente en Desacuerdo",-0.33,IF(AH15="Muy en Desacuerdo",-0.66,IF(AH15="Totalmente en Desacuerdo",-1,"error")))))) -> 0.33 | AJ15: Totalmente en Desacuerdo | AK15: =IF(AJ15="Totalmente de Acuerdo",1,IF(AJ15="Muy de Acuerdo",0.66,IF(AJ15="Levemente de Acuerdo",0.33,IF(AJ15="Levemente en Desacuerdo",-0.33,IF(AJ15="Muy en Desacuerdo",-0.66,IF(AJ15="Totalmente en Desacuerdo",-1,"error")))))) -> -1 | AL15: Totalmente de Acuerdo | AM15: =IF(AL15="Totalmente de Acuerdo",-1,IF(AL15="Muy de Acuerdo",-0.66,IF(AL15="Levemente de Acuerdo",-0.33,IF(AL15="Levemente en Desacuerdo",0.33,IF(AL15="Muy en Desacuerdo",0.66,IF(AL15="Totalmente en Desacuerdo",1,"error")))))) -> -1 | AN15: Muy en Desacuerdo | AO15: =IF(AN15="Totalmente de Acuerdo",-1,IF(AN15="Muy de Acuerdo",-0.66,IF(AN15="Levemente de Acuerdo",-0.33,IF(AN15="Levemente en Desacuerdo",0.33,IF(AN15="Muy en Desacuerdo",0.66,IF(AN15="Totalmente en Desacuerdo",1,"error")))))) -> 0.66 | AP15: Muy de Acuerdo | AQ15: =IF(AP15="Totalmente de Acuerdo",-1,IF(AP15="Muy de Acuerdo",-0.66,IF(AP15="Levemente de Acuerdo",-0.33,IF(AP15="Levemente en Desacuerdo",0.33,IF(AP15="Muy en Desacuerdo",0.66,IF(AP15="Totalmente en Desacuerdo",1,"error")))))) -> -0.66 | AR15: Muy en Desacuerdo | AS15: =IF(AR15="Totalmente de Acuerdo",1,IF(AR15="Muy de Acuerdo",0.66,IF(AR15="Levemente de Acuerdo",0.33,IF(AR15="Levemente en Desacuerdo",-0.33,IF(AR15="Muy en Desacuerdo",-0.66,IF(AR15="Totalmente en Desacuerdo",-1,"error")))))) -> -0.66 | AT15: Totalmente en Desacuerdo | AU15: =IF(AT15="Totalmente de Acuerdo",-1,IF(AT15="Muy de Acuerdo",-0.66,IF(AT15="Levemente de Acuerdo",-0.33,IF(AT15="Levemente en Desacuerdo",0.33,IF(AT15="Muy en Desacuerdo",0.66,IF(AT15="Totalmente en Desacuerdo",1,"error")))))) -> 1 | AV15: =+AU15+AS15+AQ15+AO15+AM15+AK15+AI15+AG15+AE15 -> -2.65 | AW15: Totalmente de Acuerdo | AX15: Levemente en Desacuerdo | AY15: Levemente de Acuerdo | AZ15: Muy de Acuerdo | BA15: Levemente de Acuerdo | BB15: Muy de Acuerdo | BC15: Muy de Acuerdo | BD15: Muy de Acuerdo | BE15: Muy de Acuerdo | BF15: Levemente en Desacuerdo | BG15: Muy en Desacuerdo | BH15: Me identifico | BJ15: Me identifico | BK15: Me identifico | BM15: Me identifico | BR15: Me identifico | BX15: Patricia Bullrich (Juntos por el Cambio) | BY15: Javier Milei (La Libertad Avanza) | BZ15: Javier Milei (La Libertad Avanza)
A16: 45549.732 | B16: 00546419857 | C16: 2002 | D16: Cuarto año | E16: Varón | F16: Universitario completo | G16: Universitario completo | H16: Clase Alta (ABC1): más de $2.850.000 mensuales | I16: Familia | J16: Ciudad de Córdoba | K16: , | L16: Totalmente en Desacuerdo | M16: =IF(L16="Totalmente de Acuerdo",-1,IF(L16="Muy de Acuerdo",-0.66,IF(L16="Levemente de Acuerdo",-0.33,IF(L16="Levemente en Desacuerdo",0.33,IF(L16="Muy en Desacuerdo",0.66,IF(L16="Totalmente en Desacuerdo",1,"error")))))) -> 1 | N16: Levemente de Acuerdo | O16: =IF(N16="Totalmente de Acuerdo",1,IF(N16="Muy de Acuerdo",0.66,IF(N16="Levemente de Acuerdo",0.33,IF(N16="Levemente en Desacuerdo",-0.33,IF(N16="Muy en Desacuerdo",-0.66,IF(N16="Totalmente en Desacuerdo",-1,"error")))))) -> 0.33 | P16: Muy de Acuerdo | Q16: =IF(P16="Totalmente de Acuerdo",-1,IF(P16="Muy de Acuerdo",-0.66,IF(P16="Levemente de Acuerdo",-0.33,IF(P16="Levemente en Desacuerdo",0.33,IF(P16="Muy en Desacuerdo",0.66,IF(P16="Totalmente en Desacuerdo",1,"error")))))) -> -0.66 | R16: Muy de Acuerdo | S16: =IF(R16="Totalmente de Acuerdo",1,IF(R16="Muy de Acuerdo",0.66,IF(R16="Levemente de Acuerdo",0.33,IF(R16="Levemente en Desacuerdo",-0.33,IF(R16="Muy en Desacuerdo",-0.66,IF(R16="Totalmente en Desacuerdo",-1,"error")))))) -> 0.66 | T16: Levemente en Desacuerdo | U16: =IF(T16="Totalmente de Acuerdo",-1,IF(T16="Muy de Acuerdo",-0.66,IF(T16="Levemente de Acuerdo",-0.33,IF(T16="Levemente en Desacuerdo",0.33,IF(T16="Muy en Desacuerdo",0.66,IF(T16="Totalmente en Desacuerdo",1,"error")))))) -> 0.33 | V16: Muy de Acuerdo | W16: =IF(V16="Totalmente de Acuerdo",1,IF(V16="Muy de Acuerdo",0.66,IF(V16="Levemente de Acuerdo",0.33,IF(V16="Levemente en Desacuerdo",-0.33,IF(V16="Muy en Desacuerdo",-0.66,IF(V16="Totalmente en Desacuerdo",-1,"error")))))) -> 0.66 | X16: Totalmente de Acuerdo | Y16: =IF(X16="Totalmente de Acuerdo",1,IF(X16="Muy de Acuerdo",0.66,IF(X16="Levemente de Acuerdo",0.33,IF(X16="Levemente en Desacuerdo",-0.33,IF(X16="Muy en Desacuerdo",-0.66,IF(X16="Totalmente en Desacuerdo",-1,"error")))))) -> 1 | Z16: Totalmente de Acuerdo | AA16: =IF(Z16="Totalmente de Acuerdo",1,IF(Z16="Muy de Acuerdo",0.66,IF(Z16="Levemente en Acuerdo",0.33,IF(Z16="Levemente en Desacuerdo",-0.33,IF(Z16="Muy en Desacuerdo",-0.66,IF(Z16="Totalmente en Desacuerdo",-1,"error")))))) -> 1 | AB16: =+AA16+Y16+W16+U16+S16+Q16+O16+M16 -> 4.32 | AC16: =+AB16*AB$29 -> 4.86 | AD16: Levemente en Desacuerdo | AE16: =IF(AD16="Totalmente de Acuerdo",1,IF(AD16="Muy de Acuerdo",0.66,IF(AD16="Levemente de Acuerdo",0.33,IF(AD16="Levemente en Desacuerdo",-0.33,IF(AD16="Muy en Desacuerdo",-0.66,IF(AD16="Totalmente en Desacuerdo",-1,"error")))))) -> -0.33 | AF16: Levemente en Desacuerdo | AG16: =IF(AF16="Totalmente de Acuerdo",-1,IF(AF16="Muy de Acuerdo",-0.66,IF(AF16="Levemente de Acuerdo",-0.33,IF(AF16="Levemente en Desacuerdo",0.33,IF(AF16="Muy en Desacuerdo",0.66,IF(AF16="Totalmente en Desacuerdo",1,"error")))))) -> 0.33 | AH16: Levemente en Desacuerdo | AI16: =IF(AH16="Totalmente de Acuerdo",1,IF(AH16="Muy de Acuerdo",0.66,IF(AH16="Levemente de Acuerdo",0.33,IF(AH16="Levemente en Desacuerdo",-0.33,IF(AH16="Muy en Desacuerdo",-0.66,IF(AH16="Totalmente en Desacuerdo",-1,"error")))))) -> -0.33 | AJ16: Levemente de Acuerdo | AK16: =IF(AJ16="Totalmente de Acuerdo",1,IF(AJ16="Muy de Acuerdo",0.66,IF(AJ16="Levemente de Acuerdo",0.33,IF(AJ16="Levemente en Desacuerdo",-0.33,IF(AJ16="Muy en Desacuerdo",-0.66,IF(AJ16="Totalmente en Desacuerdo",-1,"error")))))) -> 0.33 | AL16: Muy de Acuerdo | AM16: =IF(AL16="Totalmente de Acuerdo",-1,IF(AL16="Muy de Acuerdo",-0.66,IF(AL16="Levemente de Acuerdo",-0.33,IF(AL16="Levemente en Desacuerdo",0.33,IF(AL16="Muy en Desacuerdo",0.66,IF(AL16="Totalmente en Desacuerdo",1,"error")))))) -> -0.66 | AN16: Muy en Desacuerdo | AO16: =IF(AN16="Totalmente de Acuerdo",-1,IF(AN16="Muy de Acuerdo",-0.66,IF(AN16="Levemente de Acuerdo",-0.33,IF(AN16="Levemente en Desacuerdo",0.33,IF(AN16="Muy en Desacuerdo",0.66,IF(AN16="Totalmente en Desacuerdo",1,"error")))))) -> 0.66 | AP16: Totalmente de Acuerdo | AQ16: =IF(AP16="Totalmente de Acuerdo",-1,IF(AP16="Muy de Acuerdo",-0.66,IF(AP16="Levemente de Acuerdo",-0.33,IF(AP16="Levemente en Desacuerdo",0.33,IF(AP16="Muy en Desacuerdo",0.66,IF(AP16="Totalmente en Desacuerdo",1,"error")))))) -> -1 | AR16: Totalmente de Acuerdo | AS16: =IF(AR16="Totalmente de Acuerdo",1,IF(AR16="Muy de Acuerdo",0.66,IF(AR16="Levemente de Acuerdo",0.33,IF(AR16="Levemente en Desacuerdo",-0.33,IF(AR16="Muy en Desacuerdo",-0.66,IF(AR16="Totalmente en Desacuerdo",-1,"error")))))) -> 1 | AT16: Totalmente en Desacuerdo | AU16: =IF(AT16="Totalmente de Acuerdo",-1,IF(AT16="Muy de Acuerdo",-0.66,IF(AT16="Levemente de Acuerdo",-0.33,IF(AT16="Levemente en Desacuerdo",0.33,IF(AT16="Muy en Desacuerdo",0.66,IF(AT16="Totalmente en Desacuerdo",1,"error")))))) -> 1 | AV16: =+AU16+AS16+AQ16+AO16+AM16+AK16+AI16+AG16+AE16 -> 1 | AW16: Levemente de Acuerdo | AX16: Muy de Acuerdo | AY16: Muy de Acuerdo | AZ16: Muy en Desacuerdo | BA16: Muy de Acuerdo | BB16: Totalmente en Desacuerdo | BC16: Totalmente en Desacuerdo | BD16: Muy en Desacuerdo | BE16: Muy de Acuerdo | BF16: Levemente de Acuerdo | BG16: Totalmente de Acuerdo | BH16: Me identifico | BO16: Me identifico | BX16: Patricia Bullrich (Juntos por el Cambio) | BY16: Patricia Bullrich (Juntos por el Cambio) | BZ16: Javier Milei (La Libertad Avanza)
A17: 45547.901 | B17: 00576235027 | C17: 2001 | D17: Cuarto año | E17: Mujer | F17: Terciario completo | G17: Universitario incompleto | H17: Clase Media Alta (C2): entre $1.350.001 mensuales y $2.850.000 mensuales | I17: Familia | J17: Ciudad de Córdoba | K17: , | L17: Muy en Desacuerdo | M17: =IF(L17="Totalmente de Acuerdo",-1,IF(L17="Muy de Acuerdo",-0.66,IF(L17="Levemente de Acuerdo",-0.33,IF(L17="Levemente en Desacuerdo",0.33,IF(L17="Muy en Desacuerdo",0.66,IF(L17="Totalmente en Desacuerdo",1,"error")))))) -> 0.66 | N17: Levemente de Acuerdo | O17: =IF(N17="Totalmente de Acuerdo",1,IF(N17="Muy de Acuerdo",0.66,IF(N17="Levemente de Acuerdo",0.33,IF(N17="Levemente en Desacuerdo",-0.33,IF(N17="Muy en Desacuerdo",-0.66,IF(N17="Totalmente en Desacuerdo",-1,"error")))))) -> 0.33 | P17: Muy de Acuerdo | Q17: =IF(P17="Totalmente de Acuerdo",-1,IF(P17="Muy de Acuerdo",-0.66,IF(P17="Levemente de Acuerdo",-0.33,IF(P17="Levemente en Desacuerdo",0.33,IF(P17="Muy en Desacuerdo",0.66,IF(P17="Totalmente en Desacuerdo",1,"error")))))) -> -0.66 | R17: Levemente de Acuerdo | S17: =IF(R17="Totalmente de Acuerdo",1,IF(R17="Muy de Acuerdo",0.66,IF(R17="Levemente de Acuerdo",0.33,IF(R17="Levemente en Desacuerdo",-0.33,IF(R17="Muy en Desacuerdo",-0.66,IF(R17="Totalmente en Desacuerdo",-1,"error")))))) -> 0.33 | T17: Levemente de Acuerdo | U17: =IF(T17="Totalmente de Acuerdo",-1,IF(T17="Muy de Acuerdo",-0.66,IF(T17="Levemente de Acuerdo",-0.33,IF(T17="Levemente en Desacuerdo",0.33,IF(T17="Muy en Desacuerdo",0.66,IF(T17="Totalmente en Desacuerdo",1,"error")))))) -> -0.33 | V17: Levemente de Acuerdo | W17: =IF(V17="Totalmente de Acuerdo",1,IF(V17="Muy de Acuerdo",0.66,IF(V17="Levemente de Acuerdo",0.33,IF(V17="Levemente en Desacuerdo",-0.33,IF(V17="Muy en Desacuerdo",-0.66,IF(V17="Totalmente en Desacuerdo",-1,"error")))))) -> 0.33 | X17: Muy de Acuerdo | Y17: =IF(X17="Totalmente de Acuerdo",1,IF(X17="Muy de Acuerdo",0.66,IF(X17="Levemente de Acuerdo",0.33,IF(X17="Levemente en Desacuerdo",-0.33,IF(X17="Muy en Desacuerdo",-0.66,IF(X17="Totalmente en Desacuerdo",-1,"error")))))) -> 0.66 | Z17: Levemente en Acuerdo | AA17: =IF(Z17="Totalmente de Acuerdo",1,IF(Z17="Muy de Acuerdo",0.66,IF(Z17="Levemente en Acuerdo",0.33,IF(Z17="Levemente en Desacuerdo",-0.33,IF(Z17="Muy en Desacuerdo",-0.66,IF(Z17="Totalmente en Desacuerdo",-1,"error")))))) -> 0.33 | AB17: =+AA17+Y17+W17+U17+S17+Q17+O17+M17 -> 1.65 | AC17: =+AB17*AB$29 -> 1.85625 | AD17: Levemente de Acuerdo | AE17: =IF(AD17="Totalmente de Acuerdo",1,IF(AD17="Muy de Acuerdo",0.66,IF(AD17="Levemente de Acuerdo",0.33,IF(AD17="Levemente en Desacuerdo",-0.33,IF(AD17="Muy en Desacuerdo",-0.66,IF(AD17="Totalmente en Desacuerdo",-1,"error")))))) -> 0.33 | AF17: Muy de Acuerdo | AG17: =IF(AF17="Totalmente de Acuerdo",-1,IF(AF17="Muy de Acuerdo",-0.66,IF(AF17="Levemente de Acuerdo",-0.33,IF(AF17="Levemente en Desacuerdo",0.33,IF(AF17="Muy en Desacuerdo",0.66,IF(AF17="Totalmente en Desacuerdo",1,"error")))))) -> -0.66 | AH17: Muy de Acuerdo | AI17: =IF(AH17="Totalmente de Acuerdo",1,IF(AH17="Muy de Acuerdo",0.66,IF(AH17="Levemente de Acuerdo",0.33,IF(AH17="Levemente en Desacuerdo",-0.33,IF(AH17="Muy en Desacuerdo",-0.66,IF(AH17="Totalmente en Desacuerdo",-1,"error")))))) -> 0.66 | AJ17: Muy en Desacuerdo | AK17: =IF(AJ17="Totalmente de Acuerdo",1,IF(AJ17="Muy de Acuerdo",0.66,IF(AJ17="Levemente de Acuerdo",0.33,IF(AJ17="Levemente en Desacuerdo",-0.33,IF(AJ17="Muy en Desacuerdo",-0.66,IF(AJ17="Totalmente en Desacuerdo",-1,"error")))))) -> -0.66 | AL17: Levemente en Desacuerdo | AM17: =IF(AL17="Totalmente de Acuerdo",-1,IF(AL17="Muy de Acuerdo",-0.66,IF(AL17="Levemente de Acuerdo",-0.33,IF(AL17="Levemente en Desacuerdo",0.33,IF(AL17="Muy en Desacuerdo",0.66,IF(AL17="Totalmente en Desacuerdo",1,"error")))))) -> 0.33 | AN17: Totalmente en Desacuerdo | AO17: =IF(AN17="Totalmente de Acuerdo",-1,IF(AN17="Muy de Acuerdo",-0.66,IF(AN17="Levemente de Acuerdo",-0.33,IF(AN17="Levemente en Desacuerdo",0.33,IF(AN17="Muy en Desacuerdo",0.66,IF(AN17="Totalmente en Desacuerdo",1,"error")))))) -> 1 | AP17: Levemente de Acuerdo | AQ17: =IF(AP17="Totalmente de Acuerdo",-1,IF(AP17="Muy de Acuerdo",-0.66,IF(AP17="Levemente de Acuerdo",-0.33,IF(AP17="Levemente en Desacuerdo",0.33,IF(AP17="Muy en Desacuerdo",0.66,IF(AP17="Totalmente en Desacuerdo",1,"error")))))) -> -0.33 | AR17: Levemente de Acuerdo | AS17: =IF(AR17="Totalmente de Acuerdo",1,IF(AR17="Muy de Acuerdo",0.66,IF(AR17="Levemente de Acuerdo",0.33,IF(AR17="Levemente en Desacuerdo",-0.33,IF(AR17="Muy en Desacuerdo",-0.66,IF(AR17="Totalmente en Desacuerdo",-1,"error")))))) -> 0.33 | AT17: Totalmente en Desacuerdo | AU17: =IF(AT17="Totalmente de Acuerdo",-1,IF(AT17="Muy de Acuerdo",-0.66,IF(AT17="Levemente de Acuerdo",-0.33,IF(AT17="Levemente en Desacuerdo",0.33,IF(AT17="Muy en Desacuerdo",0.66,IF(AT17="Totalmente en Desacuerdo",1,"error")))))) -> 1 | AV17: =+AU17+AS17+AQ17+AO17+AM17+AK17+AI17+AG17+AE17 -> 2 | AW17: Levemente de Acuerdo | AX17: Levemente de Acuerdo | AY17: Levemente en Desacuerdo | AZ17: Muy de Acuerdo | BA17: Levemente en Desacuerdo | BB17: Levemente en Desacuerdo | BC17: Totalmente en Desacuerdo | BD17: Totalmente en Desacuerdo | BE17: Levemente de Acuerdo | BF17: Totalmente de Acuerdo | BG17: Levemente de Acuerdo | BJ17: Me identifico | BX17: Patricia Bullrich (Juntos por el Cambio) | BY17: Patricia Bullrich (Juntos por el Cambio) | BZ17: Javier Milei (La Libertad Avanza)
A18: 45547.898 | B18: 00578280042 | C18: 2003 | D18: Tercer año | E18: Varón | F18: Universitario incompleto | G18: Terciario completo | H18: Clase Media Alta (C2): entre $1.350.001 mensuales y $2.850.000 mensuales | I18: Familia | J18: Otra localidad en la Provincia de Córdoba | K18: , | L18: Levemente en Desacuerdo | M18: =IF(L18="Totalmente de Acuerdo",-1,IF(L18="Muy de Acuerdo",-0.66,IF(L18="Levemente de Acuerdo",-0.33,IF(L18="Levemente en Desacuerdo",0.33,IF(L18="Muy en Desacuerdo",0.66,IF(L18="Totalmente en Desacuerdo",1,"error")))))) -> 0.33 | N18: Muy en Desacuerdo | O18: =IF(N18="Totalmente de Acuerdo",1,IF(N18="Muy de Acuerdo",0.66,IF(N18="Levemente de Acuerdo",0.33,IF(N18="Levemente en Desacuerdo",-0.33,IF(N18="Muy en Desacuerdo",-0.66,IF(N18="Totalmente en Desacuerdo",-1,"error")))))) -> -0.66 | P18: Muy de Acuerdo | Q18: =IF(P18="Totalmente de Acuerdo",-1,IF(P18="Muy de Acuerdo",-0.66,IF(P18="Levemente de Acuerdo",-0.33,IF(P18="Levemente en Desacuerdo",0.33,IF(P18="Muy en Desacuerdo",0.66,IF(P18="Totalmente en Desacuerdo",1,"error")))))) -> -0.66 | R18: Totalmente de Acuerdo | S18: =IF(R18="Totalmente de Acuerdo",1,IF(R18="Muy de Acuerdo",0.66,IF(R18="Levemente de Acuerdo",0.33,IF(R18="Levemente en Desacuerdo",-0.33,IF(R18="Muy en Desacuerdo",-0.66,IF(R18="Totalmente en Desacuerdo",-1,"error")))))) -> 1 | T18: Levemente de Acuerdo | U18: =IF(T18="Totalmente de Acuerdo",-1,IF(T18="Muy de Acuerdo",-0.66,IF(T18="Levemente de Acuerdo",-0.33,IF(T18="Levemente en Desacuerdo",0.33,IF(T18="Muy en Desacuerdo",0.66,IF(T18="Totalmente en Desacuerdo",1,"error")))))) -> -0.33 | V18: Totalmente de Acuerdo | W18: =IF(V18="Totalmente de Acuerdo",1,IF(V18="Muy de Acuerdo",0.66,IF(V18="Levemente de Acuerdo",0.33,IF(V18="Levemente en Desacuerdo",-0.33,IF(V18="Muy en Desacuerdo",-0.66,IF(V18="Totalmente en Desacuerdo",-1,"error")))))) -> 1 | X18: Muy de Acuerdo | Y18: =IF(X18="Totalmente de Acuerdo",1,IF(X18="Muy de Acuerdo",0.66,IF(X18="Levemente de Acuerdo",0.33,IF(X18="Levemente en Desacuerdo",-0.33,IF(X18="Muy en Desacuerdo",-0.66,IF(X18="Totalmente en Desacuerdo",-1,"error")))))) -> 0.66 | Z18: Muy en Desacuerdo | AA18: =IF(Z18="Totalmente de Acuerdo",1,IF(Z18="Muy de Acuerdo",0.66,IF(Z18="Levemente en Acuerdo",0.33,IF(Z18="Levemente en Desacuerdo",-0.33,IF(Z18="Muy en Desacuerdo",-0.66,IF(Z18="Totalmente en Desacuerdo",-1,"error")))))) -> -0.66 | AB18: =+AA18+Y18+W18+U18+S18+Q18+O18+M18 -> 0.68 | AC18: =+AB18*AB$29 -> 0.765 | AD18: Totalmente de Acuerdo | AE18: =IF(AD18="Totalmente de Acuerdo",1,IF(AD18="Muy de Acuerdo",0.66,IF(AD18="Levemente de Acuerdo",0.33,IF(AD18="Levemente en Desacuerdo",-0.33,IF(AD18="Muy en Desacuerdo",-0.66,IF(AD18="Totalmente en Desacuerdo",-1,"error")))))) -> 1 | AF18: Totalmente de Acuerdo | AG18: =IF(AF18="Totalmente de Acuerdo",-1,IF(AF18="Muy de Acuerdo",-0.66,IF(AF18="Levemente de Acuerdo",-0.33,IF(AF18="Levemente en Desacuerdo",0.33,IF(AF18="Muy en Desacuerdo",0.66,IF(AF18="Totalmente en Desacuerdo",1,"error")))))) -> -1 | AH18: Levemente de Acuerdo | AI18: =IF(AH18="Totalmente de Acuerdo",1,IF(AH18="Muy de Acuerdo",0.66,IF(AH18="Levemente de Acuerdo",0.33,IF(AH18="Levemente en Desacuerdo",-0.33,IF(AH18="Muy en Desacuerdo",-0.66,IF(AH18="Totalmente en Desacuerdo",-1,"error")))))) -> 0.33 | AJ18: Totalmente en Desacuerdo | AK18: =IF(AJ18="Totalmente de Acuerdo",1,IF(AJ18="Muy de Acuerdo",0.66,IF(AJ18="Levemente de Acuerdo",0.33,IF(AJ18="Levemente en Desacuerdo",-0.33,IF(AJ18="Muy en Desacuerdo",-0.66,IF(AJ18="Totalmente en Desacuerdo",-1,"error")))))) -> -1 | AL18: Levemente en Desacuerdo | AM18: =IF(AL18="Totalmente de Acuerdo",-1,IF(AL18="Muy de Acuerdo",-0.66,IF(AL18="Levemente de Acuerdo",-0.33,IF(AL18="Levemente en Desacuerdo",0.33,IF(AL18="Muy en Desacuerdo",0.66,IF(AL18="Totalmente en Desacuerdo",1,"error")))))) -> 0.33 | AN18: Totalmente en Desacuerdo | AO18: =IF(AN18="Totalmente de Acuerdo",-1,IF(AN18="Muy de Acuerdo",-0.66,IF(AN18="Levemente de Acuerdo",-0.33,IF(AN18="Levemente en Desacuerdo",0.33,IF(AN18="Muy en Desacuerdo",0.66,IF(AN18="Totalmente en Desacuerdo",1,"error")))))) -> 1 | AP18: Totalmente en Desacuerdo | AQ18: =IF(AP18="Totalmente de Acuerdo",-1,IF(AP18="Muy de Acuerdo",-0.66,IF(AP18="Levemente de Acuerdo",-0.33,IF(AP18="Levemente en Desacuerdo",0.33,IF(AP18="Muy en Desacuerdo",0.66,IF(AP18="Totalmente en Desacuerdo",1,"error")))))) -> 1 | AR18: Levemente en Desacuerdo | AS18: =IF(AR18="Totalmente de Acuerdo",1,IF(AR18="Muy de Acuerdo",0.66,IF(AR18="Levemente de Acuerdo",0.33,IF(AR18="Levemente en Desacuerdo",-0.33,IF(AR18="Muy en Desacuerdo",-0.66,IF(AR18="Totalmente en Desacuerdo",-1,"error")))))) -> -0.33 | AT18: Muy en Desacuerdo | AU18: =IF(AT18="Totalmente de Acuerdo",-1,IF(AT18="Muy de Acuerdo",-0.66,IF(AT18="Levemente de Acuerdo",-0.33,IF(AT18="Levemente en Desacuerdo",0.33,IF(AT18="Muy en Desacuerdo",0.66,IF(AT18="Totalmente en Desacuerdo",1,"error")))))) -> 0.66 | AV18: =+AU18+AS18+AQ18+AO18+AM18+AK18+AI18+AG18+AE18 -> 1.99 | AW18: Levemente en Desacuerdo | AX18: Muy de Acuerdo | AY18: Totalmente en Desacuerdo | AZ18: Muy de Acuerdo | BA18: Levemente de Acuerdo | BB18: Levemente de Acuerdo | BC18: Levemente de Acuerdo | BD18: Totalmente de Acuerdo | BE18: Muy de Acuerdo | BF18: Levemente en Desacuerdo | BG18: Muy de Acuerdo | BH18: Me identifico | BL18: Me identifico | BM18: Me identifico | BX18: Javier Milei (La Libertad Avanza) | BY18: Javier Milei (La Libertad Avanza) | BZ18: Javier Milei (La Libertad Avanza)
A19: 45547.901 | B19: 00608003883 | C19: 2002 | D19: Cuarto año | E19: Varón | F19: Universitario completo | G19: Universitario completo | H19: Clase Media Alta (C2): entre $1.350.001 mensuales y $2.850.000 mensuales | I19: Familia | J19: Otra localidad en otra Provincia | K19: , | L19: Muy en Desacuerdo | M19: =IF(L19="Totalmente de Acuerdo",-1,IF(L19="Muy de Acuerdo",-0.66,IF(L19="Levemente de Acuerdo",-0.33,IF(L19="Levemente en Desacuerdo",0.33,IF(L19="Muy en Desacuerdo",0.66,IF(L19="Totalmente en Desacuerdo",1,"error")))))) -> 0.66 | N19: Levemente de Acuerdo | O19: =IF(N19="Totalmente de Acuerdo",1,IF(N19="Muy de Acuerdo",0.66,IF(N19="Levemente de Acuerdo",0.33,IF(N19="Levemente en Desacuerdo",-0.33,IF(N19="Muy en Desacuerdo",-0.66,IF(N19="Totalmente en Desacuerdo",-1,"error")))))) -> 0.33 | P19: Muy de Acuerdo | Q19: =IF(P19="Totalmente de Acuerdo",-1,IF(P19="Muy de Acuerdo",-0.66,IF(P19="Levemente de Acuerdo",-0.33,IF(P19="Levemente en Desacuerdo",0.33,IF(P19="Muy en Desacuerdo",0.66,IF(P19="Totalmente en Desacuerdo",1,"error")))))) -> -0.66 | R19: Totalmente de Acuerdo | S19: =IF(R19="Totalmente de Acuerdo",1,IF(R19="Muy de Acuerdo",0.66,IF(R19="Levemente de Acuerdo",0.33,IF(R19="Levemente en Desacuerdo",-0.33,IF(R19="Muy en Desacuerdo",-0.66,IF(R19="Totalmente en Desacuerdo",-1,"error")))))) -> 1 | T19: Muy en Desacuerdo | U19: =IF(T19="Totalmente de Acuerdo",-1,IF(T19="Muy de Acuerdo",-0.66,IF(T19="Levemente de Acuerdo",-0.33,IF(T19="Levemente en Desacuerdo",0.33,IF(T19="Muy en Desacuerdo",0.66,IF(T19="Totalmente en Desacuerdo",1,"error")))))) -> 0.66 | V19: Muy de Acuerdo | W19: =IF(V19="Totalmente de Acuerdo",1,IF(V19="Muy de Acuerdo",0.66,IF(V19="Levemente de Acuerdo",0.33,IF(V19="Levemente en Desacuerdo",-0.33,IF(V19="Muy en Desacuerdo",-0.66,IF(V19="Totalmente en Desacuerdo",-1,"error")))))) -> 0.66 | X19: Levemente de Acuerdo | Y19: =IF(X19="Totalmente de Acuerdo",1,IF(X19="Muy de Acuerdo",0.66,IF(X19="Levemente de Acuerdo",0.33,IF(X19="Levemente en Desacuerdo",-0.33,IF(X19="Muy en Desacuerdo",-0.66,IF(X19="Totalmente en Desacuerdo",-1,"error")))))) -> 0.33 | Z19: Levemente en Desacuerdo | AA19: =IF(Z19="Totalmente de Acuerdo",1,IF(Z19="Muy de Acuerdo",0.66,IF(Z19="Levemente en Acuerdo",0.33,IF(Z19="Levemente en Desacuerdo",-0.33,IF(Z19="Muy en Desacuerdo",-0.66,IF(Z19="Totalmente en Desacuerdo",-1,"error")))))) -> -0.33 | AB19: =+AA19+Y19+W19+U19+S19+Q19+O19+M19 -> 2.65 | AC19: =+AB19*AB$29 -> 2.98125 | AD19: Totalmente en Desacuerdo | AE19: =IF(AD19="Totalmente de Acuerdo",1,IF(AD19="Muy de Acuerdo",0.66,IF(AD19="Levemente de Acuerdo",0.33,IF(AD19="Levemente en Desacuerdo",-0.33,IF(AD19="Muy en Desacuerdo",-0.66,IF(AD19="Totalmente en Desacuerdo",-1,"error")))))) -> -1 | AF19: Muy de Acuerdo | AG19: =IF(AF19="Totalmente de Acuerdo",-1,IF(AF19="Muy de Acuerdo",-0.66,IF(AF19="Levemente de Acuerdo",-0.33,IF(AF19="Levemente en Desacuerdo",0.33,IF(AF19="Muy en Desacuerdo",0.66,IF(AF19="Totalmente en Desacuerdo",1,"error")))))) -> -0.66 | AH19: Levemente en Desacuerdo | AI19: =IF(AH19="Totalmente de Acuerdo",1,IF(AH19="Muy de Acuerdo",0.66,IF(AH19="Levemente de Acuerdo",0.33,IF(AH19="Levemente en Desacuerdo",-0.33,IF(AH19="Muy en Desacuerdo",-0.66,IF(AH19="Totalmente en Desacuerdo",-1,"error")))))) -> -0.33 | AJ19: Levemente de Acuerdo | AK19: =IF(AJ19="Totalmente de Acuerdo",1,IF(AJ19="Muy de Acuerdo",0.66,IF(AJ19="Levemente de Acuerdo",0.33,IF(AJ19="Levemente en Desacuerdo",-0.33,IF(AJ19="Muy en Desacuerdo",-0.66,IF(AJ19="Totalmente en Desacuerdo",-1,"error")))))) -> 0.33 | AL19: Muy de Acuerdo | AM19: =IF(AL19="Totalmente de Acuerdo",-1,IF(AL19="Muy de Acuerdo",-0.66,IF(AL19="Levemente de Acuerdo",-0.33,IF(AL19="Levemente en Desacuerdo",0.33,IF(AL19="Muy en Desacuerdo",0.66,IF(AL19="Totalmente en Desacuerdo",1,"error")))))) -> -0.66 | AN19: Totalmente en Desacuerdo | AO19: =IF(AN19="Totalmente de Acuerdo",-1,IF(AN19="Muy de Acuerdo",-0.66,IF(AN19="Levemente de Acuerdo",-0.33,IF(AN19="Levemente en Desacuerdo",0.33,IF(AN19="Muy en Desacuerdo",0.66,IF(AN19="Totalmente en Desacuerdo",1,"error")))))) -> 1 | AP19: Muy en Desacuerdo | AQ19: =IF(AP19="Totalmente de Acuerdo",-1,IF(AP19="Muy de Acuerdo",-0.66,IF(AP19="Levemente de Acuerdo",-0.33,IF(AP19="Levemente en Desacuerdo",0.33,IF(AP19="Muy en Desacuerdo",0.66,IF(AP19="Totalmente en Desacuerdo",1,"error")))))) -> 0.66 | AR19: Muy de Acuerdo | AS19: =IF(AR19="Totalmente de Acuerdo",1,IF(AR19="Muy de Acuerdo",0.66,IF(AR19="Levemente de Acuerdo",0.33,IF(AR19="Levemente en Desacuerdo",-0.33,IF(AR19="Muy en Desacuerdo",-0.66,IF(AR19="Totalmente en Desacuerdo",-1,"error")))))) -> 0.66 | AT19: Levemente en Desacuerdo | AU19: =IF(AT19="Totalmente de Acuerdo",-1,IF(AT19="Muy de Acuerdo",-0.66,IF(AT19="Levemente de Acuerdo",-0.33,IF(AT19="Levemente en Desacuerdo",0.33,IF(AT19="Muy en Desacuerdo",0.66,IF(AT19="Totalmente en Desacuerdo",1,"error")))))) -> 0.33 | AV19: =+AU19+AS19+AQ19+AO19+AM19+AK19+AI19+AG19+AE19 -> 0.33 | AW19: Muy de Acuerdo | AX19: Muy de Acuerdo | AY19: Muy de Acuerdo | AZ19: Muy de Acuerdo | BA19: Levemente de Acuerdo | BB19: Levemente en Desacuerdo | BC19: Levemente en Desacuerdo | BD19: Levemente de Acuerdo | BE19: Muy de Acuerdo | BF19: Muy de Acuerdo | BG19: Muy de Acuerdo | BH19: Me identifico | BM19: Me identifico | BX19: En blanco | BY19: En blanco | BZ19: Javier Milei (La Libertad Avanza)
A20: 45547.899 | B20: 00623233790 | C20: 1997 | D20: Quinto año | E20: Varón | F20: Universitario completo | G20: Universitario incompleto | H20: Clase Media Alta (C2): entre $1.350.001 mensuales y $2.850.000 mensuales | I20: Trabajo propio | J20: Ciudad de Córdoba | K20: , | L20: Totalmente en Desacuerdo | M20: =IF(L20="Totalmente de Acuerdo",-1,IF(L20="Muy de Acuerdo",-0.66,IF(L20="Levemente de Acuerdo",-0.33,IF(L20="Levemente en Desacuerdo",0.33,IF(L20="Muy en Desacuerdo",0.66,IF(L20="Totalmente en Desacuerdo",1,"error")))))) -> 1 | N20: Muy de Acuerdo | O20: =IF(N20="Totalmente de Acuerdo",1,IF(N20="Muy de Acuerdo",0.66,IF(N20="Levemente de Acuerdo",0.33,IF(N20="Levemente en Desacuerdo",-0.33,IF(N20="Muy en Desacuerdo",-0.66,IF(N20="Totalmente en Desacuerdo",-1,"error")))))) -> 0.66 | P20: Totalmente de Acuerdo | Q20: =IF(P20="Totalmente de Acuerdo",-1,IF(P20="Muy de Acuerdo",-0.66,IF(P20="Levemente de Acuerdo",-0.33,IF(P20="Levemente en Desacuerdo",0.33,IF(P20="Muy en Desacuerdo",0.66,IF(P20="Totalmente en Desacuerdo",1,"error")))))) -> -1 | R20: Totalmente de Acuerdo | S20: =IF(R20="Totalmente de Acuerdo",1,IF(R20="Muy de Acuerdo",0.66,IF(R20="Levemente de Acuerdo",0.33,IF(R20="Levemente en Desacuerdo",-0.33,IF(R20="Muy en Desacuerdo",-0.66,IF(R20="Totalmente en Desacuerdo",-1,"error")))))) -> 1 | T20: Totalmente en Desacuerdo | U20: =IF(T20="Totalmente de Acuerdo",-1,IF(T20="Muy de Acuerdo",-0.66,IF(T20="Levemente de Acuerdo",-0.33,IF(T20="Levemente en Desacuerdo",0.33,IF(T20="Muy en Desacuerdo",0.66,IF(T20="Totalmente en Desacuerdo",1,"error")))))) -> 1 | V20: Totalmente de Acuerdo | W20: =IF(V20="Totalmente de Acuerdo",1,IF(V20="Muy de Acuerdo",0.66,IF(V20="Levemente de Acuerdo",0.33,IF(V20="Levemente en Desacuerdo",-0.33,IF(V20="Muy en Desacuerdo",-0.66,IF(V20="Totalmente en Desacuerdo",-1,"error")))))) -> 1 | X20: Muy en Desacuerdo | Y20: =IF(X20="Totalmente de Acuerdo",1,IF(X20="Muy de Acuerdo",0.66,IF(X20="Levemente de Acuerdo",0.33,IF(X20="Levemente en Desacuerdo",-0.33,IF(X20="Muy en Desacuerdo",-0.66,IF(X20="Totalmente en Desacuerdo",-1,"error")))))) -> -0.66 | Z20: Muy en Desacuerdo | AA20: =IF(Z20="Totalmente de Acuerdo",1,IF(Z20="Muy de Acuerdo",0.66,IF(Z20="Levemente en Acuerdo",0.33,IF(Z20="Levemente en Desacuerdo",-0.33,IF(Z20="Muy en Desacuerdo",-0.66,IF(Z20="Totalmente en Desacuerdo",-1,"error")))))) -> -0.66 | AB20: =+AA20+Y20+W20+U20+S20+Q20+O20+M20 -> 2.34 | AC20: =+AB20*AB$29 -> 2.6325 | AD20: Totalmente en Desacuerdo | AE20: =IF(AD20="Totalmente de Acuerdo",1,IF(AD20="Muy de Acuerdo",0.66,IF(AD20="Levemente de Acuerdo",0.33,IF(AD20="Levemente en Desacuerdo",-0.33,IF(AD20="Muy en Desacuerdo",-0.66,IF(AD20="Totalmente en Desacuerdo",-1,"error")))))) -> -1 | AF20: Totalmente de Acuerdo | AG20: =IF(AF20="Totalmente de Acuerdo",-1,IF(AF20="Muy de Acuerdo",-0.66,IF(AF20="Levemente de Acuerdo",-0.33,IF(AF20="Levemente en Desacuerdo",0.33,IF(AF20="Muy en Desacuerdo",0.66,IF(AF20="Totalmente en Desacuerdo",1,"error")))))) -> -1 | AH20: Muy en Desacuerdo | AI20: =IF(AH20="Totalmente de Acuerdo",1,IF(AH20="Muy de Acuerdo",0.66,IF(AH20="Levemente de Acuerdo",0.33,IF(AH20="Levemente en Desacuerdo",-0.33,IF(AH20="Muy en Desacuerdo",-0.66,IF(AH20="Totalmente en Desacuerdo",-1,"error")))))) -> -0.66 | AJ20: Totalmente en Desacuerdo | AK20: =IF(AJ20="Totalmente de Acuerdo",1,IF(AJ20="Muy de Acuerdo",0.66,IF(AJ20="Levemente de Acuerdo",0.33,IF(AJ20="Levemente en Desacuerdo",-0.33,IF(AJ20="Muy en Desacuerdo",-0.66,IF(AJ20="Totalmente en Desacuerdo",-1,"error")))))) -> -1 | AL20: Levemente de Acuerdo | AM20: =IF(AL20="Totalmente de Acuerdo",-1,IF(AL20="Muy de Acuerdo",-0.66,IF(AL20="Levemente de Acuerdo",-0.33,IF(AL20="Levemente en Desacuerdo",0.33,IF(AL20="Muy en Desacuerdo",0.66,IF(AL20="Totalmente en Desacuerdo",1,"error")))))) -> -0.33 | AN20: Totalmente en Desacuerdo | AO20: =IF(AN20="Totalmente de Acuerdo",-1,IF(AN20="Muy de Acuerdo",-0.66,IF(AN20="Levemente de Acuerdo",-0.33,IF(AN20="Levemente en Desacuerdo",0.33,IF(AN20="Muy en Desacuerdo",0.66,IF(AN20="Totalmente en Desacuerdo",1,"error")))))) -> 1 | AP20: Totalmente de Acuerdo | AQ20: =IF(AP20="Totalmente de Acuerdo",-1,IF(AP20="Muy de Acuerdo",-0.66,IF(AP20="Levemente de Acuerdo",-0.33,IF(AP20="Levemente en Desacuerdo",0.33,IF(AP20="Muy en Desacuerdo",0.66,IF(AP20="Totalmente en Desacuerdo",1,"error")))))) -> -1 | AR20: Totalmente de Acuerdo | AS20: =IF(AR20="Totalmente de Acuerdo",1,IF(AR20="Muy de Acuerdo",0.66,IF(AR20="Levemente de Acuerdo",0.33,IF(AR20="Levemente en Desacuerdo",-0.33,IF(AR20="Muy en Desacuerdo",-0.66,IF(AR20="Totalmente en Desacuerdo",-1,"error")))))) -> 1 | AT20: Totalmente en Desacuerdo | AU20: =IF(AT20="Totalmente de Acuerdo",-1,IF(AT20="Muy de Acuerdo",-0.66,IF(AT20="Levemente de Acuerdo",-0.33,IF(AT20="Levemente en Desacuerdo",0.33,IF(AT20="Muy en Desacuerdo",0.66,IF(AT20="Totalmente en Desacuerdo",1,"error")))))) -> 1 | AV20: =+AU20+AS20+AQ20+AO20+AM20+AK20+AI20+AG20+AE20 -> -1.99 | AW20: Totalmente de Acuerdo | AX20: Muy de Acuerdo | AY20: Totalmente en Desacuerdo | AZ20: Totalmente en Desacuerdo | BA20: Totalmente en Desacuerdo | BB20: Totalmente en Desacuerdo | BC20: Totalmente en Desacuerdo | BD20: Totalmente en Desacuerdo | BE20: Totalmente en Desacuerdo | BF20: Totalmente de Acuerdo | BG20: Totalmente de Acuerdo | BH20: Me identifico | BM20: Me identifico | BX20: Patricia Bullrich (Juntos por el Cambio) | BY20: Patricia Bullrich (Juntos por el Cambio) | BZ20: Javier Milei (La Libertad Avanza)
A21: 45547.899 | B21: 00661842297 | C21: 2000 | D21: Cuarto año | E21: Varón | F21: Universitario incompleto | G21: Universitario completo | H21: Clase Media Alta (C2): entre $1.350.001 mensuales y $2.850.000 mensuales | I21: Familia | J21: Otra localidad en otra Provincia | K21: , | L21: Levemente en Desacuerdo | M21: =IF(L21="Totalmente de Acuerdo",-1,IF(L21="Muy de Acuerdo",-0.66,IF(L21="Levemente de Acuerdo",-0.33,IF(L21="Levemente en Desacuerdo",0.33,IF(L21="Muy en Desacuerdo",0.66,IF(L21="Totalmente en Desacuerdo",1,"error")))))) -> 0.33 | N21: Levemente en Desacuerdo | O21: =IF(N21="Totalmente de Acuerdo",1,IF(N21="Muy de Acuerdo",0.66,IF(N21="Levemente de Acuerdo",0.33,IF(N21="Levemente en Desacuerdo",-0.33,IF(N21="Muy en Desacuerdo",-0.66,IF(N21="Totalmente en Desacuerdo",-1,"error")))))) -> -0.33 | P21: Muy de Acuerdo | Q21: =IF(P21="Totalmente de Acuerdo",-1,IF(P21="Muy de Acuerdo",-0.66,IF(P21="Levemente de Acuerdo",-0.33,IF(P21="Levemente en Desacuerdo",0.33,IF(P21="Muy en Desacuerdo",0.66,IF(P21="Totalmente en Desacuerdo",1,"error")))))) -> -0.66 | R21: Muy de Acuerdo | S21: =IF(R21="Totalmente de Acuerdo",1,IF(R21="Muy de Acuerdo",0.66,IF(R21="Levemente de Acuerdo",0.33,IF(R21="Levemente en Desacuerdo",-0.33,IF(R21="Muy en Desacuerdo",-0.66,IF(R21="Totalmente en Desacuerdo",-1,"error")))))) -> 0.66 | T21: Levemente de Acuerdo | U21: =IF(T21="Totalmente de Acuerdo",-1,IF(T21="Muy de Acuerdo",-0.66,IF(T21="Levemente de Acuerdo",-0.33,IF(T21="Levemente en Desacuerdo",0.33,IF(T21="Muy en Desacuerdo",0.66,IF(T21="Totalmente en Desacuerdo",1,"error")))))) -> -0.33 | V21: Levemente en Desacuerdo | W21: =IF(V21="Totalmente de Acuerdo",1,IF(V21="Muy de Acuerdo",0.66,IF(V21="Levemente de Acuerdo",0.33,IF(V21="Levemente en Desacuerdo",-0.33,IF(V21="Muy en Desacuerdo",-0.66,IF(V21="Totalmente en Desacuerdo",-1,"error")))))) -> -0.33 | X21: Levemente de Acuerdo | Y21: =IF(X21="Totalmente de Acuerdo",1,IF(X21="Muy de Acuerdo",0.66,IF(X21="Levemente de Acuerdo",0.33,IF(X21="Levemente en Desacuerdo",-0.33,IF(X21="Muy en Desacuerdo",-0.66,IF(X21="Totalmente en Desacuerdo",-1,"error")))))) -> 0.33 | Z21: Muy en Desacuerdo | AA21: =IF(Z21="Totalmente de Acuerdo",1,IF(Z21="Muy de Acuerdo",0.66,IF(Z21="Levemente en Acuerdo",0.33,IF(Z21="Levemente en Desacuerdo",-0.33,IF(Z21="Muy en Desacuerdo",-0.66,IF(Z21="Totalmente en Desacuerdo",-1,"error")))))) -> -0.66 | AB21: =+AA21+Y21+W21+U21+S21+Q21+O21+M21 -> -0.99 | AC21: =+AB21*AB$29 -> -1.11375 | AD21: Muy en Desacuerdo | AE21: =IF(AD21="Totalmente de Acuerdo",1,IF(AD21="Muy de Acuerdo",0.66,IF(AD21="Levemente de Acuerdo",0.33,IF(AD21="Levemente en Desacuerdo",-0.33,IF(AD21="Muy en Desacuerdo",-0.66,IF(AD21="Totalmente en Desacuerdo",-1,"error")))))) -> -0.66 | AF21: Levemente en Desacuerdo | AG21: =IF(AF21="Totalmente de Acuerdo",-1,IF(AF21="Muy de Acuerdo",-0.66,IF(AF21="Levemente de Acuerdo",-0.33,IF(AF21="Levemente en Desacuerdo",0.33,IF(AF21="Muy en Desacuerdo",0.66,IF(AF21="Totalmente en Desacuerdo",1,"error")))))) -> 0.33 | AH21: Levemente en Desacuerdo | AI21: =IF(AH21="Totalmente de Acuerdo",1,IF(AH21="Muy de Acuerdo",0.66,IF(AH21="Levemente de Acuerdo",0.33,IF(AH21="Levemente en Desacuerdo",-0.33,IF(AH21="Muy en Desacuerdo",-0.66,IF(AH21="Totalmente en Desacuerdo",-1,"error")))))) -> -0.33 | AJ21: Totalmente en Desacuerdo | AK21: =IF(AJ21="Totalmente de Acuerdo",1,IF(AJ21="Muy de Acuerdo",0.66,IF(AJ21="Levemente de Acuerdo",0.33,IF(AJ21="Levemente en Desacuerdo",-0.33,IF(AJ21="Muy en Desacuerdo",-0.66,IF(AJ21="Totalmente en Desacuerdo",-1,"error")))))) -> -1 | AL21: Muy de Acuerdo | AM21: =IF(AL21="Totalmente de Acuerdo",-1,IF(AL21="Muy de Acuerdo",-0.66,IF(AL21="Levemente de Acuerdo",-0.33,IF(AL21="Levemente en Desacuerdo",0.33,IF(AL21="Muy en Desacuerdo",0.66,IF(AL21="Totalmente en Desacuerdo",1,"error")))))) -> -0.66 | AN21: Levemente de Acuerdo | AO21: =IF(AN21="Totalmente de Acuerdo",-1,IF(AN21="Muy de Acuerdo",-0.66,IF(AN21="Levemente de Acuerdo",-0.33,IF(AN21="Levemente en Desacuerdo",0.33,IF(AN21="Muy en Desacuerdo",0.66,IF(AN21="Totalmente en Desacuerdo",1,"error")))))) -> -0.33 | AP21: Muy en Desacuerdo | AQ21: =IF(AP21="Totalmente de Acuerdo",-1,IF(AP21="Muy de Acuerdo",-0.66,IF(AP21="Levemente de Acuerdo",-0.33,IF(AP21="Levemente en Desacuerdo",0.33,IF(AP21="Muy en Desacuerdo",0.66,IF(AP21="Totalmente en Desacuerdo",1,"error")))))) -> 0.66 | AR21: Muy de Acuerdo | AS21: =IF(AR21="Totalmente de Acuerdo",1,IF(AR21="Muy de Acuerdo",0.66,IF(AR21="Levemente de Acuerdo",0.33,IF(AR21="Levemente en Desacuerdo",-0.33,IF(AR21="Muy en Desacuerdo",-0.66,IF(AR21="Totalmente en Desacuerdo",-1,"error")))))) -> 0.66 | AT21: Levemente de Acuerdo | AU21: =IF(AT21="Totalmente de Acuerdo",-1,IF(AT21="Muy de Acuerdo",-0.66,IF(AT21="Levemente de Acuerdo",-0.33,IF(AT21="Levemente en Desacuerdo",0.33,IF(AT21="Muy en Desacuerdo",0.66,IF(AT21="Totalmente en Desacuerdo",1,"error")))))) -> -0.33 | AV21: =+AU21+AS21+AQ21+AO21+AM21+AK21+AI21+AG21+AE21 -> -1.66 | AW21: Levemente en Desacuerdo | AX21: Muy de Acuerdo | AY21: Muy en Desacuerdo | AZ21: Levemente de Acuerdo | BA21: Muy en Desacuerdo | BB21: Muy en Desacuerdo | BC21: Muy en Desacuerdo | BD21: Muy en Desacuerdo | BE21: Muy de Acuerdo | BF21: Levemente de Acuerdo | BG21: Levemente en Desacuerdo | BJ21: Me identifico | BX21: No vote | BY21: Sergio Massa (Unión por la Patria) | BZ21: Sergio Massa (Unión por la Patria)
A22: 45547.902 | B22: 00680175484 | C22: 2002 | D22: Cuarto año | E22: Mujer | F22: Secundario completo | G22: Primario completo | H22: Clase Alta (ABC1): más de $2.850.000 mensuales | I22: Familia | J22: Otra localidad en la Provincia de Córdoba | K22: , | L22: Levemente de Acuerdo | M22: =IF(L22="Totalmente de Acuerdo",-1,IF(L22="Muy de Acuerdo",-0.66,IF(L22="Levemente de Acuerdo",-0.33,IF(L22="Levemente en Desacuerdo",0.33,IF(L22="Muy en Desacuerdo",0.66,IF(L22="Totalmente en Desacuerdo",1,"error")))))) -> -0.33 | N22: Levemente en Desacuerdo | O22: =IF(N22="Totalmente de Acuerdo",1,IF(N22="Muy de Acuerdo",0.66,IF(N22="Levemente de Acuerdo",0.33,IF(N22="Levemente en Desacuerdo",-0.33,IF(N22="Muy en Desacuerdo",-0.66,IF(N22="Totalmente en Desacuerdo",-1,"error")))))) -> -0.33 | P22: Levemente de Acuerdo | Q22: =IF(P22="Totalmente de Acuerdo",-1,IF(P22="Muy de Acuerdo",-0.66,IF(P22="Levemente de Acuerdo",-0.33,IF(P22="Levemente en Desacuerdo",0.33,IF(P22="Muy en Desacuerdo",0.66,IF(P22="Totalmente en Desacuerdo",1,"error")))))) -> -0.33 | R22: Muy de Acuerdo | S22: =IF(R22="Totalmente de Acuerdo",1,IF(R22="Muy de Acuerdo",0.66,IF(R22="Levemente de Acuerdo",0.33,IF(R22="Levemente en Desacuerdo",-0.33,IF(R22="Muy en Desacuerdo",-0.66,IF(R22="Totalmente en Desacuerdo",-1,"error")))))) -> 0.66 | T22: Muy en Desacuerdo | U22: =IF(T22="Totalmente de Acuerdo",-1,IF(T22="Muy de Acuerdo",-0.66,IF(T22="Levemente de Acuerdo",-0.33,IF(T22="Levemente en Desacuerdo",0.33,IF(T22="Muy en Desacuerdo",0.66,IF(T22="Totalmente en Desacuerdo",1,"error")))))) -> 0.66 | V22: Muy de Acuerdo | W22: =IF(V22="Totalmente de Acuerdo",1,IF(V22="Muy de Acuerdo",0.66,IF(V22="Levemente de Acuerdo",0.33,IF(V22="Levemente en Desacuerdo",-0.33,IF(V22="Muy en Desacuerdo",-0.66,IF(V22="Totalmente en Desacuerdo",-1,"error")))))) -> 0.66 | X22: Totalmente de Acuerdo | Y22: =IF(X22="Totalmente de Acuerdo",1,IF(X22="Muy de Acuerdo",0.66,IF(X22="Levemente de Acuerdo",0.33,IF(X22="Levemente en Desacuerdo",-0.33,IF(X22="Muy en Desacuerdo",-0.66,IF(X22="Totalmente en Desacuerdo",-1,"error")))))) -> 1 | Z22: Muy en Desacuerdo | AA22: =IF(Z22="Totalmente de Acuerdo",1,IF(Z22="Muy de Acuerdo",0.66,IF(Z22="Levemente en Acuerdo",0.33,IF(Z22="Levemente en Desacuerdo",-0.33,IF(Z22="Muy en Desacuerdo",-0.66,IF(Z22="Totalmente en Desacuerdo",-1,"error")))))) -> -0.66 | AB22: =+AA22+Y22+W22+U22+S22+Q22+O22+M22 -> 1.33 | AC22: =+AB22*AB$29 -> 1.49625 | AD22: Levemente en Desacuerdo | AE22: =IF(AD22="Totalmente de Acuerdo",1,IF(AD22="Muy de Acuerdo",0.66,IF(AD22="Levemente de Acuerdo",0.33,IF(AD22="Levemente en Desacuerdo",-0.33,IF(AD22="Muy en Desacuerdo",-0.66,IF(AD22="Totalmente en Desacuerdo",-1,"error")))))) -> -0.33 | AF22: Muy de Acuerdo | AG22: =IF(AF22="Totalmente de Acuerdo",-1,IF(AF22="Muy de Acuerdo",-0.66,IF(AF22="Levemente de Acuerdo",-0.33,IF(AF22="Levemente en Desacuerdo",0.33,IF(AF22="Muy en Desacuerdo",0.66,IF(AF22="Totalmente en Desacuerdo",1,"error")))))) -> -0.66 | AH22: Totalmente en Desacuerdo | AI22: =IF(AH22="Totalmente de Acuerdo",1,IF(AH22="Muy de Acuerdo",0.66,IF(AH22="Levemente de Acuerdo",0.33,IF(AH22="Levemente en Desacuerdo",-0.33,IF(AH22="Muy en Desacuerdo",-0.66,IF(AH22="Totalmente en Desacuerdo",-1,"error")))))) -> -1 | AJ22: Totalmente en Desacuerdo | AK22: =IF(AJ22="Totalmente de Acuerdo",1,IF(AJ22="Muy de Acuerdo",0.66,IF(AJ22="Levemente de Acuerdo",0.33,IF(AJ22="Levemente en Desacuerdo",-0.33,IF(AJ22="Muy en Desacuerdo",-0.66,IF(AJ22="Totalmente en Desacuerdo",-1,"error")))))) -> -1 | AL22: Muy de Acuerdo | AM22: =IF(AL22="Totalmente de Acuerdo",-1,IF(AL22="Muy de Acuerdo",-0.66,IF(AL22="Levemente de Acuerdo",-0.33,IF(AL22="Levemente en Desacuerdo",0.33,IF(AL22="Muy en Desacuerdo",0.66,IF(AL22="Totalmente en Desacuerdo",1,"error")))))) -> -0.66 | AN22: Levemente en Desacuerdo | AO22: =IF(AN22="Totalmente de Acuerdo",-1,IF(AN22="Muy de Acuerdo",-0.66,IF(AN22="Levemente de Acuerdo",-0.33,IF(AN22="Levemente en Desacuerdo",0.33,IF(AN22="Muy en Desacuerdo",0.66,IF(AN22="Totalmente en Desacuerdo",1,"error")))))) -> 0.33 | AP22: Levemente en Desacuerdo | AQ22: =IF(AP22="Totalmente de Acuerdo",-1,IF(AP22="Muy de Acuerdo",-0.66,IF(AP22="Levemente de Acuerdo",-0.33,IF(AP22="Levemente en Desacuerdo",0.33,IF(AP22="Muy en Desacuerdo",0.66,IF(AP22="Totalmente en Desacuerdo",1,"error")))))) -> 0.33 | AR22: Muy de Acuerdo | AS22: =IF(AR22="Totalmente de Acuerdo",1,IF(AR22="Muy de Acuerdo",0.66,IF(AR22="Levemente de Acuerdo",0.33,IF(AR22="Levemente en Desacuerdo",-0.33,IF(AR22="Muy en Desacuerdo",-0.66,IF(AR22="Totalmente en Desacuerdo",-1,"error")))))) -> 0.66 | AT22: Muy en Desacuerdo | AU22: =IF(AT22="Totalmente de Acuerdo",-1,IF(AT22="Muy de Acuerdo",-0.66,IF(AT22="Levemente de Acuerdo",-0.33,IF(AT22="Levemente en Desacuerdo",0.33,IF(AT22="Muy en Desacuerdo",0.66,IF(AT22="Totalmente en Desacuerdo",1,"error")))))) -> 0.66 | AV22: =+AU22+AS22+AQ22+AO22+AM22+AK22+AI22+AG22+AE22 -> -1.67 | AW22: Muy de Acuerdo | AX22: Muy de Acuerdo | AY22: Levemente en Desacuerdo | AZ22: Levemente de Acuerdo | BA22: Totalmente en Desacuerdo | BB22: Totalmente en Desacuerdo | BC22: Totalmente en Desacuerdo | BD22: Muy en Desacuerdo | BE22: Muy de Acuerdo | BF22: Muy de Acuerdo | BG22: Totalmente de Acuerdo | BJ22: Me identifico | BU22: Me identifico | BV22: Me identifico | BX22: No vote | BY22: Patricia Bullrich (Juntos por el Cambio) | BZ22: Javier Milei (La Libertad Avanza)
A23: 45547.902 | B23: 00686589580 | C23: 2002 | D23: Cuarto año | E23: Varón | F23: Universitario completo | G23: Universitario completo | H23: Clase Media Alta (C2): entre $1.350.001 mensuales y $2.850.000 mensuales | I23: Familia | J23: Otra localidad en otra Provincia | K23: , | L23: Levemente de Acuerdo | M23: =IF(L23="Totalmente de Acuerdo",-1,IF(L23="Muy de Acuerdo",-0.66,IF(L23="Levemente de Acuerdo",-0.33,IF(L23="Levemente en Desacuerdo",0.33,IF(L23="Muy en Desacuerdo",0.66,IF(L23="Totalmente en Desacuerdo",1,"error")))))) -> -0.33 | N23: Levemente de Acuerdo | O23: =IF(N23="Totalmente de Acuerdo",1,IF(N23="Muy de Acuerdo",0.66,IF(N23="Levemente de Acuerdo",0.33,IF(N23="Levemente en Desacuerdo",-0.33,IF(N23="Muy en Desacuerdo",-0.66,IF(N23="Totalmente en Desacuerdo",-1,"error")))))) -> 0.33 | P23: Totalmente de Acuerdo | Q23: =IF(P23="Totalmente de Acuerdo",-1,IF(P23="Muy de Acuerdo",-0.66,IF(P23="Levemente de Acuerdo",-0.33,IF(P23="Levemente en Desacuerdo",0.33,IF(P23="Muy en Desacuerdo",0.66,IF(P23="Totalmente en Desacuerdo",1,"error")))))) -> -1 | R23: Muy de Acuerdo | S23: =IF(R23="Totalmente de Acuerdo",1,IF(R23="Muy de Acuerdo",0.66,IF(R23="Levemente de Acuerdo",0.33,IF(R23="Levemente en Desacuerdo",-0.33,IF(R23="Muy en Desacuerdo",-0.66,IF(R23="Totalmente en Desacuerdo",-1,"error")))))) -> 0.66 | T23: Muy de Acuerdo | U23: =IF(T23="Totalmente de Acuerdo",-1,IF(T23="Muy de Acuerdo",-0.66,IF(T23="Levemente de Acuerdo",-0.33,IF(T23="Levemente en Desacuerdo",0.33,IF(T23="Muy en Desacuerdo",0.66,IF(T23="Totalmente en Desacuerdo",1,"error")))))) -> -0.66 | V23: Levemente de Acuerdo | W23: =IF(V23="Totalmente de Acuerdo",1,IF(V23="Muy de Acuerdo",0.66,IF(V23="Levemente de Acuerdo",0.33,IF(V23="Levemente en Desacuerdo",-0.33,IF(V23="Muy en Desacuerdo",-0.66,IF(V23="Totalmente en Desacuerdo",-1,"error")))))) -> 0.33 | X23: Levemente de Acuerdo | Y23: =IF(X23="Totalmente de Acuerdo",1,IF(X23="Muy de Acuerdo",0.66,IF(X23="Levemente de Acuerdo",0.33,IF(X23="Levemente en Desacuerdo",-0.33,IF(X23="Muy en Desacuerdo",-0.66,IF(X23="Totalmente en Desacuerdo",-1,"error")))))) -> 0.33 | Z23: Levemente en Desacuerdo | AA23: =IF(Z23="Totalmente de Acuerdo",1,IF(Z23="Muy de Acuerdo",0.66,IF(Z23="Levemente en Acuerdo",0.33,IF(Z23="Levemente en Desacuerdo",-0.33,IF(Z23="Muy en Desacuerdo",-0.66,IF(Z23="Totalmente en Desacuerdo",-1,"error")))))) -> -0.33 | AB23: =+AA23+Y23+W23+U23+S23+Q23+O23+M23 -> -0.67 | AC23: =+AB23*AB$29 -> -0.75375 | AD23: Muy en Desacuerdo | AE23: =IF(AD23="Totalmente de Acuerdo",1,IF(AD23="Muy de Acuerdo",0.66,IF(AD23="Levemente de Acuerdo",0.33,IF(AD23="Levemente en Desacuerdo",-0.33,IF(AD23="Muy en Desacuerdo",-0.66,IF(AD23="Totalmente en Desacuerdo",-1,"error")))))) -> -0.66 | AF23: Muy en Desacuerdo | AG23: =IF(AF23="Totalmente de Acuerdo",-1,IF(AF23="Muy de Acuerdo",-0.66,IF(AF23="Levemente de Acuerdo",-0.33,IF(AF23="Levemente en Desacuerdo",0.33,IF(AF23="Muy en Desacuerdo",0.66,IF(AF23="Totalmente en Desacuerdo",1,"error")))))) -> 0.66 | AH23: Levemente de Acuerdo | AI23: =IF(AH23="Totalmente de Acuerdo",1,IF(AH23="Muy de Acuerdo",0.66,IF(AH23="Levemente de Acuerdo",0.33,IF(AH23="Levemente en Desacuerdo",-0.33,IF(AH23="Muy en Desacuerdo",-0.66,IF(AH23="Totalmente en Desacuerdo",-1,"error")))))) -> 0.33 | AJ23: Levemente de Acuerdo | AK23: =IF(AJ23="Totalmente de Acuerdo",1,IF(AJ23="Muy de Acuerdo",0.66,IF(AJ23="Levemente de Acuerdo",0.33,IF(AJ23="Levemente en Desacuerdo",-0.33,IF(AJ23="Muy en Desacuerdo",-0.66,IF(AJ23="Totalmente en Desacuerdo",-1,"error")))))) -> 0.33 | AL23: Levemente en Desacuerdo | AM23: =IF(AL23="Totalmente de Acuerdo",-1,IF(AL23="Muy de Acuerdo",-0.66,IF(AL23="Levemente de Acuerdo",-0.33,IF(AL23="Levemente en Desacuerdo",0.33,IF(AL23="Muy en Desacuerdo",0.66,IF(AL23="Totalmente en Desacuerdo",1,"error")))))) -> 0.33 | AN23: Levemente en Desacuerdo | AO23: =IF(AN23="Totalmente de Acuerdo",-1,IF(AN23="Muy de Acuerdo",-0.66,IF(AN23="Levemente de Acuerdo",-0.33,IF(AN23="Levemente en Desacuerdo",0.33,IF(AN23="Muy en Desacuerdo",0.66,IF(AN23="Totalmente en Desacuerdo",1,"error")))))) -> 0.33 | AP23: Levemente en Desacuerdo | AQ23: =IF(AP23="Totalmente de Acuerdo",-1,IF(AP23="Muy de Acuerdo",-0.66,IF(AP23="Levemente de Acuerdo",-0.33,IF(AP23="Levemente en Desacuerdo",0.33,IF(AP23="Muy en Desacuerdo",0.66,IF(AP23="Totalmente en Desacuerdo",1,"error")))))) -> 0.33 | AR23: Levemente de Acuerdo | AS23: =IF(AR23="Totalmente de Acuerdo",1,IF(AR23="Muy de Acuerdo",0.66,IF(AR23="Levemente de Acuerdo",0.33,IF(AR23="Levemente en Desacuerdo",-0.33,IF(AR23="Muy en Desacuerdo",-0.66,IF(AR23="Totalmente en Desacuerdo",-1,"error")))))) -> 0.33 | AT23: Totalmente en Desacuerdo | AU23: =IF(AT23="Totalmente de Acuerdo",-1,IF(AT23="Muy de Acuerdo",-0.66,IF(AT23="Levemente de Acuerdo",-0.33,IF(AT23="Levemente en Desacuerdo",0.33,IF(AT23="Muy en Desacuerdo",0.66,IF(AT23="Totalmente en Desacuerdo",1,"error")))))) -> 1 | AV23: =+AU23+AS23+AQ23+AO23+AM23+AK23+AI23+AG23+AE23 -> 2.98 | AW23: Levemente en Desacuerdo | AX23: Muy de Acuerdo | AY23: Totalmente en Desacuerdo | AZ23: Totalmente en Desacuerdo | BA23: Totalmente en Desacuerdo | BB23: Levemente de Acuerdo | BC23: Levemente de Acuerdo | BD23: Levemente de Acuerdo | BE23: Totalmente en Desacuerdo | BF23: Totalmente en Desacuerdo | BG23: Muy en Desacuerdo | BL23: Me identifico | BX23: Javier Milei (La Libertad Avanza) | BY23: Javier Milei (La Libertad Avanza) | BZ23: Javier Milei (La Libertad Avanza)
A24: 45547.9 | B24: 006934766847656 | C24: 2000 | D24: Cuarto año | E24: Mujer | F24: Posgrado completo | G24: Universitario completo | H24: Clase Media Alta (C2): entre $1.350.001 mensuales y $2.850.000 mensuales | I24: Familia | J24: Ciudad de Córdoba | K24: , | L24: Totalmente en Desacuerdo | M24: =IF(L24="Totalmente de Acuerdo",-1,IF(L24="Muy de Acuerdo",-0.66,IF(L24="Levemente de Acuerdo",-0.33,IF(L24="Levemente en Desacuerdo",0.33,IF(L24="Muy en Desacuerdo",0.66,IF(L24="Totalmente en Desacuerdo",1,"error")))))) -> 1 | N24: Totalmente en Desacuerdo | O24: =IF(N24="Totalmente de Acuerdo",1,IF(N24="Muy de Acuerdo",0.66,IF(N24="Levemente de Acuerdo",0.33,IF(N24="Levemente en Desacuerdo",-0.33,IF(N24="Muy en Desacuerdo",-0.66,IF(N24="Totalmente en Desacuerdo",-1,"error")))))) -> -1 | P24: Totalmente de Acuerdo | Q24: =IF(P24="Totalmente de Acuerdo",-1,IF(P24="Muy de Acuerdo",-0.66,IF(P24="Levemente de Acuerdo",-0.33,IF(P24="Levemente en Desacuerdo",0.33,IF(P24="Muy en Desacuerdo",0.66,IF(P24="Totalmente en Desacuerdo",1,"error")))))) -> -1 | R24: Totalmente en Desacuerdo | S24: =IF(R24="Totalmente de Acuerdo",1,IF(R24="Muy de Acuerdo",0.66,IF(R24="Levemente de Acuerdo",0.33,IF(R24="Levemente en Desacuerdo",-0.33,IF(R24="Muy en Desacuerdo",-0.66,IF(R24="Totalmente en Desacuerdo",-1,"error")))))) -> -1 | T24: Totalmente de Acuerdo | U24: =IF(T24="Totalmente de Acuerdo",-1,IF(T24="Muy de Acuerdo",-0.66,IF(T24="Levemente de Acuerdo",-0.33,IF(T24="Levemente en Desacuerdo",0.33,IF(T24="Muy en Desacuerdo",0.66,IF(T24="Totalmente en Desacuerdo",1,"error")))))) -> -1 | V24: Muy en Desacuerdo | W24: =IF(V24="Totalmente de Acuerdo",1,IF(V24="Muy de Acuerdo",0.66,IF(V24="Levemente de Acuerdo",0.33,IF(V24="Levemente en Desacuerdo",-0.33,IF(V24="Muy en Desacuerdo",-0.66,IF(V24="Totalmente en Desacuerdo",-1,"error")))))) -> -0.66 | X24: Levemente de Acuerdo | Y24: =IF(X24="Totalmente de Acuerdo",1,IF(X24="Muy de Acuerdo",0.66,IF(X24="Levemente de Acuerdo",0.33,IF(X24="Levemente en Desacuerdo",-0.33,IF(X24="Muy en Desacuerdo",-0.66,IF(X24="Totalmente en Desacuerdo",-1,"error")))))) -> 0.33 | Z24: Totalmente en Desacuerdo | AA24: =IF(Z24="Totalmente de Acuerdo",1,IF(Z24="Muy de Acuerdo",0.66,IF(Z24="Levemente en Acuerdo",0.33,IF(Z24="Levemente en Desacuerdo",-0.33,IF(Z24="Muy en Desacuerdo",-0.66,IF(Z24="Totalmente en Desacuerdo",-1,"error")))))) -> -1 | AB24: =+AA24+Y24+W24+U24+S24+Q24+O24+M24 -> -4.33 | AC24: =+AB24*AB$29 -> -4.87125 | AD24: Muy en Desacuerdo | AE24: =IF(AD24="Totalmente de Acuerdo",1,IF(AD24="Muy de Acuerdo",0.66,IF(AD24="Levemente de Acuerdo",0.33,IF(AD24="Levemente en Desacuerdo",-0.33,IF(AD24="Muy en Desacuerdo",-0.66,IF(AD24="Totalmente en Desacuerdo",-1,"error")))))) -> -0.66 | AF24: Totalmente en Desacuerdo | AG24: =IF(AF24="Totalmente de Acuerdo",-1,IF(AF24="Muy de Acuerdo",-0.66,IF(AF24="Levemente de Acuerdo",-0.33,IF(AF24="Levemente en Desacuerdo",0.33,IF(AF24="Muy en Desacuerdo",0.66,IF(AF24="Totalmente en Desacuerdo",1,"error")))))) -> 1 | AH24: Totalmente en Desacuerdo | AI24: =IF(AH24="Totalmente de Acuerdo",1,IF(AH24="Muy de Acuerdo",0.66,IF(AH24="Levemente de Acuerdo",0.33,IF(AH24="Levemente en Desacuerdo",-0.33,IF(AH24="Muy en Desacuerdo",-0.66,IF(AH24="Totalmente en Desacuerdo",-1,"error")))))) -> -1 | AJ24: Totalmente en Desacuerdo | AK24: =IF(AJ24="Totalmente de Acuerdo",1,IF(AJ24="Muy de Acuerdo",0.66,IF(AJ24="Levemente de Acuerdo",0.33,IF(AJ24="Levemente en Desacuerdo",-0.33,IF(AJ24="Muy en Desacuerdo",-0.66,IF(AJ24="Totalmente en Desacuerdo",-1,"error")))))) -> -1 | AL24: Totalmente de Acuerdo | AM24: =IF(AL24="Totalmente de Acuerdo",-1,IF(AL24="Muy de Acuerdo",-0.66,IF(AL24="Levemente de Acuerdo",-0.33,IF(AL24="Levemente en Desacuerdo",0.33,IF(AL24="Muy en Desacuerdo",0.66,IF(AL24="Totalmente en Desacuerdo",1,"error")))))) -> -1 | AN24: Totalmente de Acuerdo | AO24: =IF(AN24="Totalmente de Acuerdo",-1,IF(AN24="Muy de Acuerdo",-0.66,IF(AN24="Levemente de Acuerdo",-0.33,IF(AN24="Levemente en Desacuerdo",0.33,IF(AN24="Muy en Desacuerdo",0.66,IF(AN24="Totalmente en Desacuerdo",1,"error")))))) -> -1 | AP24: Totalmente de Acuerdo | AQ24: =IF(AP24="Totalmente de Acuerdo",-1,IF(AP24="Muy de Acuerdo",-0.66,IF(AP24="Levemente de Acuerdo",-0.33,IF(AP24="Levemente en Desacuerdo",0.33,IF(AP24="Muy en Desacuerdo",0.66,IF(AP24="Totalmente en Desacuerdo",1,"error")))))) -> -1 | AR24: Totalmente en Desacuerdo | AS24: =IF(AR24="Totalmente de Acuerdo",1,IF(AR24="Muy de Acuerdo",0.66,IF(AR24="Levemente de Acuerdo",0.33,IF(AR24="Levemente en Desacuerdo",-0.33,IF(AR24="Muy en Desacuerdo",-0.66,IF(AR24="Totalmente en Desacuerdo",-1,"error")))))) -> -1 | AT24: Totalmente en Desacuerdo | AU24: =IF(AT24="Totalmente de Acuerdo",-1,IF(AT24="Muy de Acuerdo",-0.66,IF(AT24="Levemente de Acuerdo",-0.33,IF(AT24="Levemente en Desacuerdo",0.33,IF(AT24="Muy en Desacuerdo",0.66,IF(AT24="Totalmente en Desacuerdo",1,"error")))))) -> 1 | AV24: =+AU24+AS24+AQ24+AO24+AM24+AK24+AI24+AG24+AE24 -> -4.66 | AW24: Totalmente en Desacuerdo | AX24: Totalmente de Acuerdo | AY24: Totalmente de Acuerdo | AZ24: Levemente de Acuerdo | BA24: Levemente de Acuerdo | BB24: Levemente en Desacuerdo | BC24: Muy en Desacuerdo | BD24: Totalmente en Desacuerdo | BE24: Totalmente de Acuerdo | BF24: Totalmente de Acuerdo | BG24: Totalmente en Desacuerdo | BJ24: Me identifico | BK24: Me identifico | BP24: Me identifico | BQ24: Me identifico | BU24: Me identifico | BX24: Juan Grabois (Unión por la Patria) | BY24: Sergio Massa (Unión por la Patria) | BZ24: Sergio Massa (Unión por la Patria)
A25: 45547.901 | B25: 00704722792 | C25: 2003 | D25: Cuarto año | E25: Mujer | F25: Universitario completo | G25: Terciario completo | H25: Clase Alta (ABC1): más de $2.850.000 mensuales | I25: Familia | J25: Otra localidad en otra Provincia | K25: , | L25: Levemente de Acuerdo | M25: =IF(L25="Totalmente de Acuerdo",-1,IF(L25="Muy de Acuerdo",-0.66,IF(L25="Levemente de Acuerdo",-0.33,IF(L25="Levemente en Desacuerdo",0.33,IF(L25="Muy en Desacuerdo",0.66,IF(L25="Totalmente en Desacuerdo",1,"error")))))) -> -0.33 | N25: Totalmente de Acuerdo | O25: =IF(N25="Totalmente de Acuerdo",1,IF(N25="Muy de Acuerdo",0.66,IF(N25="Levemente de Acuerdo",0.33,IF(N25="Levemente en Desacuerdo",-0.33,IF(N25="Muy en Desacuerdo",-0.66,IF(N25="Totalmente en Desacuerdo",-1,"error")))))) -> 1 | P25: Muy de Acuerdo | Q25: =IF(P25="Totalmente de Acuerdo",-1,IF(P25="Muy de Acuerdo",-0.66,IF(P25="Levemente de Acuerdo",-0.33,IF(P25="Levemente en Desacuerdo",0.33,IF(P25="Muy en Desacuerdo",0.66,IF(P25="Totalmente en Desacuerdo",1,"error")))))) -> -0.66 | R25: Totalmente de Acuerdo | S25: =IF(R25="Totalmente de Acuerdo",1,IF(R25="Muy de Acuerdo",0.66,IF(R25="Levemente de Acuerdo",0.33,IF(R25="Levemente en Desacuerdo",-0.33,IF(R25="Muy en Desacuerdo",-0.66,IF(R25="Totalmente en Desacuerdo",-1,"error")))))) -> 1 | T25: Muy en Desacuerdo | U25: =IF(T25="Totalmente de Acuerdo",-1,IF(T25="Muy de Acuerdo",-0.66,IF(T25="Levemente de Acuerdo",-0.33,IF(T25="Levemente en Desacuerdo",0.33,IF(T25="Muy en Desacuerdo",0.66,IF(T25="Totalmente en Desacuerdo",1,"error")))))) -> 0.66 | V25: Muy en Desacuerdo | W25: =IF(V25="Totalmente de Acuerdo",1,IF(V25="Muy de Acuerdo",0.66,IF(V25="Levemente de Acuerdo",0.33,IF(V25="Levemente en Desacuerdo",-0.33,IF(V25="Muy en Desacuerdo",-0.66,IF(V25="Totalmente en Desacuerdo",-1,"error")))))) -> -0.66 | X25: Totalmente de Acuerdo | Y25: =IF(X25="Totalmente de Acuerdo",1,IF(X25="Muy de Acuerdo",0.66,IF(X25="Levemente de Acuerdo",0.33,IF(X25="Levemente en Desacuerdo",-0.33,IF(X25="Muy en Desacuerdo",-0.66,IF(X25="Totalmente en Desacuerdo",-1,"error")))))) -> 1 | Z25: Muy de Acuerdo | AA25: =IF(Z25="Totalmente de Acuerdo",1,IF(Z25="Muy de Acuerdo",0.66,IF(Z25="Levemente en Acuerdo",0.33,IF(Z25="Levemente en Desacuerdo",-0.33,IF(Z25="Muy en Desacuerdo",-0.66,IF(Z25="Totalmente en Desacuerdo",-1,"error")))))) -> 0.66 | AB25: =+AA25+Y25+W25+U25+S25+Q25+O25+M25 -> 2.67 | AC25: =+AB25*AB$29 -> 3.00375 | AD25: Levemente de Acuerdo | AE25: =IF(AD25="Totalmente de Acuerdo",1,IF(AD25="Muy de Acuerdo",0.66,IF(AD25="Levemente de Acuerdo",0.33,IF(AD25="Levemente en Desacuerdo",-0.33,IF(AD25="Muy en Desacuerdo",-0.66,IF(AD25="Totalmente en Desacuerdo",-1,"error")))))) -> 0.33 | AF25: Muy de Acuerdo | AG25: =IF(AF25="Totalmente de Acuerdo",-1,IF(AF25="Muy de Acuerdo",-0.66,IF(AF25="Levemente de Acuerdo",-0.33,IF(AF25="Levemente en Desacuerdo",0.33,IF(AF25="Muy en Desacuerdo",0.66,IF(AF25="Totalmente en Desacuerdo",1,"error")))))) -> -0.66 | AH25: Muy de Acuerdo | AI25: =IF(AH25="Totalmente de Acuerdo",1,IF(AH25="Muy de Acuerdo",0.66,IF(AH25="Levemente de Acuerdo",0.33,IF(AH25="Levemente en Desacuerdo",-0.33,IF(AH25="Muy en Desacuerdo",-0.66,IF(AH25="Totalmente en Desacuerdo",-1,"error")))))) -> 0.66 | AJ25: Muy de Acuerdo | AK25: =IF(AJ25="Totalmente de Acuerdo",1,IF(AJ25="Muy de Acuerdo",0.66,IF(AJ25="Levemente de Acuerdo",0.33,IF(AJ25="Levemente en Desacuerdo",-0.33,IF(AJ25="Muy en Desacuerdo",-0.66,IF(AJ25="Totalmente en Desacuerdo",-1,"error")))))) -> 0.66 | AL25: Levemente de Acuerdo | AM25: =IF(AL25="Totalmente de Acuerdo",-1,IF(AL25="Muy de Acuerdo",-0.66,IF(AL25="Levemente de Acuerdo",-0.33,IF(AL25="Levemente en Desacuerdo",0.33,IF(AL25="Muy en Desacuerdo",0.66,IF(AL25="Totalmente en Desacuerdo",1,"error")))))) -> -0.33 | AN25: Totalmente en Desacuerdo | AO25: =IF(AN25="Totalmente de Acuerdo",-1,IF(AN25="Muy de Acuerdo",-0.66,IF(AN25="Levemente de Acuerdo",-0.33,IF(AN25="Levemente en Desacuerdo",0.33,IF(AN25="Muy en Desacuerdo",0.66,IF(AN25="Totalmente en Desacuerdo",1,"error")))))) -> 1 | AP25: Muy de Acuerdo | AQ25: =IF(AP25="Totalmente de Acuerdo",-1,IF(AP25="Muy de Acuerdo",-0.66,IF(AP25="Levemente de Acuerdo",-0.33,IF(AP25="Levemente en Desacuerdo",0.33,IF(AP25="Muy en Desacuerdo",0.66,IF(AP25="Totalmente en Desacuerdo",1,"error")))))) -> -0.66 | AR25: Totalmente de Acuerdo | AS25: =IF(AR25="Totalmente de Acuerdo",1,IF(AR25="Muy de Acuerdo",0.66,IF(AR25="Levemente de Acuerdo",0.33,IF(AR25="Levemente en Desacuerdo",-0.33,IF(AR25="Muy en Desacuerdo",-0.66,IF(AR25="Totalmente en Desacuerdo",-1,"error")))))) -> 1 | AT25: Muy de Acuerdo | AU25: =IF(AT25="Totalmente de Acuerdo",-1,IF(AT25="Muy de Acuerdo",-0.66,IF(AT25="Levemente de Acuerdo",-0.33,IF(AT25="Levemente en Desacuerdo",0.33,IF(AT25="Muy en Desacuerdo",0.66,IF(AT25="Totalmente en Desacuerdo",1,"error")))))) -> -0.66 | AV25: =+AU25+AS25+AQ25+AO25+AM25+AK25+AI25+AG25+AE25 -> 1.34 | AW25: Totalmente de Acuerdo | AX25: Totalmente de Acuerdo | AY25: Muy de Acuerdo | AZ25: Muy en Desacuerdo | BA25: Muy en Desacuerdo | BB25: Levemente en Desacuerdo | BC25: Levemente de Acuerdo | BD25: Muy de Acuerdo | BE25: Levemente de Acuerdo | BF25: Muy de Acuerdo | BG25: Muy de Acuerdo | BH25: Me identifico | BM25: Me identifico | BR25: Me identifico | BX25: Javier Milei (La Libertad Avanza) | BY25: Javier Milei (La Libertad Avanza) | BZ25: Javier Milei (La Libertad Avanza)
A26: 45547.9 | B26: 00712484148 | C26: 2002 | D26: Quinto año | E26: Varón | F26: Universitario incompleto | G26: Universitario incompleto | H26: Clase Media Alta (C2): entre $1.350.001 mensuales y $2.850.000 mensuales | I26: Familia | J26: Ciudad de Córdoba | K26: , | L26: Muy de Acuerdo | M26: =IF(L26="Totalmente de Acuerdo",-1,IF(L26="Muy de Acuerdo",-0.66,IF(L26="Levemente de Acuerdo",-0.33,IF(L26="Levemente en Desacuerdo",0.33,IF(L26="Muy en Desacuerdo",0.66,IF(L26="Totalmente en Desacuerdo",1,"error")))))) -> -0.66 | N26: Muy en Desacuerdo | O26: =IF(N26="Totalmente de Acuerdo",1,IF(N26="Muy de Acuerdo",0.66,IF(N26="Levemente de Acuerdo",0.33,IF(N26="Levemente en Desacuerdo",-0.33,IF(N26="Muy en Desacuerdo",-0.66,IF(N26="Totalmente en Desacuerdo",-1,"error")))))) -> -0.66 | P26: Totalmente de Acuerdo | Q26: =IF(P26="Totalmente de Acuerdo",-1,IF(P26="Muy de Acuerdo",-0.66,IF(P26="Levemente de Acuerdo",-0.33,IF(P26="Levemente en Desacuerdo",0.33,IF(P26="Muy en Desacuerdo",0.66,IF(P26="Totalmente en Desacuerdo",1,"error")))))) -> -1 | R26: Levemente de Acuerdo | S26: =IF(R26="Totalmente de Acuerdo",1,IF(R26="Muy de Acuerdo",0.66,IF(R26="Levemente de Acuerdo",0.33,IF(R26="Levemente en Desacuerdo",-0.33,IF(R26="Muy en Desacuerdo",-0.66,IF(R26="Totalmente en Desacuerdo",-1,"error")))))) -> 0.33 | T26: Levemente en Desacuerdo | U26: =IF(T26="Totalmente de Acuerdo",-1,IF(T26="Muy de Acuerdo",-0.66,IF(T26="Levemente de Acuerdo",-0.33,IF(T26="Levemente en Desacuerdo",0.33,IF(T26="Muy en Desacuerdo",0.66,IF(T26="Totalmente en Desacuerdo",1,"error")))))) -> 0.33 | V26: Levemente de Acuerdo | W26: =IF(V26="Totalmente de Acuerdo",1,IF(V26="Muy de Acuerdo",0.66,IF(V26="Levemente de Acuerdo",0.33,IF(V26="Levemente en Desacuerdo",-0.33,IF(V26="Muy en Desacuerdo",-0.66,IF(V26="Totalmente en Desacuerdo",-1,"error")))))) -> 0.33 | X26: Muy en Desacuerdo | Y26: =IF(X26="Totalmente de Acuerdo",1,IF(X26="Muy de Acuerdo",0.66,IF(X26="Levemente de Acuerdo",0.33,IF(X26="Levemente en Desacuerdo",-0.33,IF(X26="Muy en Desacuerdo",-0.66,IF(X26="Totalmente en Desacuerdo",-1,"error")))))) -> -0.66 | Z26: Totalmente en Desacuerdo | AA26: =IF(Z26="Totalmente de Acuerdo",1,IF(Z26="Muy de Acuerdo",0.66,IF(Z26="Levemente en Acuerdo",0.33,IF(Z26="Levemente en Desacuerdo",-0.33,IF(Z26="Muy en Desacuerdo",-0.66,IF(Z26="Totalmente en Desacuerdo",-1,"error")))))) -> -1 | AB26: =+AA26+Y26+W26+U26+S26+Q26+O26+M26 -> -2.99 | AC26: =+AB26*AB$29 -> -3.36375 | AD26: Totalmente en Desacuerdo | AE26: =IF(AD26="Totalmente de Acuerdo",1,IF(AD26="Muy de Acuerdo",0.66,IF(AD26="Levemente de Acuerdo",0.33,IF(AD26="Levemente en Desacuerdo",-0.33,IF(AD26="Muy en Desacuerdo",-0.66,IF(AD26="Totalmente en Desacuerdo",-1,"error")))))) -> -1 | AF26: Muy de Acuerdo | AG26: =IF(AF26="Totalmente de Acuerdo",-1,IF(AF26="Muy de Acuerdo",-0.66,IF(AF26="Levemente de Acuerdo",-0.33,IF(AF26="Levemente en Desacuerdo",0.33,IF(AF26="Muy en Desacuerdo",0.66,IF(AF26="Totalmente en Desacuerdo",1,"error")))))) -> -0.66 | AH26: Levemente en Desacuerdo | AI26: =IF(AH26="Totalmente de Acuerdo",1,IF(AH26="Muy de Acuerdo",0.66,IF(AH26="Levemente de Acuerdo",0.33,IF(AH26="Levemente en Desacuerdo",-0.33,IF(AH26="Muy en Desacuerdo",-0.66,IF(AH26="Totalmente en Desacuerdo",-1,"error")))))) -> -0.33 | AJ26: Totalmente en Desacuerdo | AK26: =IF(AJ26="Totalmente de Acuerdo",1,IF(AJ26="Muy de Acuerdo",0.66,IF(AJ26="Levemente de Acuerdo",0.33,IF(AJ26="Levemente en Desacuerdo",-0.33,IF(AJ26="Muy en Desacuerdo",-0.66,IF(AJ26="Totalmente en Desacuerdo",-1,"error")))))) -> -1 | AL26: Totalmente de Acuerdo | AM26: =IF(AL26="Totalmente de Acuerdo",-1,IF(AL26="Muy de Acuerdo",-0.66,IF(AL26="Levemente de Acuerdo",-0.33,IF(AL26="Levemente en Desacuerdo",0.33,IF(AL26="Muy en Desacuerdo",0.66,IF(AL26="Totalmente en Desacuerdo",1,"error")))))) -> -1 | AN26: Muy de Acuerdo | AO26: =IF(AN26="Totalmente de Acuerdo",-1,IF(AN26="Muy de Acuerdo",-0.66,IF(AN26="Levemente de Acuerdo",-0.33,IF(AN26="Levemente en Desacuerdo",0.33,IF(AN26="Muy en Desacuerdo",0.66,IF(AN26="Totalmente en Desacuerdo",1,"error")))))) -> -0.66 | AP26: Muy en Desacuerdo | AQ26: =IF(AP26="Totalmente de Acuerdo",-1,IF(AP26="Muy de Acuerdo",-0.66,IF(AP26="Levemente de Acuerdo",-0.33,IF(AP26="Levemente en Desacuerdo",0.33,IF(AP26="Muy en Desacuerdo",0.66,IF(AP26="Totalmente en Desacuerdo",1,"error")))))) -> 0.66 | AR26: Levemente de Acuerdo | AS26: =IF(AR26="Totalmente de Acuerdo",1,IF(AR26="Muy de Acuerdo",0.66,IF(AR26="Levemente de Acuerdo",0.33,IF(AR26="Levemente en Desacuerdo",-0.33,IF(AR26="Muy en Desacuerdo",-0.66,IF(AR26="Totalmente en Desacuerdo",-1,"error")))))) -> 0.33 | AT26: Totalmente en Desacuerdo | AU26: =IF(AT26="Totalmente de Acuerdo",-1,IF(AT26="Muy de Acuerdo",-0.66,IF(AT26="Levemente de Acuerdo",-0.33,IF(AT26="Levemente en Desacuerdo",0.33,IF(AT26="Muy en Desacuerdo",0.66,IF(AT26="Totalmente en Desacuerdo",1,"error")))))) -> 1 | AV26: =+AU26+AS26+AQ26+AO26+AM26+AK26+AI26+AG26+AE26 -> -2.66 | AW26: Levemente en Desacuerdo | AX26: Levemente de Acuerdo | AY26: Levemente de Acuerdo | AZ26: Muy de Acuerdo | BA26: Levemente de Acuerdo | BB26: Levemente en Desacuerdo | BC26: Levemente en Desacuerdo | BD26: Levemente en Desacuerdo | BE26: Muy en Desacuerdo | BF26: Totalmente de Acuerdo | BG26: Totalmente en Desacuerdo | BJ26: Me identifico | BX26: Javier Milei (La Libertad Avanza) | BY26: Javier Milei (La Libertad Avanza) | BZ26: Javier Milei (La Libertad Avanza)
A27: 45574.834 | B27: 00713342916 | C27: 2002 | D27: Quinto año | E27: Varón | F27: Secundario completo | G27: Universitario completo | H27: Clase Baja Superior (D1): entre $773.501 y $850.000 mensuales | I27: Familia | J27: Otra localidad en la Provincia de Córdoba | K27: , | L27: Levemente en Desacuerdo | M27: =IF(L27="Totalmente de Acuerdo",-1,IF(L27="Muy de Acuerdo",-0.66,IF(L27="Levemente de Acuerdo",-0.33,IF(L27="Levemente en Desacuerdo",0.33,IF(L27="Muy en Desacuerdo",0.66,IF(L27="Totalmente en Desacuerdo",1,"error")))))) -> 0.33 | N27: Levemente en Desacuerdo | O27: =IF(N27="Totalmente de Acuerdo",1,IF(N27="Muy de Acuerdo",0.66,IF(N27="Levemente de Acuerdo",0.33,IF(N27="Levemente en Desacuerdo",-0.33,IF(N27="Muy en Desacuerdo",-0.66,IF(N27="Totalmente en Desacuerdo",-1,"error")))))) -> -0.33 | P27: Muy de Acuerdo | Q27: =IF(P27="Totalmente de Acuerdo",-1,IF(P27="Muy de Acuerdo",-0.66,IF(P27="Levemente de Acuerdo",-0.33,IF(P27="Levemente en Desacuerdo",0.33,IF(P27="Muy en Desacuerdo",0.66,IF(P27="Totalmente en Desacuerdo",1,"error")))))) -> -0.66 | R27: Levemente en Desacuerdo | S27: =IF(R27="Totalmente de Acuerdo",1,IF(R27="Muy de Acuerdo",0.66,IF(R27="Levemente de Acuerdo",0.33,IF(R27="Levemente en Desacuerdo",-0.33,IF(R27="Muy en Desacuerdo",-0.66,IF(R27="Totalmente en Desacuerdo",-1,"error")))))) -> -0.33 | T27: Levemente en Desacuerdo | U27: =IF(T27="Totalmente de Acuerdo",-1,IF(T27="Muy de Acuerdo",-0.66,IF(T27="Levemente de Acuerdo",-0.33,IF(T27="Levemente en Desacuerdo",0.33,IF(T27="Muy en Desacuerdo",0.66,IF(T27="Totalmente en Desacuerdo",1,"error")))))) -> 0.33 | V27: Muy de Acuerdo | W27: =IF(V27="Totalmente de Acuerdo",1,IF(V27="Muy de Acuerdo",0.66,IF(V27="Levemente de Acuerdo",0.33,IF(V27="Levemente en Desacuerdo",-0.33,IF(V27="Muy en Desacuerdo",-0.66,IF(V27="Totalmente en Desacuerdo",-1,"error")))))) -> 0.66 | X27: Levemente de Acuerdo | Y27: =IF(X27="Totalmente de Acuerdo",1,IF(X27="Muy de Acuerdo",0.66,IF(X27="Levemente de Acuerdo",0.33,IF(X27="Levemente en Desacuerdo",-0.33,IF(X27="Muy en Desacuerdo",-0.66,IF(X27="Totalmente en Desacuerdo",-1,"error")))))) -> 0.33 | Z27: Levemente en Acuerdo | AA27: =IF(Z27="Totalmente de Acuerdo",1,IF(Z27="Muy de Acuerdo",0.66,IF(Z27="Levemente en Acuerdo",0.33,IF(Z27="Levemente en Desacuerdo",-0.33,IF(Z27="Muy en Desacuerdo",-0.66,IF(Z27="Totalmente en Desacuerdo",-1,"error")))))) -> 0.33 | AB27: =+AA27+Y27+W27+U27+S27+Q27+O27+M27 -> 0.66 | AC27: =+AB27*AB$29 -> 0.7425 | AD27: Levemente de Acuerdo | AE27: =IF(AD27="Totalmente de Acuerdo",1,IF(AD27="Muy de Acuerdo",0.66,IF(AD27="Levemente de Acuerdo",0.33,IF(AD27="Levemente en Desacuerdo",-0.33,IF(AD27="Muy en Desacuerdo",-0.66,IF(AD27="Totalmente en Desacuerdo",-1,"error")))))) -> 0.33 | AF27: Levemente en Desacuerdo | AG27: =IF(AF27="Totalmente de Acuerdo",-1,IF(AF27="Muy de Acuerdo",-0.66,IF(AF27="Levemente de Acuerdo",-0.33,IF(AF27="Levemente en Desacuerdo",0.33,IF(AF27="Muy en Desacuerdo",0.66,IF(AF27="Totalmente en Desacuerdo",1,"error")))))) -> 0.33 | AH27: Levemente en Desacuerdo | AI27: =IF(AH27="Totalmente de Acuerdo",1,IF(AH27="Muy de Acuerdo",0.66,IF(AH27="Levemente de Acuerdo",0.33,IF(AH27="Levemente en Desacuerdo",-0.33,IF(AH27="Muy en Desacuerdo",-0.66,IF(AH27="Totalmente en Desacuerdo",-1,"error")))))) -> -0.33 | AJ27: Levemente en Desacuerdo | AK27: =IF(AJ27="Totalmente de Acuerdo",1,IF(AJ27="Muy de Acuerdo",0.66,IF(AJ27="Levemente de Acuerdo",0.33,IF(AJ27="Levemente en Desacuerdo",-0.33,IF(AJ27="Muy en Desacuerdo",-0.66,IF(AJ27="Totalmente en Desacuerdo",-1,"error")))))) -> -0.33 | AL27: Muy de Acuerdo | AM27: =IF(AL27="Totalmente de Acuerdo",-1,IF(AL27="Muy de Acuerdo",-0.66,IF(AL27="Levemente de Acuerdo",-0.33,IF(AL27="Levemente en Desacuerdo",0.33,IF(AL27="Muy en Desacuerdo",0.66,IF(AL27="Totalmente en Desacuerdo",1,"error")))))) -> -0.66 | AN27: Levemente en Desacuerdo | AO27: =IF(AN27="Totalmente de Acuerdo",-1,IF(AN27="Muy de Acuerdo",-0.66,IF(AN27="Levemente de Acuerdo",-0.33,IF(AN27="Levemente en Desacuerdo",0.33,IF(AN27="Muy en Desacuerdo",0.66,IF(AN27="Totalmente en Desacuerdo",1,"error")))))) -> 0.33 | AP27: Levemente de Acuerdo | AQ27: =IF(AP27="Totalmente de Acuerdo",-1,IF(AP27="Muy de Acuerdo",-0.66,IF(AP27="Levemente de Acuerdo",-0.33,IF(AP27="Levemente en Desacuerdo",0.33,IF(AP27="Muy en Desacuerdo",0.66,IF(AP27="Totalmente en Desacuerdo",1,"error")))))) -> -0.33 | AR27: Levemente de Acuerdo | AS27: =IF(AR27="Totalmente de Acuerdo",1,IF(AR27="Muy de Acuerdo",0.66,IF(AR27="Levemente de Acuerdo",0.33,IF(AR27="Levemente en Desacuerdo",-0.33,IF(AR27="Muy en Desacuerdo",-0.66,IF(AR27="Totalmente en Desacuerdo",-1,"error")))))) -> 0.33 | AT27: Muy en Desacuerdo | AU27: =IF(AT27="Totalmente de Acuerdo",-1,IF(AT27="Muy de Acuerdo",-0.66,IF(AT27="Levemente de Acuerdo",-0.33,IF(AT27="Levemente en Desacuerdo",0.33,IF(AT27="Muy en Desacuerdo",0.66,IF(AT27="Totalmente en Desacuerdo",1,"error")))))) -> 0.66 | AV27: =+AU27+AS27+AQ27+AO27+AM27+AK27+AI27+AG27+AE27 -> 0.33 | AW27: Muy de Acuerdo | AX27: Levemente en Desacuerdo | AY27: Levemente de Acuerdo | AZ27: Levemente de Acuerdo | BA27: Levemente de Acuerdo | BB27: Levemente en Desacuerdo | BC27: Levemente en Desacuerdo | BD27: Levemente en Desacuerdo | BE27: Levemente en Desacuerdo | BF27: Levemente de Acuerdo | BG27: Totalmente de Acuerdo | BJ27: Me identifico | BX27: No voté | BY27: Juan Schiaretti (Hacemos por Nuestro País) | BZ27: En blanco
AB29: =9/8 -> 1.125

Sheet ejes1
A1: Número de Trámite DNI | B1: eje econ1 | C1: eje social1 | D1: generales | E1: ballotage
A2: 00157138797 | B2: =+'1° Encuesta Filtrada'!AC3 -> -2.2275 | C2: =+'1° Encuesta Filtrada'!AV3 -> 0.32 | D2: =+'1° Encuesta Filtrada'!BY3 -> Sergio Massa (Unión por la Patria) | E2: =+'1° Encuesta Filtrada'!BZ3 -> Sergio Massa (Unión por la Patria)
A3: 00164890275 | B3: =+'1° Encuesta Filtrada'!AC4 -> -2.98125 | C3: =+'1° Encuesta Filtrada'!AV4 -> -3.98 | D3: =+'1° Encuesta Filtrada'!BY4 -> Sergio Massa (Unión por la Patria) | E3: =+'1° Encuesta Filtrada'!BZ4 -> Sergio Massa (Unión por la Patria)
A4: 00284397411 | B4: =+'1° Encuesta Filtrada'!AC5 -> -5.6025 | C4: =+'1° Encuesta Filtrada'!AV5 -> -4.66 | D4: =+'1° Encuesta Filtrada'!BY5 -> Sergio Massa (Unión por la Patria) | E4: =+'1° Encuesta Filtrada'!BZ5 -> Sergio Massa (Unión por la Patria)
A5: 00305830361 | B5: =+'1° Encuesta Filtrada'!AC6 -> -0.7425 | C5: =+'1° Encuesta Filtrada'!AV6 -> -1.65 | D5: =+'1° Encuesta Filtrada'!BY6 -> Juan Schiaretti (Hacemos por Nuestro País) | E5: =+'1° Encuesta Filtrada'!BZ6 -> En blanco
A6: 00338374873 | B6: =+'1° Encuesta Filtrada'!AC7 -> -1.485 | C6: =+'1° Encuesta Filtrada'!AV7 -> -1.34 | D6: =+'1° Encuesta Filtrada'!BY7 -> Javier Milei (La Libertad Avanza) | E6: =+'1° Encuesta Filtrada'!BZ7 -> Javier Milei (La Libertad Avanza)
A7: 003420609968086 | B7: =+'1° Encuesta Filtrada'!AC8 -> -2.59875 | C7: =+'1° Encuesta Filtrada'!AV8 -> -1.99 | D7: =+'1° Encuesta Filtrada'!BY8 -> En blanco | E7: =+'1° Encuesta Filtrada'!BZ8 -> En blanco
A8: 00344474148 | B8: =+'1° Encuesta Filtrada'!AC9 -> 4.095 | C8: =+'1° Encuesta Filtrada'!AV9 -> 0.01 | D8: =+'1° Encuesta Filtrada'!BY9 -> En blanco | E8: =+'1° Encuesta Filtrada'!BZ9 -> En blanco
A9: 004551455698171 | B9: =+'1° Encuesta Filtrada'!AC10 -> 0.37125 | C9: =+'1° Encuesta Filtrada'!AV10 -> 0.02 | D9: =+'1° Encuesta Filtrada'!BY10 -> En blanco | E9: =+'1° Encuesta Filtrada'!BZ10 -> En blanco
A10: 00506717796 | B10: =+'1° Encuesta Filtrada'!AC11 -> 0.37125 | C10: =+'1° Encuesta Filtrada'!AV11 -> -0.99 | D10: =+'1° Encuesta Filtrada'!BY11 -> Javier Milei (La Libertad Avanza) | E10: =+'1° Encuesta Filtrada'!BZ11 -> Javier Milei (La Libertad Avanza)
A11: 00513759005 | B11: =+'1° Encuesta Filtrada'!AC12 -> -1.5075 | C11: =+'1° Encuesta Filtrada'!AV12 -> 0.33 | D11: =+'1° Encuesta Filtrada'!BY12 -> Patricia Bullrich (Juntos por el Cambio) | E11: =+'1° Encuesta Filtrada'!BZ12 -> Javier Milei (La Libertad Avanza)
A12: 00516733809 | B12: =+'1° Encuesta Filtrada'!AC13 -> 3.735 | C12: =+'1° Encuesta Filtrada'!AV13 -> 0 | D12: =+'1° Encuesta Filtrada'!BY13 -> Javier Milei (La Libertad Avanza) | E12: =+'1° Encuesta Filtrada'!BZ13 -> Javier Milei (La Libertad Avanza)
A13: 00531671249 | B13: =+'1° Encuesta Filtrada'!AC14 -> -0.75375 | C13: =+'1° Encuesta Filtrada'!AV14 -> -1.33 | D13: =+'1° Encuesta Filtrada'!BY14 -> Patricia Bullrich (Juntos por el Cambio) | E13: =+'1° Encuesta Filtrada'!BZ14 -> Javier Milei (La Libertad Avanza)
... A26: 00713342916 | B26: =+'1° Encuesta Filtrada'!AC27 -> 0.7425 | C26: =+'1° Encuesta Filtrada'!AV27 -> 0.33 | D26: =+'1° Encuesta Filtrada'!BY27 -> Juan Schiaretti (Hacemos por Nuestro País) | E26: =+'1° Encuesta Filtrada'!BZ27 -> En blanco

Sheet 2° Encuesta Filtrada
G1: eje economico | Y1: eje social
A2: Marca temporal | B2: Número de Trámite DNI | C2: Año de nacimiento | D2: Año de cursado. La mayoría de las materias obligatorias que cursaste en 2024 son de: | E2: ¿Con qué identidad de género se identifica? | F2: . | G2: Privatizar Aerolíneas Argentinas, el Banco Nación y ARSAT | H2: puntos | I2: Ley para que jueces y magistrados paguen Impuesto a las Ganancias | J2: puntos | K2: Una reforma impositiva que reduzca el IVA e implemente un impuesto a la riqueza | L2: puntos | M2: Eliminar totalmente retenciones a las exportaciones y aranceles a la importación | N2: puntos | O2: La política de Etiquetado Frontal (octógonos) en el mercado alimentario | P2: puntos | Q2: Renovar condicionalmente el cobro del Plan Potenciar Trabajo sujeto a evidencia de búsqueda activa de empleo | R2: puntos | S2: Debe eliminarse la Tarjeta Alimentar y utilizar esos fondos para reducir cargas sociales a las PYMES | T2: puntos | U2: Sancionar una Ley de Responsabilidad Social Empresaria con foco en cambio climático y programas de desarrollo comunitario. | V2: puntos | W2: Suma eje econ | X2: eje econ reescalado | Y2: El gobierno debe limitar los viajes a Brasil en enero de 2025 para evitar la introducción de Zika y Chikungunya en Argentina | Z2: PUNTOS | AA2: La Ley de Paridad de Género en Ámbitos de Representación Política | AB2: PUNTOS | AC2: El Estado debe garantizar que exista al menos un médico que no sea objetor de conciencia en cada hospital público | AD2: PUNTOS | AE2: Implementar en Argentina regulaciones de contaminación, como cupos de emisiones de dióxido de carbono | AF2: PUNTOS | AG2: Disolver el Instituto Nacional de Cine y Artes Audiovisuales (INCAA) | AH2: PUNTOS | AI2: Reducir la edad de imputabilidad a los 14 años de edad | AJ2: PUNTOS | AK2: Arancelar las universidades a extranjeros | AL2: PUNTOS | AM2: La Federación Internacional de Tennis debería equiparar los salarios de tenistas profesionales hombres y mujeres | AN2: PUNTOS | AO2: El Estado debe incluir la vacuna del Covid en el Calendario Obligatorio de Vacunación | AP2: PUNTOS | AQ2: suma eje social
A3: 45587.75 | B3: 00157138797 | C3: 1997 | D3: Quinto año | E3: Varón | F3: . | G3: Levemente en Desacuerdo | H3: =IF(G3="Totalmente de Acuerdo",1,IF(G3="Muy de Acuerdo",0.66,IF(G3="Levemente de Acuerdo",0.33,IF(G3="Levemente en Desacuerdo",-0.33,IF(G3="Muy en Desacuerdo",-0.66,IF(G3="Totalmente en Desacuerdo",-1,"error")))))) -> -0.33 | I3: Totalmente de Acuerdo | J3: =IF(I3="Totalmente de Acuerdo",-1,IF(I3="Muy de Acuerdo",-0.66,IF(I3="Levemente de Acuerdo",-0.33,IF(I3="Levemente en Desacuerdo",0.33,IF(I3="Muy en Desacuerdo",0.66,IF(I3="Totalmente en Desacuerdo",1,"error")))))) -> -1 | K3: Levemente de Acuerdo | L3: =IF(K3="Totalmente de Acuerdo",-1,IF(K3="Muy de Acuerdo",-0.66,IF(K3="Levemente de Acuerdo",-0.33,IF(K3="Levemente en Desacuerdo",0.33,IF(K3="Muy en Desacuerdo",0.66,IF(K3="Totalmente en Desacuerdo",1,"error")))))) -> -0.33 | M3: Levemente en Desacuerdo | N3: =IF(M3="Totalmente de Acuerdo",1,IF(M3="Muy de Acuerdo",0.66,IF(M3="Levemente de Acuerdo",0.33,IF(M3="Levemente en Desacuerdo",-0.33,IF(M3="Muy en Desacuerdo",-0.66,IF(M3="Totalmente en Desacuerdo",-1,"error")))))) -> -0.33 | O3: Levemente de Acuerdo | P3: =IF(O3="Totalmente de Acuerdo",-1,IF(O3="Muy de Acuerdo",-0.66,IF(O3="Levemente de Acuerdo",-0.33,IF(O3="Levemente en Desacuerdo",0.33,IF(O3="Muy en Desacuerdo",0.66,IF(O3="Totalmente en Desacuerdo",1,"error")))))) -> -0.33 | Q3: Levemente de Acuerdo | R3: =IF(Q3="Totalmente de Acuerdo",1,IF(Q3="Muy de Acuerdo",0.66,IF(Q3="Levemente de Acuerdo",0.33,IF(Q3="Levemente en Desacuerdo",-0.33,IF(Q3="Muy en Desacuerdo",-0.66,IF(Q3="Totalmente en Desacuerdo",-1,"error")))))) -> 0.33 | S3: Muy de Acuerdo | T3: =IF(S3="Totalmente de Acuerdo",1,IF(S3="Muy de Acuerdo",0.66,IF(S3="Levemente de Acuerdo",0.33,IF(S3="Levemente en Desacuerdo",-0.33,IF(S3="Muy en Desacuerdo",-0.66,IF(S3="Totalmente en Desacuerdo",-1,"error")))))) -> 0.66 | U3: Muy en Desacuerdo | V3: =IF(U3="Totalmente de Acuerdo",-1,IF(U3="Muy de Acuerdo",-0.66,IF(U3="Levemente de Acuerdo",-0.33,IF(U3="Levemente en Desacuerdo",0.33,IF(U3="Muy en Desacuerdo",0.66,IF(U3="Totalmente en Desacuerdo",1,"error")))))) -> 0.66 | W3: =V3+T3+R3+P3+N3+L3+J3+H3 -> -0.67 | X3: =+W3*W$29 -> -0.75375 | Y3: Totalmente en Desacuerdo | Z3: =IF(Y3="Totalmente de Acuerdo",1,IF(Y3="Muy de Acuerdo",0.66,IF(Y3="Levemente de Acuerdo",0.33,IF(Y3="Levemente en Desacuerdo",-0.33,IF(Y3="Muy en Desacuerdo",-0.66,IF(Y3="Totalmente en Desacuerdo",-1,"error")))))) -> -1 | AA3: Muy de Acuerdo | AB3: =IF(AA3="Totalmente de Acuerdo",-1,IF(AA3="Muy de Acuerdo",-0.66,IF(AA3="Levemente de Acuerdo",-0.33,IF(AA3="Levemente en Desacuerdo",0.33,IF(AA3="Muy en Desacuerdo",0.66,IF(AA3="Totalmente en Desacuerdo",1,"error")))))) -> -0.66 | AC3: Muy en Desacuerdo | AD3: =IF(AC3="Totalmente de Acuerdo",-1,IF(AC3="Muy de Acuerdo",-0.66,IF(AC3="Levemente de Acuerdo",-0.33,IF(AC3="Levemente en Desacuerdo",0.33,IF(AC3="Muy en Desacuerdo",0.66,IF(AC3="Totalmente en Desacuerdo",1,"error")))))) -> 0.66 | AE3: Levemente de Acuerdo | AF3: =IF(AE3="Totalmente de Acuerdo",1,IF(AE3="Muy de Acuerdo",0.66,IF(AE3="Levemente de Acuerdo",0.33,IF(AE3="Levemente en Desacuerdo",-0.33,IF(AE3="Muy en Desacuerdo",-0.66,IF(AE3="Totalmente en Desacuerdo",-1,"error")))))) -> 0.33 | AG3: Totalmente en Desacuerdo | AH3: =IF(AG3="Totalmente de Acuerdo",1,IF(AG3="Muy de Acuerdo",0.66,IF(AG3="Levemente de Acuerdo",0.33,IF(AG3="Levemente en Desacuerdo",-0.33,IF(AG3="Muy en Desacuerdo",-0.66,IF(AG3="Totalmente en Desacuerdo",-1,"error")))))) -> -1 | AI3: Levemente en Desacuerdo | AJ3: =IF(AI3="Totalmente de Acuerdo",1,IF(AI3="Muy de Acuerdo",0.66,IF(AI3="Levemente de Acuerdo",0.33,IF(AI3="Levemente en Desacuerdo",-0.33,IF(AI3="Muy en Desacuerdo",-0.66,IF(AI3="Totalmente en Desacuerdo",-1,"error")))))) -> -0.33 | AK3: Levemente de Acuerdo | AL3: =IF(AK3="Totalmente de Acuerdo",1,IF(AK3="Muy de Acuerdo",0.66,IF(AK3="Levemente de Acuerdo",0.33,IF(AK3="Levemente en Desacuerdo",-0.33,IF(AK3="Muy en Desacuerdo",-0.66,IF(AK3="Totalmente en Desacuerdo",-1,"error")))))) -> 0.33 | AM3: Muy en Desacuerdo | AN3: =IF(AM3="Totalmente de Acuerdo",-1,IF(AM3="Muy de Acuerdo",-0.66,IF(AM3="Levemente de Acuerdo",-0.33,IF(AM3="Levemente en Desacuerdo",0.33,IF(AM3="Muy en Desacuerdo",0.66,IF(AM3="Totalmente en Desacuerdo",1,"error")))))) -> 0.66 | AO3: Totalmente en Desacuerdo | AP3: =IF(AO3="Totalmente de Acuerdo",1,IF(AO3="Muy de Acuerdo",0.66,IF(AO3="Levemente de Acuerdo",0.33,IF(AO3="Levemente en Desacuerdo",-0.33,IF(AO3="Muy en Desacuerdo",-0.66,IF(AO3="Totalmente en Desacuerdo",-1,"error")))))) -> -1 | AQ3: =+AP3+AN3+AL3+AJ3+AH3+AF3+AD3+AB3+Z3 -> -2.01
A4: 45592.959 | B4: 00164890275 | C4: 1998 | D4: Quinto año | E4: Varón | F4: . | G4: Muy en Desacuerdo | H4: =IF(G4="Totalmente de Acuerdo",1,IF(G4="Muy de Acuerdo",0.66,IF(G4="Levemente de Acuerdo",0.33,IF(G4="Levemente en Desacuerdo",-0.33,IF(G4="Muy en Desacuerdo",-0.66,IF(G4="Totalmente en Desacuerdo",-1,"error")))))) -> -0.66 | I4: Totalmente de Acuerdo | J4: =IF(I4="Totalmente de Acuerdo",-1,IF(I4="Muy de Acuerdo",-0.66,IF(I4="Levemente de Acuerdo",-0.33,IF(I4="Levemente en Desacuerdo",0.33,IF(I4="Muy en Desacuerdo",0.66,IF(I4="Totalmente en Desacuerdo",1,"error")))))) -> -1 | K4: Levemente en Desacuerdo | L4: =IF(K4="Totalmente de Acuerdo",-1,IF(K4="Muy de Acuerdo",-0.66,IF(K4="Levemente de Acuerdo",-0.33,IF(K4="Levemente en Desacuerdo",0.33,IF(K4="Muy en Desacuerdo",0.66,IF(K4="Totalmente en Desacuerdo",1,"error")))))) -> 0.33 | M4: Muy en Desacuerdo | N4: =IF(M4="Totalmente de Acuerdo",1,IF(M4="Muy de Acuerdo",0.66,IF(M4="Levemente de Acuerdo",0.33,IF(M4="Levemente en Desacuerdo",-0.33,IF(M4="Muy en Desacuerdo",-0.66,IF(M4="Totalmente en Desacuerdo",-1,"error")))))) -> -0.66 | O4: Totalmente de Acuerdo | P4: =IF(O4="Totalmente de Acuerdo",-1,IF(O4="Muy de Acuerdo",-0.66,IF(O4="Levemente de Acuerdo",-0.33,IF(O4="Levemente en Desacuerdo",0.33,IF(O4="Muy en Desacuerdo",0.66,IF(O4="Totalmente en Desacuerdo",1,"error")))))) -> -1 | Q4: Totalmente de Acuerdo | R4: =IF(Q4="Totalmente de Acuerdo",1,IF(Q4="Muy de Acuerdo",0.66,IF(Q4="Levemente de Acuerdo",0.33,IF(Q4="Levemente en Desacuerdo",-0.33,IF(Q4="Muy en Desacuerdo",-0.66,IF(Q4="Totalmente en Desacuerdo",-1,"error")))))) -> 1 | S4: Totalmente en Desacuerdo | T4: =IF(S4="Totalmente de Acuerdo",1,IF(S4="Muy de Acuerdo",0.66,IF(S4="Levemente de Acuerdo",0.33,IF(S4="Levemente en Desacuerdo",-0.33,IF(S4="Muy en Desacuerdo",-0.66,IF(S4="Totalmente en Desacuerdo",-1,"error")))))) -> -1 | U4: Levemente en Desacuerdo | V4: =IF(U4="Totalmente de Acuerdo",-1,IF(U4="Muy de Acuerdo",-0.66,IF(U4="Levemente de Acuerdo",-0.33,IF(U4="Levemente en Desacuerdo",0.33,IF(U4="Muy en Desacuerdo",0.66,IF(U4="Totalmente en Desacuerdo",1,"error")))))) -> 0.33 | W4: =+V4+T4+R4+P4+N4+L4+J4+H4 -> -2.66 | X4: =+W4*W$29 -> -2.9925 | Y4: Totalmente en Desacuerdo | Z4: =IF(Y4="Totalmente de Acuerdo",1,IF(Y4="Muy de Acuerdo",0.66,IF(Y4="Levemente de Acuerdo",0.33,IF(Y4="Levemente en Desacuerdo",-0.33,IF(Y4="Muy en Desacuerdo",-0.66,IF(Y4="Totalmente en Desacuerdo",-1,"error")))))) -> -1 | AA4: Levemente en Desacuerdo | AB4: =IF(AA4="Totalmente de Acuerdo",-1,IF(AA4="Muy de Acuerdo",-0.66,IF(AA4="Levemente de Acuerdo",-0.33,IF(AA4="Levemente en Desacuerdo",0.33,IF(AA4="Muy en Desacuerdo",0.66,IF(AA4="Totalmente en Desacuerdo",1,"error")))))) -> 0.33 | AC4: Levemente de Acuerdo | AD4: =IF(AC4="Totalmente de Acuerdo",-1,IF(AC4="Muy de Acuerdo",-0.66,IF(AC4="Levemente de Acuerdo",-0.33,IF(AC4="Levemente en Desacuerdo",0.33,IF(AC4="Muy en Desacuerdo",0.66,IF(AC4="Totalmente en Desacuerdo",1,"error")))))) -> -0.33 | AE4: Totalmente de Acuerdo | AF4: =IF(AE4="Totalmente de Acuerdo",1,IF(AE4="Muy de Acuerdo",0.66,IF(AE4="Levemente de Acuerdo",0.33,IF(AE4="Levemente en Desacuerdo",-0.33,IF(AE4="Muy en Desacuerdo",-0.66,IF(AE4="Totalmente en Desacuerdo",-1,"error")))))) -> 1 | AG4: Muy en Desacuerdo | AH4: =IF(AG4="Totalmente de Acuerdo",1,IF(AG4="Muy de Acuerdo",0.66,IF(AG4="Levemente de Acuerdo",0.33,IF(AG4="Levemente en Desacuerdo",-0.33,IF(AG4="Muy en Desacuerdo",-0.66,IF(AG4="Totalmente en Desacuerdo",-1,"error")))))) -> -0.66 | AI4: Muy en Desacuerdo | AJ4: =IF(AI4="Totalmente de Acuerdo",1,IF(AI4="Muy de Acuerdo",0.66,IF(AI4="Levemente de Acuerdo",0.33,IF(AI4="Levemente en Desacuerdo",-0.33,IF(AI4="Muy en Desacuerdo",-0.66,IF(AI4="Totalmente en Desacuerdo",-1,"error")))))) -> -0.66 | AK4: Muy en Desacuerdo | AL4: =IF(AK4="Totalmente de Acuerdo",1,IF(AK4="Muy de Acuerdo",0.66,IF(AK4="Levemente de Acuerdo",0.33,IF(AK4="Levemente en Desacuerdo",-0.33,IF(AK4="Muy en Desacuerdo",-0.66,IF(AK4="Totalmente en Desacuerdo",-1,"error")))))) -> -0.66 | AM4: Muy en Desacuerdo | AN4: =IF(AM4="Totalmente de Acuerdo",-1,IF(AM4="Muy de Acuerdo",-0.66,IF(AM4="Levemente de Acuerdo",-0.33,IF(AM4="Levemente en Desacuerdo",0.33,IF(AM4="Muy en Desacuerdo",0.66,IF(AM4="Totalmente en Desacuerdo",1,"error")))))) -> 0.66 | AO4: Levemente de Acuerdo | AP4: =IF(AO4="Totalmente de Acuerdo",1,IF(AO4="Muy de Acuerdo",0.66,IF(AO4="Levemente de Acuerdo",0.33,IF(AO4="Levemente en Desacuerdo",-0.33,IF(AO4="Muy en Desacuerdo",-0.66,IF(AO4="Totalmente en Desacuerdo",-1,"error")))))) -> 0.33 | AQ4: =+AP4+AN4+AL4+AJ4+AH4+AF4+AD4+AB4+Z4 -> -0.99
A5: 45601.777 | B5: 00284397411 | C5: 1999 | D5: Cuarto año | E5: Otra | F5: . | G5: Totalmente en Desacuerdo | H5: =IF(G5="Totalmente de Acuerdo",1,IF(G5="Muy de Acuerdo",0.66,IF(G5="Levemente de Acuerdo",0.33,IF(G5="Levemente en Desacuerdo",-0.33,IF(G5="Muy en Desacuerdo",-0.66,IF(G5="Totalmente en Desacuerdo",-1,"error")))))) -> -1 | I5: Totalmente de Acuerdo | J5: =IF(I5="Totalmente de Acuerdo",-1,IF(I5="Muy de Acuerdo",-0.66,IF(I5="Levemente de Acuerdo",-0.33,IF(I5="Levemente en Desacuerdo",0.33,IF(I5="Muy en Desacuerdo",0.66,IF(I5="Totalmente en Desacuerdo",1,"error")))))) -> -1 | K5: Totalmente de Acuerdo | L5: =IF(K5="Totalmente de Acuerdo",-1,IF(K5="Muy de Acuerdo",-0.66,IF(K5="Levemente de Acuerdo",-0.33,IF(K5="Levemente en Desacuerdo",0.33,IF(K5="Muy en Desacuerdo",0.66,IF(K5="Totalmente en Desacuerdo",1,"error")))))) -> -1 | M5: Muy en Desacuerdo | N5: =IF(M5="Totalmente de Acuerdo",1,IF(M5="Muy de Acuerdo",0.66,IF(M5="Levemente de Acuerdo",0.33,IF(M5="Levemente en Desacuerdo",-0.33,IF(M5="Muy en Desacuerdo",-0.66,IF(M5="Totalmente en Desacuerdo",-1,"error")))))) -> -0.66 | O5: Muy de Acuerdo | P5: =IF(O5="Totalmente de Acuerdo",-1,IF(O5="Muy de Acuerdo",-0.66,IF(O5="Levemente de Acuerdo",-0.33,IF(O5="Levemente en Desacuerdo",0.33,IF(O5="Muy en Desacuerdo",0.66,IF(O5="Totalmente en Desacuerdo",1,"error")))))) -> -0.66 | Q5: Levemente en Desacuerdo | R5: =IF(Q5="Totalmente de Acuerdo",1,IF(Q5="Muy de Acuerdo",0.66,IF(Q5="Levemente de Acuerdo",0.33,IF(Q5="Levemente en Desacuerdo",-0.33,IF(Q5="Muy en Desacuerdo",-0.66,IF(Q5="Totalmente en Desacuerdo",-1,"error")))))) -> -0.33 | S5: Muy en Desacuerdo | T5: =IF(S5="Totalmente de Acuerdo",1,IF(S5="Muy de Acuerdo",0.66,IF(S5="Levemente de Acuerdo",0.33,IF(S5="Levemente en Desacuerdo",-0.33,IF(S5="Muy en Desacuerdo",-0.66,IF(S5="Totalmente en Desacuerdo",-1,"error")))))) -> -0.66 | U5: Muy de Acuerdo | V5: =IF(U5="Totalmente de Acuerdo",-1,IF(U5="Muy de Acuerdo",-0.66,IF(U5="Levemente de Acuerdo",-0.33,IF(U5="Levemente en Desacuerdo",0.33,IF(U5="Muy en Desacuerdo",0.66,IF(U5="Totalmente en Desacuerdo",1,"error")))))) -> -0.66 | W5: =+V5+T5+R5+P5+N5+L5+J5+H5 -> -5.97 | X5: =+W5*W$29 -> -6.71625 | Y5: Levemente en Desacuerdo | Z5: =IF(Y5="Totalmente de Acuerdo",1,IF(Y5="Muy de Acuerdo",0.66,IF(Y5="Levemente de Acuerdo",0.33,IF(Y5="Levemente en Desacuerdo",-0.33,IF(Y5="Muy en Desacuerdo",-0.66,IF(Y5="Totalmente en Desacuerdo",-1,"error")))))) -> -0.33 | AA5: Totalmente de Acuerdo | AB5: =IF(AA5="Totalmente de Acuerdo",-1,IF(AA5="Muy de Acuerdo",-0.66,IF(AA5="Levemente de Acuerdo",-0.33,IF(AA5="Levemente en Desacuerdo",0.33,IF(AA5="Muy en Desacuerdo",0.66,IF(AA5="Totalmente en Desacuerdo",1,"error")))))) -> -1 | AC5: Muy de Acuerdo | AD5: =IF(AC5="Totalmente de Acuerdo",-1,IF(AC5="Muy de Acuerdo",-0.66,IF(AC5="Levemente de Acuerdo",-0.33,IF(AC5="Levemente en Desacuerdo",0.33,IF(AC5="Muy en Desacuerdo",0.66,IF(AC5="Totalmente en Desacuerdo",1,"error")))))) -> -0.66 | AE5: Levemente de Acuerdo | AF5: =IF(AE5="Totalmente de Acuerdo",1,IF(AE5="Muy de Acuerdo",0.66,IF(AE5="Levemente de Acuerdo",0.33,IF(AE5="Levemente en Desacuerdo",-0.33,IF(AE5="Muy en Desacuerdo",-0.66,IF(AE5="Totalmente en Desacuerdo",-1,"error")))))) -> 0.33 | AG5: Totalmente en Desacuerdo | AH5: =IF(AG5="Totalmente de Acuerdo",1,IF(AG5="Muy de Acuerdo",0.66,IF(AG5="Levemente de Acuerdo",0.33,IF(AG5="Levemente en Desacuerdo",-0.33,IF(AG5="Muy en Desacuerdo",-0.66,IF(AG5="Totalmente en Desacuerdo",-1,"error")))))) -> -1 | AI5: Muy en Desacuerdo | AJ5: =IF(AI5="Totalmente de Acuerdo",1,IF(AI5="Muy de Acuerdo",0.66,IF(AI5="Levemente de Acuerdo",0.33,IF(AI5="Levemente en Desacuerdo",-0.33,IF(AI5="Muy en Desacuerdo",-0.66,IF(AI5="Totalmente en Desacuerdo",-1,"error")))))) -> -0.66 | AK5: Muy en Desacuerdo | AL5: =IF(AK5="Totalmente de Acuerdo",1,IF(AK5="Muy de Acuerdo",0.66,IF(AK5="Levemente de Acuerdo",0.33,IF(AK5="Levemente en Desacuerdo",-0.33,IF(AK5="Muy en Desacuerdo",-0.66,IF(AK5="Totalmente en Desacuerdo",-1,"error")))))) -> -0.66 | AM5: Muy de Acuerdo | AN5: =IF(AM5="Totalmente de Acuerdo",-1,IF(AM5="Muy de Acuerdo",-0.66,IF(AM5="Levemente de Acuerdo",-0.33,IF(AM5="Levemente en Desacuerdo",0.33,IF(AM5="Muy en Desacuerdo",0.66,IF(AM5="Totalmente en Desacuerdo",1,"error")))))) -> -0.66 | AO5: Levemente de Acuerdo | AP5: =IF(AO5="Totalmente de Acuerdo",1,IF(AO5="Muy de Acuerdo",0.66,IF(AO5="Levemente de Acuerdo",0.33,IF(AO5="Levemente en Desacuerdo",-0.33,IF(AO5="Muy en Desacuerdo",-0.66,IF(AO5="Totalmente en Desacuerdo",-1,"error")))))) -> 0.33 | AQ5: =+AP5+AN5+AL5+AJ5+AH5+AF5+AD5+AB5+Z5 -> -4.31
A6: 45589.546 | B6: 00305830361 | C6: 2000 | D6: Cuarto año | E6: Mujer | F6: . | G6: Levemente en Desacuerdo | H6: =IF(G6="Totalmente de Acuerdo",1,IF(G6="Muy de Acuerdo",0.66,IF(G6="Levemente de Acuerdo",0.33,IF(G6="Levemente en Desacuerdo",-0.33,IF(G6="Muy en Desacuerdo",-0.66,IF(G6="Totalmente en Desacuerdo",-1,"error")))))) -> -0.33 | I6: Totalmente de Acuerdo | J6: =IF(I6="Totalmente de Acuerdo",-1,IF(I6="Muy de Acuerdo",-0.66,IF(I6="Levemente de Acuerdo",-0.33,IF(I6="Levemente en Desacuerdo",0.33,IF(I6="Muy en Desacuerdo",0.66,IF(I6="Totalmente en Desacuerdo",1,"error")))))) -> -1 | K6: Levemente de Acuerdo | L6: =IF(K6="Totalmente de Acuerdo",-1,IF(K6="Muy de Acuerdo",-0.66,IF(K6="Levemente de Acuerdo",-0.33,IF(K6="Levemente en Desacuerdo",0.33,IF(K6="Muy en Desacuerdo",0.66,IF(K6="Totalmente en Desacuerdo",1,"error")))))) -> -0.33 | M6: Muy en Desacuerdo | N6: =IF(M6="Totalmente de Acuerdo",1,IF(M6="Muy de Acuerdo",0.66,IF(M6="Levemente de Acuerdo",0.33,IF(M6="Levemente en Desacuerdo",-0.33,IF(M6="Muy en Desacuerdo",-0.66,IF(M6="Totalmente en Desacuerdo",-1,"error")))))) -> -0.66 | O6: Totalmente de Acuerdo | P6: =IF(O6="Totalmente de Acuerdo",-1,IF(O6="Muy de Acuerdo",-0.66,IF(O6="Levemente de Acuerdo",-0.33,IF(O6="Levemente en Desacuerdo",0.33,IF(O6="Muy en Desacuerdo",0.66,IF(O6="Totalmente en Desacuerdo",1,"error")))))) -> -1 | Q6: Totalmente de Acuerdo | R6: =IF(Q6="Totalmente de Acuerdo",1,IF(Q6="Muy de Acuerdo",0.66,IF(Q6="Levemente de Acuerdo",0.33,IF(Q6="Levemente en Desacuerdo",-0.33,IF(Q6="Muy en Desacuerdo",-0.66,IF(Q6="Totalmente en Desacuerdo",-1,"error")))))) -> 1 | S6: Levemente en Desacuerdo | T6: =IF(S6="Totalmente de Acuerdo",1,IF(S6="Muy de Acuerdo",0.66,IF(S6="Levemente de Acuerdo",0.33,IF(S6="Levemente en Desacuerdo",-0.33,IF(S6="Muy en Desacuerdo",-0.66,IF(S6="Totalmente en Desacuerdo",-1,"error")))))) -> -0.33 | U6: Levemente en Acuerdo | V6: =IF(U6="Totalmente de Acuerdo",-1,IF(U6="Muy de Acuerdo",-0.66,IF(U6="Levemente en Acuerdo",-0.33,IF(U6="Levemente en Desacuerdo",0.33,IF(U6="Muy en Desacuerdo",0.66,IF(U6="Totalmente en Desacuerdo",1,"error")))))) -> -0.33 | W6: =+V6+T6+R6+P6+N6+L6+J6+H6 -> -2.98 | X6: =+W6*W$29 -> -3.3525 | Y6: Muy en Desacuerdo | Z6: =IF(Y6="Totalmente de Acuerdo",1,IF(Y6="Muy de Acuerdo",0.66,IF(Y6="Levemente de Acuerdo",0.33,IF(Y6="Levemente en Desacuerdo",-0.33,IF(Y6="Muy en Desacuerdo",-0.66,IF(Y6="Totalmente en Desacuerdo",-1,"error")))))) -> -0.66 | AA6: Totalmente en Desacuerdo | AB6: =IF(AA6="Totalmente de Acuerdo",-1,IF(AA6="Muy de Acuerdo",-0.66,IF(AA6="Levemente de Acuerdo",-0.33,IF(AA6="Levemente en Desacuerdo",0.33,IF(AA6="Muy en Desacuerdo",0.66,IF(AA6="Totalmente en Desacuerdo",1,"error")))))) -> 1 | AC6: Levemente en Desacuerdo | AD6: =IF(AC6="Totalmente de Acuerdo",-1,IF(AC6="Muy de Acuerdo",-0.66,IF(AC6="Levemente de Acuerdo",-0.33,IF(AC6="Levemente en Desacuerdo",0.33,IF(AC6="Muy en Desacuerdo",0.66,IF(AC6="Totalmente en Desacuerdo",1,"error")))))) -> 0.33 | AE6: Muy de Acuerdo | AF6: =IF(AE6="Totalmente de Acuerdo",1,IF(AE6="Muy de Acuerdo",0.66,IF(AE6="Levemente de Acuerdo",0.33,IF(AE6="Levemente en Desacuerdo",-0.33,IF(AE6="Muy en Desacuerdo",-0.66,IF(AE6="Totalmente en Desacuerdo",-1,"error")))))) -> 0.66 | AG6: Muy en Desacuerdo | AH6: =IF(AG6="Totalmente de Acuerdo",1,IF(AG6="Muy de Acuerdo",0.66,IF(AG6="Levemente de Acuerdo",0.33,IF(AG6="Levemente en Desacuerdo",-0.33,IF(AG6="Muy en Desacuerdo",-0.66,IF(AG6="Totalmente en Desacuerdo",-1,"error")))))) -> -0.66 | AI6: Totalmente en Desacuerdo | AJ6: =IF(AI6="Totalmente de Acuerdo",1,IF(AI6="Muy de Acuerdo",0.66,IF(AI6="Levemente de Acuerdo",0.33,IF(AI6="Levemente en Desacuerdo",-0.33,IF(AI6="Muy en Desacuerdo",-0.66,IF(AI6="Totalmente en Desacuerdo",-1,"error")))))) -> -1 | AK6: Muy de Acuerdo | AL6: =IF(AK6="Totalmente de Acuerdo",1,IF(AK6="Muy de Acuerdo",0.66,IF(AK6="Levemente de Acuerdo",0.33,IF(AK6="Levemente en Desacuerdo",-0.33,IF(AK6="Muy en Desacuerdo",-0.66,IF(AK6="Totalmente en Desacuerdo",-1,"error")))))) -> 0.66 | AM6: Muy en Desacuerdo | AN6: =IF(AM6="Totalmente de Acuerdo",-1,IF(AM6="Muy de Acuerdo",-0.66,IF(AM6="Levemente de Acuerdo",-0.33,IF(AM6="Levemente en Desacuerdo",0.33,IF(AM6="Muy en Desacuerdo",0.66,IF(AM6="Totalmente en Desacuerdo",1,"error")))))) -> 0.66 | AO6: Levemente de Acuerdo | AP6: =IF(AO6="Totalmente de Acuerdo",1,IF(AO6="Muy de Acuerdo",0.66,IF(AO6="Levemente de Acuerdo",0.33,IF(AO6="Levemente en Desacuerdo",-0.33,IF(AO6="Muy en Desacuerdo",-0.66,IF(AO6="Totalmente en Desacuerdo",-1,"error")))))) -> 0.33 | AQ6: =+AP6+AN6+AL6+AJ6+AH6+AF6+AD6+AB6+Z6 -> 1.32
A7: 45587.737 | B7: 00338374873 | C7: 2000 | D7: Quinto año | E7: Mujer | F7: . | G7: Levemente de Acuerdo | H7: =IF(G7="Totalmente de Acuerdo",1,IF(G7="Muy de Acuerdo",0.66,IF(G7="Levemente de Acuerdo",0.33,IF(G7="Levemente en Desacuerdo",-0.33,IF(G7="Muy en Desacuerdo",-0.66,IF(G7="Totalmente en Desacuerdo",-1,"error")))))) -> 0.33 | I7: Levemente de Acuerdo | J7: =IF(I7="Totalmente de Acuerdo",-1,IF(I7="Muy de Acuerdo",-0.66,IF(I7="Levemente de Acuerdo",-0.33,IF(I7="Levemente en Desacuerdo",0.33,IF(I7="Muy en Desacuerdo",0.66,IF(I7="Totalmente en Desacuerdo",1,"error")))))) -> -0.33 | K7: Levemente en Desacuerdo | L7: =IF(K7="Totalmente de Acuerdo",-1,IF(K7="Muy de Acuerdo",-0.66,IF(K7="Levemente de Acuerdo",-0.33,IF(K7="Levemente en Desacuerdo",0.33,IF(K7="Muy en Desacuerdo",0.66,IF(K7="Totalmente en Desacuerdo",1,"error")))))) -> 0.33 | M7: Muy de Acuerdo | N7: =IF(M7="Totalmente de Acuerdo",1,IF(M7="Muy de Acuerdo",0.66,IF(M7="Levemente de Acuerdo",0.33,IF(M7="Levemente en Desacuerdo",-0.33,IF(M7="Muy en Desacuerdo",-0.66,IF(M7="Totalmente en Desacuerdo",-1,"error")))))) -> 0.66 | O7: Levemente de Acuerdo | P7: =IF(O7="Totalmente de Acuerdo",-1,IF(O7="Muy de Acuerdo",-0.66,IF(O7="Levemente de Acuerdo",-0.33,IF(O7="Levemente en Desacuerdo",0.33,IF(O7="Muy en Desacuerdo",0.66,IF(O7="Totalmente en Desacuerdo",1,"error")))))) -> -0.33 | Q7: Levemente de Acuerdo | R7: =IF(Q7="Totalmente de Acuerdo",1,IF(Q7="Muy de Acuerdo",0.66,IF(Q7="Levemente de Acuerdo",0.33,IF(Q7="Levemente en Desacuerdo",-0.33,IF(Q7="Muy en Desacuerdo",-0.66,IF(Q7="Totalmente en Desacuerdo",-1,"error")))))) -> 0.33 | S7: Levemente en Desacuerdo | T7: =IF(S7="Totalmente de Acuerdo",1,IF(S7="Muy de Acuerdo",0.66,IF(S7="Levemente de Acuerdo",0.33,IF(S7="Levemente en Desacuerdo",-0.33,IF(S7="Muy en Desacuerdo",-0.66,IF(S7="Totalmente en Desacuerdo",-1,"error")))))) -> -0.33 | U7: Levemente en Desacuerdo | V7: =IF(U7="Totalmente de Acuerdo",-1,IF(U7="Muy de Acuerdo",-0.66,IF(U7="Levemente en Acuerdo",-0.33,IF(U7="Levemente en Desacuerdo",0.33,IF(U7="Muy en Desacuerdo",0.66,IF(U7="Totalmente en Desacuerdo",1,"error")))))) -> 0.33 | W7: =+V7+T7+R7+P7+N7+L7+J7+H7 -> 0.99 | X7: =+W7*W$29 -> 1.11375 | Y7: Totalmente en Desacuerdo | Z7: =IF(Y7="Totalmente de Acuerdo",1,IF(Y7="Muy de Acuerdo",0.66,IF(Y7="Levemente de Acuerdo",0.33,IF(Y7="Levemente en Desacuerdo",-0.33,IF(Y7="Muy en Desacuerdo",-0.66,IF(Y7="Totalmente en Desacuerdo",-1,"error")))))) -> -1 | AA7: Levemente de Acuerdo | AB7: =IF(AA7="Totalmente de Acuerdo",-1,IF(AA7="Muy de Acuerdo",-0.66,IF(AA7="Levemente de Acuerdo",-0.33,IF(AA7="Levemente en Desacuerdo",0.33,IF(AA7="Muy en Desacuerdo",0.66,IF(AA7="Totalmente en Desacuerdo",1,"error")))))) -> -0.33 | AC7: Muy de Acuerdo | AD7: =IF(AC7="Totalmente de Acuerdo",-1,IF(AC7="Muy de Acuerdo",-0.66,IF(AC7="Levemente de Acuerdo",-0.33,IF(AC7="Levemente en Desacuerdo",0.33,IF(AC7="Muy en Desacuerdo",0.66,IF(AC7="Totalmente en Desacuerdo",1,"error")))))) -> -0.66 | AE7: Levemente de Acuerdo | AF7: =IF(AE7="Totalmente de Acuerdo",1,IF(AE7="Muy de Acuerdo",0.66,IF(AE7="Levemente de Acuerdo",0.33,IF(AE7="Levemente en Desacuerdo",-0.33,IF(AE7="Muy en Desacuerdo",-0.66,IF(AE7="Totalmente en Desacuerdo",-1,"error")))))) -> 0.33 | AG7: Levemente en Desacuerdo | AH7: =IF(AG7="Totalmente de Acuerdo",1,IF(AG7="Muy de Acuerdo",0.66,IF(AG7="Levemente de Acuerdo",0.33,IF(AG7="Levemente en Desacuerdo",-0.33,IF(AG7="Muy en Desacuerdo",-0.66,IF(AG7="Totalmente en Desacuerdo",-1,"error")))))) -> -0.33 | AI7: Muy de Acuerdo | AJ7: =IF(AI7="Totalmente de Acuerdo",1,IF(AI7="Muy de Acuerdo",0.66,IF(AI7="Levemente de Acuerdo",0.33,IF(AI7="Levemente en Desacuerdo",-0.33,IF(AI7="Muy en Desacuerdo",-0.66,IF(AI7="Totalmente en Desacuerdo",-1,"error")))))) -> 0.66 | AK7: Muy de Acuerdo | AL7: =IF(AK7="Totalmente de Acuerdo",1,IF(AK7="Muy de Acuerdo",0.66,IF(AK7="Levemente de Acuerdo",0.33,IF(AK7="Levemente en Desacuerdo",-0.33,IF(AK7="Muy en Desacuerdo",-0.66,IF(AK7="Totalmente en Desacuerdo",-1,"error")))))) -> 0.66 | AM7: Levemente de Acuerdo | AN7: =IF(AM7="Totalmente de Acuerdo",-1,IF(AM7="Muy de Acuerdo",-0.66,IF(AM7="Levemente de Acuerdo",-0.33,IF(AM7="Levemente en Desacuerdo",0.33,IF(AM7="Muy en Desacuerdo",0.66,IF(AM7="Totalmente en Desacuerdo",1,"error")))))) -> -0.33 | AO7: Levemente de Acuerdo | AP7: =IF(AO7="Totalmente de Acuerdo",1,IF(AO7="Muy de Acuerdo",0.66,IF(AO7="Levemente de Acuerdo",0.33,IF(AO7="Levemente en Desacuerdo",-0.33,IF(AO7="Muy en Desacuerdo",-0.66,IF(AO7="Totalmente en Desacuerdo",-1,"error")))))) -> 0.33 | AQ7: =+AP7+AN7+AL7+AJ7+AH7+AF7+AD7+AB7+Z7 -> -0.67
A8: 45587.736 | B8: 003420609968086 | C8: 2000 | D8: Quinto año | E8: Varón | F8: . | G8: Levemente de Acuerdo | H8: =IF(G8="Totalmente de Acuerdo",1,IF(G8="Muy de Acuerdo",0.66,IF(G8="Levemente de Acuerdo",0.33,IF(G8="Levemente en Desacuerdo",-0.33,IF(G8="Muy en Desacuerdo",-0.66,IF(G8="Totalmente en Desacuerdo",-1,"error")))))) -> 0.33 | I8: Totalmente de Acuerdo | J8: =IF(I8="Totalmente de Acuerdo",-1,IF(I8="Muy de Acuerdo",-0.66,IF(I8="Levemente de Acuerdo",-0.33,IF(I8="Levemente en Desacuerdo",0.33,IF(I8="Muy en Desacuerdo",0.66,IF(I8="Totalmente en Desacuerdo",1,"error")))))) -> -1 | K8: Muy de Acuerdo | L8: =IF(K8="Totalmente de Acuerdo",-1,IF(K8="Muy de Acuerdo",-0.66,IF(K8="Levemente de Acuerdo",-0.33,IF(K8="Levemente en Desacuerdo",0.33,IF(K8="Muy en Desacuerdo",0.66,IF(K8="Totalmente en Desacuerdo",1,"error")))))) -> -0.66 | M8: Levemente de Acuerdo | N8: =IF(M8="Totalmente de Acuerdo",1,IF(M8="Muy de Acuerdo",0.66,IF(M8="Levemente de Acuerdo",0.33,IF(M8="Levemente en Desacuerdo",-0.33,IF(M8="Muy en Desacuerdo",-0.66,IF(M8="Totalmente en Desacuerdo",-1,"error")))))) -> 0.33 | O8: Levemente de Acuerdo | P8: =IF(O8="Totalmente de Acuerdo",-1,IF(O8="Muy de Acuerdo",-0.66,IF(O8="Levemente de Acuerdo",-0.33,IF(O8="Levemente en Desacuerdo",0.33,IF(O8="Muy en Desacuerdo",0.66,IF(O8="Totalmente en Desacuerdo",1,"error")))))) -> -0.33 | Q8: Muy de Acuerdo | R8: =IF(Q8="Totalmente de Acuerdo",1,IF(Q8="Muy de Acuerdo",0.66,IF(Q8="Levemente de Acuerdo",0.33,IF(Q8="Levemente en Desacuerdo",-0.33,IF(Q8="Muy en Desacuerdo",-0.66,IF(Q8="Totalmente en Desacuerdo",-1,"error")))))) -> 0.66 | S8: Levemente en Desacuerdo | T8: =IF(S8="Totalmente de Acuerdo",1,IF(S8="Muy de Acuerdo",0.66,IF(S8="Levemente de Acuerdo",0.33,IF(S8="Levemente en Desacuerdo",-0.33,IF(S8="Muy en Desacuerdo",-0.66,IF(S8="Totalmente en Desacuerdo",-1,"error")))))) -> -0.33 | U8: Levemente en Acuerdo | V8: =IF(U8="Totalmente de Acuerdo",-1,IF(U8="Muy de Acuerdo",-0.66,IF(U8="Levemente en Acuerdo",-0.33,IF(U8="Levemente en Desacuerdo",0.33,IF(U8="Muy en Desacuerdo",0.66,IF(U8="Totalmente en Desacuerdo",1,"error")))))) -> -0.33 | W8: =+V8+T8+R8+P8+N8+L8+J8+H8 -> -1.33 | X8: =+W8*W$29 -> -1.49625 | Y8: Totalmente en Desacuerdo | Z8: =IF(Y8="Totalmente de Acuerdo",1,IF(Y8="Muy de Acuerdo",0.66,IF(Y8="Levemente de Acuerdo",0.33,IF(Y8="Levemente en Desacuerdo",-0.33,IF(Y8="Muy en Desacuerdo",-0.66,IF(Y8="Totalmente en Desacuerdo",-1,"error")))))) -> -1 | AA8: Levemente de Acuerdo | AB8: =IF(AA8="Totalmente de Acuerdo",-1,IF(AA8="Muy de Acuerdo",-0.66,IF(AA8="Levemente de Acuerdo",-0.33,IF(AA8="Levemente en Desacuerdo",0.33,IF(AA8="Muy en Desacuerdo",0.66,IF(AA8="Totalmente en Desacuerdo",1,"error")))))) -> -0.33 | AC8: Levemente de Acuerdo | AD8: =IF(AC8="Totalmente de Acuerdo",-1,IF(AC8="Muy de Acuerdo",-0.66,IF(AC8="Levemente de Acuerdo",-0.33,IF(AC8="Levemente en Desacuerdo",0.33,IF(AC8="Muy en Desacuerdo",0.66,IF(AC8="Totalmente en Desacuerdo",1,"error")))))) -> -0.33 | AE8: Levemente de Acuerdo | AF8: =IF(AE8="Totalmente de Acuerdo",1,IF(AE8="Muy de Acuerdo",0.66,IF(AE8="Levemente de Acuerdo",0.33,IF(AE8="Levemente en Desacuerdo",-0.33,IF(AE8="Muy en Desacuerdo",-0.66,IF(AE8="Totalmente en Desacuerdo",-1,"error")))))) -> 0.33 | AG8: Levemente de Acuerdo | AH8: =IF(AG8="Totalmente de Acuerdo",1,IF(AG8="Muy de Acuerdo",0.66,IF(AG8="Levemente de Acuerdo",0.33,IF(AG8="Levemente en Desacuerdo",-0.33,IF(AG8="Muy en Desacuerdo",-0.66,IF(AG8="Totalmente en Desacuerdo",-1,"error")))))) -> 0.33 | AI8: Levemente en Desacuerdo | AJ8: =IF(AI8="Totalmente de Acuerdo",1,IF(AI8="Muy de Acuerdo",0.66,IF(AI8="Levemente de Acuerdo",0.33,IF(AI8="Levemente en Desacuerdo",-0.33,IF(AI8="Muy en Desacuerdo",-0.66,IF(AI8="Totalmente en Desacuerdo",-1,"error")))))) -> -0.33 | AK8: Totalmente de Acuerdo | AL8: =IF(AK8="Totalmente de Acuerdo",1,IF(AK8="Muy de Acuerdo",0.66,IF(AK8="Levemente de Acuerdo",0.33,IF(AK8="Levemente en Desacuerdo",-0.33,IF(AK8="Muy en Desacuerdo",-0.66,IF(AK8="Totalmente en Desacuerdo",-1,"error")))))) -> 1 | AM8: Muy de Acuerdo | AN8: =IF(AM8="Totalmente de Acuerdo",-1,IF(AM8="Muy de Acuerdo",-0.66,IF(AM8="Levemente de Acuerdo",-0.33,IF(AM8="Levemente en Desacuerdo",0.33,IF(AM8="Muy en Desacuerdo",0.66,IF(AM8="Totalmente en Desacuerdo",1,"error")))))) -> -0.66 | AO8: Totalmente de Acuerdo | AP8: =IF(AO8="Totalmente de Acuerdo",1,IF(AO8="Muy de Acuerdo",0.66,IF(AO8="Levemente de Acuerdo",0.33,IF(AO8="Levemente en Desacuerdo",-0.33,IF(AO8="Muy en Desacuerdo",-0.66,IF(AO8="Totalmente en Desacuerdo",-1,"error")))))) -> 1 | AQ8: =+AP8+AN8+AL8+AJ8+AH8+AF8+AD8+AB8+Z8 -> 0.01
A9: 45594.632 | B9: 00344474148 | C9: 1999 | D9: Tercer año | E9: Varón | F9: . | G9: Muy de Acuerdo | H9: =IF(G9="Totalmente de Acuerdo",1,IF(G9="Muy de Acuerdo",0.66,IF(G9="Levemente de Acuerdo",0.33,IF(G9="Levemente en Desacuerdo",-0.33,IF(G9="Muy en Desacuerdo",-0.66,IF(G9="Totalmente en Desacuerdo",-1,"error")))))) -> 0.66 | I9: Totalmente de Acuerdo | J9: =IF(I9="Totalmente de Acuerdo",-1,IF(I9="Muy de Acuerdo",-0.66,IF(I9="Levemente de Acuerdo",-0.33,IF(I9="Levemente en Desacuerdo",0.33,IF(I9="Muy en Desacuerdo",0.66,IF(I9="Totalmente en Desacuerdo",1,"error")))))) -> -1 | K9: Muy de Acuerdo | L9: =IF(K9="Totalmente de Acuerdo",-1,IF(K9="Muy de Acuerdo",-0.66,IF(K9="Levemente de Acuerdo",-0.33,IF(K9="Levemente en Desacuerdo",0.33,IF(K9="Muy en Desacuerdo",0.66,IF(K9="Totalmente en Desacuerdo",1,"error")))))) -> -0.66 | M9: Muy de Acuerdo | N9: =IF(M9="Totalmente de Acuerdo",1,IF(M9="Muy de Acuerdo",0.66,IF(M9="Levemente de Acuerdo",0.33,IF(M9="Levemente en Desacuerdo",-0.33,IF(M9="Muy en Desacuerdo",-0.66,IF(M9="Totalmente en Desacuerdo",-1,"error")))))) -> 0.66 | O9: Totalmente en Desacuerdo | P9: =IF(O9="Totalmente de Acuerdo",-1,IF(O9="Muy de Acuerdo",-0.66,IF(O9="Levemente de Acuerdo",-0.33,IF(O9="Levemente en Desacuerdo",0.33,IF(O9="Muy en Desacuerdo",0.66,IF(O9="Totalmente en Desacuerdo",1,"error")))))) -> 1 | Q9: Muy de Acuerdo | R9: =IF(Q9="Totalmente de Acuerdo",1,IF(Q9="Muy de Acuerdo",0.66,IF(Q9="Levemente de Acuerdo",0.33,IF(Q9="Levemente en Desacuerdo",-0.33,IF(Q9="Muy en Desacuerdo",-0.66,IF(Q9="Totalmente en Desacuerdo",-1,"error")))))) -> 0.66 | S9: Levemente de Acuerdo | T9: =IF(S9="Totalmente de Acuerdo",1,IF(S9="Muy de Acuerdo",0.66,IF(S9="Levemente de Acuerdo",0.33,IF(S9="Levemente en Desacuerdo",-0.33,IF(S9="Muy en Desacuerdo",-0.66,IF(S9="Totalmente en Desacuerdo",-1,"error")))))) -> 0.33 | U9: Levemente en Desacuerdo | V9: =IF(U9="Totalmente de Acuerdo",-1,IF(U9="Muy de Acuerdo",-0.66,IF(U9="Levemente en Acuerdo",-0.33,IF(U9="Levemente en Desacuerdo",0.33,IF(U9="Muy en Desacuerdo",0.66,IF(U9="Totalmente en Desacuerdo",1,"error")))))) -> 0.33 | W9: =+V9+T9+R9+P9+N9+L9+J9+H9 -> 1.98 | X9: =+W9*W$29 -> 2.2275 | Y9: Totalmente en Desacuerdo | Z9: =IF(Y9="Totalmente de Acuerdo",1,IF(Y9="Muy de Acuerdo",0.66,IF(Y9="Levemente de Acuerdo",0.33,IF(Y9="Levemente en Desacuerdo",-0.33,IF(Y9="Muy en Desacuerdo",-0.66,IF(Y9="Totalmente en Desacuerdo",-1,"error")))))) -> -1 | AA9: Totalmente en Desacuerdo | AB9: =IF(AA9="Totalmente de Acuerdo",-1,IF(AA9="Muy de Acuerdo",-0.66,IF(AA9="Levemente de Acuerdo",-0.33,IF(AA9="Levemente en Desacuerdo",0.33,IF(AA9="Muy en Desacuerdo",0.66,IF(AA9="Totalmente en Desacuerdo",1,"error")))))) -> 1 | AC9: Totalmente en Desacuerdo | AD9: =IF(AC9="Totalmente de Acuerdo",-1,IF(AC9="Muy de Acuerdo",-0.66,IF(AC9="Levemente de Acuerdo",-0.33,IF(AC9="Levemente en Desacuerdo",0.33,IF(AC9="Muy en Desacuerdo",0.66,IF(AC9="Totalmente en Desacuerdo",1,"error")))))) -> 1 | AE9: Totalmente en Desacuerdo | AF9: =IF(AE9="Totalmente de Acuerdo",1,IF(AE9="Muy de Acuerdo",0.66,IF(AE9="Levemente de Acuerdo",0.33,IF(AE9="Levemente en Desacuerdo",-0.33,IF(AE9="Muy en Desacuerdo",-0.66,IF(AE9="Totalmente en Desacuerdo",-1,"error")))))) -> -1 | AG9: Totalmente de Acuerdo | AH9: =IF(AG9="Totalmente de Acuerdo",1,IF(AG9="Muy de Acuerdo",0.66,IF(AG9="Levemente de Acuerdo",0.33,IF(AG9="Levemente en Desacuerdo",-0.33,IF(AG9="Muy en Desacuerdo",-0.66,IF(AG9="Totalmente en Desacuerdo",-1,"error")))))) -> 1 | AI9: Levemente en Desacuerdo | AJ9: =IF(AI9="Totalmente de Acuerdo",1,IF(AI9="Muy de Acuerdo",0.66,IF(AI9="Levemente de Acuerdo",0.33,IF(AI9="Levemente en Desacuerdo",-0.33,IF(AI9="Muy en Desacuerdo",-0.66,IF(AI9="Totalmente en Desacuerdo",-1,"error")))))) -> -0.33 | AK9: Totalmente de Acuerdo | AL9: =IF(AK9="Totalmente de Acuerdo",1,IF(AK9="Muy de Acuerdo",0.66,IF(AK9="Levemente de Acuerdo",0.33,IF(AK9="Levemente en Desacuerdo",-0.33,IF(AK9="Muy en Desacuerdo",-0.66,IF(AK9="Totalmente en Desacuerdo",-1,"error")))))) -> 1 | AM9: Totalmente en Desacuerdo | AN9: =IF(AM9="Totalmente de Acuerdo",-1,IF(AM9="Muy de Acuerdo",-0.66,IF(AM9="Levemente de Acuerdo",-0.33,IF(AM9="Levemente en Desacuerdo",0.33,IF(AM9="Muy en Desacuerdo",0.66,IF(AM9="Totalmente en Desacuerdo",1,"error")))))) -> 1 | AO9: Totalmente en Desacuerdo | AP9: =IF(AO9="Totalmente de Acuerdo",1,IF(AO9="Muy de Acuerdo",0.66,IF(AO9="Levemente de Acuerdo",0.33,IF(AO9="Levemente en Desacuerdo",-0.33,IF(AO9="Muy en Desacuerdo",-0.66,IF(AO9="Totalmente en Desacuerdo",-1,"error")))))) -> -1 | AQ9: =+AP9+AN9+AL9+AJ9+AH9+AF9+AD9+AB9+Z9 -> 1.67
A10: 45587.738 | B10: 004551455698171 | C10: 2001 | D10: Cuarto año | E10: Mujer | F10: . | G10: Muy de Acuerdo | H10: =IF(G10="Totalmente de Acuerdo",1,IF(G10="Muy de Acuerdo",0.66,IF(G10="Levemente de Acuerdo",0.33,IF(G10="Levemente en Desacuerdo",-0.33,IF(G10="Muy en Desacuerdo",-0.66,IF(G10="Totalmente en Desacuerdo",-1,"error")))))) -> 0.66 | I10: Levemente de Acuerdo | J10: =IF(I10="Totalmente de Acuerdo",-1,IF(I10="Muy de Acuerdo",-0.66,IF(I10="Levemente de Acuerdo",-0.33,IF(I10="Levemente en Desacuerdo",0.33,IF(I10="Muy en Desacuerdo",0.66,IF(I10="Totalmente en Desacuerdo",1,"error")))))) -> -0.33 | K10: Levemente de Acuerdo | L10: =IF(K10="Totalmente de Acuerdo",-1,IF(K10="Muy de Acuerdo",-0.66,IF(K10="Levemente de Acuerdo",-0.33,IF(K10="Levemente en Desacuerdo",0.33,IF(K10="Muy en Desacuerdo",0.66,IF(K10="Totalmente en Desacuerdo",1,"error")))))) -> -0.33 | M10: Levemente de Acuerdo | N10: =IF(M10="Totalmente de Acuerdo",1,IF(M10="Muy de Acuerdo",0.66,IF(M10="Levemente de Acuerdo",0.33,IF(M10="Levemente en Desacuerdo",-0.33,IF(M10="Muy en Desacuerdo",-0.66,IF(M10="Totalmente en Desacuerdo",-1,"error")))))) -> 0.33 | O10: Muy de Acuerdo | P10: =IF(O10="Totalmente de Acuerdo",-1,IF(O10="Muy de Acuerdo",-0.66,IF(O10="Levemente de Acuerdo",-0.33,IF(O10="Levemente en Desacuerdo",0.33,IF(O10="Muy en Desacuerdo",0.66,IF(O10="Totalmente en Desacuerdo",1,"error")))))) -> -0.66 | Q10: Muy de Acuerdo | R10: =IF(Q10="Totalmente de Acuerdo",1,IF(Q10="Muy de Acuerdo",0.66,IF(Q10="Levemente de Acuerdo",0.33,IF(Q10="Levemente en Desacuerdo",-0.33,IF(Q10="Muy en Desacuerdo",-0.66,IF(Q10="Totalmente en Desacuerdo",-1,"error")))))) -> 0.66 | S10: Levemente en Desacuerdo | T10: =IF(S10="Totalmente de Acuerdo",1,IF(S10="Muy de Acuerdo",0.66,IF(S10="Levemente de Acuerdo",0.33,IF(S10="Levemente en Desacuerdo",-0.33,IF(S10="Muy en Desacuerdo",-0.66,IF(S10="Totalmente en Desacuerdo",-1,"error")))))) -> -0.33 | U10: Muy de Acuerdo | V10: =IF(U10="Totalmente de Acuerdo",-1,IF(U10="Muy de Acuerdo",-0.66,IF(U10="Levemente en Acuerdo",-0.33,IF(U10="Levemente en Desacuerdo",0.33,IF(U10="Muy en Desacuerdo",0.66,IF(U10="Totalmente en Desacuerdo",1,"error")))))) -> -0.66 | W10: =+V10+T10+R10+P10+N10+L10+J10+H10 -> -0.66 | X10: =+W10*W$29 -> -0.7425 | Y10: Muy en Desacuerdo | Z10: =IF(Y10="Totalmente de Acuerdo",1,IF(Y10="Muy de Acuerdo",0.66,IF(Y10="Levemente de Acuerdo",0.33,IF(Y10="Levemente en Desacuerdo",-0.33,IF(Y10="Muy en Desacuerdo",-0.66,IF(Y10="Totalmente en Desacuerdo",-1,"error")))))) -> -0.66 | AA10: Muy de Acuerdo | AB10: =IF(AA10="Totalmente de Acuerdo",-1,IF(AA10="Muy de Acuerdo",-0.66,IF(AA10="Levemente de Acuerdo",-0.33,IF(AA10="Levemente en Desacuerdo",0.33,IF(AA10="Muy en Desacuerdo",0.66,IF(AA10="Totalmente en Desacuerdo",1,"error")))))) -> -0.66 | AC10: Levemente de Acuerdo | AD10: =IF(AC10="Totalmente de Acuerdo",-1,IF(AC10="Muy de Acuerdo",-0.66,IF(AC10="Levemente de Acuerdo",-0.33,IF(AC10="Levemente en Desacuerdo",0.33,IF(AC10="Muy en Desacuerdo",0.66,IF(AC10="Totalmente en Desacuerdo",1,"error")))))) -> -0.33 | AE10: Muy de Acuerdo | AF10: =IF(AE10="Totalmente de Acuerdo",1,IF(AE10="Muy de Acuerdo",0.66,IF(AE10="Levemente de Acuerdo",0.33,IF(AE10="Levemente en Desacuerdo",-0.33,IF(AE10="Muy en Desacuerdo",-0.66,IF(AE10="Totalmente en Desacuerdo",-1,"error")))))) -> 0.66 | AG10: Levemente en Desacuerdo | AH10: =IF(AG10="Totalmente de Acuerdo",1,IF(AG10="Muy de Acuerdo",0.66,IF(AG10="Levemente de Acuerdo",0.33,IF(AG10="Levemente en Desacuerdo",-0.33,IF(AG10="Muy en Desacuerdo",-0.66,IF(AG10="Totalmente en Desacuerdo",-1,"error")))))) -> -0.33 | AI10: Levemente de Acuerdo | AJ10: =IF(AI10="Totalmente de Acuerdo",1,IF(AI10="Muy de Acuerdo",0.66,IF(AI10="Levemente de Acuerdo",0.33,IF(AI10="Levemente en Desacuerdo",-0.33,IF(AI10="Muy en Desacuerdo",-0.66,IF(AI10="Totalmente en Desacuerdo",-1,"error")))))) -> 0.33 | AK10: Muy de Acuerdo | AL10: =IF(AK10="Totalmente de Acuerdo",1,IF(AK10="Muy de Acuerdo",0.66,IF(AK10="Levemente de Acuerdo",0.33,IF(AK10="Levemente en Desacuerdo",-0.33,IF(AK10="Muy en Desacuerdo",-0.66,IF(AK10="Totalmente en Desacuerdo",-1,"error")))))) -> 0.66 | AM10: Muy de Acuerdo | AN10: =IF(AM10="Totalmente de Acuerdo",-1,IF(AM10="Muy de Acuerdo",-0.66,IF(AM10="Levemente de Acuerdo",-0.33,IF(AM10="Levemente en Desacuerdo",0.33,IF(AM10="Muy en Desacuerdo",0.66,IF(AM10="Totalmente en Desacuerdo",1,"error")))))) -> -0.66 | AO10: Levemente de Acuerdo | AP10: =IF(AO10="Totalmente de Acuerdo",1,IF(AO10="Muy de Acuerdo",0.66,IF(AO10="Levemente de Acuerdo",0.33,IF(AO10="Levemente en Desacuerdo",-0.33,IF(AO10="Muy en Desacuerdo",-0.66,IF(AO10="Totalmente en Desacuerdo",-1,"error")))))) -> 0.33 | AQ10: =+AP10+AN10+AL10+AJ10+AH10+AF10+AD10+AB10+Z10 -> -0.66
A11: 45590.799 | B11: 00506717796 | C11: 2001 | D11: Cuarto año | E11: Mujer | F11: . | G11: Totalmente de Acuerdo | H11: =IF(G11="Totalmente de Acuerdo",1,IF(G11="Muy de Acuerdo",0.66,IF(G11="Levemente de Acuerdo",0.33,IF(G11="Levemente en Desacuerdo",-0.33,IF(G11="Muy en Desacuerdo",-0.66,IF(G11="Totalmente en Desacuerdo",-1,"error")))))) -> 1 | I11: Totalmente de Acuerdo | J11: =IF(I11="Totalmente de Acuerdo",-1,IF(I11="Muy de Acuerdo",-0.66,IF(I11="Levemente de Acuerdo",-0.33,IF(I11="Levemente en Desacuerdo",0.33,IF(I11="Muy en Desacuerdo",0.66,IF(I11="Totalmente en Desacuerdo",1,"error")))))) -> -1 | K11: Totalmente de Acuerdo | L11: =IF(K11="Totalmente de Acuerdo",-1,IF(K11="Muy de Acuerdo",-0.66,IF(K11="Levemente de Acuerdo",-0.33,IF(K11="Levemente en Desacuerdo",0.33,IF(K11="Muy en Desacuerdo",0.66,IF(K11="Totalmente en Desacuerdo",1,"error")))))) -> -1 | M11: Levemente de Acuerdo | N11: =IF(M11="Totalmente de Acuerdo",1,IF(M11="Muy de Acuerdo",0.66,IF(M11="Levemente de Acuerdo",0.33,IF(M11="Levemente en Desacuerdo",-0.33,IF(M11="Muy en Desacuerdo",-0.66,IF(M11="Totalmente en Desacuerdo",-1,"error")))))) -> 0.33 | O11: Muy en Desacuerdo | P11: =IF(O11="Totalmente de Acuerdo",-1,IF(O11="Muy de Acuerdo",-0.66,IF(O11="Levemente de Acuerdo",-0.33,IF(O11="Levemente en Desacuerdo",0.33,IF(O11="Muy en Desacuerdo",0.66,IF(O11="Totalmente en Desacuerdo",1,"error")))))) -> 0.66 | Q11: Muy de Acuerdo | R11: =IF(Q11="Totalmente de Acuerdo",1,IF(Q11="Muy de Acuerdo",0.66,IF(Q11="Levemente de Acuerdo",0.33,IF(Q11="Levemente en Desacuerdo",-0.33,IF(Q11="Muy en Desacuerdo",-0.66,IF(Q11="Totalmente en Desacuerdo",-1,"error")))))) -> 0.66 | S11: Muy de Acuerdo | T11: =IF(S11="Totalmente de Acuerdo",1,IF(S11="Muy de Acuerdo",0.66,IF(S11="Levemente de Acuerdo",0.33,IF(S11="Levemente en Desacuerdo",-0.33,IF(S11="Muy en Desacuerdo",-0.66,IF(S11="Totalmente en Desacuerdo",-1,"error")))))) -> 0.66 | U11: Levemente en Acuerdo | V11: =IF(U11="Totalmente de Acuerdo",-1,IF(U11="Muy de Acuerdo",-0.66,IF(U11="Levemente en Acuerdo",-0.33,IF(U11="Levemente en Desacuerdo",0.33,IF(U11="Muy en Desacuerdo",0.66,IF(U11="Totalmente en Desacuerdo",1,"error")))))) -> -0.33 | W11: =+V11+T11+R11+P11+N11+L11+J11+H11 -> 0.98 | X11: =+W11*W$29 -> 1.1025 | Y11: Totalmente en Desacuerdo | Z11: =IF(Y11="Totalmente de Acuerdo",1,IF(Y11="Muy de Acuerdo",0.66,IF(Y11="Levemente de Acuerdo",0.33,IF(Y11="Levemente en Desacuerdo",-0.33,IF(Y11="Muy en Desacuerdo",-0.66,IF(Y11="Totalmente en Desacuerdo",-1,"error")))))) -> -1 | AA11: Levemente en Desacuerdo | AB11: =IF(AA11="Totalmente de Acuerdo",-1,IF(AA11="Muy de Acuerdo",-0.66,IF(AA11="Levemente de Acuerdo",-0.33,IF(AA11="Levemente en Desacuerdo",0.33,IF(AA11="Muy en Desacuerdo",0.66,IF(AA11="Totalmente en Desacuerdo",1,"error")))))) -> 0.33 | AC11: Muy en Desacuerdo | AD11: =IF(AC11="Totalmente de Acuerdo",-1,IF(AC11="Muy de Acuerdo",-0.66,IF(AC11="Levemente de Acuerdo",-0.33,IF(AC11="Levemente en Desacuerdo",0.33,IF(AC11="Muy en Desacuerdo",0.66,IF(AC11="Totalmente en Desacuerdo",1,"error")))))) -> 0.66 | AE11: Muy de Acuerdo | AF11: =IF(AE11="Totalmente de Acuerdo",1,IF(AE11="Muy de Acuerdo",0.66,IF(AE11="Levemente de Acuerdo",0.33,IF(AE11="Levemente en Desacuerdo",-0.33,IF(AE11="Muy en Desacuerdo",-0.66,IF(AE11="Totalmente en Desacuerdo",-1,"error")))))) -> 0.66 | AG11: Levemente en Desacuerdo | AH11: =IF(AG11="Totalmente de Acuerdo",1,IF(AG11="Muy de Acuerdo",0.66,IF(AG11="Levemente de Acuerdo",0.33,IF(AG11="Levemente en Desacuerdo",-0.33,IF(AG11="Muy en Desacuerdo",-0.66,IF(AG11="Totalmente en Desacuerdo",-1,"error")))))) -> -0.33 | AI11: Levemente en Desacuerdo | AJ11: =IF(AI11="Totalmente de Acuerdo",1,IF(AI11="Muy de Acuerdo",0.66,IF(AI11="Levemente de Acuerdo",0.33,IF(AI11="Levemente en Desacuerdo",-0.33,IF(AI11="Muy en Desacuerdo",-0.66,IF(AI11="Totalmente en Desacuerdo",-1,"error")))))) -> -0.33 | AK11: Totalmente de Acuerdo | AL11: =IF(AK11="Totalmente de Acuerdo",1,IF(AK11="Muy de Acuerdo",0.66,IF(AK11="Levemente de Acuerdo",0.33,IF(AK11="Levemente en Desacuerdo",-0.33,IF(AK11="Muy en Desacuerdo",-0.66,IF(AK11="Totalmente en Desacuerdo",-1,"error")))))) -> 1 | AM11: Totalmente en Desacuerdo | AN11: =IF(AM11="Totalmente de Acuerdo",-1,IF(AM11="Muy de Acuerdo",-0.66,IF(AM11="Levemente de Acuerdo",-0.33,IF(AM11="Levemente en Desacuerdo",0.33,IF(AM11="Muy en Desacuerdo",0.66,IF(AM11="Totalmente en Desacuerdo",1,"error")))))) -> 1 | AO11: Totalmente en Desacuerdo | AP11: =IF(AO11="Totalmente de Acuerdo",1,IF(AO11="Muy de Acuerdo",0.66,IF(AO11="Levemente de Acuerdo",0.33,IF(AO11="Levemente en Desacuerdo",-0.33,IF(AO11="Muy en Desacuerdo",-0.66,IF(AO11="Totalmente en Desacuerdo",-1,"error")))))) -> -1 | AQ11: =+AP11+AN11+AL11+AJ11+AH11+AF11+AD11+AB11+Z11 -> 0.99
A12: 45589.016 | B12: 00513759005 | C12: 2002 | D12: Cuarto año | E12: Varón | F12: . | G12: Levemente de Acuerdo | H12: =IF(G12="Totalmente de Acuerdo",1,IF(G12="Muy de Acuerdo",0.66,IF(G12="Levemente de Acuerdo",0.33,IF(G12="Levemente en Desacuerdo",-0.33,IF(G12="Muy en Desacuerdo",-0.66,IF(G12="Totalmente en Desacuerdo",-1,"error")))))) -> 0.33 | I12: Totalmente de Acuerdo | J12: =IF(I12="Totalmente de Acuerdo",-1,IF(I12="Muy de Acuerdo",-0.66,IF(I12="Levemente de Acuerdo",-0.33,IF(I12="Levemente en Desacuerdo",0.33,IF(I12="Muy en Desacuerdo",0.66,IF(I12="Totalmente en Desacuerdo",1,"error")))))) -> -1 | K12: Levemente en Desacuerdo | L12: =IF(K12="Totalmente de Acuerdo",-1,IF(K12="Muy de Acuerdo",-0.66,IF(K12="Levemente de Acuerdo",-0.33,IF(K12="Levemente en Desacuerdo",0.33,IF(K12="Muy en Desacuerdo",0.66,IF(K12="Totalmente en Desacuerdo",1,"error")))))) -> 0.33 | M12: Muy de Acuerdo | N12: =IF(M12="Totalmente de Acuerdo",1,IF(M12="Muy de Acuerdo",0.66,IF(M12="Levemente de Acuerdo",0.33,IF(M12="Levemente en Desacuerdo",-0.33,IF(M12="Muy en Desacuerdo",-0.66,IF(M12="Totalmente en Desacuerdo",-1,"error")))))) -> 0.66 | O12: Levemente de Acuerdo | P12: =IF(O12="Totalmente de Acuerdo",-1,IF(O12="Muy de Acuerdo",-0.66,IF(O12="Levemente de Acuerdo",-0.33,IF(O12="Levemente en Desacuerdo",0.33,IF(O12="Muy en Desacuerdo",0.66,IF(O12="Totalmente en Desacuerdo",1,"error")))))) -> -0.33 | Q12: Levemente de Acuerdo | R12: =IF(Q12="Totalmente de Acuerdo",1,IF(Q12="Muy de Acuerdo",0.66,IF(Q12="Levemente de Acuerdo",0.33,IF(Q12="Levemente en Desacuerdo",-0.33,IF(Q12="Muy en Desacuerdo",-0.66,IF(Q12="Totalmente en Desacuerdo",-1,"error")))))) -> 0.33 | S12: Muy en Desacuerdo | T12: =IF(S12="Totalmente de Acuerdo",1,IF(S12="Muy de Acuerdo",0.66,IF(S12="Levemente de Acuerdo",0.33,IF(S12="Levemente en Desacuerdo",-0.33,IF(S12="Muy en Desacuerdo",-0.66,IF(S12="Totalmente en Desacuerdo",-1,"error")))))) -> -0.66 | U12: Levemente en Acuerdo | V12: =IF(U12="Totalmente de Acuerdo",-1,IF(U12="Muy de Acuerdo",-0.66,IF(U12="Levemente en Acuerdo",-0.33,IF(U12="Levemente en Desacuerdo",0.33,IF(U12="Muy en Desacuerdo",0.66,IF(U12="Totalmente en Desacuerdo",1,"error")))))) -> -0.33 | W12: =+V12+T12+R12+P12+N12+L12+J12+H12 -> -0.67 | X12: =+W12*W$29 -> -0.75375 | Y12: Muy en Desacuerdo | Z12: =IF(Y12="Totalmente de Acuerdo",1,IF(Y12="Muy de Acuerdo",0.66,IF(Y12="Levemente de Acuerdo",0.33,IF(Y12="Levemente en Desacuerdo",-0.33,IF(Y12="Muy en Desacuerdo",-0.66,IF(Y12="Totalmente en Desacuerdo",-1,"error")))))) -> -0.66 | AA12: Levemente en Desacuerdo | AB12: =IF(AA12="Totalmente de Acuerdo",-1,IF(AA12="Muy de Acuerdo",-0.66,IF(AA12="Levemente de Acuerdo",-0.33,IF(AA12="Levemente en Desacuerdo",0.33,IF(AA12="Muy en Desacuerdo",0.66,IF(AA12="Totalmente en Desacuerdo",1,"error")))))) -> 0.33 | AC12: Muy en Desacuerdo | AD12: =IF(AC12="Totalmente de Acuerdo",-1,IF(AC12="Muy de Acuerdo",-0.66,IF(AC12="Levemente de Acuerdo",-0.33,IF(AC12="Levemente en Desacuerdo",0.33,IF(AC12="Muy en Desacuerdo",0.66,IF(AC12="Totalmente en Desacuerdo",1,"error")))))) -> 0.66 | AE12: Muy de Acuerdo | AF12: =IF(AE12="Totalmente de Acuerdo",1,IF(AE12="Muy de Acuerdo",0.66,IF(AE12="Levemente de Acuerdo",0.33,IF(AE12="Levemente en Desacuerdo",-0.33,IF(AE12="Muy en Desacuerdo",-0.66,IF(AE12="Totalmente en Desacuerdo",-1,"error")))))) -> 0.66 | AG12: Muy de Acuerdo | AH12: =IF(AG12="Totalmente de Acuerdo",1,IF(AG12="Muy de Acuerdo",0.66,IF(AG12="Levemente de Acuerdo",0.33,IF(AG12="Levemente en Desacuerdo",-0.33,IF(AG12="Muy en Desacuerdo",-0.66,IF(AG12="Totalmente en Desacuerdo",-1,"error")))))) -> 0.66 | AI12: Muy en Desacuerdo | AJ12: =IF(AI12="Totalmente de Acuerdo",1,IF(AI12="Muy de Acuerdo",0.66,IF(AI12="Levemente de Acuerdo",0.33,IF(AI12="Levemente en Desacuerdo",-0.33,IF(AI12="Muy en Desacuerdo",-0.66,IF(AI12="Totalmente en Desacuerdo",-1,"error")))))) -> -0.66 | AK12: Levemente de Acuerdo | AL12: =IF(AK12="Totalmente de Acuerdo",1,IF(AK12="Muy de Acuerdo",0.66,IF(AK12="Levemente de Acuerdo",0.33,IF(AK12="Levemente en Desacuerdo",-0.33,IF(AK12="Muy en Desacuerdo",-0.66,IF(AK12="Totalmente en Desacuerdo",-1,"error")))))) -> 0.33 | AM12: Muy en Desacuerdo | AN12: =IF(AM12="Totalmente de Acuerdo",-1,IF(AM12="Muy de Acuerdo",-0.66,IF(AM12="Levemente de Acuerdo",-0.33,IF(AM12="Levemente en Desacuerdo",0.33,IF(AM12="Muy en Desacuerdo",0.66,IF(AM12="Totalmente en Desacuerdo",1,"error")))))) -> 0.66 | AO12: Muy de Acuerdo | AP12: =IF(AO12="Totalmente de Acuerdo",1,IF(AO12="Muy de Acuerdo",0.66,IF(AO12="Levemente de Acuerdo",0.33,IF(AO12="Levemente en Desacuerdo",-0.33,IF(AO12="Muy en Desacuerdo",-0.66,IF(AO12="Totalmente en Desacuerdo",-1,"error")))))) -> 0.66 | AQ12: =+AP12+AN12+AL12+AJ12+AH12+AF12+AD12+AB12+Z12 -> 2.64
A13: 45597.797 | B13: 00516733809 | C13: 2002 | D13: Cuarto año | E13: Mujer | F13: . | G13: Totalmente de Acuerdo | H13: =IF(G13="Totalmente de Acuerdo",1,IF(G13="Muy de Acuerdo",0.66,IF(G13="Levemente de Acuerdo",0.33,IF(G13="Levemente en Desacuerdo",-0.33,IF(G13="Muy en Desacuerdo",-0.66,IF(G13="Totalmente en Desacuerdo",-1,"error")))))) -> 1 | I13: Totalmente de Acuerdo | J13: =IF(I13="Totalmente de Acuerdo",-1,IF(I13="Muy de Acuerdo",-0.66,IF(I13="Levemente de Acuerdo",-0.33,IF(I13="Levemente en Desacuerdo",0.33,IF(I13="Muy en Desacuerdo",0.66,IF(I13="Totalmente en Desacuerdo",1,"error")))))) -> -1 | K13: Levemente de Acuerdo | L13: =IF(K13="Totalmente de Acuerdo",-1,IF(K13="Muy de Acuerdo",-0.66,IF(K13="Levemente de Acuerdo",-0.33,IF(K13="Levemente en Desacuerdo",0.33,IF(K13="Muy en Desacuerdo",0.66,IF(K13="Totalmente en Desacuerdo",1,"error")))))) -> -0.33 | M13: Totalmente de Acuerdo | N13: =IF(M13="Totalmente de Acuerdo",1,IF(M13="Muy de Acuerdo",0.66,IF(M13="Levemente de Acuerdo",0.33,IF(M13="Levemente en Desacuerdo",-0.33,IF(M13="Muy en Desacuerdo",-0.66,IF(M13="Totalmente en Desacuerdo",-1,"error")))))) -> 1 | O13: Totalmente de Acuerdo | P13: =IF(O13="Totalmente de Acuerdo",-1,IF(O13="Muy de Acuerdo",-0.66,IF(O13="Levemente de Acuerdo",-0.33,IF(O13="Levemente en Desacuerdo",0.33,IF(O13="Muy en Desacuerdo",0.66,IF(O13="Totalmente en Desacuerdo",1,"error")))))) -> -1 | Q13: Totalmente en Desacuerdo | R13: =IF(Q13="Totalmente de Acuerdo",1,IF(Q13="Muy de Acuerdo",0.66,IF(Q13="Levemente de Acuerdo",0.33,IF(Q13="Levemente en Desacuerdo",-0.33,IF(Q13="Muy en Desacuerdo",-0.66,IF(Q13="Totalmente en Desacuerdo",-1,"error")))))) -> -1 | S13: Muy en Desacuerdo | T13: =IF(S13="Totalmente de Acuerdo",1,IF(S13="Muy de Acuerdo",0.66,IF(S13="Levemente de Acuerdo",0.33,IF(S13="Levemente en Desacuerdo",-0.33,IF(S13="Muy en Desacuerdo",-0.66,IF(S13="Totalmente en Desacuerdo",-1,"error")))))) -> -0.66 | U13: Totalmente de Acuerdo | V13: =IF(U13="Totalmente de Acuerdo",-1,IF(U13="Muy de Acuerdo",-0.66,IF(U13="Levemente en Acuerdo",-0.33,IF(U13="Levemente en Desacuerdo",0.33,IF(U13="Muy en Desacuerdo",0.66,IF(U13="Totalmente en Desacuerdo",1,"error")))))) -> -1 | W13: =+V13+T13+R13+P13+N13+L13+J13+H13 -> -2.99 | X13: =+W13*W$29 -> -3.36375 | Y13: Muy en Desacuerdo | Z13: =IF(Y13="Totalmente de Acuerdo",1,IF(Y13="Muy de Acuerdo",0.66,IF(Y13="Levemente de Acuerdo",0.33,IF(Y13="Levemente en Desacuerdo",-0.33,IF(Y13="Muy en Desacuerdo",-0.66,IF(Y13="Totalmente en Desacuerdo",-1,"error")))))) -> -0.66 | AA13: Totalmente en Desacuerdo | AB13: =IF(AA13="Totalmente de Acuerdo",-1,IF(AA13="Muy de Acuerdo",-0.66,IF(AA13="Levemente de Acuerdo",-0.33,IF(AA13="Levemente en Desacuerdo",0.33,IF(AA13="Muy en Desacuerdo",0.66,IF(AA13="Totalmente en Desacuerdo",1,"error")))))) -> 1 | AC13: Levemente en Desacuerdo | AD13: =IF(AC13="Totalmente de Acuerdo",-1,IF(AC13="Muy de Acuerdo",-0.66,IF(AC13="Levemente de Acuerdo",-0.33,IF(AC13="Levemente en Desacuerdo",0.33,IF(AC13="Muy en Desacuerdo",0.66,IF(AC13="Totalmente en Desacuerdo",1,"error")))))) -> 0.33 | AE13: Muy de Acuerdo | AF13: =IF(AE13="Totalmente de Acuerdo",1,IF(AE13="Muy de Acuerdo",0.66,IF(AE13="Levemente de Acuerdo",0.33,IF(AE13="Levemente en Desacuerdo",-0.33,IF(AE13="Muy en Desacuerdo",-0.66,IF(AE13="Totalmente en Desacuerdo",-1,"error")))))) -> 0.66 | AG13: Levemente de Acuerdo | AH13: =IF(AG13="Totalmente de Acuerdo",1,IF(AG13="Muy de Acuerdo",0.66,IF(AG13="Levemente de Acuerdo",0.33,IF(AG13="Levemente en Desacuerdo",-0.33,IF(AG13="Muy en Desacuerdo",-0.66,IF(AG13="Totalmente en Desacuerdo",-1,"error")))))) -> 0.33 | AI13: Totalmente de Acuerdo | AJ13: =IF(AI13="Totalmente de Acuerdo",1,IF(AI13="Muy de Acuerdo",0.66,IF(AI13="Levemente de Acuerdo",0.33,IF(AI13="Levemente en Desacuerdo",-0.33,IF(AI13="Muy en Desacuerdo",-0.66,IF(AI13="Totalmente en Desacuerdo",-1,"error")))))) -> 1 | AK13: Muy de Acuerdo | AL13: =IF(AK13="Totalmente de Acuerdo",1,IF(AK13="Muy de Acuerdo",0.66,IF(AK13="Levemente de Acuerdo",0.33,IF(AK13="Levemente en Desacuerdo",-0.33,IF(AK13="Muy en Desacuerdo",-0.66,IF(AK13="Totalmente en Desacuerdo",-1,"error")))))) -> 0.66 | AM13: Levemente de Acuerdo | AN13: =IF(AM13="Totalmente de Acuerdo",-1,IF(AM13="Muy de Acuerdo",-0.66,IF(AM13="Levemente de Acuerdo",-0.33,IF(AM13="Levemente en Desacuerdo",0.33,IF(AM13="Muy en Desacuerdo",0.66,IF(AM13="Totalmente en Desacuerdo",1,"error")))))) -> -0.33 | AO13: Muy en Desacuerdo | AP13: =IF(AO13="Totalmente de Acuerdo",1,IF(AO13="Muy de Acuerdo",0.66,IF(AO13="Levemente de Acuerdo",0.33,IF(AO13="Levemente en Desacuerdo",-0.33,IF(AO13="Muy en Desacuerdo",-0.66,IF(AO13="Totalmente en Desacuerdo",-1,"error")))))) -> -0.66 | AQ13: =+AP13+AN13+AL13+AJ13+AH13+AF13+AD13+AB13+Z13 -> 2.33
