Workbook

Sheet regresion
A1: Número de Trámite DNI | B1: puntaje 1E | C1: puntaje 2E | D1: puntaje 3E | E1: puntaje 4E | F1: puntaje 5E | G1: puntaje 6E | H1: puntaje 7E | I1: puntaje 8E | K1: puntaje 1S | L1: puntaje 2S | M1: puntaje 3S | N1: puntaje 4S | O1: puntaje 5S | P1: puntaje 6S | Q1: puntaje 7S | R1: puntaje 8S | S1: puntaje 9S | U1: ¿Cómo votó para Presidente en el ballotage de noviembre de 2023? | V1: voto
A2: 00686630540 | B2: 1 | C2: 0.33 | D2: -0.66 | E2: 1 | F2: 0.66 | G2: 1 | H2: 1 | I2: -0.66 | K2: -0.33 | L2: -1 | M2: -0.33 | N2: -0.33 | O2: 0.66 | P2: 1 | Q2: 0.66 | R2: 1 | S2: 1 | U2: Javier Milei (La Libertad Avanza) | V2: =+IF(U2="Javier Milei (La Libertad Avanza)",1,0) -> 1
A3: 00164890275 | B3: -0.33 | C3: -0.66 | D3: -1 | E3: 0.33 | F3: 0.33 | G3: -0.33 | H3: -0.33 | I3: -0.66 | K3: 0.33 | L3: -0.33 | M3: -1 | N3: -1 | O3: -0.66 | P3: -0.66 | Q3: -0.66 | R3: -1 | S3: 1 | U3: Sergio Massa (Unión por la Patria) | V3: =+IF(U3="Javier Milei (La Libertad Avanza)",1,0) -> 0
A4: 00578280042 | B4: 0.33 | C4: -0.66 | D4: -0.66 | E4: 1 | F4: -0.33 | G4: 1 | H4: 0.66 | I4: -0.66 | K4: 1 | L4: -1 | M4: 0.33 | N4: -1 | O4: 0.33 | P4: 1 | Q4: 1 | R4: -0.33 | S4: 0.66 | U4: Javier Milei (La Libertad Avanza) | V4: =+IF(U4="Javier Milei (La Libertad Avanza)",1,0) -> 1
A5: 00464782483 | B5: -0.66 | C5: 0.33 | D5: -0.33 | E5: 0.33 | F5: -0.66 | G5: 0.66 | H5: 0.66 | I5: 0.33 | K5: 0.33 | L5: -1 | M5: 0.66 | N5: -1 | O5: -0.66 | P5: 0.33 | Q5: 0.33 | R5: 0.66 | S5: 0.33 | U5: Javier Milei (La Libertad Avanza) | V5: =+IF(U5="Javier Milei (La Libertad Avanza)",1,0) -> 1
A6: 00661842297 | B6: 0.33 | C6: -0.33 | D6: -0.66 | E6: 0.66 | F6: -0.33 | G6: -0.33 | H6: 0.33 | I6: -0.66 | K6: -0.66 | L6: 0.33 | M6: -0.33 | N6: -1 | O6: -0.66 | P6: -0.33 | Q6: 0.66 | R6: 0.66 | S6: -0.33 | U6: Sergio Massa (Unión por la Patria) | V6: =+IF(U6="Javier Milei (La Libertad Avanza)",1,0) -> 0
A7: 00623233790 | B7: 1 | C7: 0.66 | D7: -1 | E7: 1 | F7: 1 | G7: 1 | H7: -0.66 | I7: -0.66 | K7: -1 | L7: -1 | M7: -0.66 | N7: -1 | O7: -0.33 | P7: 1 | Q7: -1 | R7: 1 | S7: 1 | U7: Javier Milei (La Libertad Avanza) | V7: =+IF(U7="Javier Milei (La Libertad Avanza)",1,0) -> 1
A8: 00544287188 | B8: -0.33 | C8: 0.33 | D8: -0.66 | E8: 0.33 | F8: -0.33 | G8: 1 | H8: 0.33 | I8: -0.66 | K8: -0.66 | L8: -0.66 | M8: 0.33 | N8: -1 | O8: -1 | P8: 0.66 | Q8: -0.66 | R8: -0.66 | S8: 1 | U8: Javier Milei (La Libertad Avanza) | V8: =+IF(U8="Javier Milei (La Libertad Avanza)",1,0) -> 1
A9: 00305830361 | B9: -0.66 | C9: -0.33 | D9: -0.66 | E9: 0.66 | F9: 0.66 | G9: 0.66 | H9: -0.33 | I9: -0.66 | K9: -0.66 | L9: -0.66 | M9: -0.33 | N9: 0.33 | O9: -1 | P9: -0.33 | Q9: -0.66 | R9: 1 | S9: 0.66 | U9: En blanco | V9: =+IF(U9="Javier Milei (La Libertad Avanza)",1,0) -> 0
A10: 00712484148 | B10: -0.66 | C10: -0.66 | D10: -1 | E10: 0.33 | F10: 0.33 | G10: 0.33 | H10: -0.66 | I10: -1 | K10: -1 | L10: -0.66 | M10: -0.33 | N10: -1 | O10: -1 | P10: -0.66 | Q10: 0.66 | R10: 0.33 | S10: 1 | U10: Javier Milei (La Libertad Avanza) | V10: =+IF(U10="Javier Milei (La Libertad Avanza)",1,0) -> 1
A11: 006934766847656 | B11: 1 | C11: -1 | D11: -1 | E11: -1 | F11: -1 | G11: -0.66 | H11: 0.33 | I11: -1 | K11: -0.66 | L11: 1 | M11: -1 | N11: -1 | O11: -1 | P11: -1 | Q11: -1 | R11: -1 | S11: 1 | U11: Sergio Massa (Unión por la Patria) | V11: =+IF(U11="Javier Milei (La Libertad Avanza)",1,0) -> 0
A12: 00338374873 | B12: -0.33 | C12: -0.33 | D12: -0.66 | E12: 0.33 | F12: -0.33 | G12: 0.66 | H12: -0.33 | I12: -0.33 | K12: 0.33 | L12: -0.66 | M12: -1 | N12: -1 | O12: -0.33 | P12: 0.33 | Q12: -0.33 | R12: 0.66 | S12: 0.66 | U12: Javier Milei (La Libertad Avanza) | V12: =+IF(U12="Javier Milei (La Libertad Avanza)",1,0) -> 1
A13: 00576235027 | B13: 0.66 | C13: 0.33 | D13: -0.66 | E13: 0.33 | F13: -0.33 | G13: 0.33 | H13: 0.66 | I13: 0.33 | K13: 0.33 | L13: -0.66 | M13: 0.66 | N13: -0.66 | O13: 0.33 | P13: 1 | Q13: -0.33 | R13: 0.33 | S13: 1 | U13: Javier Milei (La Libertad Avanza) | V13: =+IF(U13="Javier Milei (La Libertad Avanza)",1,0) -> 1
... A31: 00284397411 | B31: -0.66 | C31: -0.66 | D31: -1 | E31: -1 | F31: -0.66 | G31: 0.33 | H31: -0.33 | I31: -1 | K31: -0.66 | L31: 0.66 | M31: -1 | N31: -1 | O31: -1 | P31: -0.33 | Q31: -0.66 | R31: -1 | S31: 0.33 | U31: Sergio Massa (Unión por la Patria) | V31: =+IF(U31="Javier Milei (La Libertad Avanza)",1,0) -> 0

Sheet prediccones
A1: voto | B1: P5E | C1: P7E | D1: predicciones.Ec | G1: voto | H1: P2S | I1: P7E | J1: predicciones.Tot | M1: voto | N1: predicciones.Tot | R1: voto | S1: predicciones.Ec | AA1: coef = 1,9 | AB1: coef = 2,1 | AH1: coef = -2 | AI1: coef = 1,85
A2: 1 | B2: 0.66 | C2: 1 | D2: 0.98044092 | G2: 1 | H2: -1 | I2: 1 | J2: 0.96976892 | M2: 0 | N2: 0.41166422 | O2: media | R2: 0 | S2: 0.62167917 | T2: media | Z2: voto | AA2: P5E | AB2: P7E | AC2: predicciones.Ec | AG2: voto | AH2: P2S | AI2: P7E | AJ2: predicciones.Tot
A3: 0 | B3: 0.33 | C3: -0.33 | D3: 0.62167917 | G3: 0 | H3: -0.33 | I3: -0.33 | J3: 0.41166422 | M3: 0 | N3: 0.38642571 | O3: =+AVERAGE(N2:N11) -> 0.41433543 | R3: 0 | S3: 0.64728114 | T3: =+AVERAGE(S2:S11) -> 0.4561862 | Z3: 0 | AA3: -1 | AB3: -0.66 | AC3: 0.059867636 | AG3: 0 | AH3: 0.66 | AI3: -0.33 | AJ3: 0.086620831
A4: 1 | B4: -0.33 | C4: 0.66 | D4: 0.78542135 | G4: 1 | H4: -1 | I4: 0.66 | J4: 0.94459349 | M4: 0 | N4: 0.57666162 | P4: min | Q4: =+MIN(N2:N11) -> 0.086620831 | R4: 0 | S4: 0.75618977 | U4: min | V4: =+MIN(S2:S11) -> 0.059867636 | Z4: 0 | AA4: -0.66 | AB4: -0.33 | AC4: 0.19639494 | AG4: 0 | AH4: 0.33 | AI4: -0.66 | AJ4: 0.090876888
A5: 1 | B5: -0.66 | C5: 0.66 | D5: 0.65978211 | G5: 1 | H5: -1 | I5: 0.66 | J5: 0.94459349 | M5: 0 | N5: 0.14004743 | O5: des | P5: max | Q5: =+MAX(N2:N11) -> 0.89564045 | R5: 0 | S5: 0.33568551 | T5: des | U5: max | V5: =+MAX(S2:S11) -> 0.78542135 | Z5: 0 | AA5: -0.66 | AB5: -0.33 | AC5: 0.19639494 | AG5: 0 | AH5: 1 | AI5: 0.33 | AJ5: 0.14004743
A6: 0 | B6: -0.33 | C6: 0.33 | D6: 0.64728114 | G6: 0 | H6: 0.33 | I6: 0.33 | J6: 0.38642571 | M6: 0 | N6: 0.8229057 | O6: =+_xlfn.STDEV.S(N2:N11) -> 0.29928449 | R6: 0 | S6: 0.64728114 | T6: =+_xlfn.STDEV.S(S2:S11) -> 0.26355224 | Z6: 1 | AA6: -0.33 | AB6: -0.33 | AC6: 0.31566637 | AD6: =+AVERAGE(AC3:AC13) -> 0.35899889 | AG6: 0 | AH6: 0.33 | AI6: -0.33 | AJ6: 0.15584988
A7: 1 | B7: 1 | C7: -0.66 | D7: 0.74949811 | G7: 1 | H7: -1 | I7: -0.66 | J7: 0.59433293 | M7: 0 | N7: 0.89564045 | R7: 0 | S7: 0.78542135 | Z7: 1 | AA7: -0.33 | AB7: -0.33 | AC7: 0.31566637 | AG7: 1 | AH7: 0.66 | AI7: 0.33 | AJ7: 0.2444315
A8: 1 | B8: -0.33 | C8: 0.33 | D8: 0.64728114 | G8: 1 | H8: -0.66 | I8: 0.33 | J8: 0.8229057 | M8: 0 | N8: 0.15584988 | R8: 0 | S8: 0.31566637 | Z8: 0 | AA8: -0.33 | AB8: -0.33 | AC8: 0.31566637 | AG8: 0 | AH8: 0.33 | AI8: 0.33 | AJ8: 0.38642571
A9: 0 | B9: 0.66 | C9: -0.33 | D9: 0.75618977 | G9: 0 | H9: -0.66 | I9: -0.33 | J9: 0.57666162 | M9: 0 | N9: 0.57666162 | R9: 0 | S9: 0.19639494 | Z9: 0 | AA9: -1 | AB9: 0.33 | AC9: 0.33568551 | AG9: 0 | AH9: -0.33 | AI9: -0.33 | AJ9: 0.41166422
A10: 1 | B10: 0.33 | C10: -0.66 | D10: 0.45171271 | G10: 1 | H10: -0.66 | I10: -0.66 | J10: 0.42446906 | M10: 0 | N10: 0.090876888 | R10: 0 | S10: 0.059867636 | Z10: 1 | AA10: 0.33 | AB10: -0.66 | AC10: 0.45171271 | AG10: 1 | AH10: -0.66 | AI10: -0.66 | AJ10: 0.42446906
A11: 0 | B11: -1 | C11: 0.33 | D11: 0.33568551 | G11: 0 | H11: 1 | I11: 0.33 | J11: 0.14004743 | M11: 0 | N11: 0.086620831 | R11: 0 | S11: 0.19639494 | Z11: 1 | AA11: -0.66 | AB11: 0.33 | AC11: 0.49297266 | AG11: 0 | AH11: -0.66 | AI11: -0.33 | AJ11: 0.57666162 | AK11: =+AVERAGE(AJ3:AJ12) -> 0.30937088
A12: 1 | B12: -0.33 | C12: -0.33 | D12: 0.31566637 | G12: 1 | H12: -0.66 | I12: -0.33 | J12: 0.57666162 | M12: 1 | N12: 0.96976892 | R12: 1 | S12: 0.98044092 | Z12: 0 | AA12: 0.33 | AB12: -0.33 | AC12: 0.62167917 | AG12: 0 | AH12: -0.66 | AI12: -0.33 | AJ12: 0.57666162
A13: 1 | B13: -0.33 | C13: 0.66 | D13: 0.78542135 | G13: 1 | H13: -0.66 | I13: 0.66 | J13: 0.89564045 | M13: 1 | N13: 0.94459349 | O13: media | R13: 1 | S13: 0.78542135 | T13: media | Z13: 0 | AA13: -0.33 | AB13: 0.33 | AC13: 0.64728114 | AG13: 1 | AH13: -0.66 | AI13: -0.33 | AJ13: 0.57666162
A14: 1 | B14: 0.66 | C14: 1 | D14: 0.98044092 | G14: 1 | H14: -0.66 | I14: 1 | J14: 0.94168584 | M14: 1 | N14: 0.94459349 | O14: =+AVERAGE(N12:N31) -> 0.79283228 | R14: 1 | S14: 0.65978211 | T14: =+AVERAGE(S12:S31) -> 0.7719069 | Z14: 1 | AA14: -0.33 | AB14: 0.33 | AC14: 0.64728114 | AG14: 1 | AH14: -0.66 | AI14: -0.33 | AJ14: 0.57666162
A15: 0 | B15: -0.33 | C15: 0.33 | D15: 0.64728114 | G15: 0 | H15: -0.66 | I15: 0.33 | J15: 0.8229057 | M15: 1 | N15: 0.59433293 | R15: 1 | S15: 0.74949811 | U15: min | V15: =+MIN(S12:S31) -> 0.31566637 | Z15: 0 | AA15: -0.33 | AB15: 0.33 | AC15: 0.64728114 | AG15: 1 | AH15: -1 | AI15: -0.66 | AJ15: 0.59433293
A16: 1 | B16: 0.66 | C16: 0.33 | D16: 0.9250323 | G16: 1 | H16: -0.66 | I16: 0.33 | J16: 0.8229057 | M16: 1 | N16: 0.8229057 | O16: des | R16: 1 | S16: 0.64728114 | T16: =+_xlfn.STDEV.S(S12:S31) -> 0.22260279 | U16: max | V16: =+MAX(S12:S31) -> 0.98044092 | Z16: 1 | AA16: -0.66 | AB16: 0.66 | AC16: 0.65978211 | AG16: 1 | AH16: 0.33 | AI16: 1 | AJ16: 0.68639214
A17: 1 | B17: -0.66 | C17: 0.33 | D17: 0.49297266 | G17: 1 | H17: 0.66 | I17: 0.33 | J17: 0.2444315 | M17: 1 | N17: 0.42446906 | O17: =+_xlfn.STDEV.S(N12:N31) -> 0.20691324 | R17: 1 | S17: 0.45171271 | Z17: 1 | AA17: 1 | AB17: -0.66 | AC17: 0.74949811 | AG17: 0 | AH17: -0.66 | AI17: 0.33 | AJ17: 0.8229057
A18: 1 | B18: -0.33 | C18: 0.66 | D18: 0.78542135 | G18: 1 | H18: -1 | I18: 0.66 | J18: 0.94459349 | M18: 1 | N18: 0.57666162 | R18: 1 | S18: 0.31566637 | Z18: 0 | AA18: 0.66 | AB18: -0.33 | AC18: 0.75618977 | AG18: 1 | AH18: -0.66 | AI18: 0.33 | AJ18: 0.8229057
A19: 1 | B19: 0.66 | C19: 1 | D19: 0.98044092 | G19: 1 | H19: -0.33 | I19: 1 | J19: 0.89241529 | M19: 1 | N19: 0.89564045 | O19: min | P19: =+MIN(N12:N31) -> 0.2444315 | R19: 1 | S19: 0.78542135 | Z19: 1 | AA19: -0.33 | AB19: 0.66 | AC19: 0.78542135 | AG19: 1 | AH19: -0.66 | AI19: 0.33 | AJ19: 0.8229057
A20: 1 | B20: 0.66 | C20: 1 | D20: 0.98044092 | G20: 1 | H20: -0.66 | I20: 1 | J20: 0.94168584 | M20: 1 | N20: 0.94168584 | O20: max | P20: =+MAX(N12:N31) -> 0.96976892 | R20: 1 | S20: 0.98044092 | Z20: 1 | AA20: -0.33 | AB20: 0.66 | AC20: 0.78542135 | AG20: 1 | AH20: -0.66 | AI20: 0.33 | AJ20: 0.8229057
A21: 0 | B21: -0.33 | C21: 0.66 | D21: 0.78542135 | G21: 0 | H21: -0.66 | I21: 0.66 | J21: 0.89564045 | M21: 1 | N21: 0.8229057 | R21: 1 | S21: 0.9250323 | Z21: 1 | AA21: -0.33 | AB21: 0.66 | AC21: 0.78542135 | AG21: 1 | AH21: -0.33 | AI21: 1 | AJ21: 0.89241529
A22: 1 | B22: 0.33 | C22: 1 | D22: 0.96371328 | G22: 1 | H22: 0.33 | I22: 1 | J22: 0.68639214 | M22: 1 | N22: 0.2444315 | R22: 1 | S22: 0.49297266 | Z22: 0 | AA22: -0.33 | AB22: 0.66 | AC22: 0.78542135 | AG22: 0 | AH22: -0.66 | AI22: 0.66 | AJ22: 0.89564045
A23: 1 | B23: -0.33 | C23: -0.33 | D23: 0.31566637 | G23: 1 | H23: -0.66 | I23: -0.33 | J23: 0.57666162 | M23: 1 | N23: 0.94459349 | R23: 1 | S23: 0.78542135 | Z23: 1 | AA23: 0.33 | AB23: 0.33 | AC23: 0.86732954 | AG23: 1 | AH23: -0.66 | AI23: 0.66 | AJ23: 0.89564045
A24: 0 | B24: -0.33 | C24: -0.33 | D24: 0.31566637 | G24: 0 | H24: 0.33 | I24: -0.33 | J24: 0.15584988 | M24: 1 | N24: 0.89241529 | R24: 1 | S24: 0.98044092 | Z24: 1 | AA24: -0.33 | AB24: 1 | AC24: 0.88172844 | AG24: 1 | AH24: -0.66 | AI24: 0.66 | AJ24: 0.89564045
A25: 1 | B25: -0.33 | C25: 1 | D25: 0.88172844 | G25: 1 | H25: -1 | I25: 1 | J25: 0.96976892 | M25: 1 | N25: 0.94168584 | R25: 1 | S25: 0.98044092 | Z25: 1 | AA25: 0.66 | AB25: 0.33 | AC25: 0.9250323 | AG25: 1 | AH25: -0.66 | AI25: 1 | AJ25: 0.94168584
A26: 0 | B26: -0.66 | C26: -0.33 | D26: 0.19639494 | G26: 0 | H26: -0.66 | I26: -0.33 | J26: 0.57666162 | M26: 1 | N26: 0.68639214 | R26: 1 | S26: 0.96371328 | Z26: 1 | AA26: 0.33 | AB26: 0.66 | AC26: 0.92877253 | AG26: 1 | AH26: -0.66 | AI26: 1 | AJ26: 0.94168584
A27: 1 | B27: 0.33 | C27: 0.66 | D27: 0.92877253 | G27: 1 | H27: -0.66 | I27: 0.66 | J27: 0.89564045 | M27: 1 | N27: 0.57666162 | R27: 1 | S27: 0.31566637 | Z27: 1 | AA27: 0.66 | AB27: 0.66 | AC27: 0.96095474 | AG27: 1 | AH27: -1 | AI27: 0.66 | AJ27: 0.94459349
A28: 1 | B28: 0.66 | C28: 0.66 | D28: 0.96095474 | G28: 1 | H28: -1 | I28: 0.66 | J28: 0.94459349 | M28: 1 | N28: 0.96976892 | R28: 1 | S28: 0.88172844 | Z28: 1 | AA28: 0.33 | AB28: 1 | AC28: 0.96371328 | AG28: 1 | AH28: -1 | AI28: 0.66 | AJ28: 0.94459349
A29: 1 | B29: 0.33 | C29: 0.33 | D29: 0.86732954 | G29: 1 | H29: -0.66 | I29: 0.33 | J29: 0.8229057 | M29: 1 | N29: 0.89564045 | R29: 1 | S29: 0.92877253 | Z29: 1 | AA29: 0.66 | AB29: 1 | AC29: 0.98044092 | AG29: 1 | AH29: -1 | AI29: 0.66 | AJ29: 0.94459349
A30: 0 | B30: -1 | C30: -0.66 | D30: 0.059867636 | G30: 0 | H30: 0.33 | I30: -0.66 | J30: 0.090876888 | M30: 1 | N30: 0.94459349 | R30: 1 | S30: 0.96095474 | Z30: 1 | AA30: 0.66 | AB30: 1 | AC30: 0.98044092 | AG30: 1 | AH30: -1 | AI30: 0.66 | AJ30: 0.94459349
A31: 0 | B31: -0.66 | C31: -0.33 | D31: 0.19639494 | G31: 0 | H31: 0.66 | I31: -0.33 | J31: 0.086620831 | M31: 1 | N31: 0.8229057 | R31: 1 | S31: 0.86732954 | Z31: 1 | AA31: 0.66 | AB31: 1 | AC31: 0.98044092 | AG31: 1 | AH31: -1 | AI31: 1 | AJ31: 0.96976892
Z32: 1 | AA32: 0.66 | AB32: 1 | AC32: 0.98044092 | AG32: 1 | AH32: -1 | AI32: 1 | AJ32: 0.96976892

Sheet regresion3
A1: Número de Trámite DNI | B1: voto | C1: puntaje 1E | D1: puntaje 2E | E1: puntaje 3E | F1: puntaje 4E | G1: puntaje 5E | H1: puntaje 6E | I1: puntaje 7E | J1: puntaje 8E | L1: puntaje 1S | M1: puntaje 2S | N1: puntaje 3S | O1: puntaje 4S | P1: puntaje 5S | Q1: puntaje 6S | R1: puntaje 7S | S1: puntaje 8S | T1: puntaje 9S
A2: 00686630540 | B2: 1 | C2: =+dato3!M2 -> 1 | D2: =+dato3!O2 -> 0 | E2: =+dato3!Q2 -> -0.5 | F2: =+dato3!S2 -> 1 | G2: =+dato3!U2 -> 0.5 | H2: =+dato3!W2 -> 1 | I2: =+dato3!Y2 -> 1 | J2: =+dato3!AA2 -> -0.5 | L2: =+dato3!AE2 -> 0 | M2: =+dato3!AG2 -> -1 | N2: =+dato3!AI2 -> 0 | O2: =+dato3!AK2 -> 0 | P2: =+dato3!AM2 -> 0.5 | Q2: =+dato3!AO2 -> 1 | R2: =+dato3!AQ2 -> 0.5 | S2: =+dato3!AS2 -> 1 | T2: =+dato3!AU2 -> 1
A3: 00164890275 | B3: 0 | C3: =+dato3!M3 -> 0 | D3: =+dato3!O3 -> -0.5 | E3: =+dato3!Q3 -> -1 | F3: =+dato3!S3 -> 0 | G3: =+dato3!U3 -> 0 | H3: =+dato3!W3 -> 0 | I3: =+dato3!Y3 -> 0 | J3: =+dato3!AA3 -> -0.5 | L3: =+dato3!AE3 -> 0 | M3: =+dato3!AG3 -> 0 | N3: =+dato3!AI3 -> -1 | O3: =+dato3!AK3 -> -1 | P3: =+dato3!AM3 -> -0.5 | Q3: =+dato3!AO3 -> -0.5 | R3: =+dato3!AQ3 -> -0.5 | S3: =+dato3!AS3 -> -1 | T3: =+dato3!AU3 -> 1
A4: 00578280042 | B4: 1 | C4: =+dato3!M4 -> 0 | D4: =+dato3!O4 -> -0.5 | E4: =+dato3!Q4 -> -0.5 | F4: =+dato3!S4 -> 1 | G4: =+dato3!U4 -> 0 | H4: =+dato3!W4 -> 1 | I4: =+dato3!Y4 -> 0.5 | J4: =+dato3!AA4 -> -0.5 | L4: =+dato3!AE4 -> 1 | M4: =+dato3!AG4 -> -1 | N4: =+dato3!AI4 -> 0 | O4: =+dato3!AK4 -> -1 | P4: =+dato3!AM4 -> 0 | Q4: =+dato3!AO4 -> 1 | R4: =+dato3!AQ4 -> 1 | S4: =+dato3!AS4 -> 0 | T4: =+dato3!AU4 -> 0.5
A5: 00464782483 | B5: 1 | C5: =+dato3!M5 -> -0.5 | D5: =+dato3!O5 -> 0 | E5: =+dato3!Q5 -> 0 | F5: =+dato3!S5 -> 0 | G5: =+dato3!U5 -> -0.5 | H5: =+dato3!W5 -> 0.5 | I5: =+dato3!Y5 -> 0.5 | J5: =+dato3!AA5 -> 0 | L5: =+dato3!AE5 -> 0 | M5: =+dato3!AG5 -> -1 | N5: =+dato3!AI5 -> 0.5 | O5: =+dato3!AK5 -> -1 | P5: =+dato3!AM5 -> -0.5 | Q5: =+dato3!AO5 -> 0 | R5: =+dato3!AQ5 -> 0 | S5: =+dato3!AS5 -> 0.5 | T5: =+dato3!AU5 -> 0
A6: 00661842297 | B6: 0 | C6: =+dato3!M6 -> 0 | D6: =+dato3!O6 -> 0 | E6: =+dato3!Q6 -> -0.5 | F6: =+dato3!S6 -> 0.5 | G6: =+dato3!U6 -> 0 | H6: =+dato3!W6 -> 0 | I6: =+dato3!Y6 -> 0 | J6: =+dato3!AA6 -> -0.5 | L6: =+dato3!AE6 -> -0.5 | M6: =+dato3!AG6 -> 0 | N6: =+dato3!AI6 -> 0 | O6: =+dato3!AK6 -> -1 | P6: =+dato3!AM6 -> -0.5 | Q6: =+dato3!AO6 -> 0 | R6: =+dato3!AQ6 -> 0.5 | S6: =+dato3!AS6 -> 0.5 | T6: =+dato3!AU6 -> 0
A7: 00623233790 | B7: 1 | C7: =+dato3!M7 -> 1 | D7: =+dato3!O7 -> 0.5 | E7: =+dato3!Q7 -> -1 | F7: =+dato3!S7 -> 1 | G7: =+dato3!U7 -> 1 | H7: =+dato3!W7 -> 1 | I7: =+dato3!Y7 -> -0.5 | J7: =+dato3!AA7 -> -0.5 | L7: =+dato3!AE7 -> -1 | M7: =+dato3!AG7 -> -1 | N7: =+dato3!AI7 -> -0.5 | O7: =+dato3!AK7 -> -1 | P7: =+dato3!AM7 -> 0 | Q7: =+dato3!AO7 -> 1 | R7: =+dato3!AQ7 -> -1 | S7: =+dato3!AS7 -> 1 | T7: =+dato3!AU7 -> 1
A8: 00544287188 | B8: 1 | C8: =+dato3!M8 -> 0 | D8: =+dato3!O8 -> 0 | E8: =+dato3!Q8 -> -0.5 | F8: =+dato3!S8 -> 0 | G8: =+dato3!U8 -> 0 | H8: =+dato3!W8 -> 1 | I8: =+dato3!Y8 -> 0 | J8: =+dato3!AA8 -> -0.5 | L8: =+dato3!AE8 -> -0.5 | M8: =+dato3!AG8 -> -0.5 | N8: =+dato3!AI8 -> 0 | O8: =+dato3!AK8 -> -1 | P8: =+dato3!AM8 -> -1 | Q8: =+dato3!AO8 -> 0.5 | R8: =+dato3!AQ8 -> -0.5 | S8: =+dato3!AS8 -> -0.5 | T8: =+dato3!AU8 -> 1
A9: 00305830361 | B9: 0 | C9: =+dato3!M9 -> -0.5 | D9: =+dato3!O9 -> 0 | E9: =+dato3!Q9 -> -0.5 | F9: =+dato3!S9 -> 0.5 | G9: =+dato3!U9 -> 0.5 | H9: =+dato3!W9 -> 0.5 | I9: =+dato3!Y9 -> 0 | J9: =+dato3!AA9 -> -0.5 | L9: =+dato3!AE9 -> -0.5 | M9: =+dato3!AG9 -> -0.5 | N9: =+dato3!AI9 -> 0 | O9: =+dato3!AK9 -> 0 | P9: =+dato3!AM9 -> -1 | Q9: =+dato3!AO9 -> 0 | R9: =+dato3!AQ9 -> -0.5 | S9: =+dato3!AS9 -> 1 | T9: =+dato3!AU9 -> 0.5
A10: 00712484148 | B10: 1 | C10: =+dato3!M10 -> -0.5 | D10: =+dato3!O10 -> -0.5 | E10: =+dato3!Q10 -> -1 | F10: =+dato3!S10 -> 0 | G10: =+dato3!U10 -> 0 | H10: =+dato3!W10 -> 0 | I10: =+dato3!Y10 -> -0.5 | J10: =+dato3!AA10 -> -1 | L10: =+dato3!AE10 -> -1 | M10: =+dato3!AG10 -> -0.5 | N10: =+dato3!AI10 -> 0 | O10: =+dato3!AK10 -> -1 | P10: =+dato3!AM10 -> -1 | Q10: =+dato3!AO10 -> -0.5 | R10: =+dato3!AQ10 -> 0.5 | S10: =+dato3!AS10 -> 0 | T10: =+dato3!AU10 -> 1
A11: 006934766847656 | B11: 0 | C11: =+dato3!M11 -> 1 | D11: =+dato3!O11 -> -1 | E11: =+dato3!Q11 -> -1 | F11: =+dato3!S11 -> -1 | G11: =+dato3!U11 -> -1 | H11: =+dato3!W11 -> -0.5 | I11: =+dato3!Y11 -> 0 | J11: =+dato3!AA11 -> -1 | L11: =+dato3!AE11 -> -0.5 | M11: =+dato3!AG11 -> 1 | N11: =+dato3!AI11 -> -1 | O11: =+dato3!AK11 -> -1 | P11: =+dato3!AM11 -> -1 | Q11: =+dato3!AO11 -> -1 | R11: =+dato3!AQ11 -> -1 | S11: =+dato3!AS11 -> -1 | T11: =+dato3!AU11 -> 1
A12: 00338374873 | B12: 1 | C12: =+dato3!M12 -> 0 | D12: =+dato3!O12 -> 0 | E12: =+dato3!Q12 -> -0.5 | F12: =+dato3!S12 -> 0 | G12: =+dato3!U12 -> 0 | H12: =+dato3!W12 -> 0.5 | I12: =+dato3!Y12 -> 0 | J12: =+dato3!AA12 -> 0 | L12: =+dato3!AE12 -> 0 | M12: =+dato3!AG12 -> -0.5 | N12: =+dato3!AI12 -> -1 | O12: =+dato3!AK12 -> -1 | P12: =+dato3!AM12 -> 0 | Q12: =+dato3!AO12 -> 0 | R12: =+dato3!AQ12 -> 0 | S12: =+dato3!AS12 -> 0.5 | T12: =+dato3!AU12 -> 0.5
A13: 00576235027 | B13: 1 | C13: =+dato3!M13 -> 0.5 | D13: =+dato3!O13 -> 0 | E13: =+dato3!Q13 -> -0.5 | F13: =+dato3!S13 -> 0 | G13: =+dato3!U13 -> 0 | H13: =+dato3!W13 -> 0 | I13: =+dato3!Y13 -> 0.5 | J13: =+dato3!AA13 -> 0 | L13: =+dato3!AE13 -> 0 | M13: =+dato3!AG13 -> -0.5 | N13: =+dato3!AI13 -> 0.5 | O13: =+dato3!AK13 -> -0.5 | P13: =+dato3!AM13 -> 0 | Q13: =+dato3!AO13 -> 1 | R13: =+dato3!AQ13 -> 0 | S13: =+dato3!AS13 -> 0 | T13: =+dato3!AU13 -> 1
... A31: 00284397411 | B31: 0 | C31: =+dato3!M31 -> -0.5 | D31: =+dato3!O31 -> -0.5 | E31: =+dato3!Q31 -> -1 | F31: =+dato3!S31 -> -1 | G31: =+dato3!U31 -> -0.5 | H31: =+dato3!W31 -> 0 | I31: =+dato3!Y31 -> 0 | J31: =+dato3!AA31 -> -1 | L31: =+dato3!AE31 -> -0.5 | M31: =+dato3!AG31 -> 0.5 | N31: =+dato3!AI31 -> -1 | O31: =+dato3!AK31 -> -1 | P31: =+dato3!AM31 -> -1 | Q31: =+dato3!AO31 -> 0 | R31: =+dato3!AQ31 -> -0.5 | S31: =+dato3!AS31 -> -1 | T31: =+dato3!AU31 -> 0

Sheet predicciones3
A1: voto | B1: P5E | C1: P7E | D1: predicciones.Ec | F1: voto | G1: P2S | H1: P7E | I1: predicciones.Tot | N1: coef= -2,6 | O1: coef = 2 | T1: coef = 2 | U1: coef = 2,2
A2: 1 | B2: 0.5 | C2: 1 | D2: 0.97545455 | F2: 1 | G2: -1 | H2: 1 | I2: 0.98356854 | M2: voto | N2: P2S | O2: P7E | P2: predicciones.Tot | S2: voto | T2: P5E | U2: P7E | V2: predicciones.Ec | Y2: voto | Z2: P1E | AA2: P2E | AB2: P3E | AC2: P4E | AD2: P5E | AE2: P6E | AF2: P7E | AG2: P8E | AH2: predicciones
A3: 0 | B3: 0 | C3: 0 | D3: 0.58791929 | F3: 0 | G3: 0 | H3: 0 | I3: 0.36116576 | M3: 0 | N3: 1 | O3: 0 | P3: 0.039494625 | S3: 0 | T3: 0 | U3: 0 | V3: 0.58791929 | Y3: 0 | Z3: 0 | AA3: -0.5 | AB3: -1 | AC3: 0 | AD3: 0 | AE3: 0 | AF3: 0 | AG3: -0.5 | AH3: 0.48101905
A4: 1 | B4: 0 | C4: 0.5 | D4: 0.81667823 | F4: 1 | G4: -1 | H4: 0.5 | I4: 0.95569471 | M4: 0 | N4: 0.5 | O4: 0 | P4: 0.13229684 | S4: 0 | T4: 0 | U4: 0 | V4: 0.58791929 | Y4: 0 | Z4: 0 | AA4: 0 | AB4: -0.5 | AC4: 0.5 | AD4: 0 | AE4: 0 | AF4: 0 | AG4: -0.5 | AH4: 0.67659946
A5: 1 | B5: -0.5 | C5: 0.5 | D5: 0.60927342 | F5: 1 | G5: -1 | H5: 0.5 | I5: 0.95569471 | M5: 0 | N5: 0 | O5: -0.5 | P5: 0.16924841 | S5: 0 | T5: 0.5 | U5: 0 | V5: 0.80299408 | Y5: 0 | Z5: -0.5 | AA5: 0 | AB5: -0.5 | AC5: 0.5 | AD5: 0.5 | AE5: 0.5 | AF5: 0 | AG5: -0.5 | AH5: 0.77371147
A6: 0 | B6: 0 | C6: 0 | D6: 0.58791929 | F6: 0 | G6: 0 | H6: 0 | I6: 0.36116576 | M6: 0 | N6: 0 | O6: 0 | P6: 0.36116576 | S6: 0 | T6: -1 | U6: 0 | V6: 0.1487909 | Y6: 0 | Z6: 1 | AA6: -1 | AB6: -1 | AC6: -1 | AD6: -1 | AE6: -0.5 | AF6: 0 | AG6: -1 | AH6: 0.049727858 | AI6: =+AVERAGE(AH3:AH12) -> 0.41659273
A7: 1 | B7: 1 | C7: -0.5 | D7: 0.78855294 | F7: 1 | G7: -1 | H7: -0.5 | I7: 0.73692049 | M7: 0 | N7: 0 | O7: 0 | P7: 0.36116576 | Q7: =+AVERAGE(P3:P12) -> 0.43089613 | S7: 0 | T7: 0 | U7: 0 | V7: 0.58791929 | W7: =+AVERAGE(V3:V12) -> 0.48392755 | Y7: 0 | Z7: 0 | AA7: 0 | AB7: 0 | AC7: 0 | AD7: 0 | AE7: 0.5 | AF7: 0 | AG7: 0 | AH7: 0.16472469
A8: 1 | B8: 0 | C8: 0 | D8: 0.58791929 | F8: 1 | G8: -0.5 | H8: 0 | I8: 0.67703642 | M8: 0 | N8: 0 | O8: 0 | P8: 0.36116576 | S8: 0 | T8: 0 | U8: 0.5 | V8: 0.81667823 | Y8: 0 | Z8: 0.5 | AA8: 0 | AB8: 0 | AC8: 0.5 | AD8: 0 | AE8: 1 | AF8: 0.5 | AG8: 0 | AH8: 0.73357306
A9: 0 | B9: 0.5 | C9: 0 | D9: 0.80299408 | F9: 0 | G9: -0.5 | H9: 0 | I9: 0.67703642 | M9: 0 | N9: -0.5 | O9: 0 | P9: 0.67703642 | S9: 0 | T9: 0 | U9: 0 | V9: 0.58791929 | Y9: 0 | Z9: 0 | AA9: 0 | AB9: -0.5 | AC9: 0.5 | AD9: 0 | AE9: 0 | AF9: 0 | AG9: 0 | AH9: 0.52402848
A10: 1 | B10: 0 | C10: -0.5 | D10: 0.31361741 | F10: 1 | G10: -0.5 | H10: -0.5 | I10: 0.4303386 | M10: 0 | N10: -0.5 | O10: 0 | P10: 0.67703642 | S10: 0 | T10: -0.5 | U10: 0 | V10: 0.33306105 | Y10: 0 | Z10: -0.5 | AA10: 0 | AB10: -0.5 | AC10: 0 | AD10: -0.5 | AE10: 0.5 | AF10: 0 | AG10: -0.5 | AH10: 0.46311987
A11: 0 | B11: -1 | C11: 0 | D11: 0.1487909 | F11: 0 | G11: 1 | H11: 0 | I11: 0.039494625 | M11: 0 | N11: -0.5 | O11: 0 | P11: 0.67703642 | S11: 0 | T11: -1 | U11: -0.5 | V11: 0.053013029 | Y11: 0 | Z11: -1 | AA11: -1 | AB11: -1 | AC11: -0.5 | AD11: -1 | AE11: 0 | AF11: -0.5 | AG11: -1 | AH11: 0.019544374
A12: 1 | B12: 0 | C12: 0 | D12: 0.58791929 | F12: 1 | G12: -0.5 | H12: 0 | I12: 0.67703642 | M12: 0 | N12: -0.5 | O12: 0.5 | P12: 0.85331494 | S12: 0 | T12: -0.5 | U12: 0 | V12: 0.33306105 | Y12: 0 | Z12: -0.5 | AA12: -0.5 | AB12: -1 | AC12: -1 | AD12: -0.5 | AE12: 0 | AF12: 0 | AG12: -1 | AH12: 0.27987896
A13: 1 | B13: 0 | C13: 0.5 | D13: 0.81667823 | F13: 1 | G13: -0.5 | H13: 0.5 | I13: 0.85331494 | M13: 1 | N13: 0.5 | O13: 0 | P13: 0.13229684 | S13: 1 | T13: 0.5 | U13: 1 | V13: 0.97545455 | Y13: 1 | Z13: 1 | AA13: 0 | AB13: -0.5 | AC13: 1 | AD13: 0.5 | AE13: 1 | AF13: 1 | AG13: -0.5 | AH13: 0.9967846
A14: 1 | B14: 0.5 | C14: 1 | D14: 0.97545455 | F14: 1 | G14: -0.5 | H14: 1 | I14: 0.94166768 | M14: 1 | N14: -0.5 | O14: -0.5 | P14: 0.4303386 | S14: 1 | T14: 0 | U14: 0.5 | V14: 0.81667823 | Y14: 1 | Z14: 0 | AA14: -0.5 | AB14: -0.5 | AC14: 1 | AD14: 0 | AE14: 1 | AF14: 0.5 | AG14: -0.5 | AH14: 0.90591462
A15: 0 | B15: 0 | C15: 0 | D15: 0.58791929 | F15: 0 | G15: -0.5 | H15: 0 | I15: 0.67703642 | M15: 1 | N15: -0.5 | O15: 0 | P15: 0.67703642 | S15: 1 | T15: -0.5 | U15: 0.5 | V15: 0.60927342 | Y15: 1 | Z15: -0.5 | AA15: 0 | AB15: 0 | AC15: 0 | AD15: -0.5 | AE15: 0.5 | AF15: 0.5 | AG15: 0 | AH15: 0.57460489
A16: 1 | B16: 0.5 | C16: 0 | D16: 0.80299408 | F16: 1 | G16: -0.5 | H16: 0 | I16: 0.67703642 | M16: 1 | N16: -0.5 | O16: 0 | P16: 0.67703642 | S16: 1 | T16: 1 | U16: -0.5 | V16: 0.78855294 | Y16: 1 | Z16: 1 | AA16: 0.5 | AB16: -1 | AC16: 1 | AD16: 1 | AE16: 1 | AF16: -0.5 | AG16: -0.5 | AH16: 0.87480213
A17: 1 | B17: -0.5 | C17: 0 | D17: 0.33306105 | F17: 1 | G17: 0.5 | H17: 0 | I17: 0.13229684 | M17: 1 | N17: -0.5 | O17: 0 | P17: 0.67703642 | S17: 1 | T17: 0 | U17: 0 | V17: 0.58791929 | Y17: 1 | Z17: 0 | AA17: 0 | AB17: -0.5 | AC17: 0 | AD17: 0 | AE17: 1 | AF17: 0 | AG17: -0.5 | AH17: 0.51569494
A18: 1 | B18: 0 | C18: 0.5 | D18: 0.81667823 | F18: 1 | G18: -1 | H18: 0.5 | I18: 0.95569471 | M18: 1 | N18: -0.5 | O18: 0 | P18: 0.67703642 | S18: 1 | T18: 0 | U18: -0.5 | V18: 0.31361741 | Y18: 1 | Z18: -0.5 | AA18: -0.5 | AB18: -1 | AC18: 0 | AD18: 0 | AE18: 0 | AF18: -0.5 | AG18: -1 | AH18: 0.19074933
A19: 1 | B19: 0.5 | C19: 1 | D19: 0.97545455 | F19: 1 | G19: 0 | H19: 1 | I19: 0.81320974 | M19: 1 | N19: -0.5 | O19: 0 | P19: 0.67703642 | S19: 1 | T19: 0 | U19: 0 | V19: 0.58791929 | Y19: 1 | Z19: 0 | AA19: 0 | AB19: -0.5 | AC19: 0 | AD19: 0 | AE19: 0.5 | AF19: 0 | AG19: 0 | AH19: 0.36298186
... A31: 0 | B31: -0.5 | C31: 0 | D31: 0.33306105 | F31: 0 | G31: 0.5 | H31: 0 | I31: 0.13229684 | M31: 1 | N31: -1 | O31: 1 | P31: 0.98356854 | S31: 1 | T31: 0.5 | U31: 0.5 | V31: 0.9271522 | Y31: 1 | Z31: 0.5 | AA31: 1 | AB31: 1 | AC31: 0.5 | AD31: 0.5 | AE31: -0.5 | AF31: 0.5 | AG31: -0.5 | AH31: 0.9181353
M32: 1 | N32: -1 | O32: 1 | P32: 0.98356854 | S32: 1 | T32: 0 | U32: 0 | V32: 0.58791929 | Y32: 1 | Z32: 0 | AA32: 0 | AB32: -1 | AC32: 0.5 | AD32: 0 | AE32: 0 | AF32: 0 | AG32: -0.5 | AH32: 0.85805499

Sheet dato
L1: Eje economico | AD1: Eje Social
A2: Marca temporal | B2: Número de Trámite DNI | C2: Año de nacimiento | D2: Año de cursado. La mayoría de las materias obligatorias que cursaste en 2024 son de: | E2: ¿Con qué identidad de género se identifica? | F2: ¿Cuál fue el último nivel educativo alcanzado por su padre o tutor? | G2: ¿Cuál fue el último nivel educativo alcanzado por su madre o tutora? | H2: Ubíquese en la pirámide en base a su ingreso total familiar aproximado | I2: ¿De dónde provienen tus ingresos? | J2: ¿Dónde vivías antes de venir a estudiar a Córdoba? | K2: . | L2: El Estado debe intervenir en el mercado laboral para reducir la brecha salarial entre hombres y mujeres | M2: puntaje 1E | N2: Los países con Estados más “pequeños” (menor gasto público) son más exitosos y sus habitantes gozan de una mejor calidad de vida. | O2: puntaje 2E | P2: Los ricos deben pagar relativamente más impuestos que los pobres | Q2: puntaje 3E | R2: El país sólo puede crecer a largo plazo si reorienta sus políticas hacia una economía de mercado y libre comercio | S2: puntaje 4E | T2: El gobierno siempre debe intervenir en el mercado cuando lo crea necesario | U2: puntaje 5E | V2: Aquellos que puedan trabajar, y rechacen la oportunidad, no deberían esperar ayuda social | W2: puntaje 6E | X2: El gasto público en planes y asistencia social debe reducirse a un mínimo y en su lugar debe gastarse el dinero público en planes de empleo e inversión | Y2: puntaje 7E | Z2: La única responsabilidad social de una empresa debería ser proporcionar utilidades a sus accionistas | AA2: puntaje 8E | AB2: suma eje economico | AC2: eje econ | AD2: Altos salarios para funcionarios estatales (en los 3 poderes) son beneficiosos por disminuir las posibilidades de que estos cometan actos de corrupción | AE2: puntaje 1S | AF2: Las medidas de restricción de la circulación y aislamiento obligatorio durante la pandemia fueron excesivas y un atropello a la libertad individual de los ciudadanos | AG2: puntaje 2S | AH2: El movimiento feminista carece de sentido ya que actualmente mujeres y hombres se encuentran en pie de igualdad | AI2: puntaje 3S | AJ2: El aborto, cuando no esté amenazada la vida de la madre, siempre debería ser ilegal | AK2: puntaje 4S | AL2: El cambio climático es una problemática alarmante y a la que todos los Estados deberían prestar atención | AM2: puntaje 5S | AN2: Los contribuyentes deberían financiar con impuestos aquellos teatros o museos que no fuesen rentables por sí mismos | AO2: puntaje 6S | AP2: En la justicia penal la rehabilitación debería ser más importante que el castigo | AQ2: puntaje 7S | AR2: Los extranjeros no deberían acceder a educación y salud gratuita | AS2: puntaje 8S | AT2: El Estado no debería obligar a vacunar a los niños | AU2: puntaje 9S | AV2: eje social | AW2: El peronismo es el responsable de arruinar nuestro país en los últimos años | AX2: La política tradicional es responsable de la crisis económica y social del país | AY2: El FMI es partícipe del fracaso económico de los últimos años | AZ2: La falta de dólares es uno de los principales problemas de la argentina | BA2: Se puede pagar el precio de cierto grado de corrupción, siempre que se solucionen los problemas del país | BB2: Estoy dispuesto a sacrificar derechos políticos por más seguridad | BC2: Estoy dispuesto a sacrificar derechos políticos por más bienestar económico | BD2: Si me asegura 30 años de estabilidad económica y crecimiento, estoy dispuesto a sacrificar derechos políticos | BE2: La vida en los barrios cerrados ("countries") es de mejor calidad que en barrios abiertos, incluso si estos son seguros | BF2: Suponiendo un transporte público eficiente, de calidad y bajo costo, estaría dispuesto a disminuir el uso del automóvil particular | BG2: La educación secundaria privada prepara mejor a los ciudadanos que la escuela pública | BH2: ¿Con cuáles de los siguientes términos se identifica? (Puede elegir más de uno) [De derecha] | BI2: ¿Con cuáles de los siguientes términos se identifica? (Puede elegir más de uno) [De izquierda] | BJ2: ¿Con cuáles de los siguientes términos se identifica? (Puede elegir más de uno) [De centro] | BK2: ¿Con cuáles de los siguientes términos se identifica? (Puede elegir más de uno) [Progresista] | BL2: ¿Con cuáles de los siguientes términos se identifica? (Puede elegir más de uno) [Conservador] | BM2: ¿Con cuáles de los siguientes términos se identifica? (Puede elegir más de uno) [Liberal] | BN2: ¿Con cuáles de los siguientes términos se identifica? (Puede elegir más de uno) [Socialista] | BO2: ¿Con cuáles de los siguientes términos se identifica? (Puede elegir más de uno) [Del PRO] | BP2: ¿Con cuáles de los siguientes términos se identifica? (Puede elegir más de uno) [Peronista] | BQ2: ¿Con cuáles de los siguientes términos se identifica? (Puede elegir más de uno) [Kirchnerista] | BR2: ¿Con cuáles de los siguientes términos se identifica? (Puede elegir más de uno) [Libertario] | BS2: ¿Con cuáles de los siguientes términos se identifica? (Puede elegir más de uno) [Radical] | BT2: ¿Con cuáles de los siguientes términos se identifica? (Puede elegir más de uno) [Macrista] | BU2: ¿Con cuáles de los siguientes términos se identifica? (Puede elegir más de uno) [Feminista] | BV2: ¿Con cuáles de los siguientes términos se identifica? (Puede elegir más de uno) [Ecologista] | BW2: ¿Con cuáles de los siguientes términos se identifica? (Puede elegir más de uno) [Anarquista] | BX2: ¿Cómo votó para Presidente en las elecciones PASO de agosto de 2023? | BY2: ¿Cómo votó para Presidente en las elecciones generales de octubre de 2023? | BZ2: ¿Cómo votó para Presidente en el ballotage de noviembre de 2023? | CA2: ¿Cuál es tu sexo registrado al nacer?
A3: 45547.897 | B3: 00686630540 | C3: 2002 | D3: Cuarto año | E3: Varón | F3: Universitario incompleto | G3: Universitario incompleto | H3: Clase Alta (ABC1): más de $2.850.000 mensuales | I3: Familia | J3: Otra localidad en la Provincia de Córdoba | K3: . | L3: Totalmente en Desacuerdo | M3: =IF(L3="Totalmente de Acuerdo",-1,IF(L3="Muy de Acuerdo",-0.66,IF(L3="Levemente de Acuerdo",-0.33,IF(L3="Levemente en Desacuerdo",0.33,IF(L3="Muy en Desacuerdo",0.66,IF(L3="Totalmente en Desacuerdo",1,"error")))))) -> 1 | N3: Levemente de Acuerdo | O3: =IF(N3="Totalmente de Acuerdo",1,IF(N3="Muy de Acuerdo",0.66,IF(N3="Levemente de Acuerdo",0.33,IF(N3="Levemente en Desacuerdo",-0.33,IF(N3="Muy en Desacuerdo",-0.66,IF(N3="Totalmente en Desacuerdo",-1,"error")))))) -> 0.33 | P3: Muy de Acuerdo | Q3: =IF(P3="Totalmente de Acuerdo",-1,IF(P3="Muy de Acuerdo",-0.66,IF(P3="Levemente de Acuerdo",-0.33,IF(P3="Levemente en Desacuerdo",0.33,IF(P3="Muy en Desacuerdo",0.66,IF(P3="Totalmente en Desacuerdo",1,"error")))))) -> -0.66 | R3: Totalmente de Acuerdo | S3: =IF(R3="Totalmente de Acuerdo",1,IF(R3="Muy de Acuerdo",0.66,IF(R3="Levemente de Acuerdo",0.33,IF(R3="Levemente en Desacuerdo",-0.33,IF(R3="Muy en Desacuerdo",-0.66,IF(R3="Totalmente en Desacuerdo",-1,"error")))))) -> 1 | T3: Muy en Desacuerdo | U3: =IF(T3="Totalmente de Acuerdo",-1,IF(T3="Muy de Acuerdo",-0.66,IF(T3="Levemente de Acuerdo",-0.33,IF(T3="Levemente en Desacuerdo",0.33,IF(T3="Muy en Desacuerdo",0.66,IF(T3="Totalmente en Desacuerdo",1,"error")))))) -> 0.66 | V3: Totalmente de Acuerdo | W3: =IF(V3="Totalmente de Acuerdo",1,IF(V3="Muy de Acuerdo",0.66,IF(V3="Levemente de Acuerdo",0.33,IF(V3="Levemente en Desacuerdo",-0.33,IF(V3="Muy en Desacuerdo",-0.66,IF(V3="Totalmente en Desacuerdo",-1,"error")))))) -> 1 | X3: Totalmente de Acuerdo | Y3: =IF(X3="Totalmente de Acuerdo",1,IF(X3="Muy de Acuerdo",0.66,IF(X3="Levemente de Acuerdo",0.33,IF(X3="Levemente en Desacuerdo",-0.33,IF(X3="Muy en Desacuerdo",-0.66,IF(X3="Totalmente en Desacuerdo",-1,"error")))))) -> 1 | Z3: Muy en Desacuerdo | AA3: =IF(Z3="Totalmente de Acuerdo",1,IF(Z3="Muy de Acuerdo",0.66,IF(Z3="Levemente en Acuerdo",0.33,IF(Z3="Levemente en Desacuerdo",-0.33,IF(Z3="Muy en Desacuerdo",-0.66,IF(Z3="Totalmente en Desacuerdo",-1,"error")))))) -> -0.66 | AB3: =+AA3+Y3+W3+U3+S3+Q3+O3+M3 -> 3.67 | AC3: =+AB3*AB$36 -> 4.12875 | AD3: Levemente en Desacuerdo | AE3: =IF(AD3="Totalmente de Acuerdo",1,IF(AD3="Muy de Acuerdo",0.66,IF(AD3="Levemente de Acuerdo",0.33,IF(AD3="Levemente en Desacuerdo",-0.33,IF(AD3="Muy en Desacuerdo",-0.66,IF(AD3="Totalmente en Desacuerdo",-1,"error")))))) -> -0.33 | AF3: Totalmente de Acuerdo | AG3: =IF(AF3="Totalmente de Acuerdo",-1,IF(AF3="Muy de Acuerdo",-0.66,IF(AF3="Levemente de Acuerdo",-0.33,IF(AF3="Levemente en Desacuerdo",0.33,IF(AF3="Muy en Desacuerdo",0.66,IF(AF3="Totalmente en Desacuerdo",1,"error")))))) -> -1 | AH3: Levemente en Desacuerdo | AI3: =IF(AH3="Totalmente de Acuerdo",1,IF(AH3="Muy de Acuerdo",0.66,IF(AH3="Levemente de Acuerdo",0.33,IF(AH3="Levemente en Desacuerdo",-0.33,IF(AH3="Muy en Desacuerdo",-0.66,IF(AH3="Totalmente en Desacuerdo",-1,"error")))))) -> -0.33 | AJ3: Levemente en Desacuerdo | AK3: =IF(AJ3="Totalmente de Acuerdo",1,IF(AJ3="Muy de Acuerdo",0.66,IF(AJ3="Levemente de Acuerdo",0.33,IF(AJ3="Levemente en Desacuerdo",-0.33,IF(AJ3="Muy en Desacuerdo",-0.66,IF(AJ3="Totalmente en Desacuerdo",-1,"error")))))) -> -0.33 | AL3: Muy en Desacuerdo | AM3: =IF(AL3="Totalmente de Acuerdo",-1,IF(AL3="Muy de Acuerdo",-0.66,IF(AL3="Levemente de Acuerdo",-0.33,IF(AL3="Levemente en Desacuerdo",0.33,IF(AL3="Muy en Desacuerdo",0.66,IF(AL3="Totalmente en Desacuerdo",1,"error")))))) -> 0.66 | AN3: Totalmente en Desacuerdo | AO3: =IF(AN3="Totalmente de Acuerdo",-1,IF(AN3="Muy de Acuerdo",-0.66,IF(AN3="Levemente de Acuerdo",-0.33,IF(AN3="Levemente en Desacuerdo",0.33,IF(AN3="Muy en Desacuerdo",0.66,IF(AN3="Totalmente en Desacuerdo",1,"error")))))) -> 1 | AP3: Muy en Desacuerdo | AQ3: =IF(AP3="Totalmente de Acuerdo",-1,IF(AP3="Muy de Acuerdo",-0.66,IF(AP3="Levemente de Acuerdo",-0.33,IF(AP3="Levemente en Desacuerdo",0.33,IF(AP3="Muy en Desacuerdo",0.66,IF(AP3="Totalmente en Desacuerdo",1,"error")))))) -> 0.66 | AR3: Totalmente de Acuerdo | AS3: =IF(AR3="Totalmente de Acuerdo",1,IF(AR3="Muy de Acuerdo",0.66,IF(AR3="Levemente de Acuerdo",0.33,IF(AR3="Levemente en Desacuerdo",-0.33,IF(AR3="Muy en Desacuerdo",-0.66,IF(AR3="Totalmente en Desacuerdo",-1,"error")))))) -> 1 | AT3: Totalmente en Desacuerdo | AU3: =IF(AT3="Totalmente de Acuerdo",-1,IF(AT3="Muy de Acuerdo",-0.66,IF(AT3="Levemente de Acuerdo",-0.33,IF(AT3="Levemente en Desacuerdo",0.33,IF(AT3="Muy en Desacuerdo",0.66,IF(AT3="Totalmente en Desacuerdo",1,"error")))))) -> 1 | AV3: =AU3+AS3+AQ3+AO3+AM3+AK3+AI3+AG3+AE3 -> 2.33 | AW3: Totalmente de Acuerdo | AX3: Muy en Desacuerdo | AY3: Totalmente en Desacuerdo | AZ3: Muy de Acuerdo | BA3: Totalmente en Desacuerdo | BB3: Totalmente de Acuerdo | BC3: Levemente de Acuerdo | BD3: Levemente de Acuerdo | BE3: Levemente en Desacuerdo | BF3: Muy en Desacuerdo | BG3: Muy de Acuerdo | BH3: Me identifico | BL3: Me identifico | BX3: Patricia Bullrich (Juntos por el Cambio) | BY3: Javier Milei (La Libertad Avanza) | BZ3: Javier Milei (La Libertad Avanza)
A4: 45547.898 | B4: 00164890275 | C4: 1998 | D4: Quinto año | E4: Varón | F4: Universitario completo | G4: Universitario incompleto | H4: Clase Alta (ABC1): más de $2.850.000 mensuales | I4: Familia | J4: Otra localidad en otra Provincia | K4: . | L4: Levemente de Acuerdo | M4: =IF(L4="Totalmente de Acuerdo",-1,IF(L4="Muy de Acuerdo",-0.66,IF(L4="Levemente de Acuerdo",-0.33,IF(L4="Levemente en Desacuerdo",0.33,IF(L4="Muy en Desacuerdo",0.66,IF(L4="Totalmente en Desacuerdo",1,"error")))))) -> -0.33 | N4: Muy en Desacuerdo | O4: =IF(N4="Totalmente de Acuerdo",1,IF(N4="Muy de Acuerdo",0.66,IF(N4="Levemente de Acuerdo",0.33,IF(N4="Levemente en Desacuerdo",-0.33,IF(N4="Muy en Desacuerdo",-0.66,IF(N4="Totalmente en Desacuerdo",-1,"error")))))) -> -0.66 | P4: Totalmente de Acuerdo | Q4: =IF(P4="Totalmente de Acuerdo",-1,IF(P4="Muy de Acuerdo",-0.66,IF(P4="Levemente de Acuerdo",-0.33,IF(P4="Levemente en Desacuerdo",0.33,IF(P4="Muy en Desacuerdo",0.66,IF(P4="Totalmente en Desacuerdo",1,"error")))))) -> -1 | R4: Levemente de Acuerdo | S4: =IF(R4="Totalmente de Acuerdo",1,IF(R4="Muy de Acuerdo",0.66,IF(R4="Levemente de Acuerdo",0.33,IF(R4="Levemente en Desacuerdo",-0.33,IF(R4="Muy en Desacuerdo",-0.66,IF(R4="Totalmente en Desacuerdo",-1,"error")))))) -> 0.33 | T4: Levemente en Desacuerdo | U4: =IF(T4="Totalmente de Acuerdo",-1,IF(T4="Muy de Acuerdo",-0.66,IF(T4="Levemente de Acuerdo",-0.33,IF(T4="Levemente en Desacuerdo",0.33,IF(T4="Muy en Desacuerdo",0.66,IF(T4="Totalmente en Desacuerdo",1,"error")))))) -> 0.33 | V4: Levemente en Desacuerdo | W4: =IF(V4="Totalmente de Acuerdo",1,IF(V4="Muy de Acuerdo",0.66,IF(V4="Levemente de Acuerdo",0.33,IF(V4="Levemente en Desacuerdo",-0.33,IF(V4="Muy en Desacuerdo",-0.66,IF(V4="Totalmente en Desacuerdo",-1,"error")))))) -> -0.33 | X4: Levemente en Desacuerdo | Y4: =IF(X4="Totalmente de Acuerdo",1,IF(X4="Muy de Acuerdo",0.66,IF(X4="Levemente de Acuerdo",0.33,IF(X4="Levemente en Desacuerdo",-0.33,IF(X4="Muy en Desacuerdo",-0.66,IF(X4="Totalmente en Desacuerdo",-1,"error")))))) -> -0.33 | Z4: Muy en Desacuerdo | AA4: =IF(Z4="Totalmente de Acuerdo",1,IF(Z4="Muy de Acuerdo",0.66,IF(Z4="Levemente en Acuerdo",0.33,IF(Z4="Levemente en Desacuerdo",-0.33,IF(Z4="Muy en Desacuerdo",-0.66,IF(Z4="Totalmente en Desacuerdo",-1,"error")))))) -> -0.66 | AB4: =+AA4+Y4+W4+U4+S4+Q4+O4+M4 -> -2.65 | AC4: =+AB4*AB$36 -> -2.98125 | AD4: Levemente de Acuerdo | AE4: =IF(AD4="Totalmente de Acuerdo",1,IF(AD4="Muy de Acuerdo",0.66,IF(AD4="Levemente de Acuerdo",0.33,IF(AD4="Levemente en Desacuerdo",-0.33,IF(AD4="Muy en Desacuerdo",-0.66,IF(AD4="Totalmente en Desacuerdo",-1,"error")))))) -> 0.33 | AF4: Levemente de Acuerdo | AG4: =IF(AF4="Totalmente de Acuerdo",-1,IF(AF4="Muy de Acuerdo",-0.66,IF(AF4="Levemente de Acuerdo",-0.33,IF(AF4="Levemente en Desacuerdo",0.33,IF(AF4="Muy en Desacuerdo",0.66,IF(AF4="Totalmente en Desacuerdo",1,"error")))))) -> -0.33 | AH4: Totalmente en Desacuerdo | AI4: =IF(AH4="Totalmente de Acuerdo",1,IF(AH4="Muy de Acuerdo",0.66,IF(AH4="Levemente de Acuerdo",0.33,IF(AH4="Levemente en Desacuerdo",-0.33,IF(AH4="Muy en Desacuerdo",-0.66,IF(AH4="Totalmente en Desacuerdo",-1,"error")))))) -> -1 | AJ4: Totalmente en Desacuerdo | AK4: =IF(AJ4="Totalmente de Acuerdo",1,IF(AJ4="Muy de Acuerdo",0.66,IF(AJ4="Levemente de Acuerdo",0.33,IF(AJ4="Levemente en Desacuerdo",-0.33,IF(AJ4="Muy en Desacuerdo",-0.66,IF(AJ4="Totalmente en Desacuerdo",-1,"error")))))) -> -1 | AL4: Muy de Acuerdo | AM4: =IF(AL4="Totalmente de Acuerdo",-1,IF(AL4="Muy de Acuerdo",-0.66,IF(AL4="Levemente de Acuerdo",-0.33,IF(AL4="Levemente en Desacuerdo",0.33,IF(AL4="Muy en Desacuerdo",0.66,IF(AL4="Totalmente en Desacuerdo",1,"error")))))) -> -0.66 | AN4: Muy de Acuerdo | AO4: =IF(AN4="Totalmente de Acuerdo",-1,IF(AN4="Muy de Acuerdo",-0.66,IF(AN4="Levemente de Acuerdo",-0.33,IF(AN4="Levemente en Desacuerdo",0.33,IF(AN4="Muy en Desacuerdo",0.66,IF(AN4="Totalmente en Desacuerdo",1,"error")))))) -> -0.66 | AP4: Muy de Acuerdo | AQ4: =IF(AP4="Totalmente de Acuerdo",-1,IF(AP4="Muy de Acuerdo",-0.66,IF(AP4="Levemente de Acuerdo",-0.33,IF(AP4="Levemente en Desacuerdo",0.33,IF(AP4="Muy en Desacuerdo",0.66,IF(AP4="Totalmente en Desacuerdo",1,"error")))))) -> -0.66 | AR4: Totalmente en Desacuerdo | AS4: =IF(AR4="Totalmente de Acuerdo",1,IF(AR4="Muy de Acuerdo",0.66,IF(AR4="Levemente de Acuerdo",0.33,IF(AR4="Levemente en Desacuerdo",-0.33,IF(AR4="Muy en Desacuerdo",-0.66,IF(AR4="Totalmente en Desacuerdo",-1,"error")))))) -> -1 | AT4: Totalmente en Desacuerdo | AU4: =IF(AT4="Totalmente de Acuerdo",-1,IF(AT4="Muy de Acuerdo",-0.66,IF(AT4="Levemente de Acuerdo",-0.33,IF(AT4="Levemente en Desacuerdo",0.33,IF(AT4="Muy en Desacuerdo",0.66,IF(AT4="Totalmente en Desacuerdo",1,"error")))))) -> 1 | AV4: =AU4+AS4+AQ4+AO4+AM4+AK4+AI4+AG4+AE4 -> -3.98 | AW4: Totalmente en Desacuerdo | AX4: Levemente de Acuerdo | AY4: Levemente de Acuerdo | AZ4: Levemente de Acuerdo | BA4: Levemente en Desacuerdo | BB4: Muy en Desacuerdo | BC4: Muy en Desacuerdo | BD4: Levemente en Desacuerdo | BE4: Levemente en Desacuerdo | BF4: Muy de Acuerdo | BG4: Levemente de Acuerdo | BJ4: Me identifico | BK4: Me identifico | BX4: Horacio Rodríguez Larreta (Juntos por el Cambio) | BY4: Sergio Massa (Unión por la Patria) | BZ4: Sergio Massa (Unión por la Patria)
A5: 45547.898 | B5: 00578280042 | C5: 2003 | D5: Tercer año | E5: Varón | F5: Universitario incompleto | G5: Terciario completo | H5: Clase Media Alta (C2): entre $1.350.001 mensuales y $2.850.000 mensuales | I5: Familia | J5: Otra localidad en la Provincia de Córdoba | K5: . | L5: Levemente en Desacuerdo | M5: =IF(L5="Totalmente de Acuerdo",-1,IF(L5="Muy de Acuerdo",-0.66,IF(L5="Levemente de Acuerdo",-0.33,IF(L5="Levemente en Desacuerdo",0.33,IF(L5="Muy en Desacuerdo",0.66,IF(L5="Totalmente en Desacuerdo",1,"error")))))) -> 0.33 | N5: Muy en Desacuerdo | O5: =IF(N5="Totalmente de Acuerdo",1,IF(N5="Muy de Acuerdo",0.66,IF(N5="Levemente de Acuerdo",0.33,IF(N5="Levemente en Desacuerdo",-0.33,IF(N5="Muy en Desacuerdo",-0.66,IF(N5="Totalmente en Desacuerdo",-1,"error")))))) -> -0.66 | P5: Muy de Acuerdo | Q5: =IF(P5="Totalmente de Acuerdo",-1,IF(P5="Muy de Acuerdo",-0.66,IF(P5="Levemente de Acuerdo",-0.33,IF(P5="Levemente en Desacuerdo",0.33,IF(P5="Muy en Desacuerdo",0.66,IF(P5="Totalmente en Desacuerdo",1,"error")))))) -> -0.66 | R5: Totalmente de Acuerdo | S5: =IF(R5="Totalmente de Acuerdo",1,IF(R5="Muy de Acuerdo",0.66,IF(R5="Levemente de Acuerdo",0.33,IF(R5="Levemente en Desacuerdo",-0.33,IF(R5="Muy en Desacuerdo",-0.66,IF(R5="Totalmente en Desacuerdo",-1,"error")))))) -> 1 | T5: Levemente de Acuerdo | U5: =IF(T5="Totalmente de Acuerdo",-1,IF(T5="Muy de Acuerdo",-0.66,IF(T5="Levemente de Acuerdo",-0.33,IF(T5="Levemente en Desacuerdo",0.33,IF(T5="Muy en Desacuerdo",0.66,IF(T5="Totalmente en Desacuerdo",1,"error")))))) -> -0.33 | V5: Totalmente de Acuerdo | W5: =IF(V5="Totalmente de Acuerdo",1,IF(V5="Muy de Acuerdo",0.66,IF(V5="Levemente de Acuerdo",0.33,IF(V5="Levemente en Desacuerdo",-0.33,IF(V5="Muy en Desacuerdo",-0.66,IF(V5="Totalmente en Desacuerdo",-1,"error")))))) -> 1 | X5: Muy de Acuerdo | Y5: =IF(X5="Totalmente de Acuerdo",1,IF(X5="Muy de Acuerdo",0.66,IF(X5="Levemente de Acuerdo",0.33,IF(X5="Levemente en Desacuerdo",-0.33,IF(X5="Muy en Desacuerdo",-0.66,IF(X5="Totalmente en Desacuerdo",-1,"error")))))) -> 0.66 | Z5: Muy en Desacuerdo | AA5: =IF(Z5="Totalmente de Acuerdo",1,IF(Z5="Muy de Acuerdo",0.66,IF(Z5="Levemente en Acuerdo",0.33,IF(Z5="Levemente en Desacuerdo",-0.33,IF(Z5="Muy en Desacuerdo",-0.66,IF(Z5="Totalmente en Desacuerdo",-1,"error")))))) -> -0.66 | AB5: =+AA5+Y5+W5+U5+S5+Q5+O5+M5 -> 0.68 | AC5: =+AB5*AB$36 -> 0.765 | AD5: Totalmente de Acuerdo | AE5: =IF(AD5="Totalmente de Acuerdo",1,IF(AD5="Muy de Acuerdo",0.66,IF(AD5="Levemente de Acuerdo",0.33,IF(AD5="Levemente en Desacuerdo",-0.33,IF(AD5="Muy en Desacuerdo",-0.66,IF(AD5="Totalmente en Desacuerdo",-1,"error")))))) -> 1 | AF5: Totalmente de Acuerdo | AG5: =IF(AF5="Totalmente de Acuerdo",-1,IF(AF5="Muy de Acuerdo",-0.66,IF(AF5="Levemente de Acuerdo",-0.33,IF(AF5="Levemente en Desacuerdo",0.33,IF(AF5="Muy en Desacuerdo",0.66,IF(AF5="Totalmente en Desacuerdo",1,"error")))))) -> -1 | AH5: Levemente de Acuerdo | AI5: =IF(AH5="Totalmente de Acuerdo",1,IF(AH5="Muy de Acuerdo",0.66,IF(AH5="Levemente de Acuerdo",0.33,IF(AH5="Levemente en Desacuerdo",-0.33,IF(AH5="Muy en Desacuerdo",-0.66,IF(AH5="Totalmente en Desacuerdo",-1,"error")))))) -> 0.33 | AJ5: Totalmente en Desacuerdo | AK5: =IF(AJ5="Totalmente de Acuerdo",1,IF(AJ5="Muy de Acuerdo",0.66,IF(AJ5="Levemente de Acuerdo",0.33,IF(AJ5="Levemente en Desacuerdo",-0.33,IF(AJ5="Muy en Desacuerdo",-0.66,IF(AJ5="Totalmente en Desacuerdo",-1,"error")))))) -> -1 | AL5: Levemente en Desacuerdo | AM5: =IF(AL5="Totalmente de Acuerdo",-1,IF(AL5="Muy de Acuerdo",-0.66,IF(AL5="Levemente de Acuerdo",-0.33,IF(AL5="Levemente en Desacuerdo",0.33,IF(AL5="Muy en Desacuerdo",0.66,IF(AL5="Totalmente en Desacuerdo",1,"error")))))) -> 0.33 | AN5: Totalmente en Desacuerdo | AO5: =IF(AN5="Totalmente de Acuerdo",-1,IF(AN5="Muy de Acuerdo",-0.66,IF(AN5="Levemente de Acuerdo",-0.33,IF(AN5="Levemente en Desacuerdo",0.33,IF(AN5="Muy en Desacuerdo",0.66,IF(AN5="Totalmente en Desacuerdo",1,"error")))))) -> 1 | AP5: Totalmente en Desacuerdo | AQ5: =IF(AP5="Totalmente de Acuerdo",-1,IF(AP5="Muy de Acuerdo",-0.66,IF(AP5="Levemente de Acuerdo",-0.33,IF(AP5="Levemente en Desacuerdo",0.33,IF(AP5="Muy en Desacuerdo",0.66,IF(AP5="Totalmente en Desacuerdo",1,"error")))))) -> 1 | AR5: Levemente en Desacuerdo | AS5: =IF(AR5="Totalmente de Acuerdo",1,IF(AR5="Muy de Acuerdo",0.66,IF(AR5="Levemente de Acuerdo",0.33,IF(AR5="Levemente en Desacuerdo",-0.33,IF(AR5="Muy en Desacuerdo",-0.66,IF(AR5="Totalmente en Desacuerdo",-1,"error")))))) -> -0.33 | AT5: Muy en Desacuerdo | AU5: =IF(AT5="Totalmente de Acuerdo",-1,IF(AT5="Muy de Acuerdo",-0.66,IF(AT5="Levemente de Acuerdo",-0.33,IF(AT5="Levemente en Desacuerdo",0.33,IF(AT5="Muy en Desacuerdo",0.66,IF(AT5="Totalmente en Desacuerdo",1,"error")))))) -> 0.66 | AV5: =AU5+AS5+AQ5+AO5+AM5+AK5+AI5+AG5+AE5 -> 1.99 | AW5: Levemente en Desacuerdo | AX5: Muy de Acuerdo | AY5: Totalmente en Desacuerdo | AZ5: Muy de Acuerdo | BA5: Levemente de Acuerdo | BB5: Levemente de Acuerdo | BC5: Levemente de Acuerdo | BD5: Totalmente de Acuerdo | BE5: Muy de Acuerdo | BF5: Levemente en Desacuerdo | BG5: Muy de Acuerdo | BH5: Me identifico | BL5: Me identifico | BM5: Me identifico | BX5: Javier Milei (La Libertad Avanza) | BY5: Javier Milei (La Libertad Avanza) | BZ5: Javier Milei (La Libertad Avanza)
A6: 45547.899 | B6: 00464782483 | C6: 2001 | D6: Cuarto año | E6: Varón | F6: Universitario completo | G6: Universitario completo | H6: Clase Media Alta (C2): entre $1.350.001 mensuales y $2.850.000 mensuales | I6: Familia | J6: Otra localidad en la Provincia de Córdoba | K6: . | L6: Muy de Acuerdo | M6: =IF(L6="Totalmente de Acuerdo",-1,IF(L6="Muy de Acuerdo",-0.66,IF(L6="Levemente de Acuerdo",-0.33,IF(L6="Levemente en Desacuerdo",0.33,IF(L6="Muy en Desacuerdo",0.66,IF(L6="Totalmente en Desacuerdo",1,"error")))))) -> -0.66 | N6: Levemente de Acuerdo | O6: =IF(N6="Totalmente de Acuerdo",1,IF(N6="Muy de Acuerdo",0.66,IF(N6="Levemente de Acuerdo",0.33,IF(N6="Levemente en Desacuerdo",-0.33,IF(N6="Muy en Desacuerdo",-0.66,IF(N6="Totalmente en Desacuerdo",-1,"error")))))) -> 0.33 | P6: Levemente de Acuerdo | Q6: =IF(P6="Totalmente de Acuerdo",-1,IF(P6="Muy de Acuerdo",-0.66,IF(P6="Levemente de Acuerdo",-0.33,IF(P6="Levemente en Desacuerdo",0.33,IF(P6="Muy en Desacuerdo",0.66,IF(P6="Totalmente en Desacuerdo",1,"error")))))) -> -0.33 | R6: Levemente de Acuerdo | S6: =IF(R6="Totalmente de Acuerdo",1,IF(R6="Muy de Acuerdo",0.66,IF(R6="Levemente de Acuerdo",0.33,IF(R6="Levemente en Desacuerdo",-0.33,IF(R6="Muy en Desacuerdo",-0.66,IF(R6="Totalmente en Desacuerdo",-1,"error")))))) -> 0.33 | T6: Muy de Acuerdo | U6: =IF(T6="Totalmente de Acuerdo",-1,IF(T6="Muy de Acuerdo",-0.66,IF(T6="Levemente de Acuerdo",-0.33,IF(T6="Levemente en Desacuerdo",0.33,IF(T6="Muy en Desacuerdo",0.66,IF(T6="Totalmente en Desacuerdo",1,"error")))))) -> -0.66 | V6: Muy de Acuerdo | W6: =IF(V6="Totalmente de Acuerdo",1,IF(V6="Muy de Acuerdo",0.66,IF(V6="Levemente de Acuerdo",0.33,IF(V6="Levemente en Desacuerdo",-0.33,IF(V6="Muy en Desacuerdo",-0.66,IF(V6="Totalmente en Desacuerdo",-1,"error")))))) -> 0.66 | X6: Muy de Acuerdo | Y6: =IF(X6="Totalmente de Acuerdo",1,IF(X6="Muy de Acuerdo",0.66,IF(X6="Levemente de Acuerdo",0.33,IF(X6="Levemente en Desacuerdo",-0.33,IF(X6="Muy en Desacuerdo",-0.66,IF(X6="Totalmente en Desacuerdo",-1,"error")))))) -> 0.66 | Z6: Levemente en Acuerdo | AA6: =IF(Z6="Totalmente de Acuerdo",1,IF(Z6="Muy de Acuerdo",0.66,IF(Z6="Levemente en Acuerdo",0.33,IF(Z6="Levemente en Desacuerdo",-0.33,IF(Z6="Muy en Desacuerdo",-0.66,IF(Z6="Totalmente en Desacuerdo",-1,"error")))))) -> 0.33 | AB6: =+AA6+Y6+W6+U6+S6+Q6+O6+M6 -> 0.66 | AC6: =+AB6*AB$36 -> 0.7425 | AD6: Levemente de Acuerdo | AE6: =IF(AD6="Totalmente de Acuerdo",1,IF(AD6="Muy de Acuerdo",0.66,IF(AD6="Levemente de Acuerdo",0.33,IF(AD6="Levemente en Desacuerdo",-0.33,IF(AD6="Muy en Desacuerdo",-0.66,IF(AD6="Totalmente en Desacuerdo",-1,"error")))))) -> 0.33 | AF6: Totalmente de Acuerdo | AG6: =IF(AF6="Totalmente de Acuerdo",-1,IF(AF6="Muy de Acuerdo",-0.66,IF(AF6="Levemente de Acuerdo",-0.33,IF(AF6="Levemente en Desacuerdo",0.33,IF(AF6="Muy en Desacuerdo",0.66,IF(AF6="Totalmente en Desacuerdo",1,"error")))))) -> -1 | AH6: Muy de Acuerdo | AI6: =IF(AH6="Totalmente de Acuerdo",1,IF(AH6="Muy de Acuerdo",0.66,IF(AH6="Levemente de Acuerdo",0.33,IF(AH6="Levemente en Desacuerdo",-0.33,IF(AH6="Muy en Desacuerdo",-0.66,IF(AH6="Totalmente en Desacuerdo",-1,"error")))))) -> 0.66 | AJ6: Totalmente en Desacuerdo | AK6: =IF(AJ6="Totalmente de Acuerdo",1,IF(AJ6="Muy de Acuerdo",0.66,IF(AJ6="Levemente de Acuerdo",0.33,IF(AJ6="Levemente en Desacuerdo",-0.33,IF(AJ6="Muy en Desacuerdo",-0.66,IF(AJ6="Totalmente en Desacuerdo",-1,"error")))))) -> -1 | AL6: Muy de Acuerdo | AM6: =IF(AL6="Totalmente de Acuerdo",-1,IF(AL6="Muy de Acuerdo",-0.66,IF(AL6="Levemente de Acuerdo",-0.33,IF(AL6="Levemente en Desacuerdo",0.33,IF(AL6="Muy en Desacuerdo",0.66,IF(AL6="Totalmente en Desacuerdo",1,"error")))))) -> -0.66 | AN6: Levemente en Desacuerdo | AO6: =IF(AN6="Totalmente de Acuerdo",-1,IF(AN6="Muy de Acuerdo",-0.66,IF(AN6="Levemente de Acuerdo",-0.33,IF(AN6="Levemente en Desacuerdo",0.33,IF(AN6="Muy en Desacuerdo",0.66,IF(AN6="Totalmente en Desacuerdo",1,"error")))))) -> 0.33 | AP6: Levemente en Desacuerdo | AQ6: =IF(AP6="Totalmente de Acuerdo",-1,IF(AP6="Muy de Acuerdo",-0.66,IF(AP6="Levemente de Acuerdo",-0.33,IF(AP6="Levemente en Desacuerdo",0.33,IF(AP6="Muy en Desacuerdo",0.66,IF(AP6="Totalmente en Desacuerdo",1,"error")))))) -> 0.33 | AR6: Muy de Acuerdo | AS6: =IF(AR6="Totalmente de Acuerdo",1,IF(AR6="Muy de Acuerdo",0.66,IF(AR6="Levemente de Acuerdo",0.33,IF(AR6="Levemente en Desacuerdo",-0.33,IF(AR6="Muy en Desacuerdo",-0.66,IF(AR6="Totalmente en Desacuerdo",-1,"error")))))) -> 0.66 | AT6: Levemente en Desacuerdo | AU6: =IF(AT6="Totalmente de Acuerdo",-1,IF(AT6="Muy de Acuerdo",-0.66,IF(AT6="Levemente de Acuerdo",-0.33,IF(AT6="Levemente en Desacuerdo",0.33,IF(AT6="Muy en Desacuerdo",0.66,IF(AT6="Totalmente en Desacuerdo",1,"error")))))) -> 0.33 | AV6: =AU6+AS6+AQ6+AO6+AM6+AK6+AI6+AG6+AE6 -> -0.02 | AW6: Levemente de Acuerdo | AX6: Levemente de Acuerdo | AY6: Levemente en Desacuerdo | AZ6: Levemente de Acuerdo | BA6: Levemente de Acuerdo | BB6: Levemente de Acuerdo | BC6: Levemente de Acuerdo | BD6: Levemente de Acuerdo | BE6: Muy de Acuerdo | BF6: Muy de Acuerdo | BG6: Muy de Acuerdo | BM6: Me identifico | BX6: Javier Milei (La Libertad Avanza) | BY6: Javier Milei (La Libertad Avanza) | BZ6: Javier Milei (La Libertad Avanza)
A7: 45547.899 | B7: 00661842297 | C7: 2000 | D7: Cuarto año | E7: Varón | F7: Universitario incompleto | G7: Universitario completo | H7: Clase Media Alta (C2): entre $1.350.001 mensuales y $2.850.000 mensuales | I7: Familia | J7: Otra localidad en otra Provincia | K7: . | L7: Levemente en Desacuerdo | M7: =IF(L7="Totalmente de Acuerdo",-1,IF(L7="Muy de Acuerdo",-0.66,IF(L7="Levemente de Acuerdo",-0.33,IF(L7="Levemente en Desacuerdo",0.33,IF(L7="Muy en Desacuerdo",0.66,IF(L7="Totalmente en Desacuerdo",1,"error")))))) -> 0.33 | N7: Levemente en Desacuerdo | O7: =IF(N7="Totalmente de Acuerdo",1,IF(N7="Muy de Acuerdo",0.66,IF(N7="Levemente de Acuerdo",0.33,IF(N7="Levemente en Desacuerdo",-0.33,IF(N7="Muy en Desacuerdo",-0.66,IF(N7="Totalmente en Desacuerdo",-1,"error")))))) -> -0.33 | P7: Muy de Acuerdo | Q7: =IF(P7="Totalmente de Acuerdo",-1,IF(P7="Muy de Acuerdo",-0.66,IF(P7="Levemente de Acuerdo",-0.33,IF(P7="Levemente en Desacuerdo",0.33,IF(P7="Muy en Desacuerdo",0.66,IF(P7="Totalmente en Desacuerdo",1,"error")))))) -> -0.66 | R7: Muy de Acuerdo | S7: =IF(R7="Totalmente de Acuerdo",1,IF(R7="Muy de Acuerdo",0.66,IF(R7="Levemente de Acuerdo",0.33,IF(R7="Levemente en Desacuerdo",-0.33,IF(R7="Muy en Desacuerdo",-0.66,IF(R7="Totalmente en Desacuerdo",-1,"error")))))) -> 0.66 | T7: Levemente de Acuerdo | U7: =IF(T7="Totalmente de Acuerdo",-1,IF(T7="Muy de Acuerdo",-0.66,IF(T7="Levemente de Acuerdo",-0.33,IF(T7="Levemente en Desacuerdo",0.33,IF(T7="Muy en Desacuerdo",0.66,IF(T7="Totalmente en Desacuerdo",1,"error")))))) -> -0.33 | V7: Levemente en Desacuerdo | W7: =IF(V7="Totalmente de Acuerdo",1,IF(V7="Muy de Acuerdo",0.66,IF(V7="Levemente de Acuerdo",0.33,IF(V7="Levemente en Desacuerdo",-0.33,IF(V7="Muy en Desacuerdo",-0.66,IF(V7="Totalmente en Desacuerdo",-1,"error")))))) -> -0.33 | X7: Levemente de Acuerdo | Y7: =IF(X7="Totalmente de Acuerdo",1,IF(X7="Muy de Acuerdo",0.66,IF(X7="Levemente de Acuerdo",0.33,IF(X7="Levemente en Desacuerdo",-0.33,IF(X7="Muy en Desacuerdo",-0.66,IF(X7="Totalmente en Desacuerdo",-1,"error")))))) -> 0.33 | Z7: Muy en Desacuerdo | AA7: =IF(Z7="Totalmente de Acuerdo",1,IF(Z7="Muy de Acuerdo",0.66,IF(Z7="Levemente en Acuerdo",0.33,IF(Z7="Levemente en Desacuerdo",-0.33,IF(Z7="Muy en Desacuerdo",-0.66,IF(Z7="Totalmente en Desacuerdo",-1,"error")))))) -> -0.66 | AB7: =+AA7+Y7+W7+U7+S7+Q7+O7+M7 -> -0.99 | AC7: =+AB7*AB$36 -> -1.11375 | AD7: Muy en Desacuerdo | AE7: =IF(AD7="Totalmente de Acuerdo",1,IF(AD7="Muy de Acuerdo",0.66,IF(AD7="Levemente de Acuerdo",0.33,IF(AD7="Levemente en Desacuerdo",-0.33,IF(AD7="Muy en Desacuerdo",-0.66,IF(AD7="Totalmente en Desacuerdo",-1,"error")))))) -> -0.66 | AF7: Levemente en Desacuerdo | AG7: =IF(AF7="Totalmente de Acuerdo",-1,IF(AF7="Muy de Acuerdo",-0.66,IF(AF7="Levemente de Acuerdo",-0.33,IF(AF7="Levemente en Desacuerdo",0.33,IF(AF7="Muy en Desacuerdo",0.66,IF(AF7="Totalmente en Desacuerdo",1,"error")))))) -> 0.33 | AH7: Levemente en Desacuerdo | AI7: =IF(AH7="Totalmente de Acuerdo",1,IF(AH7="Muy de Acuerdo",0.66,IF(AH7="Levemente de Acuerdo",0.33,IF(AH7="Levemente en Desacuerdo",-0.33,IF(AH7="Muy en Desacuerdo",-0.66,IF(AH7="Totalmente en Desacuerdo",-1,"error")))))) -> -0.33 | AJ7: Totalmente en Desacuerdo | AK7: =IF(AJ7="Totalmente de Acuerdo",1,IF(AJ7="Muy de Acuerdo",0.66,IF(AJ7="Levemente de Acuerdo",0.33,IF(AJ7="Levemente en Desacuerdo",-0.33,IF(AJ7="Muy en Desacuerdo",-0.66,IF(AJ7="Totalmente en Desacuerdo",-1,"error")))))) -> -1 | AL7: Muy de Acuerdo | AM7: =IF(AL7="Totalmente de Acuerdo",-1,IF(AL7="Muy de Acuerdo",-0.66,IF(AL7="Levemente de Acuerdo",-0.33,IF(AL7="Levemente en Desacuerdo",0.33,IF(AL7="Muy en Desacuerdo",0.66,IF(AL7="Totalmente en Desacuerdo",1,"error")))))) -> -0.66 | AN7: Levemente de Acuerdo | AO7: =IF(AN7="Totalmente de Acuerdo",-1,IF(AN7="Muy de Acuerdo",-0.66,IF(AN7="Levemente de Acuerdo",-0.33,IF(AN7="Levemente en Desacuerdo",0.33,IF(AN7="Muy en Desacuerdo",0.66,IF(AN7="Totalmente en Desacuerdo",1,"error")))))) -> -0.33 | AP7: Muy en Desacuerdo | AQ7: =IF(AP7="Totalmente de Acuerdo",-1,IF(AP7="Muy de Acuerdo",-0.66,IF(AP7="Levemente de Acuerdo",-0.33,IF(AP7="Levemente en Desacuerdo",0.33,IF(AP7="Muy en Desacuerdo",0.66,IF(AP7="Totalmente en Desacuerdo",1,"error")))))) -> 0.66 | AR7: Muy de Acuerdo | AS7: =IF(AR7="Totalmente de Acuerdo",1,IF(AR7="Muy de Acuerdo",0.66,IF(AR7="Levemente de Acuerdo",0.33,IF(AR7="Levemente en Desacuerdo",-0.33,IF(AR7="Muy en Desacuerdo",-0.66,IF(AR7="Totalmente en Desacuerdo",-1,"error")))))) -> 0.66 | AT7: Levemente de Acuerdo | AU7: =IF(AT7="Totalmente de Acuerdo",-1,IF(AT7="Muy de Acuerdo",-0.66,IF(AT7="Levemente de Acuerdo",-0.33,IF(AT7="Levemente en Desacuerdo",0.33,IF(AT7="Muy en Desacuerdo",0.66,IF(AT7="Totalmente en Desacuerdo",1,"error")))))) -> -0.33 | AV7: =AU7+AS7+AQ7+AO7+AM7+AK7+AI7+AG7+AE7 -> -1.66 | AW7: Levemente en Desacuerdo | AX7: Muy de Acuerdo | AY7: Muy en Desacuerdo | AZ7: Levemente de Acuerdo | BA7: Muy en Desacuerdo | BB7: Muy en Desacuerdo | BC7: Muy en Desacuerdo | BD7: Muy en Desacuerdo | BE7: Muy de Acuerdo | BF7: Levemente de Acuerdo | BG7: Levemente en Desacuerdo | BJ7: Me identifico | BX7: No vote | BY7: Sergio Massa (Unión por la Patria) | BZ7: Sergio Massa (Unión por la Patria)
A8: 45547.899 | B8: 00623233790 | C8: 1997 | D8: Quinto año | E8: Varón | F8: Universitario completo | G8: Universitario incompleto | H8: Clase Media Alta (C2): entre $1.350.001 mensuales y $2.850.000 mensuales | I8: Trabajo propio | J8: Ciudad de Córdoba | K8: . | L8: Totalmente en Desacuerdo | M8: =IF(L8="Totalmente de Acuerdo",-1,IF(L8="Muy de Acuerdo",-0.66,IF(L8="Levemente de Acuerdo",-0.33,IF(L8="Levemente en Desacuerdo",0.33,IF(L8="Muy en Desacuerdo",0.66,IF(L8="Totalmente en Desacuerdo",1,"error")))))) -> 1 | N8: Muy de Acuerdo | O8: =IF(N8="Totalmente de Acuerdo",1,IF(N8="Muy de Acuerdo",0.66,IF(N8="Levemente de Acuerdo",0.33,IF(N8="Levemente en Desacuerdo",-0.33,IF(N8="Muy en Desacuerdo",-0.66,IF(N8="Totalmente en Desacuerdo",-1,"error")))))) -> 0.66 | P8: Totalmente de Acuerdo | Q8: =IF(P8="Totalmente de Acuerdo",-1,IF(P8="Muy de Acuerdo",-0.66,IF(P8="Levemente de Acuerdo",-0.33,IF(P8="Levemente en Desacuerdo",0.33,IF(P8="Muy en Desacuerdo",0.66,IF(P8="Totalmente en Desacuerdo",1,"error")))))) -> -1 | R8: Totalmente de Acuerdo | S8: =IF(R8="Totalmente de Acuerdo",1,IF(R8="Muy de Acuerdo",0.66,IF(R8="Levemente de Acuerdo",0.33,IF(R8="Levemente en Desacuerdo",-0.33,IF(R8="Muy en Desacuerdo",-0.66,IF(R8="Totalmente en Desacuerdo",-1,"error")))))) -> 1 | T8: Totalmente en Desacuerdo | U8: =IF(T8="Totalmente de Acuerdo",-1,IF(T8="Muy de Acuerdo",-0.66,IF(T8="Levemente de Acuerdo",-0.33,IF(T8="Levemente en Desacuerdo",0.33,IF(T8="Muy en Desacuerdo",0.66,IF(T8="Totalmente en Desacuerdo",1,"error")))))) -> 1 | V8: Totalmente de Acuerdo | W8: =IF(V8="Totalmente de Acuerdo",1,IF(V8="Muy de Acuerdo",0.66,IF(V8="Levemente de Acuerdo",0.33,IF(V8="Levemente en Desacuerdo",-0.33,IF(V8="Muy en Desacuerdo",-0.66,IF(V8="Totalmente en Desacuerdo",-1,"error")))))) -> 1 | X8: Muy en Desacuerdo | Y8: =IF(X8="Totalmente de Acuerdo",1,IF(X8="Muy de Acuerdo",0.66,IF(X8="Levemente de Acuerdo",0.33,IF(X8="Levemente en Desacuerdo",-0.33,IF(X8="Muy en Desacuerdo",-0.66,IF(X8="Totalmente en Desacuerdo",-1,"error")))))) -> -0.66 | Z8: Muy en Desacuerdo | AA8: =IF(Z8="Totalmente de Acuerdo",1,IF(Z8="Muy de Acuerdo",0.66,IF(Z8="Levemente en Acuerdo",0.33,IF(Z8="Levemente en Desacuerdo",-0.33,IF(Z8="Muy en Desacuerdo",-0.66,IF(Z8="Totalmente en Desacuerdo",-1,"error")))))) -> -0.66 | AB8: =+AA8+Y8+W8+U8+S8+Q8+O8+M8 -> 2.34 | AC8: =+AB8*AB$36 -> 2.6325 | AD8: Totalmente en Desacuerdo | AE8: =IF(AD8="Totalmente de Acuerdo",1,IF(AD8="Muy de Acuerdo",0.66,IF(AD8="Levemente de Acuerdo",0.33,IF(AD8="Levemente en Desacuerdo",-0.33,IF(AD8="Muy en Desacuerdo",-0.66,IF(AD8="Totalmente en Desacuerdo",-1,"error")))))) -> -1 | AF8: Totalmente de Acuerdo | AG8: =IF(AF8="Totalmente de Acuerdo",-1,IF(AF8="Muy de Acuerdo",-0.66,IF(AF8="Levemente de Acuerdo",-0.33,IF(AF8="Levemente en Desacuerdo",0.33,IF(AF8="Muy en Desacuerdo",0.66,IF(AF8="Totalmente en Desacuerdo",1,"error")))))) -> -1 | AH8: Muy en Desacuerdo | AI8: =IF(AH8="Totalmente de Acuerdo",1,IF(AH8="Muy de Acuerdo",0.66,IF(AH8="Levemente de Acuerdo",0.33,IF(AH8="Levemente en Desacuerdo",-0.33,IF(AH8="Muy en Desacuerdo",-0.66,IF(AH8="Totalmente en Desacuerdo",-1,"error")))))) -> -0.66 | AJ8: Totalmente en Desacuerdo | AK8: =IF(AJ8="Totalmente de Acuerdo",1,IF(AJ8="Muy de Acuerdo",0.66,IF(AJ8="Levemente de Acuerdo",0.33,IF(AJ8="Levemente en Desacuerdo",-0.33,IF(AJ8="Muy en Desacuerdo",-0.66,IF(AJ8="Totalmente en Desacuerdo",-1,"error")))))) -> -1 | AL8: Levemente de Acuerdo | AM8: =IF(AL8="Totalmente de Acuerdo",-1,IF(AL8="Muy de Acuerdo",-0.66,IF(AL8="Levemente de Acuerdo",-0.33,IF(AL8="Levemente en Desacuerdo",0.33,IF(AL8="Muy en Desacuerdo",0.66,IF(AL8="Totalmente en Desacuerdo",1,"error")))))) -> -0.33 | AN8: Totalmente en Desacuerdo | AO8: =IF(AN8="Totalmente de Acuerdo",-1,IF(AN8="Muy de Acuerdo",-0.66,IF(AN8="Levemente de Acuerdo",-0.33,IF(AN8="Levemente en Desacuerdo",0.33,IF(AN8="Muy en Desacuerdo",0.66,IF(AN8="Totalmente en Desacuerdo",1,"error")))))) -> 1 | AP8: Totalmente de Acuerdo | AQ8: =IF(AP8="Totalmente de Acuerdo",-1,IF(AP8="Muy de Acuerdo",-0.66,IF(AP8="Levemente de Acuerdo",-0.33,IF(AP8="Levemente en Desacuerdo",0.33,IF(AP8="Muy en Desacuerdo",0.66,IF(AP8="Totalmente en Desacuerdo",1,"error")))))) -> -1 | AR8: Totalmente de Acuerdo | AS8: =IF(AR8="Totalmente de Acuerdo",1,IF(AR8="Muy de Acuerdo",0.66,IF(AR8="Levemente de Acuerdo",0.33,IF(AR8="Levemente en Desacuerdo",-0.33,IF(AR8="Muy en Desacuerdo",-0.66,IF(AR8="Totalmente en Desacuerdo",-1,"error")))))) -> 1 | AT8: Totalmente en Desacuerdo | AU8: =IF(AT8="Totalmente de Acuerdo",-1,IF(AT8="Muy de Acuerdo",-0.66,IF(AT8="Levemente de Acuerdo",-0.33,IF(AT8="Levemente en Desacuerdo",0.33,IF(AT8="Muy en Desacuerdo",0.66,IF(AT8="Totalmente en Desacuerdo",1,"error")))))) -> 1 | AV8: =AU8+AS8+AQ8+AO8+AM8+AK8+AI8+AG8+AE8 -> -1.99 | AW8: Totalmente de Acuerdo | AX8: Muy de Acuerdo | AY8: Totalmente en Desacuerdo | AZ8: Totalmente en Desacuerdo | BA8: Totalmente en Desacuerdo | BB8: Totalmente en Desacuerdo | BC8: Totalmente en Desacuerdo | BD8: Totalmente en Desacuerdo | BE8: Totalmente en Desacuerdo | BF8: Totalmente de Acuerdo | BG8: Totalmente de Acuerdo | BH8: Me identifico | BM8: Me identifico | BX8: Patricia Bullrich (Juntos por el Cambio) | BY8: Patricia Bullrich (Juntos por el Cambio) | BZ8: Javier Milei (La Libertad Avanza)
A9: 45547.9 | B9: 00544287188 | C9: 2003 | D9: Cuarto año | E9: Varón | F9: NS/NC | G9: Terciario completo | H9: Clase Baja Superior (D1): entre $773.501 y $850.000 mensuales | I9: Familia | J9: Otra localidad en la Provincia de Córdoba | K9: . | L9: Levemente de Acuerdo | M9: =IF(L9="Totalmente de Acuerdo",-1,IF(L9="Muy de Acuerdo",-0.66,IF(L9="Levemente de Acuerdo",-0.33,IF(L9="Levemente en Desacuerdo",0.33,IF(L9="Muy en Desacuerdo",0.66,IF(L9="Totalmente en Desacuerdo",1,"error")))))) -> -0.33 | N9: Levemente de Acuerdo | O9: =IF(N9="Totalmente de Acuerdo",1,IF(N9="Muy de Acuerdo",0.66,IF(N9="Levemente de Acuerdo",0.33,IF(N9="Levemente en Desacuerdo",-0.33,IF(N9="Muy en Desacuerdo",-0.66,IF(N9="Totalmente en Desacuerdo",-1,"error")))))) -> 0.33 | P9: Muy de Acuerdo | Q9: =IF(P9="Totalmente de Acuerdo",-1,IF(P9="Muy de Acuerdo",-0.66,IF(P9="Levemente de Acuerdo",-0.33,IF(P9="Levemente en Desacuerdo",0.33,IF(P9="Muy en Desacuerdo",0.66,IF(P9="Totalmente en Desacuerdo",1,"error")))))) -> -0.66 | R9: Levemente de Acuerdo | S9: =IF(R9="Totalmente de Acuerdo",1,IF(R9="Muy de Acuerdo",0.66,IF(R9="Levemente de Acuerdo",0.33,IF(R9="Levemente en Desacuerdo",-0.33,IF(R9="Muy en Desacuerdo",-0.66,IF(R9="Totalmente en Desacuerdo",-1,"error")))))) -> 0.33 | T9: Levemente de Acuerdo | U9: =IF(T9="Totalmente de Acuerdo",-1,IF(T9="Muy de Acuerdo",-0.66,IF(T9="Levemente de Acuerdo",-0.33,IF(T9="Levemente en Desacuerdo",0.33,IF(T9="Muy en Desacuerdo",0.66,IF(T9="Totalmente en Desacuerdo",1,"error")))))) -> -0.33 | V9: Totalmente de Acuerdo | W9: =IF(V9="Totalmente de Acuerdo",1,IF(V9="Muy de Acuerdo",0.66,IF(V9="Levemente de Acuerdo",0.33,IF(V9="Levemente en Desacuerdo",-0.33,IF(V9="Muy en Desacuerdo",-0.66,IF(V9="Totalmente en Desacuerdo",-1,"error")))))) -> 1 | X9: Levemente de Acuerdo | Y9: =IF(X9="Totalmente de Acuerdo",1,IF(X9="Muy de Acuerdo",0.66,IF(X9="Levemente de Acuerdo",0.33,IF(X9="Levemente en Desacuerdo",-0.33,IF(X9="Muy en Desacuerdo",-0.66,IF(X9="Totalmente en Desacuerdo",-1,"error")))))) -> 0.33 | Z9: Muy en Desacuerdo | AA9: =IF(Z9="Totalmente de Acuerdo",1,IF(Z9="Muy de Acuerdo",0.66,IF(Z9="Levemente en Acuerdo",0.33,IF(Z9="Levemente en Desacuerdo",-0.33,IF(Z9="Muy en Desacuerdo",-0.66,IF(Z9="Totalmente en Desacuerdo",-1,"error")))))) -> -0.66 | AB9: =+AA9+Y9+W9+U9+S9+Q9+O9+M9 -> 0.01 | AC9: =+AB9*AB$36 -> 0.01125 | AD9: Muy en Desacuerdo | AE9: =IF(AD9="Totalmente de Acuerdo",1,IF(AD9="Muy de Acuerdo",0.66,IF(AD9="Levemente de Acuerdo",0.33,IF(AD9="Levemente en Desacuerdo",-0.33,IF(AD9="Muy en Desacuerdo",-0.66,IF(AD9="Totalmente en Desacuerdo",-1,"error")))))) -> -0.66 | AF9: Muy de Acuerdo | AG9: =IF(AF9="Totalmente de Acuerdo",-1,IF(AF9="Muy de Acuerdo",-0.66,IF(AF9="Levemente de Acuerdo",-0.33,IF(AF9="Levemente en Desacuerdo",0.33,IF(AF9="Muy en Desacuerdo",0.66,IF(AF9="Totalmente en Desacuerdo",1,"error")))))) -> -0.66 | AH9: Levemente de Acuerdo | AI9: =IF(AH9="Totalmente de Acuerdo",1,IF(AH9="Muy de Acuerdo",0.66,IF(AH9="Levemente de Acuerdo",0.33,IF(AH9="Levemente en Desacuerdo",-0.33,IF(AH9="Muy en Desacuerdo",-0.66,IF(AH9="Totalmente en Desacuerdo",-1,"error")))))) -> 0.33 | AJ9: Totalmente en Desacuerdo | AK9: =IF(AJ9="Totalmente de Acuerdo",1,IF(AJ9="Muy de Acuerdo",0.66,IF(AJ9="Levemente de Acuerdo",0.33,IF(AJ9="Levemente en Desacuerdo",-0.33,IF(AJ9="Muy en Desacuerdo",-0.66,IF(AJ9="Totalmente en Desacuerdo",-1,"error")))))) -> -1 | AL9: Totalmente de Acuerdo | AM9: =IF(AL9="Totalmente de Acuerdo",-1,IF(AL9="Muy de Acuerdo",-0.66,IF(AL9="Levemente de Acuerdo",-0.33,IF(AL9="Levemente en Desacuerdo",0.33,IF(AL9="Muy en Desacuerdo",0.66,IF(AL9="Totalmente en Desacuerdo",1,"error")))))) -> -1 | AN9: Muy en Desacuerdo | AO9: =IF(AN9="Totalmente de Acuerdo",-1,IF(AN9="Muy de Acuerdo",-0.66,IF(AN9="Levemente de Acuerdo",-0.33,IF(AN9="Levemente en Desacuerdo",0.33,IF(AN9="Muy en Desacuerdo",0.66,IF(AN9="Totalmente en Desacuerdo",1,"error")))))) -> 0.66 | AP9: Muy de Acuerdo | AQ9: =IF(AP9="Totalmente de Acuerdo",-1,IF(AP9="Muy de Acuerdo",-0.66,IF(AP9="Levemente de Acuerdo",-0.33,IF(AP9="Levemente en Desacuerdo",0.33,IF(AP9="Muy en Desacuerdo",0.66,IF(AP9="Totalmente en Desacuerdo",1,"error")))))) -> -0.66 | AR9: Muy en Desacuerdo | AS9: =IF(AR9="Totalmente de Acuerdo",1,IF(AR9="Muy de Acuerdo",0.66,IF(AR9="Levemente de Acuerdo",0.33,IF(AR9="Levemente en Desacuerdo",-0.33,IF(AR9="Muy en Desacuerdo",-0.66,IF(AR9="Totalmente en Desacuerdo",-1,"error")))))) -> -0.66 | AT9: Totalmente en Desacuerdo | AU9: =IF(AT9="Totalmente de Acuerdo",-1,IF(AT9="Muy de Acuerdo",-0.66,IF(AT9="Levemente de Acuerdo",-0.33,IF(AT9="Levemente en Desacuerdo",0.33,IF(AT9="Muy en Desacuerdo",0.66,IF(AT9="Totalmente en Desacuerdo",1,"error")))))) -> 1 | AV9: =AU9+AS9+AQ9+AO9+AM9+AK9+AI9+AG9+AE9 -> -2.65 | AW9: Totalmente de Acuerdo | AX9: Levemente en Desacuerdo | AY9: Levemente de Acuerdo | AZ9: Muy de Acuerdo | BA9: Levemente de Acuerdo | BB9: Muy de Acuerdo | BC9: Muy de Acuerdo | BD9: Muy de Acuerdo | BE9: Muy de Acuerdo | BF9: Levemente en Desacuerdo | BG9: Muy en Desacuerdo | BH9: Me identifico | BJ9: Me identifico | BK9: Me identifico | BM9: Me identifico | BR9: Me identifico | BX9: Patricia Bullrich (Juntos por el Cambio) | BY9: Javier Milei (La Libertad Avanza) | BZ9: Javier Milei (La Libertad Avanza)
A10: 45547.9 | B10: 00305830361 | C10: 2000 | D10: Cuarto año | E10: Mujer | F10: Universitario completo | G10: Posgrado completo | H10: Clase Media Alta (C2): entre $1.350.001 mensuales y $2.850.000 mensuales | I10: Trabajo propio | J10: Ciudad de Córdoba | K10: . | L10: Muy de Acuerdo | M10: =IF(L10="Totalmente de Acuerdo",-1,IF(L10="Muy de Acuerdo",-0.66,IF(L10="Levemente de Acuerdo",-0.33,IF(L10="Levemente en Desacuerdo",0.33,IF(L10="Muy en Desacuerdo",0.66,IF(L10="Totalmente en Desacuerdo",1,"error")))))) -> -0.66 | N10: Levemente en Desacuerdo | O10: =IF(N10="Totalmente de Acuerdo",1,IF(N10="Muy de Acuerdo",0.66,IF(N10="Levemente de Acuerdo",0.33,IF(N10="Levemente en Desacuerdo",-0.33,IF(N10="Muy en Desacuerdo",-0.66,IF(N10="Totalmente en Desacuerdo",-1,"error")))))) -> -0.33 | P10: Muy de Acuerdo | Q10: =IF(P10="Totalmente de Acuerdo",-1,IF(P10="Muy de Acuerdo",-0.66,IF(P10="Levemente de Acuerdo",-0.33,IF(P10="Levemente en Desacuerdo",0.33,IF(P10="Muy en Desacuerdo",0.66,IF(P10="Totalmente en Desacuerdo",1,"error")))))) -> -0.66 | R10: Muy de Acuerdo | S10: =IF(R10="Totalmente de Acuerdo",1,IF(R10="Muy de Acuerdo",0.66,IF(R10="Levemente de Acuerdo",0.33,IF(R10="Levemente en Desacuerdo",-0.33,IF(R10="Muy en Desacuerdo",-0.66,IF(R10="Totalmente en Desacuerdo",-1,"error")))))) -> 0.66 | T10: Muy en Desacuerdo | U10: =IF(T10="Totalmente de Acuerdo",-1,IF(T10="Muy de Acuerdo",-0.66,IF(T10="Levemente de Acuerdo",-0.33,IF(T10="Levemente en Desacuerdo",0.33,IF(T10="Muy en Desacuerdo",0.66,IF(T10="Totalmente en Desacuerdo",1,"error")))))) -> 0.66 | V10: Muy de Acuerdo | W10: =IF(V10="Totalmente de Acuerdo",1,IF(V10="Muy de Acuerdo",0.66,IF(V10="Levemente de Acuerdo",0.33,IF(V10="Levemente en Desacuerdo",-0.33,IF(V10="Muy en Desacuerdo",-0.66,IF(V10="Totalmente en Desacuerdo",-1,"error")))))) -> 0.66 | X10: Levemente en Desacuerdo | Y10: =IF(X10="Totalmente de Acuerdo",1,IF(X10="Muy de Acuerdo",0.66,IF(X10="Levemente de Acuerdo",0.33,IF(X10="Levemente en Desacuerdo",-0.33,IF(X10="Muy en Desacuerdo",-0.66,IF(X10="Totalmente en Desacuerdo",-1,"error")))))) -> -0.33 | Z10: Muy en Desacuerdo | AA10: =IF(Z10="Totalmente de Acuerdo",1,IF(Z10="Muy de Acuerdo",0.66,IF(Z10="Levemente en Acuerdo",0.33,IF(Z10="Levemente en Desacuerdo",-0.33,IF(Z10="Muy en Desacuerdo",-0.66,IF(Z10="Totalmente en Desacuerdo",-1,"error")))))) -> -0.66 | AB10: =+AA10+Y10+W10+U10+S10+Q10+O10+M10 -> -0.66 | AC10: =+AB10*AB$36 -> -0.7425 | AD10: Muy en Desacuerdo | AE10: =IF(AD10="Totalmente de Acuerdo",1,IF(AD10="Muy de Acuerdo",0.66,IF(AD10="Levemente de Acuerdo",0.33,IF(AD10="Levemente en Desacuerdo",-0.33,IF(AD10="Muy en Desacuerdo",-0.66,IF(AD10="Totalmente en Desacuerdo",-1,"error")))))) -> -0.66 | AF10: Muy de Acuerdo | AG10: =IF(AF10="Totalmente de Acuerdo",-1,IF(AF10="Muy de Acuerdo",-0.66,IF(AF10="Levemente de Acuerdo",-0.33,IF(AF10="Levemente en Desacuerdo",0.33,IF(AF10="Muy en Desacuerdo",0.66,IF(AF10="Totalmente en Desacuerdo",1,"error")))))) -> -0.66 | AH10: Levemente en Desacuerdo | AI10: =IF(AH10="Totalmente de Acuerdo",1,IF(AH10="Muy de Acuerdo",0.66,IF(AH10="Levemente de Acuerdo",0.33,IF(AH10="Levemente en Desacuerdo",-0.33,IF(AH10="Muy en Desacuerdo",-0.66,IF(AH10="Totalmente en Desacuerdo",-1,"error")))))) -> -0.33 | AJ10: Levemente de Acuerdo | AK10: =IF(AJ10="Totalmente de Acuerdo",1,IF(AJ10="Muy de Acuerdo",0.66,IF(AJ10="Levemente de Acuerdo",0.33,IF(AJ10="Levemente en Desacuerdo",-0.33,IF(AJ10="Muy en Desacuerdo",-0.66,IF(AJ10="Totalmente en Desacuerdo",-1,"error")))))) -> 0.33 | AL10: Totalmente de Acuerdo | AM10: =IF(AL10="Totalmente de Acuerdo",-1,IF(AL10="Muy de Acuerdo",-0.66,IF(AL10="Levemente de Acuerdo",-0.33,IF(AL10="Levemente en Desacuerdo",0.33,IF(AL10="Muy en Desacuerdo",0.66,IF(AL10="Totalmente en Desacuerdo",1,"error")))))) -> -1 | AN10: Levemente de Acuerdo | AO10: =IF(AN10="Totalmente de Acuerdo",-1,IF(AN10="Muy de Acuerdo",-0.66,IF(AN10="Levemente de Acuerdo",-0.33,IF(AN10="Levemente en Desacuerdo",0.33,IF(AN10="Muy en Desacuerdo",0.66,IF(AN10="Totalmente en Desacuerdo",1,"error")))))) -> -0.33 | AP10: Muy de Acuerdo | AQ10: =IF(AP10="Totalmente de Acuerdo",-1,IF(AP10="Muy de Acuerdo",-0.66,IF(AP10="Levemente de Acuerdo",-0.33,IF(AP10="Levemente en Desacuerdo",0.33,IF(AP10="Muy en Desacuerdo",0.66,IF(AP10="Totalmente en Desacuerdo",1,"error")))))) -> -0.66 | AR10: Totalmente de Acuerdo | AS10: =IF(AR10="Totalmente de Acuerdo",1,IF(AR10="Muy de Acuerdo",0.66,IF(AR10="Levemente de Acuerdo",0.33,IF(AR10="Levemente en Desacuerdo",-0.33,IF(AR10="Muy en Desacuerdo",-0.66,IF(AR10="Totalmente en Desacuerdo",-1,"error")))))) -> 1 | AT10: Muy en Desacuerdo | AU10: =IF(AT10="Totalmente de Acuerdo",-1,IF(AT10="Muy de Acuerdo",-0.66,IF(AT10="Levemente de Acuerdo",-0.33,IF(AT10="Levemente en Desacuerdo",0.33,IF(AT10="Muy en Desacuerdo",0.66,IF(AT10="Totalmente en Desacuerdo",1,"error")))))) -> 0.66 | AV10: =AU10+AS10+AQ10+AO10+AM10+AK10+AI10+AG10+AE10 -> -1.65 | AW10: Levemente de Acuerdo | AX10: Levemente en Desacuerdo | AY10: Levemente en Desacuerdo | AZ10: Muy de Acuerdo | BA10: Muy de Acuerdo | BB10: Levemente de Acuerdo | BC10: Levemente de Acuerdo | BD10: Muy de Acuerdo | BE10: Muy en Desacuerdo | BF10: Totalmente de Acuerdo | BG10: Muy de Acuerdo | BJ10: Me identifico | BV10: Me identifico | BX10: Juan Schiaretti (Hacemos por Nuestro País) | BY10: Juan Schiaretti (Hacemos por Nuestro País) | BZ10: En blanco
A11: 45547.9 | B11: 00712484148 | C11: 2002 | D11: Quinto año | E11: Varón | F11: Universitario incompleto | G11: Universitario incompleto | H11: Clase Media Alta (C2): entre $1.350.001 mensuales y $2.850.000 mensuales | I11: Familia | J11: Ciudad de Córdoba | K11: . | L11: Muy de Acuerdo | M11: =IF(L11="Totalmente de Acuerdo",-1,IF(L11="Muy de Acuerdo",-0.66,IF(L11="Levemente de Acuerdo",-0.33,IF(L11="Levemente en Desacuerdo",0.33,IF(L11="Muy en Desacuerdo",0.66,IF(L11="Totalmente en Desacuerdo",1,"error")))))) -> -0.66 | N11: Muy en Desacuerdo | O11: =IF(N11="Totalmente de Acuerdo",1,IF(N11="Muy de Acuerdo",0.66,IF(N11="Levemente de Acuerdo",0.33,IF(N11="Levemente en Desacuerdo",-0.33,IF(N11="Muy en Desacuerdo",-0.66,IF(N11="Totalmente en Desacuerdo",-1,"error")))))) -> -0.66 | P11: Totalmente de Acuerdo | Q11: =IF(P11="Totalmente de Acuerdo",-1,IF(P11="Muy de Acuerdo",-0.66,IF(P11="Levemente de Acuerdo",-0.33,IF(P11="Levemente en Desacuerdo",0.33,IF(P11="Muy en Desacuerdo",0.66,IF(P11="Totalmente en Desacuerdo",1,"error")))))) -> -1 | R11: Levemente de Acuerdo | S11: =IF(R11="Totalmente de Acuerdo",1,IF(R11="Muy de Acuerdo",0.66,IF(R11="Levemente de Acuerdo",0.33,IF(R11="Levemente en Desacuerdo",-0.33,IF(R11="Muy en Desacuerdo",-0.66,IF(R11="Totalmente en Desacuerdo",-1,"error")))))) -> 0.33 | T11: Levemente en Desacuerdo | U11: =IF(T11="Totalmente de Acuerdo",-1,IF(T11="Muy de Acuerdo",-0.66,IF(T11="Levemente de Acuerdo",-0.33,IF(T11="Levemente en Desacuerdo",0.33,IF(T11="Muy en Desacuerdo",0.66,IF(T11="Totalmente en Desacuerdo",1,"error")))))) -> 0.33 | V11: Levemente de Acuerdo | W11: =IF(V11="Totalmente de Acuerdo",1,IF(V11="Muy de Acuerdo",0.66,IF(V11="Levemente de Acuerdo",0.33,IF(V11="Levemente en Desacuerdo",-0.33,IF(V11="Muy en Desacuerdo",-0.66,IF(V11="Totalmente en Desacuerdo",-1,"error")))))) -> 0.33 | X11: Muy en Desacuerdo | Y11: =IF(X11="Totalmente de Acuerdo",1,IF(X11="Muy de Acuerdo",0.66,IF(X11="Levemente de Acuerdo",0.33,IF(X11="Levemente en Desacuerdo",-0.33,IF(X11="Muy en Desacuerdo",-0.66,IF(X11="Totalmente en Desacuerdo",-1,"error")))))) -> -0.66 | Z11: Totalmente en Desacuerdo | AA11: =IF(Z11="Totalmente de Acuerdo",1,IF(Z11="Muy de Acuerdo",0.66,IF(Z11="Levemente en Acuerdo",0.33,IF(Z11="Levemente en Desacuerdo",-0.33,IF(Z11="Muy en Desacuerdo",-0.66,IF(Z11="Totalmente en Desacuerdo",-1,"error")))))) -> -1 | AB11: =+AA11+Y11+W11+U11+S11+Q11+O11+M11 -> -2.99 | AC11: =+AB11*AB$36 -> -3.36375 | AD11: Totalmente en Desacuerdo | AE11: =IF(AD11="Totalmente de Acuerdo",1,IF(AD11="Muy de Acuerdo",0.66,IF(AD11="Levemente de Acuerdo",0.33,IF(AD11="Levemente en Desacuerdo",-0.33,IF(AD11="Muy en Desacuerdo",-0.66,IF(AD11="Totalmente en Desacuerdo",-1,"error")))))) -> -1 | AF11: Muy de Acuerdo | AG11: =IF(AF11="Totalmente de Acuerdo",-1,IF(AF11="Muy de Acuerdo",-0.66,IF(AF11="Levemente de Acuerdo",-0.33,IF(AF11="Levemente en Desacuerdo",0.33,IF(AF11="Muy en Desacuerdo",0.66,IF(AF11="Totalmente en Desacuerdo",1,"error")))))) -> -0.66 | AH11: Levemente en Desacuerdo | AI11: =IF(AH11="Totalmente de Acuerdo",1,IF(AH11="Muy de Acuerdo",0.66,IF(AH11="Levemente de Acuerdo",0.33,IF(AH11="Levemente en Desacuerdo",-0.33,IF(AH11="Muy en Desacuerdo",-0.66,IF(AH11="Totalmente en Desacuerdo",-1,"error")))))) -> -0.33 | AJ11: Totalmente en Desacuerdo | AK11: =IF(AJ11="Totalmente de Acuerdo",1,IF(AJ11="Muy de Acuerdo",0.66,IF(AJ11="Levemente de Acuerdo",0.33,IF(AJ11="Levemente en Desacuerdo",-0.33,IF(AJ11="Muy en Desacuerdo",-0.66,IF(AJ11="Totalmente en Desacuerdo",-1,"error")))))) -> -1 | AL11: Totalmente de Acuerdo | AM11: =IF(AL11="Totalmente de Acuerdo",-1,IF(AL11="Muy de Acuerdo",-0.66,IF(AL11="Levemente de Acuerdo",-0.33,IF(AL11="Levemente en Desacuerdo",0.33,IF(AL11="Muy en Desacuerdo",0.66,IF(AL11="Totalmente en Desacuerdo",1,"error")))))) -> -1 | AN11: Muy de Acuerdo | AO11: =IF(AN11="Totalmente de Acuerdo",-1,IF(AN11="Muy de Acuerdo",-0.66,IF(AN11="Levemente de Acuerdo",-0.33,IF(AN11="Levemente en Desacuerdo",0.33,IF(AN11="Muy en Desacuerdo",0.66,IF(AN11="Totalmente en Desacuerdo",1,"error")))))) -> -0.66 | AP11: Muy en Desacuerdo | AQ11: =IF(AP11="Totalmente de Acuerdo",-1,IF(AP11="Muy de Acuerdo",-0.66,IF(AP11="Levemente de Acuerdo",-0.33,IF(AP11="Levemente en Desacuerdo",0.33,IF(AP11="Muy en Desacuerdo",0.66,IF(AP11="Totalmente en Desacuerdo",1,"error")))))) -> 0.66 | AR11: Levemente de Acuerdo | AS11: =IF(AR11="Totalmente de Acuerdo",1,IF(AR11="Muy de Acuerdo",0.66,IF(AR11="Levemente de Acuerdo",0.33,IF(AR11="Levemente en Desacuerdo",-0.33,IF(AR11="Muy en Desacuerdo",-0.66,IF(AR11="Totalmente en Desacuerdo",-1,"error")))))) -> 0.33 | AT11: Totalmente en Desacuerdo | AU11: =IF(AT11="Totalmente de Acuerdo",-1,IF(AT11="Muy de Acuerdo",-0.66,IF(AT11="Levemente de Acuerdo",-0.33,IF(AT11="Levemente en Desacuerdo",0.33,IF(AT11="Muy en Desacuerdo",0.66,IF(AT11="Totalmente en Desacuerdo",1,"error")))))) -> 1 | AV11: =AU11+AS11+AQ11+AO11+AM11+AK11+AI11+AG11+AE11 -> -2.66 | AW11: Levemente en Desacuerdo | AX11: Levemente de Acuerdo | AY11: Levemente de Acuerdo | AZ11: Muy de Acuerdo | BA11: Levemente de Acuerdo | BB11: Levemente en Desacuerdo | BC11: Levemente en Desacuerdo | BD11: Levemente en Desacuerdo | BE11: Muy en Desacuerdo | BF11: Totalmente de Acuerdo | BG11: Totalmente en Desacuerdo | BJ11: Me identifico | BX11: Javier Milei (La Libertad Avanza) | BY11: Javier Milei (La Libertad Avanza) | BZ11: Javier Milei (La Libertad Avanza)
A12: 45547.9 | B12: 006934766847656 | C12: 2000 | D12: Cuarto año | E12: Mujer | F12: Posgrado completo | G12: Universitario completo | H12: Clase Media Alta (C2): entre $1.350.001 mensuales y $2.850.000 mensuales | I12: Familia | J12: Ciudad de Córdoba | K12: . | L12: Totalmente en Desacuerdo | M12: =IF(L12="Totalmente de Acuerdo",-1,IF(L12="Muy de Acuerdo",-0.66,IF(L12="Levemente de Acuerdo",-0.33,IF(L12="Levemente en Desacuerdo",0.33,IF(L12="Muy en Desacuerdo",0.66,IF(L12="Totalmente en Desacuerdo",1,"error")))))) -> 1 | N12: Totalmente en Desacuerdo | O12: =IF(N12="Totalmente de Acuerdo",1,IF(N12="Muy de Acuerdo",0.66,IF(N12="Levemente de Acuerdo",0.33,IF(N12="Levemente en Desacuerdo",-0.33,IF(N12="Muy en Desacuerdo",-0.66,IF(N12="Totalmente en Desacuerdo",-1,"error")))))) -> -1 | P12: Totalmente de Acuerdo | Q12: =IF(P12="Totalmente de Acuerdo",-1,IF(P12="Muy de Acuerdo",-0.66,IF(P12="Levemente de Acuerdo",-0.33,IF(P12="Levemente en Desacuerdo",0.33,IF(P12="Muy en Desacuerdo",0.66,IF(P12="Totalmente en Desacuerdo",1,"error")))))) -> -1 | R12: Totalmente en Desacuerdo | S12: =IF(R12="Totalmente de Acuerdo",1,IF(R12="Muy de Acuerdo",0.66,IF(R12="Levemente de Acuerdo",0.33,IF(R12="Levemente en Desacuerdo",-0.33,IF(R12="Muy en Desacuerdo",-0.66,IF(R12="Totalmente en Desacuerdo",-1,"error")))))) -> -1 | T12: Totalmente de Acuerdo | U12: =IF(T12="Totalmente de Acuerdo",-1,IF(T12="Muy de Acuerdo",-0.66,IF(T12="Levemente de Acuerdo",-0.33,IF(T12="Levemente en Desacuerdo",0.33,IF(T12="Muy en Desacuerdo",0.66,IF(T12="Totalmente en Desacuerdo",1,"error")))))) -> -1 | V12: Muy en Desacuerdo | W12: =IF(V12="Totalmente de Acuerdo",1,IF(V12="Muy de Acuerdo",0.66,IF(V12="Levemente de Acuerdo",0.33,IF(V12="Levemente en Desacuerdo",-0.33,IF(V12="Muy en Desacuerdo",-0.66,IF(V12="Totalmente en Desacuerdo",-1,"error")))))) -> -0.66 | X12: Levemente de Acuerdo | Y12: =IF(X12="Totalmente de Acuerdo",1,IF(X12="Muy de Acuerdo",0.66,IF(X12="Levemente de Acuerdo",0.33,IF(X12="Levemente en Desacuerdo",-0.33,IF(X12="Muy en Desacuerdo",-0.66,IF(X12="Totalmente en Desacuerdo",-1,"error")))))) -> 0.33 | Z12: Totalmente en Desacuerdo | AA12: =IF(Z12="Totalmente de Acuerdo",1,IF(Z12="Muy de Acuerdo",0.66,IF(Z12="Levemente en Acuerdo",0.33,IF(Z12="Levemente en Desacuerdo",-0.33,IF(Z12="Muy en Desacuerdo",-0.66,IF(Z12="Totalmente en Desacuerdo",-1,"error")))))) -> -1 | AB12: =+AA12+Y12+W12+U12+S12+Q12+O12+M12 -> -4.33 | AC12: =+AB12*AB$36 -> -4.87125 | AD12: Muy en Desacuerdo | AE12: =IF(AD12="Totalmente de Acuerdo",1,IF(AD12="Muy de Acuerdo",0.66,IF(AD12="Levemente de Acuerdo",0.33,IF(AD12="Levemente en Desacuerdo",-0.33,IF(AD12="Muy en Desacuerdo",-0.66,IF(AD12="Totalmente en Desacuerdo",-1,"error")))))) -> -0.66 | AF12: Totalmente en Desacuerdo | AG12: =IF(AF12="Totalmente de Acuerdo",-1,IF(AF12="Muy de Acuerdo",-0.66,IF(AF12="Levemente de Acuerdo",-0.33,IF(AF12="Levemente en Desacuerdo",0.33,IF(AF12="Muy en Desacuerdo",0.66,IF(AF12="Totalmente en Desacuerdo",1,"error")))))) -> 1 | AH12: Totalmente en Desacuerdo | AI12: =IF(AH12="Totalmente de Acuerdo",1,IF(AH12="Muy de Acuerdo",0.66,IF(AH12="Levemente de Acuerdo",0.33,IF(AH12="Levemente en Desacuerdo",-0.33,IF(AH12="Muy en Desacuerdo",-0.66,IF(AH12="Totalmente en Desacuerdo",-1,"error")))))) -> -1 | AJ12: Totalmente en Desacuerdo | AK12: =IF(AJ12="Totalmente de Acuerdo",1,IF(AJ12="Muy de Acuerdo",0.66,IF(AJ12="Levemente de Acuerdo",0.33,IF(AJ12="Levemente en Desacuerdo",-0.33,IF(AJ12="Muy en Desacuerdo",-0.66,IF(AJ12="Totalmente en Desacuerdo",-1,"error")))))) -> -1 | AL12: Totalmente de Acuerdo | AM12: =IF(AL12="Totalmente de Acuerdo",-1,IF(AL12="Muy de Acuerdo",-0.66,IF(AL12="Levemente de Acuerdo",-0.33,IF(AL12="Levemente en Desacuerdo",0.33,IF(AL12="Muy en Desacuerdo",0.66,IF(AL12="Totalmente en Desacuerdo",1,"error")))))) -> -1 | AN12: Totalmente de Acuerdo | AO12: =IF(AN12="Totalmente de Acuerdo",-1,IF(AN12="Muy de Acuerdo",-0.66,IF(AN12="Levemente de Acuerdo",-0.33,IF(AN12="Levemente en Desacuerdo",0.33,IF(AN12="Muy en Desacuerdo",0.66,IF(AN12="Totalmente en Desacuerdo",1,"error")))))) -> -1 | AP12: Totalmente de Acuerdo | AQ12: =IF(AP12="Totalmente de Acuerdo",-1,IF(AP12="Muy de Acuerdo",-0.66,IF(AP12="Levemente de Acuerdo",-0.33,IF(AP12="Levemente en Desacuerdo",0.33,IF(AP12="Muy en Desacuerdo",0.66,IF(AP12="Totalmente en Desacuerdo",1,"error")))))) -> -1 | AR12: Totalmente en Desacuerdo | AS12: =IF(AR12="Totalmente de Acuerdo",1,IF(AR12="Muy de Acuerdo",0.66,IF(AR12="Levemente de Acuerdo",0.33,IF(AR12="Levemente en Desacuerdo",-0.33,IF(AR12="Muy en Desacuerdo",-0.66,IF(AR12="Totalmente en Desacuerdo",-1,"error")))))) -> -1 | AT12: Totalmente en Desacuerdo | AU12: =IF(AT12="Totalmente de Acuerdo",-1,IF(AT12="Muy de Acuerdo",-0.66,IF(AT12="Levemente de Acuerdo",-0.33,IF(AT12="Levemente en Desacuerdo",0.33,IF(AT12="Muy en Desacuerdo",0.66,IF(AT12="Totalmente en Desacuerdo",1,"error")))))) -> 1 | AV12: =AU12+AS12+AQ12+AO12+AM12+AK12+AI12+AG12+AE12 -> -4.66 | AW12: Totalmente en Desacuerdo | AX12: Totalmente de Acuerdo | AY12: Totalmente de Acuerdo | AZ12: Levemente de Acuerdo | BA12: Levemente de Acuerdo | BB12: Levemente en Desacuerdo | BC12: Muy en Desacuerdo | BD12: Totalmente en Desacuerdo | BE12: Totalmente de Acuerdo | BF12: Totalmente de Acuerdo | BG12: Totalmente en Desacuerdo | BJ12: Me identifico | BK12: Me identifico | BP12: Me identifico | BQ12: Me identifico | BU12: Me identifico | BX12: Juan Grabois (Unión por la Patria) | BY12: Sergio Massa (Unión por la Patria) | BZ12: Sergio Massa (Unión por la Patria)
A13: 45547.9 | B13: 00338374873 | C13: 2000 | D13: Quinto año | E13: Mujer | F13: Posgrado completo | G13: Posgrado completo | H13: Clase Alta (ABC1): más de $2.850.000 mensuales | I13: Familia | J13: Otra localidad en la Provincia de Córdoba | K13: . | L13: Levemente de Acuerdo | M13: =IF(L13="Totalmente de Acuerdo",-1,IF(L13="Muy de Acuerdo",-0.66,IF(L13="Levemente de Acuerdo",-0.33,IF(L13="Levemente en Desacuerdo",0.33,IF(L13="Muy en Desacuerdo",0.66,IF(L13="Totalmente en Desacuerdo",1,"error")))))) -> -0.33 | N13: Levemente en Desacuerdo | O13: =IF(N13="Totalmente de Acuerdo",1,IF(N13="Muy de Acuerdo",0.66,IF(N13="Levemente de Acuerdo",0.33,IF(N13="Levemente en Desacuerdo",-0.33,IF(N13="Muy en Desacuerdo",-0.66,IF(N13="Totalmente en Desacuerdo",-1,"error")))))) -> -0.33 | P13: Muy de Acuerdo | Q13: =IF(P13="Totalmente de Acuerdo",-1,IF(P13="Muy de Acuerdo",-0.66,IF(P13="Levemente de Acuerdo",-0.33,IF(P13="Levemente en Desacuerdo",0.33,IF(P13="Muy en Desacuerdo",0.66,IF(P13="Totalmente en Desacuerdo",1,"error")))))) -> -0.66 | R13: Levemente de Acuerdo | S13: =IF(R13="Totalmente de Acuerdo",1,IF(R13="Muy de Acuerdo",0.66,IF(R13="Levemente de Acuerdo",0.33,IF(R13="Levemente en Desacuerdo",-0.33,IF(R13="Muy en Desacuerdo",-0.66,IF(R13="Totalmente en Desacuerdo",-1,"error")))))) -> 0.33 | T13: Levemente de Acuerdo | U13: =IF(T13="Totalmente de Acuerdo",-1,IF(T13="Muy de Acuerdo",-0.66,IF(T13="Levemente de Acuerdo",-0.33,IF(T13="Levemente en Desacuerdo",0.33,IF(T13="Muy en Desacuerdo",0.66,IF(T13="Totalmente en Desacuerdo",1,"error")))))) -> -0.33 | V13: Muy de Acuerdo | W13: =IF(V13="Totalmente de Acuerdo",1,IF(V13="Muy de Acuerdo",0.66,IF(V13="Levemente de Acuerdo",0.33,IF(V13="Levemente en Desacuerdo",-0.33,IF(V13="Muy en Desacuerdo",-0.66,IF(V13="Totalmente en Desacuerdo",-1,"error")))))) -> 0.66 | X13: Levemente en Desacuerdo | Y13: =IF(X13="Totalmente de Acuerdo",1,IF(X13="Muy de Acuerdo",0.66,IF(X13="Levemente de Acuerdo",0.33,IF(X13="Levemente en Desacuerdo",-0.33,IF(X13="Muy en Desacuerdo",-0.66,IF(X13="Totalmente en Desacuerdo",-1,"error")))))) -> -0.33 | Z13: Levemente en Desacuerdo | AA13: =IF(Z13="Totalmente de Acuerdo",1,IF(Z13="Muy de Acuerdo",0.66,IF(Z13="Levemente en Acuerdo",0.33,IF(Z13="Levemente en Desacuerdo",-0.33,IF(Z13="Muy en Desacuerdo",-0.66,IF(Z13="Totalmente en Desacuerdo",-1,"error")))))) -> -0.33 | AB13: =+AA13+Y13+W13+U13+S13+Q13+O13+M13 -> -1.32 | AC13: =+AB13*AB$36 -> -1.485 | AD13: Levemente de Acuerdo | AE13: =IF(AD13="Totalmente de Acuerdo",1,IF(AD13="Muy de Acuerdo",0.66,IF(AD13="Levemente de Acuerdo",0.33,IF(AD13="Levemente en Desacuerdo",-0.33,IF(AD13="Muy en Desacuerdo",-0.66,IF(AD13="Totalmente en Desacuerdo",-1,"error")))))) -> 0.33 | AF13: Muy de Acuerdo | AG13: =IF(AF13="Totalmente de Acuerdo",-1,IF(AF13="Muy de Acuerdo",-0.66,IF(AF13="Levemente de Acuerdo",-0.33,IF(AF13="Levemente en Desacuerdo",0.33,IF(AF13="Muy en Desacuerdo",0.66,IF(AF13="Totalmente en Desacuerdo",1,"error")))))) -> -0.66 | AH13: Totalmente en Desacuerdo | AI13: =IF(AH13="Totalmente de Acuerdo",1,IF(AH13="Muy de Acuerdo",0.66,IF(AH13="Levemente de Acuerdo",0.33,IF(AH13="Levemente en Desacuerdo",-0.33,IF(AH13="Muy en Desacuerdo",-0.66,IF(AH13="Totalmente en Desacuerdo",-1,"error")))))) -> -1 | AJ13: Totalmente en Desacuerdo | AK13: =IF(AJ13="Totalmente de Acuerdo",1,IF(AJ13="Muy de Acuerdo",0.66,IF(AJ13="Levemente de Acuerdo",0.33,IF(AJ13="Levemente en Desacuerdo",-0.33,IF(AJ13="Muy en Desacuerdo",-0.66,IF(AJ13="Totalmente en Desacuerdo",-1,"error")))))) -> -1 | AL13: Levemente de Acuerdo | AM13: =IF(AL13="Totalmente de Acuerdo",-1,IF(AL13="Muy de Acuerdo",-0.66,IF(AL13="Levemente de Acuerdo",-0.33,IF(AL13="Levemente en Desacuerdo",0.33,IF(AL13="Muy en Desacuerdo",0.66,IF(AL13="Totalmente en Desacuerdo",1,"error")))))) -> -0.33 | AN13: Levemente en Desacuerdo | AO13: =IF(AN13="Totalmente de Acuerdo",-1,IF(AN13="Muy de Acuerdo",-0.66,IF(AN13="Levemente de Acuerdo",-0.33,IF(AN13="Levemente en Desacuerdo",0.33,IF(AN13="Muy en Desacuerdo",0.66,IF(AN13="Totalmente en Desacuerdo",1,"error")))))) -> 0.33 | AP13: Levemente de Acuerdo | AQ13: =IF(AP13="Totalmente de Acuerdo",-1,IF(AP13="Muy de Acuerdo",-0.66,IF(AP13="Levemente de Acuerdo",-0.33,IF(AP13="Levemente en Desacuerdo",0.33,IF(AP13="Muy en Desacuerdo",0.66,IF(AP13="Totalmente en Desacuerdo",1,"error")))))) -> -0.33 | AR13: Muy de Acuerdo | AS13: =IF(AR13="Totalmente de Acuerdo",1,IF(AR13="Muy de Acuerdo",0.66,IF(AR13="Levemente de Acuerdo",0.33,IF(AR13="Levemente en Desacuerdo",-0.33,IF(AR13="Muy en Desacuerdo",-0.66,IF(AR13="Totalmente en Desacuerdo",-1,"error")))))) -> 0.66 | AT13: Muy en Desacuerdo | AU13: =IF(AT13="Totalmente de Acuerdo",-1,IF(AT13="Muy de Acuerdo",-0.66,IF(AT13="Levemente de Acuerdo",-0.33,IF(AT13="Levemente en Desacuerdo",0.33,IF(AT13="Muy en Desacuerdo",0.66,IF(AT13="Totalmente en Desacuerdo",1,"error")))))) -> 0.66 | AV13: =AU13+AS13+AQ13+AO13+AM13+AK13+AI13+AG13+AE13 -> -1.34 | AW13: Levemente de Acuerdo | AX13: Levemente de Acuerdo | AY13: Muy en Desacuerdo | AZ13: Levemente en Desacuerdo | BA13: Muy de Acuerdo | BB13: Levemente en Desacuerdo | BC13: Levemente en Desacuerdo | BD13: Levemente de Acuerdo | BE13: Muy en Desacuerdo | BF13: Muy de Acuerdo | BG13: Muy de Acuerdo | BJ13: Me identifico | BK13: Me identifico | BU13: Me identifico | BX13: No vote | BY13: Javier Milei (La Libertad Avanza) | BZ13: Javier Milei (La Libertad Avanza)
A14: 45547.901 | B14: 00576235027 | C14: 2001 | D14: Cuarto año | E14: Mujer | F14: Terciario completo | G14: Universitario incompleto | H14: Clase Media Alta (C2): entre $1.350.001 mensuales y $2.850.000 mensuales | I14: Familia | J14: Ciudad de Córdoba | K14: . | L14: Muy en Desacuerdo | M14: =IF(L14="Totalmente de Acuerdo",-1,IF(L14="Muy de Acuerdo",-0.66,IF(L14="Levemente de Acuerdo",-0.33,IF(L14="Levemente en Desacuerdo",0.33,IF(L14="Muy en Desacuerdo",0.66,IF(L14="Totalmente en Desacuerdo",1,"error")))))) -> 0.66 | N14: Levemente de Acuerdo | O14: =IF(N14="Totalmente de Acuerdo",1,IF(N14="Muy de Acuerdo",0.66,IF(N14="Levemente de Acuerdo",0.33,IF(N14="Levemente en Desacuerdo",-0.33,IF(N14="Muy en Desacuerdo",-0.66,IF(N14="Totalmente en Desacuerdo",-1,"error")))))) -> 0.33 | P14: Muy de Acuerdo | Q14: =IF(P14="Totalmente de Acuerdo",-1,IF(P14="Muy de Acuerdo",-0.66,IF(P14="Levemente de Acuerdo",-0.33,IF(P14="Levemente en Desacuerdo",0.33,IF(P14="Muy en Desacuerdo",0.66,IF(P14="Totalmente en Desacuerdo",1,"error")))))) -> -0.66 | R14: Levemente de Acuerdo | S14: =IF(R14="Totalmente de Acuerdo",1,IF(R14="Muy de Acuerdo",0.66,IF(R14="Levemente de Acuerdo",0.33,IF(R14="Levemente en Desacuerdo",-0.33,IF(R14="Muy en Desacuerdo",-0.66,IF(R14="Totalmente en Desacuerdo",-1,"error")))))) -> 0.33 | T14: Levemente de Acuerdo | U14: =IF(T14="Totalmente de Acuerdo",-1,IF(T14="Muy de Acuerdo",-0.66,IF(T14="Levemente de Acuerdo",-0.33,IF(T14="Levemente en Desacuerdo",0.33,IF(T14="Muy en Desacuerdo",0.66,IF(T14="Totalmente en Desacuerdo",1,"error")))))) -> -0.33 | V14: Levemente de Acuerdo | W14: =IF(V14="Totalmente de Acuerdo",1,IF(V14="Muy de Acuerdo",0.66,IF(V14="Levemente de Acuerdo",0.33,IF(V14="Levemente en Desacuerdo",-0.33,IF(V14="Muy en Desacuerdo",-0.66,IF(V14="Totalmente en Desacuerdo",-1,"error")))))) -> 0.33 | X14: Muy de Acuerdo | Y14: =IF(X14="Totalmente de Acuerdo",1,IF(X14="Muy de Acuerdo",0.66,IF(X14="Levemente de Acuerdo",0.33,IF(X14="Levemente en Desacuerdo",-0.33,IF(X14="Muy en Desacuerdo",-0.66,IF(X14="Totalmente en Desacuerdo",-1,"error")))))) -> 0.66 | Z14: Levemente en Acuerdo | AA14: =IF(Z14="Totalmente de Acuerdo",1,IF(Z14="Muy de Acuerdo",0.66,IF(Z14="Levemente en Acuerdo",0.33,IF(Z14="Levemente en Desacuerdo",-0.33,IF(Z14="Muy en Desacuerdo",-0.66,IF(Z14="Totalmente en Desacuerdo",-1,"error")))))) -> 0.33 | AB14: =+AA14+Y14+W14+U14+S14+Q14+O14+M14 -> 1.65 | AC14: =+AB14*AB$36 -> 1.85625 | AD14: Levemente de Acuerdo | AE14: =IF(AD14="Totalmente de Acuerdo",1,IF(AD14="Muy de Acuerdo",0.66,IF(AD14="Levemente de Acuerdo",0.33,IF(AD14="Levemente en Desacuerdo",-0.33,IF(AD14="Muy en Desacuerdo",-0.66,IF(AD14="Totalmente en Desacuerdo",-1,"error")))))) -> 0.33 | AF14: Muy de Acuerdo | AG14: =IF(AF14="Totalmente de Acuerdo",-1,IF(AF14="Muy de Acuerdo",-0.66,IF(AF14="Levemente de Acuerdo",-0.33,IF(AF14="Levemente en Desacuerdo",0.33,IF(AF14="Muy en Desacuerdo",0.66,IF(AF14="Totalmente en Desacuerdo",1,"error")))))) -> -0.66 | AH14: Muy de Acuerdo | AI14: =IF(AH14="Totalmente de Acuerdo",1,IF(AH14="Muy de Acuerdo",0.66,IF(AH14="Levemente de Acuerdo",0.33,IF(AH14="Levemente en Desacuerdo",-0.33,IF(AH14="Muy en Desacuerdo",-0.66,IF(AH14="Totalmente en Desacuerdo",-1,"error")))))) -> 0.66 | AJ14: Muy en Desacuerdo | AK14: =IF(AJ14="Totalmente de Acuerdo",1,IF(AJ14="Muy de Acuerdo",0.66,IF(AJ14="Levemente de Acuerdo",0.33,IF(AJ14="Levemente en Desacuerdo",-0.33,IF(AJ14="Muy en Desacuerdo",-0.66,IF(AJ14="Totalmente en Desacuerdo",-1,"error")))))) -> -0.66 | AL14: Levemente en Desacuerdo | AM14: =IF(AL14="Totalmente de Acuerdo",-1,IF(AL14="Muy de Acuerdo",-0.66,IF(AL14="Levemente de Acuerdo",-0.33,IF(AL14="Levemente en Desacuerdo",0.33,IF(AL14="Muy en Desacuerdo",0.66,IF(AL14="Totalmente en Desacuerdo",1,"error")))))) -> 0.33 | AN14: Totalmente en Desacuerdo | AO14: =IF(AN14="Totalmente de Acuerdo",-1,IF(AN14="Muy de Acuerdo",-0.66,IF(AN14="Levemente de Acuerdo",-0.33,IF(AN14="Levemente en Desacuerdo",0.33,IF(AN14="Muy en Desacuerdo",0.66,IF(AN14="Totalmente en Desacuerdo",1,"error")))))) -> 1 | AP14: Levemente de Acuerdo | AQ14: =IF(AP14="Totalmente de Acuerdo",-1,IF(AP14="Muy de Acuerdo",-0.66,IF(AP14="Levemente de Acuerdo",-0.33,IF(AP14="Levemente en Desacuerdo",0.33,IF(AP14="Muy en Desacuerdo",0.66,IF(AP14="Totalmente en Desacuerdo",1,"error")))))) -> -0.33 | AR14: Levemente de Acuerdo | AS14: =IF(AR14="Totalmente de Acuerdo",1,IF(AR14="Muy de Acuerdo",0.66,IF(AR14="Levemente de Acuerdo",0.33,IF(AR14="Levemente en Desacuerdo",-0.33,IF(AR14="Muy en Desacuerdo",-0.66,IF(AR14="Totalmente en Desacuerdo",-1,"error")))))) -> 0.33 | AT14: Totalmente en Desacuerdo | AU14: =IF(AT14="Totalmente de Acuerdo",-1,IF(AT14="Muy de Acuerdo",-0.66,IF(AT14="Levemente de Acuerdo",-0.33,IF(AT14="Levemente en Desacuerdo",0.33,IF(AT14="Muy en Desacuerdo",0.66,IF(AT14="Totalmente en Desacuerdo",1,"error")))))) -> 1 | AV14: =AU14+AS14+AQ14+AO14+AM14+AK14+AI14+AG14+AE14 -> 2 | AW14: Levemente de Acuerdo | AX14: Levemente de Acuerdo | AY14: Levemente en Desacuerdo | AZ14: Muy de Acuerdo | BA14: Levemente en Desacuerdo | BB14: Levemente en Desacuerdo | BC14: Totalmente en Desacuerdo | BD14: Totalmente en Desacuerdo | BE14: Levemente de Acuerdo | BF14: Totalmente de Acuerdo | BG14: Levemente de Acuerdo | BJ14: Me identifico | BX14: Patricia Bullrich (Juntos por el Cambio) | BY14: Patricia Bullrich (Juntos por el Cambio) | BZ14: Javier Milei (La Libertad Avanza)
A15: 45547.901 | B15: 00704722792 | C15: 2003 | D15: Cuarto año | E15: Mujer | F15: Universitario completo | G15: Terciario completo | H15: Clase Alta (ABC1): más de $2.850.000 mensuales | I15: Familia | J15: Otra localidad en otra Provincia | K15: . | L15: Levemente de Acuerdo | M15: =IF(L15="Totalmente de Acuerdo",-1,IF(L15="Muy de Acuerdo",-0.66,IF(L15="Levemente de Acuerdo",-0.33,IF(L15="Levemente en Desacuerdo",0.33,IF(L15="Muy en Desacuerdo",0.66,IF(L15="Totalmente en Desacuerdo",1,"error")))))) -> -0.33 | N15: Totalmente de Acuerdo | O15: =IF(N15="Totalmente de Acuerdo",1,IF(N15="Muy de Acuerdo",0.66,IF(N15="Levemente de Acuerdo",0.33,IF(N15="Levemente en Desacuerdo",-0.33,IF(N15="Muy en Desacuerdo",-0.66,IF(N15="Totalmente en Desacuerdo",-1,"error")))))) -> 1 | P15: Muy de Acuerdo | Q15: =IF(P15="Totalmente de Acuerdo",-1,IF(P15="Muy de Acuerdo",-0.66,IF(P15="Levemente de Acuerdo",-0.33,IF(P15="Levemente en Desacuerdo",0.33,IF(P15="Muy en Desacuerdo",0.66,IF(P15="Totalmente en Desacuerdo",1,"error")))))) -> -0.66 | R15: Totalmente de Acuerdo | S15: =IF(R15="Totalmente de Acuerdo",1,IF(R15="Muy de Acuerdo",0.66,IF(R15="Levemente de Acuerdo",0.33,IF(R15="Levemente en Desacuerdo",-0.33,IF(R15="Muy en Desacuerdo",-0.66,IF(R15="Totalmente en Desacuerdo",-1,"error")))))) -> 1 | T15: Muy en Desacuerdo | U15: =IF(T15="Totalmente de Acuerdo",-1,IF(T15="Muy de Acuerdo",-0.66,IF(T15="Levemente de Acuerdo",-0.33,IF(T15="Levemente en Desacuerdo",0.33,IF(T15="Muy en Desacuerdo",0.66,IF(T15="Totalmente en Desacuerdo",1,"error")))))) -> 0.66 | V15: Muy en Desacuerdo | W15: =IF(V15="Totalmente de Acuerdo",1,IF(V15="Muy de Acuerdo",0.66,IF(V15="Levemente de Acuerdo",0.33,IF(V15="Levemente en Desacuerdo",-0.33,IF(V15="Muy en Desacuerdo",-0.66,IF(V15="Totalmente en Desacuerdo",-1,"error")))))) -> -0.66 | X15: Totalmente de Acuerdo | Y15: =IF(X15="Totalmente de Acuerdo",1,IF(X15="Muy de Acuerdo",0.66,IF(X15="Levemente de Acuerdo",0.33,IF(X15="Levemente en Desacuerdo",-0.33,IF(X15="Muy en Desacuerdo",-0.66,IF(X15="Totalmente en Desacuerdo",-1,"error")))))) -> 1 | Z15: Muy de Acuerdo | AA15: =IF(Z15="Totalmente de Acuerdo",1,IF(Z15="Muy de Acuerdo",0.66,IF(Z15="Levemente en Acuerdo",0.33,IF(Z15="Levemente en Desacuerdo",-0.33,IF(Z15="Muy en Desacuerdo",-0.66,IF(Z15="Totalmente en Desacuerdo",-1,"error")))))) -> 0.66 | AB15: =+AA15+Y15+W15+U15+S15+Q15+O15+M15 -> 2.67 | AC15: =+AB15*AB$36 -> 3.00375 | AD15: Levemente de Acuerdo | AE15: =IF(AD15="Totalmente de Acuerdo",1,IF(AD15="Muy de Acuerdo",0.66,IF(AD15="Levemente de Acuerdo",0.33,IF(AD15="Levemente en Desacuerdo",-0.33,IF(AD15="Muy en Desacuerdo",-0.66,IF(AD15="Totalmente en Desacuerdo",-1,"error")))))) -> 0.33 | AF15: Muy de Acuerdo | AG15: =IF(AF15="Totalmente de Acuerdo",-1,IF(AF15="Muy de Acuerdo",-0.66,IF(AF15="Levemente de Acuerdo",-0.33,IF(AF15="Levemente en Desacuerdo",0.33,IF(AF15="Muy en Desacuerdo",0.66,IF(AF15="Totalmente en Desacuerdo",1,"error")))))) -> -0.66 | AH15: Muy de Acuerdo | AI15: =IF(AH15="Totalmente de Acuerdo",1,IF(AH15="Muy de Acuerdo",0.66,IF(AH15="Levemente de Acuerdo",0.33,IF(AH15="Levemente en Desacuerdo",-0.33,IF(AH15="Muy en Desacuerdo",-0.66,IF(AH15="Totalmente en Desacuerdo",-1,"error")))))) -> 0.66 | AJ15: Muy de Acuerdo | AK15: =IF(AJ15="Totalmente de Acuerdo",1,IF(AJ15="Muy de Acuerdo",0.66,IF(AJ15="Levemente de Acuerdo",0.33,IF(AJ15="Levemente en Desacuerdo",-0.33,IF(AJ15="Muy en Desacuerdo",-0.66,IF(AJ15="Totalmente en Desacuerdo",-1,"error")))))) -> 0.66 | AL15: Levemente de Acuerdo | AM15: =IF(AL15="Totalmente de Acuerdo",-1,IF(AL15="Muy de Acuerdo",-0.66,IF(AL15="Levemente de Acuerdo",-0.33,IF(AL15="Levemente en Desacuerdo",0.33,IF(AL15="Muy en Desacuerdo",0.66,IF(AL15="Totalmente en Desacuerdo",1,"error")))))) -> -0.33 | AN15: Totalmente en Desacuerdo | AO15: =IF(AN15="Totalmente de Acuerdo",-1,IF(AN15="Muy de Acuerdo",-0.66,IF(AN15="Levemente de Acuerdo",-0.33,IF(AN15="Levemente en Desacuerdo",0.33,IF(AN15="Muy en Desacuerdo",0.66,IF(AN15="Totalmente en Desacuerdo",1,"error")))))) -> 1 | AP15: Muy de Acuerdo | AQ15: =IF(AP15="Totalmente de Acuerdo",-1,IF(AP15="Muy de Acuerdo",-0.66,IF(AP15="Levemente de Acuerdo",-0.33,IF(AP15="Levemente en Desacuerdo",0.33,IF(AP15="Muy en Desacuerdo",0.66,IF(AP15="Totalmente en Desacuerdo",1,"error")))))) -> -0.66 | AR15: Totalmente de Acuerdo | AS15: =IF(AR15="Totalmente de Acuerdo",1,IF(AR15="Muy de Acuerdo",0.66,IF(AR15="Levemente de Acuerdo",0.33,IF(AR15="Levemente en Desacuerdo",-0.33,IF(AR15="Muy en Desacuerdo",-0.66,IF(AR15="Totalmente en Desacuerdo",-1,"error")))))) -> 1 | AT15: Muy de Acuerdo | AU15: =IF(AT15="Totalmente de Acuerdo",-1,IF(AT15="Muy de Acuerdo",-0.66,IF(AT15="Levemente de Acuerdo",-0.33,IF(AT15="Levemente en Desacuerdo",0.33,IF(AT15="Muy en Desacuerdo",0.66,IF(AT15="Totalmente en Desacuerdo",1,"error")))))) -> -0.66 | AV15: =AU15+AS15+AQ15+AO15+AM15+AK15+AI15+AG15+AE15 -> 1.34 | AW15: Totalmente de Acuerdo | AX15: Totalmente de Acuerdo | AY15: Muy de Acuerdo | AZ15: Muy en Desacuerdo | BA15: Muy en Desacuerdo | BB15: Levemente en Desacuerdo | BC15: Levemente de Acuerdo | BD15: Muy de Acuerdo | BE15: Levemente de Acuerdo | BF15: Muy de Acuerdo | BG15: Muy de Acuerdo | BH15: Me identifico | BM15: Me identifico | BR15: Me identifico | BX15: Javier Milei (La Libertad Avanza) | BY15: Javier Milei (La Libertad Avanza) | BZ15: Javier Milei (La Libertad Avanza)
A16: 45547.901 | B16: 004551455698171 | C16: 2001 | D16: Cuarto año | E16: Mujer | F16: Secundario incompleto | G16: Universitario completo | H16: Clase Alta (ABC1): más de $2.850.000 mensuales | I16: Familia | J16: Otra localidad en otra Provincia | K16: . | L16: Levemente de Acuerdo | M16: =IF(L16="Totalmente de Acuerdo",-1,IF(L16="Muy de Acuerdo",-0.66,IF(L16="Levemente de Acuerdo",-0.33,IF(L16="Levemente en Desacuerdo",0.33,IF(L16="Muy en Desacuerdo",0.66,IF(L16="Totalmente en Desacuerdo",1,"error")))))) -> -0.33 | N16: Levemente de Acuerdo | O16: =IF(N16="Totalmente de Acuerdo",1,IF(N16="Muy de Acuerdo",0.66,IF(N16="Levemente de Acuerdo",0.33,IF(N16="Levemente en Desacuerdo",-0.33,IF(N16="Muy en Desacuerdo",-0.66,IF(N16="Totalmente en Desacuerdo",-1,"error")))))) -> 0.33 | P16: Levemente de Acuerdo | Q16: =IF(P16="Totalmente de Acuerdo",-1,IF(P16="Muy de Acuerdo",-0.66,IF(P16="Levemente de Acuerdo",-0.33,IF(P16="Levemente en Desacuerdo",0.33,IF(P16="Muy en Desacuerdo",0.66,IF(P16="Totalmente en Desacuerdo",1,"error")))))) -> -0.33 | R16: Levemente de Acuerdo | S16: =IF(R16="Totalmente de Acuerdo",1,IF(R16="Muy de Acuerdo",0.66,IF(R16="Levemente de Acuerdo",0.33,IF(R16="Levemente en Desacuerdo",-0.33,IF(R16="Muy en Desacuerdo",-0.66,IF(R16="Totalmente en Desacuerdo",-1,"error")))))) -> 0.33 | T16: Levemente de Acuerdo | U16: =IF(T16="Totalmente de Acuerdo",-1,IF(T16="Muy de Acuerdo",-0.66,IF(T16="Levemente de Acuerdo",-0.33,IF(T16="Levemente en Desacuerdo",0.33,IF(T16="Muy en Desacuerdo",0.66,IF(T16="Totalmente en Desacuerdo",1,"error")))))) -> -0.33 | V16: Muy de Acuerdo | W16: =IF(V16="Totalmente de Acuerdo",1,IF(V16="Muy de Acuerdo",0.66,IF(V16="Levemente de Acuerdo",0.33,IF(V16="Levemente en Desacuerdo",-0.33,IF(V16="Muy en Desacuerdo",-0.66,IF(V16="Totalmente en Desacuerdo",-1,"error")))))) -> 0.66 | X16: Levemente de Acuerdo | Y16: =IF(X16="Totalmente de Acuerdo",1,IF(X16="Muy de Acuerdo",0.66,IF(X16="Levemente de Acuerdo",0.33,IF(X16="Levemente en Desacuerdo",-0.33,IF(X16="Muy en Desacuerdo",-0.66,IF(X16="Totalmente en Desacuerdo",-1,"error")))))) -> 0.33 | Z16: Levemente en Desacuerdo | AA16: =IF(Z16="Totalmente de Acuerdo",1,IF(Z16="Muy de Acuerdo",0.66,IF(Z16="Levemente en Acuerdo",0.33,IF(Z16="Levemente en Desacuerdo",-0.33,IF(Z16="Muy en Desacuerdo",-0.66,IF(Z16="Totalmente en Desacuerdo",-1,"error")))))) -> -0.33 | AB16: =+AA16+Y16+W16+U16+S16+Q16+O16+M16 -> 0.33 | AC16: =+AB16*AB$36 -> 0.37125 | AD16: Levemente en Desacuerdo | AE16: =IF(AD16="Totalmente de Acuerdo",1,IF(AD16="Muy de Acuerdo",0.66,IF(AD16="Levemente de Acuerdo",0.33,IF(AD16="Levemente en Desacuerdo",-0.33,IF(AD16="Muy en Desacuerdo",-0.66,IF(AD16="Totalmente en Desacuerdo",-1,"error")))))) -> -0.33 | AF16: Muy de Acuerdo | AG16: =IF(AF16="Totalmente de Acuerdo",-1,IF(AF16="Muy de Acuerdo",-0.66,IF(AF16="Levemente de Acuerdo",-0.33,IF(AF16="Levemente en Desacuerdo",0.33,IF(AF16="Muy en Desacuerdo",0.66,IF(AF16="Totalmente en Desacuerdo",1,"error")))))) -> -0.66 | AH16: Levemente en Desacuerdo | AI16: =IF(AH16="Totalmente de Acuerdo",1,IF(AH16="Muy de Acuerdo",0.66,IF(AH16="Levemente de Acuerdo",0.33,IF(AH16="Levemente en Desacuerdo",-0.33,IF(AH16="Muy en Desacuerdo",-0.66,IF(AH16="Totalmente en Desacuerdo",-1,"error")))))) -> -0.33 | AJ16: Levemente en Desacuerdo | AK16: =IF(AJ16="Totalmente de Acuerdo",1,IF(AJ16="Muy de Acuerdo",0.66,IF(AJ16="Levemente de Acuerdo",0.33,IF(AJ16="Levemente en Desacuerdo",-0.33,IF(AJ16="Muy en Desacuerdo",-0.66,IF(AJ16="Totalmente en Desacuerdo",-1,"error")))))) -> -0.33 | AL16: Muy de Acuerdo | AM16: =IF(AL16="Totalmente de Acuerdo",-1,IF(AL16="Muy de Acuerdo",-0.66,IF(AL16="Levemente de Acuerdo",-0.33,IF(AL16="Levemente en Desacuerdo",0.33,IF(AL16="Muy en Desacuerdo",0.66,IF(AL16="Totalmente en Desacuerdo",1,"error")))))) -> -0.66 | AN16: Totalmente en Desacuerdo | AO16: =IF(AN16="Totalmente de Acuerdo",-1,IF(AN16="Muy de Acuerdo",-0.66,IF(AN16="Levemente de Acuerdo",-0.33,IF(AN16="Levemente en Desacuerdo",0.33,IF(AN16="Muy en Desacuerdo",0.66,IF(AN16="Totalmente en Desacuerdo",1,"error")))))) -> 1 | AP16: Levemente de Acuerdo | AQ16: =IF(AP16="Totalmente de Acuerdo",-1,IF(AP16="Muy de Acuerdo",-0.66,IF(AP16="Levemente de Acuerdo",-0.33,IF(AP16="Levemente en Desacuerdo",0.33,IF(AP16="Muy en Desacuerdo",0.66,IF(AP16="Totalmente en Desacuerdo",1,"error")))))) -> -0.33 | AR16: Muy de Acuerdo | AS16: =IF(AR16="Totalmente de Acuerdo",1,IF(AR16="Muy de Acuerdo",0.66,IF(AR16="Levemente de Acuerdo",0.33,IF(AR16="Levemente en Desacuerdo",-0.33,IF(AR16="Muy en Desacuerdo",-0.66,IF(AR16="Totalmente en Desacuerdo",-1,"error")))))) -> 0.66 | AT16: Totalmente en Desacuerdo | AU16: =IF(AT16="Totalmente de Acuerdo",-1,IF(AT16="Muy de Acuerdo",-0.66,IF(AT16="Levemente de Acuerdo",-0.33,IF(AT16="Levemente en Desacuerdo",0.33,IF(AT16="Muy en Desacuerdo",0.66,IF(AT16="Totalmente en Desacuerdo",1,"error")))))) -> 1 | AV16: =AU16+AS16+AQ16+AO16+AM16+AK16+AI16+AG16+AE16 -> 0.02 | AW16: Muy de Acuerdo | AX16: Levemente de Acuerdo | AY16: Muy en Desacuerdo | AZ16: Muy en Desacuerdo | BA16: Totalmente en Desacuerdo | BB16: Totalmente en Desacuerdo | BC16: Totalmente en Desacuerdo | BD16: Muy en Desacuerdo | BE16: Muy de Acuerdo | BF16: Levemente en Desacuerdo | BG16: Muy de Acuerdo | BO16: Me identifico | BX16: No vote | BY16: En blanco | BZ16: En blanco
A17: 45547.901 | B17: 00608003883 | C17: 2002 | D17: Cuarto año | E17: Varón | F17: Universitario completo | G17: Universitario completo | H17: Clase Media Alta (C2): entre $1.350.001 mensuales y $2.850.000 mensuales | I17: Familia | J17: Otra localidad en otra Provincia | K17: . | L17: Muy en Desacuerdo | M17: =IF(L17="Totalmente de Acuerdo",-1,IF(L17="Muy de Acuerdo",-0.66,IF(L17="Levemente de Acuerdo",-0.33,IF(L17="Levemente en Desacuerdo",0.33,IF(L17="Muy en Desacuerdo",0.66,IF(L17="Totalmente en Desacuerdo",1,"error")))))) -> 0.66 | N17: Levemente de Acuerdo | O17: =IF(N17="Totalmente de Acuerdo",1,IF(N17="Muy de Acuerdo",0.66,IF(N17="Levemente de Acuerdo",0.33,IF(N17="Levemente en Desacuerdo",-0.33,IF(N17="Muy en Desacuerdo",-0.66,IF(N17="Totalmente en Desacuerdo",-1,"error")))))) -> 0.33 | P17: Muy de Acuerdo | Q17: =IF(P17="Totalmente de Acuerdo",-1,IF(P17="Muy de Acuerdo",-0.66,IF(P17="Levemente de Acuerdo",-0.33,IF(P17="Levemente en Desacuerdo",0.33,IF(P17="Muy en Desacuerdo",0.66,IF(P17="Totalmente en Desacuerdo",1,"error")))))) -> -0.66 | R17: Totalmente de Acuerdo | S17: =IF(R17="Totalmente de Acuerdo",1,IF(R17="Muy de Acuerdo",0.66,IF(R17="Levemente de Acuerdo",0.33,IF(R17="Levemente en Desacuerdo",-0.33,IF(R17="Muy en Desacuerdo",-0.66,IF(R17="Totalmente en Desacuerdo",-1,"error")))))) -> 1 | T17: Muy en Desacuerdo | U17: =IF(T17="Totalmente de Acuerdo",-1,IF(T17="Muy de Acuerdo",-0.66,IF(T17="Levemente de Acuerdo",-0.33,IF(T17="Levemente en Desacuerdo",0.33,IF(T17="Muy en Desacuerdo",0.66,IF(T17="Totalmente en Desacuerdo",1,"error")))))) -> 0.66 | V17: Muy de Acuerdo | W17: =IF(V17="Totalmente de Acuerdo",1,IF(V17="Muy de Acuerdo",0.66,IF(V17="Levemente de Acuerdo",0.33,IF(V17="Levemente en Desacuerdo",-0.33,IF(V17="Muy en Desacuerdo",-0.66,IF(V17="Totalmente en Desacuerdo",-1,"error")))))) -> 0.66 | X17: Levemente de Acuerdo | Y17: =IF(X17="Totalmente de Acuerdo",1,IF(X17="Muy de Acuerdo",0.66,IF(X17="Levemente de Acuerdo",0.33,IF(X17="Levemente en Desacuerdo",-0.33,IF(X17="Muy en Desacuerdo",-0.66,IF(X17="Totalmente en Desacuerdo",-1,"error")))))) -> 0.33 | Z17: Levemente en Desacuerdo | AA17: =IF(Z17="Totalmente de Acuerdo",1,IF(Z17="Muy de Acuerdo",0.66,IF(Z17="Levemente en Acuerdo",0.33,IF(Z17="Levemente en Desacuerdo",-0.33,IF(Z17="Muy en Desacuerdo",-0.66,IF(Z17="Totalmente en Desacuerdo",-1,"error")))))) -> -0.33 | AB17: =+AA17+Y17+W17+U17+S17+Q17+O17+M17 -> 2.65 | AC17: =+AB17*AB$36 -> 2.98125 | AD17: Totalmente en Desacuerdo | AE17: =IF(AD17="Totalmente de Acuerdo",1,IF(AD17="Muy de Acuerdo",0.66,IF(AD17="Levemente de Acuerdo",0.33,IF(AD17="Levemente en Desacuerdo",-0.33,IF(AD17="Muy en Desacuerdo",-0.66,IF(AD17="Totalmente en Desacuerdo",-1,"error")))))) -> -1 | AF17: Muy de Acuerdo | AG17: =IF(AF17="Totalmente de Acuerdo",-1,IF(AF17="Muy de Acuerdo",-0.66,IF(AF17="Levemente de Acuerdo",-0.33,IF(AF17="Levemente en Desacuerdo",0.33,IF(AF17="Muy en Desacuerdo",0.66,IF(AF17="Totalmente en Desacuerdo",1,"error")))))) -> -0.66 | AH17: Levemente en Desacuerdo | AI17: =IF(AH17="Totalmente de Acuerdo",1,IF(AH17="Muy de Acuerdo",0.66,IF(AH17="Levemente de Acuerdo",0.33,IF(AH17="Levemente en Desacuerdo",-0.33,IF(AH17="Muy en Desacuerdo",-0.66,IF(AH17="Totalmente en Desacuerdo",-1,"error")))))) -> -0.33 | AJ17: Levemente de Acuerdo | AK17: =IF(AJ17="Totalmente de Acuerdo",1,IF(AJ17="Muy de Acuerdo",0.66,IF(AJ17="Levemente de Acuerdo",0.33,IF(AJ17="Levemente en Desacuerdo",-0.33,IF(AJ17="Muy en Desacuerdo",-0.66,IF(AJ17="Totalmente en Desacuerdo",-1,"error")))))) -> 0.33 | AL17: Muy de Acuerdo | AM17: =IF(AL17="Totalmente de Acuerdo",-1,IF(AL17="Muy de Acuerdo",-0.66,IF(AL17="Levemente de Acuerdo",-0.33,IF(AL17="Levemente en Desacuerdo",0.33,IF(AL17="Muy en Desacuerdo",0.66,IF(AL17="Totalmente en Desacuerdo",1,"error")))))) -> -0.66 | AN17: Totalmente en Desacuerdo | AO17: =IF(AN17="Totalmente de Acuerdo",-1,IF(AN17="Muy de Acuerdo",-0.66,IF(AN17="Levemente de Acuerdo",-0.33,IF(AN17="Levemente en Desacuerdo",0.33,IF(AN17="Muy en Desacuerdo",0.66,IF(AN17="Totalmente en Desacuerdo",1,"error")))))) -> 1 | AP17: Muy en Desacuerdo | AQ17: =IF(AP17="Totalmente de Acuerdo",-1,IF(AP17="Muy de Acuerdo",-0.66,IF(AP17="Levemente de Acuerdo",-0.33,IF(AP17="Levemente en Desacuerdo",0.33,IF(AP17="Muy en Desacuerdo",0.66,IF(AP17="Totalmente en Desacuerdo",1,"error")))))) -> 0.66 | AR17: Muy de Acuerdo | AS17: =IF(AR17="Totalmente de Acuerdo",1,IF(AR17="Muy de Acuerdo",0.66,IF(AR17="Levemente de Acuerdo",0.33,IF(AR17="Levemente en Desacuerdo",-0.33,IF(AR17="Muy en Desacuerdo",-0.66,IF(AR17="Totalmente en Desacuerdo",-1,"error")))))) -> 0.66 | AT17: Levemente en Desacuerdo | AU17: =IF(AT17="Totalmente de Acuerdo",-1,IF(AT17="Muy de Acuerdo",-0.66,IF(AT17="Levemente de Acuerdo",-0.33,IF(AT17="Levemente en Desacuerdo",0.33,IF(AT17="Muy en Desacuerdo",0.66,IF(AT17="Totalmente en Desacuerdo",1,"error")))))) -> 0.33 | AV17: =AU17+AS17+AQ17+AO17+AM17+AK17+AI17+AG17+AE17 -> 0.33 | AW17: Muy de Acuerdo | AX17: Muy de Acuerdo | AY17: Muy de Acuerdo | AZ17: Muy de Acuerdo | BA17: Levemente de Acuerdo | BB17: Levemente en Desacuerdo | BC17: Levemente en Desacuerdo | BD17: Levemente de Acuerdo | BE17: Muy de Acuerdo | BF17: Muy de Acuerdo | BG17: Muy de Acuerdo | BH17: Me identifico | BM17: Me identifico | BX17: En blanco | BY17: En blanco | BZ17: Javier Milei (La Libertad Avanza)
A18: 45547.902 | B18: 00686589580 | C18: 2002 | D18: Cuarto año | E18: Varón | F18: Universitario completo | G18: Universitario completo | H18: Clase Media Alta (C2): entre $1.350.001 mensuales y $2.850.000 mensuales | I18: Familia | J18: Otra localidad en otra Provincia | K18: . | L18: Levemente de Acuerdo | M18: =IF(L18="Totalmente de Acuerdo",-1,IF(L18="Muy de Acuerdo",-0.66,IF(L18="Levemente de Acuerdo",-0.33,IF(L18="Levemente en Desacuerdo",0.33,IF(L18="Muy en Desacuerdo",0.66,IF(L18="Totalmente en Desacuerdo",1,"error")))))) -> -0.33 | N18: Levemente de Acuerdo | O18: =IF(N18="Totalmente de Acuerdo",1,IF(N18="Muy de Acuerdo",0.66,IF(N18="Levemente de Acuerdo",0.33,IF(N18="Levemente en Desacuerdo",-0.33,IF(N18="Muy en Desacuerdo",-0.66,IF(N18="Totalmente en Desacuerdo",-1,"error")))))) -> 0.33 | P18: Totalmente de Acuerdo | Q18: =IF(P18="Totalmente de Acuerdo",-1,IF(P18="Muy de Acuerdo",-0.66,IF(P18="Levemente de Acuerdo",-0.33,IF(P18="Levemente en Desacuerdo",0.33,IF(P18="Muy en Desacuerdo",0.66,IF(P18="Totalmente en Desacuerdo",1,"error")))))) -> -1 | R18: Muy de Acuerdo | S18: =IF(R18="Totalmente de Acuerdo",1,IF(R18="Muy de Acuerdo",0.66,IF(R18="Levemente de Acuerdo",0.33,IF(R18="Levemente en Desacuerdo",-0.33,IF(R18="Muy en Desacuerdo",-0.66,IF(R18="Totalmente en Desacuerdo",-1,"error")))))) -> 0.66 | T18: Muy de Acuerdo | U18: =IF(T18="Totalmente de Acuerdo",-1,IF(T18="Muy de Acuerdo",-0.66,IF(T18="Levemente de Acuerdo",-0.33,IF(T18="Levemente en Desacuerdo",0.33,IF(T18="Muy en Desacuerdo",0.66,IF(T18="Totalmente en Desacuerdo",1,"error")))))) -> -0.66 | V18: Levemente de Acuerdo | W18: =IF(V18="Totalmente de Acuerdo",1,IF(V18="Muy de Acuerdo",0.66,IF(V18="Levemente de Acuerdo",0.33,IF(V18="Levemente en Desacuerdo",-0.33,IF(V18="Muy en Desacuerdo",-0.66,IF(V18="Totalmente en Desacuerdo",-1,"error")))))) -> 0.33 | X18: Levemente de Acuerdo | Y18: =IF(X18="Totalmente de Acuerdo",1,IF(X18="Muy de Acuerdo",0.66,IF(X18="Levemente de Acuerdo",0.33,IF(X18="Levemente en Desacuerdo",-0.33,IF(X18="Muy en Desacuerdo",-0.66,IF(X18="Totalmente en Desacuerdo",-1,"error")))))) -> 0.33 | Z18: Levemente en Desacuerdo | AA18: =IF(Z18="Totalmente de Acuerdo",1,IF(Z18="Muy de Acuerdo",0.66,IF(Z18="Levemente en Acuerdo",0.33,IF(Z18="Levemente en Desacuerdo",-0.33,IF(Z18="Muy en Desacuerdo",-0.66,IF(Z18="Totalmente en Desacuerdo",-1,"error")))))) -> -0.33 | AB18: =+AA18+Y18+W18+U18+S18+Q18+O18+M18 -> -0.67 | AC18: =+AB18*AB$36 -> -0.75375 | AD18: Muy en Desacuerdo | AE18: =IF(AD18="Totalmente de Acuerdo",1,IF(AD18="Muy de Acuerdo",0.66,IF(AD18="Levemente de Acuerdo",0.33,IF(AD18="Levemente en Desacuerdo",-0.33,IF(AD18="Muy en Desacuerdo",-0.66,IF(AD18="Totalmente en Desacuerdo",-1,"error")))))) -> -0.66 | AF18: Muy en Desacuerdo | AG18: =IF(AF18="Totalmente de Acuerdo",-1,IF(AF18="Muy de Acuerdo",-0.66,IF(AF18="Levemente de Acuerdo",-0.33,IF(AF18="Levemente en Desacuerdo",0.33,IF(AF18="Muy en Desacuerdo",0.66,IF(AF18="Totalmente en Desacuerdo",1,"error")))))) -> 0.66 | AH18: Levemente de Acuerdo | AI18: =IF(AH18="Totalmente de Acuerdo",1,IF(AH18="Muy de Acuerdo",0.66,IF(AH18="Levemente de Acuerdo",0.33,IF(AH18="Levemente en Desacuerdo",-0.33,IF(AH18="Muy en Desacuerdo",-0.66,IF(AH18="Totalmente en Desacuerdo",-1,"error")))))) -> 0.33 | AJ18: Levemente de Acuerdo | AK18: =IF(AJ18="Totalmente de Acuerdo",1,IF(AJ18="Muy de Acuerdo",0.66,IF(AJ18="Levemente de Acuerdo",0.33,IF(AJ18="Levemente en Desacuerdo",-0.33,IF(AJ18="Muy en Desacuerdo",-0.66,IF(AJ18="Totalmente en Desacuerdo",-1,"error")))))) -> 0.33 | AL18: Levemente en Desacuerdo | AM18: =IF(AL18="Totalmente de Acuerdo",-1,IF(AL18="Muy de Acuerdo",-0.66,IF(AL18="Levemente de Acuerdo",-0.33,IF(AL18="Levemente en Desacuerdo",0.33,IF(AL18="Muy en Desacuerdo",0.66,IF(AL18="Totalmente en Desacuerdo",1,"error")))))) -> 0.33 | AN18: Levemente en Desacuerdo | AO18: =IF(AN18="Totalmente de Acuerdo",-1,IF(AN18="Muy de Acuerdo",-0.66,IF(AN18="Levemente de Acuerdo",-0.33,IF(AN18="Levemente en Desacuerdo",0.33,IF(AN18="Muy en Desacuerdo",0.66,IF(AN18="Totalmente en Desacuerdo",1,"error")))))) -> 0.33 | AP18: Levemente en Desacuerdo | AQ18: =IF(AP18="Totalmente de Acuerdo",-1,IF(AP18="Muy de Acuerdo",-0.66,IF(AP18="Levemente de Acuerdo",-0.33,IF(AP18="Levemente en Desacuerdo",0.33,IF(AP18="Muy en Desacuerdo",0.66,IF(AP18="Totalmente en Desacuerdo",1,"error")))))) -> 0.33 | AR18: Levemente de Acuerdo | AS18: =IF(AR18="Totalmente de Acuerdo",1,IF(AR18="Muy de Acuerdo",0.66,IF(AR18="Levemente de Acuerdo",0.33,IF(AR18="Levemente en Desacuerdo",-0.33,IF(AR18="Muy en Desacuerdo",-0.66,IF(AR18="Totalmente en Desacuerdo",-1,"error")))))) -> 0.33 | AT18: Totalmente en Desacuerdo | AU18: =IF(AT18="Totalmente de Acuerdo",-1,IF(AT18="Muy de Acuerdo",-0.66,IF(AT18="Levemente de Acuerdo",-0.33,IF(AT18="Levemente en Desacuerdo",0.33,IF(AT18="Muy en Desacuerdo",0.66,IF(AT18="Totalmente en Desacuerdo",1,"error")))))) -> 1 | AV18: =AU18+AS18+AQ18+AO18+AM18+AK18+AI18+AG18+AE18 -> 2.98 | AW18: Levemente en Desacuerdo | AX18: Muy de Acuerdo | AY18: Totalmente en Desacuerdo | AZ18: Totalmente en Desacuerdo | BA18: Totalmente en Desacuerdo | BB18: Levemente de Acuerdo | BC18: Levemente de Acuerdo | BD18: Levemente de Acuerdo | BE18: Totalmente en Desacuerdo | BF18: Totalmente en Desacuerdo | BG18: Muy en Desacuerdo | BL18: Me identifico | BX18: Javier Milei (La Libertad Avanza) | BY18: Javier Milei (La Libertad Avanza) | BZ18: Javier Milei (La Libertad Avanza)
A19: 45547.902 | B19: 00530483055 | C19: 2000 | D19: Cuarto año | E19: Varón | F19: Secundario incompleto | G19: Terciario completo | H19: Clase Alta (ABC1): más de $2.850.000 mensuales | I19: Familia | J19: Otra localidad en la Provincia de Córdoba | K19: . | L19: Totalmente en Desacuerdo | M19: =IF(L19="Totalmente de Acuerdo",-1,IF(L19="Muy de Acuerdo",-0.66,IF(L19="Levemente de Acuerdo",-0.33,IF(L19="Levemente en Desacuerdo",0.33,IF(L19="Muy en Desacuerdo",0.66,IF(L19="Totalmente en Desacuerdo",1,"error")))))) -> 1 | N19: Levemente de Acuerdo | O19: =IF(N19="Totalmente de Acuerdo",1,IF(N19="Muy de Acuerdo",0.66,IF(N19="Levemente de Acuerdo",0.33,IF(N19="Levemente en Desacuerdo",-0.33,IF(N19="Muy en Desacuerdo",-0.66,IF(N19="Totalmente en Desacuerdo",-1,"error")))))) -> 0.33 | P19: Muy de Acuerdo | Q19: =IF(P19="Totalmente de Acuerdo",-1,IF(P19="Muy de Acuerdo",-0.66,IF(P19="Levemente de Acuerdo",-0.33,IF(P19="Levemente en Desacuerdo",0.33,IF(P19="Muy en Desacuerdo",0.66,IF(P19="Totalmente en Desacuerdo",1,"error")))))) -> -0.66 | R19: Muy de Acuerdo | S19: =IF(R19="Totalmente de Acuerdo",1,IF(R19="Muy de Acuerdo",0.66,IF(R19="Levemente de Acuerdo",0.33,IF(R19="Levemente en Desacuerdo",-0.33,IF(R19="Muy en Desacuerdo",-0.66,IF(R19="Totalmente en Desacuerdo",-1,"error")))))) -> 0.66 | T19: Levemente de Acuerdo | U19: =IF(T19="Totalmente de Acuerdo",-1,IF(T19="Muy de Acuerdo",-0.66,IF(T19="Levemente de Acuerdo",-0.33,IF(T19="Levemente en Desacuerdo",0.33,IF(T19="Muy en Desacuerdo",0.66,IF(T19="Totalmente en Desacuerdo",1,"error")))))) -> -0.33 | V19: Totalmente de Acuerdo | W19: =IF(V19="Totalmente de Acuerdo",1,IF(V19="Muy de Acuerdo",0.66,IF(V19="Levemente de Acuerdo",0.33,IF(V19="Levemente en Desacuerdo",-0.33,IF(V19="Muy en Desacuerdo",-0.66,IF(V19="Totalmente en Desacuerdo",-1,"error")))))) -> 1 | X19: Muy de Acuerdo | Y19: =IF(X19="Totalmente de Acuerdo",1,IF(X19="Muy de Acuerdo",0.66,IF(X19="Levemente de Acuerdo",0.33,IF(X19="Levemente en Desacuerdo",-0.33,IF(X19="Muy en Desacuerdo",-0.66,IF(X19="Totalmente en Desacuerdo",-1,"error")))))) -> 0.66 | Z19: Totalmente en Desacuerdo | AA19: =IF(Z19="Totalmente de Acuerdo",1,IF(Z19="Muy de Acuerdo",0.66,IF(Z19="Levemente en Acuerdo",0.33,IF(Z19="Levemente en Desacuerdo",-0.33,IF(Z19="Muy en Desacuerdo",-0.66,IF(Z19="Totalmente en Desacuerdo",-1,"error")))))) -> -1 | AB19: =+AA19+Y19+W19+U19+S19+Q19+O19+M19 -> 1.66 | AC19: =+AB19*AB$36 -> 1.8675 | AD19: Muy en Desacuerdo | AE19: =IF(AD19="Totalmente de Acuerdo",1,IF(AD19="Muy de Acuerdo",0.66,IF(AD19="Levemente de Acuerdo",0.33,IF(AD19="Levemente en Desacuerdo",-0.33,IF(AD19="Muy en Desacuerdo",-0.66,IF(AD19="Totalmente en Desacuerdo",-1,"error")))))) -> -0.66 | AF19: Totalmente de Acuerdo | AG19: =IF(AF19="Totalmente de Acuerdo",-1,IF(AF19="Muy de Acuerdo",-0.66,IF(AF19="Levemente de Acuerdo",-0.33,IF(AF19="Levemente en Desacuerdo",0.33,IF(AF19="Muy en Desacuerdo",0.66,IF(AF19="Totalmente en Desacuerdo",1,"error")))))) -> -1 | AH19: Muy en Desacuerdo | AI19: =IF(AH19="Totalmente de Acuerdo",1,IF(AH19="Muy de Acuerdo",0.66,IF(AH19="Levemente de Acuerdo",0.33,IF(AH19="Levemente en Desacuerdo",-0.33,IF(AH19="Muy en Desacuerdo",-0.66,IF(AH19="Totalmente en Desacuerdo",-1,"error")))))) -> -0.66 | AJ19: Totalmente en Desacuerdo | AK19: =IF(AJ19="Totalmente de Acuerdo",1,IF(AJ19="Muy de Acuerdo",0.66,IF(AJ19="Levemente de Acuerdo",0.33,IF(AJ19="Levemente en Desacuerdo",-0.33,IF(AJ19="Muy en Desacuerdo",-0.66,IF(AJ19="Totalmente en Desacuerdo",-1,"error")))))) -> -1 | AL19: Muy en Desacuerdo | AM19: =IF(AL19="Totalmente de Acuerdo",-1,IF(AL19="Muy de Acuerdo",-0.66,IF(AL19="Levemente de Acuerdo",-0.33,IF(AL19="Levemente en Desacuerdo",0.33,IF(AL19="Muy en Desacuerdo",0.66,IF(AL19="Totalmente en Desacuerdo",1,"error")))))) -> 0.66 | AN19: Muy en Desacuerdo | AO19: =IF(AN19="Totalmente de Acuerdo",-1,IF(AN19="Muy de Acuerdo",-0.66,IF(AN19="Levemente de Acuerdo",-0.33,IF(AN19="Levemente en Desacuerdo",0.33,IF(AN19="Muy en Desacuerdo",0.66,IF(AN19="Totalmente en Desacuerdo",1,"error")))))) -> 0.66 | AP19: Levemente de Acuerdo | AQ19: =IF(AP19="Totalmente de Acuerdo",-1,IF(AP19="Muy de Acuerdo",-0.66,IF(AP19="Levemente de Acuerdo",-0.33,IF(AP19="Levemente en Desacuerdo",0.33,IF(AP19="Muy en Desacuerdo",0.66,IF(AP19="Totalmente en Desacuerdo",1,"error")))))) -> -0.33 | AR19: Totalmente de Acuerdo | AS19: =IF(AR19="Totalmente de Acuerdo",1,IF(AR19="Muy de Acuerdo",0.66,IF(AR19="Levemente de Acuerdo",0.33,IF(AR19="Levemente en Desacuerdo",-0.33,IF(AR19="Muy en Desacuerdo",-0.66,IF(AR19="Totalmente en Desacuerdo",-1,"error")))))) -> 1 | AT19: Muy en Desacuerdo | AU19: =IF(AT19="Totalmente de Acuerdo",-1,IF(AT19="Muy de Acuerdo",-0.66,IF(AT19="Levemente de Acuerdo",-0.33,IF(AT19="Levemente en Desacuerdo",0.33,IF(AT19="Muy en Desacuerdo",0.66,IF(AT19="Totalmente en Desacuerdo",1,"error")))))) -> 0.66 | AV19: =AU19+AS19+AQ19+AO19+AM19+AK19+AI19+AG19+AE19 -> -0.67 | AW19: Muy de Acuerdo | AX19: Levemente de Acuerdo | AY19: Totalmente en Desacuerdo | AZ19: Totalmente en Desacuerdo | BA19: Levemente de Acuerdo | BB19: Totalmente en Desacuerdo | BC19: Totalmente en Desacuerdo | BD19: Levemente de Acuerdo | BE19: Totalmente de Acuerdo | BF19: Totalmente de Acuerdo | BG19: Muy en Desacuerdo | BH19: Me identifico | BX19: Javier Milei (La Libertad Avanza) | BY19: Javier Milei (La Libertad Avanza) | BZ19: Javier Milei (La Libertad Avanza)
A20: 45547.902 | B20: 003772232568073 | C20: 2000 | D20: Quinto año | E20: Mujer | F20: Terciario completo | G20: Secundario completo | H20: Clase Media Baja (C3): entre $850.001 mensuales y $1.350.000 mensuales | I20: Trabajo propio | J20: Otra localidad en la Provincia de Córdoba | K20: . | L20: Muy en Desacuerdo | M20: =IF(L20="Totalmente de Acuerdo",-1,IF(L20="Muy de Acuerdo",-0.66,IF(L20="Levemente de Acuerdo",-0.33,IF(L20="Levemente en Desacuerdo",0.33,IF(L20="Muy en Desacuerdo",0.66,IF(L20="Totalmente en Desacuerdo",1,"error")))))) -> 0.66 | N20: Muy de Acuerdo | O20: =IF(N20="Totalmente de Acuerdo",1,IF(N20="Muy de Acuerdo",0.66,IF(N20="Levemente de Acuerdo",0.33,IF(N20="Levemente en Desacuerdo",-0.33,IF(N20="Muy en Desacuerdo",-0.66,IF(N20="Totalmente en Desacuerdo",-1,"error")))))) -> 0.66 | P20: Muy de Acuerdo | Q20: =IF(P20="Totalmente de Acuerdo",-1,IF(P20="Muy de Acuerdo",-0.66,IF(P20="Levemente de Acuerdo",-0.33,IF(P20="Levemente en Desacuerdo",0.33,IF(P20="Muy en Desacuerdo",0.66,IF(P20="Totalmente en Desacuerdo",1,"error")))))) -> -0.66 | R20: Muy de Acuerdo | S20: =IF(R20="Totalmente de Acuerdo",1,IF(R20="Muy de Acuerdo",0.66,IF(R20="Levemente de Acuerdo",0.33,IF(R20="Levemente en Desacuerdo",-0.33,IF(R20="Muy en Desacuerdo",-0.66,IF(R20="Totalmente en Desacuerdo",-1,"error")))))) -> 0.66 | T20: Muy en Desacuerdo | U20: =IF(T20="Totalmente de Acuerdo",-1,IF(T20="Muy de Acuerdo",-0.66,IF(T20="Levemente de Acuerdo",-0.33,IF(T20="Levemente en Desacuerdo",0.33,IF(T20="Muy en Desacuerdo",0.66,IF(T20="Totalmente en Desacuerdo",1,"error")))))) -> 0.66 | V20: Levemente de Acuerdo | W20: =IF(V20="Totalmente de Acuerdo",1,IF(V20="Muy de Acuerdo",0.66,IF(V20="Levemente de Acuerdo",0.33,IF(V20="Levemente en Desacuerdo",-0.33,IF(V20="Muy en Desacuerdo",-0.66,IF(V20="Totalmente en Desacuerdo",-1,"error")))))) -> 0.33 | X20: Totalmente de Acuerdo | Y20: =IF(X20="Totalmente de Acuerdo",1,IF(X20="Muy de Acuerdo",0.66,IF(X20="Levemente de Acuerdo",0.33,IF(X20="Levemente en Desacuerdo",-0.33,IF(X20="Muy en Desacuerdo",-0.66,IF(X20="Totalmente en Desacuerdo",-1,"error")))))) -> 1 | Z20: Muy en Desacuerdo | AA20: =IF(Z20="Totalmente de Acuerdo",1,IF(Z20="Muy de Acuerdo",0.66,IF(Z20="Levemente en Acuerdo",0.33,IF(Z20="Levemente en Desacuerdo",-0.33,IF(Z20="Muy en Desacuerdo",-0.66,IF(Z20="Totalmente en Desacuerdo",-1,"error")))))) -> -0.66 | AB20: =+AA20+Y20+W20+U20+S20+Q20+O20+M20 -> 2.65 | AC20: =+AB20*AB$36 -> 2.98125 | AD20: Levemente de Acuerdo | AE20: =IF(AD20="Totalmente de Acuerdo",1,IF(AD20="Muy de Acuerdo",0.66,IF(AD20="Levemente de Acuerdo",0.33,IF(AD20="Levemente en Desacuerdo",-0.33,IF(AD20="Muy en Desacuerdo",-0.66,IF(AD20="Totalmente en Desacuerdo",-1,"error")))))) -> 0.33 | AF20: Levemente de Acuerdo | AG20: =IF(AF20="Totalmente de Acuerdo",-1,IF(AF20="Muy de Acuerdo",-0.66,IF(AF20="Levemente de Acuerdo",-0.33,IF(AF20="Levemente en Desacuerdo",0.33,IF(AF20="Muy en Desacuerdo",0.66,IF(AF20="Totalmente en Desacuerdo",1,"error")))))) -> -0.33 | AH20: Totalmente en Desacuerdo | AI20: =IF(AH20="Totalmente de Acuerdo",1,IF(AH20="Muy de Acuerdo",0.66,IF(AH20="Levemente de Acuerdo",0.33,IF(AH20="Levemente en Desacuerdo",-0.33,IF(AH20="Muy en Desacuerdo",-0.66,IF(AH20="Totalmente en Desacuerdo",-1,"error")))))) -> -1 | AJ20: Totalmente en Desacuerdo | AK20: =IF(AJ20="Totalmente de Acuerdo",1,IF(AJ20="Muy de Acuerdo",0.66,IF(AJ20="Levemente de Acuerdo",0.33,IF(AJ20="Levemente en Desacuerdo",-0.33,IF(AJ20="Muy en Desacuerdo",-0.66,IF(AJ20="Totalmente en Desacuerdo",-1,"error")))))) -> -1 | AL20: Totalmente de Acuerdo | AM20: =IF(AL20="Totalmente de Acuerdo",-1,IF(AL20="Muy de Acuerdo",-0.66,IF(AL20="Levemente de Acuerdo",-0.33,IF(AL20="Levemente en Desacuerdo",0.33,IF(AL20="Muy en Desacuerdo",0.66,IF(AL20="Totalmente en Desacuerdo",1,"error")))))) -> -1 | AN20: Muy en Desacuerdo | AO20: =IF(AN20="Totalmente de Acuerdo",-1,IF(AN20="Muy de Acuerdo",-0.66,IF(AN20="Levemente de Acuerdo",-0.33,IF(AN20="Levemente en Desacuerdo",0.33,IF(AN20="Muy en Desacuerdo",0.66,IF(AN20="Totalmente en Desacuerdo",1,"error")))))) -> 0.66 | AP20: Levemente de Acuerdo | AQ20: =IF(AP20="Totalmente de Acuerdo",-1,IF(AP20="Muy de Acuerdo",-0.66,IF(AP20="Levemente de Acuerdo",-0.33,IF(AP20="Levemente en Desacuerdo",0.33,IF(AP20="Muy en Desacuerdo",0.66,IF(AP20="Totalmente en Desacuerdo",1,"error")))))) -> -0.33 | AR20: Muy en Desacuerdo | AS20: =IF(AR20="Totalmente de Acuerdo",1,IF(AR20="Muy de Acuerdo",0.66,IF(AR20="Levemente de Acuerdo",0.33,IF(AR20="Levemente en Desacuerdo",-0.33,IF(AR20="Muy en Desacuerdo",-0.66,IF(AR20="Totalmente en Desacuerdo",-1,"error")))))) -> -0.66 | AT20: Muy en Desacuerdo | AU20: =IF(AT20="Totalmente de Acuerdo",-1,IF(AT20="Muy de Acuerdo",-0.66,IF(AT20="Levemente de Acuerdo",-0.33,IF(AT20="Levemente en Desacuerdo",0.33,IF(AT20="Muy en Desacuerdo",0.66,IF(AT20="Totalmente en Desacuerdo",1,"error")))))) -> 0.66 | AV20: =AU20+AS20+AQ20+AO20+AM20+AK20+AI20+AG20+AE20 -> -2.67 | AW20: Muy de Acuerdo | AX20: Muy en Desacuerdo | AY20: Levemente en Desacuerdo | AZ20: Totalmente de Acuerdo | BA20: Totalmente en Desacuerdo | BB20: Totalmente en Desacuerdo | BC20: Totalmente en Desacuerdo | BD20: Totalmente en Desacuerdo | BE20: Levemente en Desacuerdo | BF20: Totalmente de Acuerdo | BG20: Levemente de Acuerdo | BH20: Me identifico | BJ20: Me identifico | BO20: Me identifico | BU20: Me identifico | BX20: Patricia Bullrich (Juntos por el Cambio) | BY20: Patricia Bullrich (Juntos por el Cambio) | BZ20: Javier Milei (La Libertad Avanza)
A21: 45547.902 | B21: 00680175484 | C21: 2002 | D21: Cuarto año | E21: Mujer | F21: Secundario completo | G21: Primario completo | H21: Clase Alta (ABC1): más de $2.850.000 mensuales | I21: Familia | J21: Otra localidad en la Provincia de Córdoba | K21: . | L21: Levemente de Acuerdo | M21: =IF(L21="Totalmente de Acuerdo",-1,IF(L21="Muy de Acuerdo",-0.66,IF(L21="Levemente de Acuerdo",-0.33,IF(L21="Levemente en Desacuerdo",0.33,IF(L21="Muy en Desacuerdo",0.66,IF(L21="Totalmente en Desacuerdo",1,"error")))))) -> -0.33 | N21: Levemente en Desacuerdo | O21: =IF(N21="Totalmente de Acuerdo",1,IF(N21="Muy de Acuerdo",0.66,IF(N21="Levemente de Acuerdo",0.33,IF(N21="Levemente en Desacuerdo",-0.33,IF(N21="Muy en Desacuerdo",-0.66,IF(N21="Totalmente en Desacuerdo",-1,"error")))))) -> -0.33 | P21: Levemente de Acuerdo | Q21: =IF(P21="Totalmente de Acuerdo",-1,IF(P21="Muy de Acuerdo",-0.66,IF(P21="Levemente de Acuerdo",-0.33,IF(P21="Levemente en Desacuerdo",0.33,IF(P21="Muy en Desacuerdo",0.66,IF(P21="Totalmente en Desacuerdo",1,"error")))))) -> -0.33 | R21: Muy de Acuerdo | S21: =IF(R21="Totalmente de Acuerdo",1,IF(R21="Muy de Acuerdo",0.66,IF(R21="Levemente de Acuerdo",0.33,IF(R21="Levemente en Desacuerdo",-0.33,IF(R21="Muy en Desacuerdo",-0.66,IF(R21="Totalmente en Desacuerdo",-1,"error")))))) -> 0.66 | T21: Muy en Desacuerdo | U21: =IF(T21="Totalmente de Acuerdo",-1,IF(T21="Muy de Acuerdo",-0.66,IF(T21="Levemente de Acuerdo",-0.33,IF(T21="Levemente en Desacuerdo",0.33,IF(T21="Muy en Desacuerdo",0.66,IF(T21="Totalmente en Desacuerdo",1,"error")))))) -> 0.66 | V21: Muy de Acuerdo | W21: =IF(V21="Totalmente de Acuerdo",1,IF(V21="Muy de Acuerdo",0.66,IF(V21="Levemente de Acuerdo",0.33,IF(V21="Levemente en Desacuerdo",-0.33,IF(V21="Muy en Desacuerdo",-0.66,IF(V21="Totalmente en Desacuerdo",-1,"error")))))) -> 0.66 | X21: Totalmente de Acuerdo | Y21: =IF(X21="Totalmente de Acuerdo",1,IF(X21="Muy de Acuerdo",0.66,IF(X21="Levemente de Acuerdo",0.33,IF(X21="Levemente en Desacuerdo",-0.33,IF(X21="Muy en Desacuerdo",-0.66,IF(X21="Totalmente en Desacuerdo",-1,"error")))))) -> 1 | Z21: Muy en Desacuerdo | AA21: =IF(Z21="Totalmente de Acuerdo",1,IF(Z21="Muy de Acuerdo",0.66,IF(Z21="Levemente en Acuerdo",0.33,IF(Z21="Levemente en Desacuerdo",-0.33,IF(Z21="Muy en Desacuerdo",-0.66,IF(Z21="Totalmente en Desacuerdo",-1,"error")))))) -> -0.66 | AB21: =+AA21+Y21+W21+U21+S21+Q21+O21+M21 -> 1.33 | AC21: =+AB21*AB$36 -> 1.49625 | AD21: Levemente en Desacuerdo | AE21: =IF(AD21="Totalmente de Acuerdo",1,IF(AD21="Muy de Acuerdo",0.66,IF(AD21="Levemente de Acuerdo",0.33,IF(AD21="Levemente en Desacuerdo",-0.33,IF(AD21="Muy en Desacuerdo",-0.66,IF(AD21="Totalmente en Desacuerdo",-1,"error")))))) -> -0.33 | AF21: Muy de Acuerdo | AG21: =IF(AF21="Totalmente de Acuerdo",-1,IF(AF21="Muy de Acuerdo",-0.66,IF(AF21="Levemente de Acuerdo",-0.33,IF(AF21="Levemente en Desacuerdo",0.33,IF(AF21="Muy en Desacuerdo",0.66,IF(AF21="Totalmente en Desacuerdo",1,"error")))))) -> -0.66 | AH21: Totalmente en Desacuerdo | AI21: =IF(AH21="Totalmente de Acuerdo",1,IF(AH21="Muy de Acuerdo",0.66,IF(AH21="Levemente de Acuerdo",0.33,IF(AH21="Levemente en Desacuerdo",-0.33,IF(AH21="Muy en Desacuerdo",-0.66,IF(AH21="Totalmente en Desacuerdo",-1,"error")))))) -> -1 | AJ21: Totalmente en Desacuerdo | AK21: =IF(AJ21="Totalmente de Acuerdo",1,IF(AJ21="Muy de Acuerdo",0.66,IF(AJ21="Levemente de Acuerdo",0.33,IF(AJ21="Levemente en Desacuerdo",-0.33,IF(AJ21="Muy en Desacuerdo",-0.66,IF(AJ21="Totalmente en Desacuerdo",-1,"error")))))) -> -1 | AL21: Muy de Acuerdo | AM21: =IF(AL21="Totalmente de Acuerdo",-1,IF(AL21="Muy de Acuerdo",-0.66,IF(AL21="Levemente de Acuerdo",-0.33,IF(AL21="Levemente en Desacuerdo",0.33,IF(AL21="Muy en Desacuerdo",0.66,IF(AL21="Totalmente en Desacuerdo",1,"error")))))) -> -0.66 | AN21: Levemente en Desacuerdo | AO21: =IF(AN21="Totalmente de Acuerdo",-1,IF(AN21="Muy de Acuerdo",-0.66,IF(AN21="Levemente de Acuerdo",-0.33,IF(AN21="Levemente en Desacuerdo",0.33,IF(AN21="Muy en Desacuerdo",0.66,IF(AN21="Totalmente en Desacuerdo",1,"error")))))) -> 0.33 | AP21: Levemente en Desacuerdo | AQ21: =IF(AP21="Totalmente de Acuerdo",-1,IF(AP21="Muy de Acuerdo",-0.66,IF(AP21="Levemente de Acuerdo",-0.33,IF(AP21="Levemente en Desacuerdo",0.33,IF(AP21="Muy en Desacuerdo",0.66,IF(AP21="Totalmente en Desacuerdo",1,"error")))))) -> 0.33 | AR21: Muy de Acuerdo | AS21: =IF(AR21="Totalmente de Acuerdo",1,IF(AR21="Muy de Acuerdo",0.66,IF(AR21="Levemente de Acuerdo",0.33,IF(AR21="Levemente en Desacuerdo",-0.33,IF(AR21="Muy en Desacuerdo",-0.66,IF(AR21="Totalmente en Desacuerdo",-1,"error")))))) -> 0.66 | AT21: Muy en Desacuerdo | AU21: =IF(AT21="Totalmente de Acuerdo",-1,IF(AT21="Muy de Acuerdo",-0.66,IF(AT21="Levemente de Acuerdo",-0.33,IF(AT21="Levemente en Desacuerdo",0.33,IF(AT21="Muy en Desacuerdo",0.66,IF(AT21="Totalmente en Desacuerdo",1,"error")))))) -> 0.66 | AV21: =AU21+AS21+AQ21+AO21+AM21+AK21+AI21+AG21+AE21 -> -1.67 | AW21: Muy de Acuerdo | AX21: Muy de Acuerdo | AY21: Levemente en Desacuerdo | AZ21: Levemente de Acuerdo | BA21: Totalmente en Desacuerdo | BB21: Totalmente en Desacuerdo | BC21: Totalmente en Desacuerdo | BD21: Muy en Desacuerdo | BE21: Muy de Acuerdo | BF21: Muy de Acuerdo | BG21: Totalmente de Acuerdo | BJ21: Me identifico | BU21: Me identifico | BV21: Me identifico | BX21: No vote | BY21: Patricia Bullrich (Juntos por el Cambio) | BZ21: Javier Milei (La Libertad Avanza)
A22: 45547.903 | B22: 00344474148 | C22: 1999 | D22: Tercer año | E22: Varón | F22: Terciario completo | G22: Terciario completo | H22: Clase Media Alta (C2): entre $1.350.001 mensuales y $2.850.000 mensuales | I22: Trabajo propio | J22: Otra localidad en la Provincia de Córdoba | K22: . | L22: Muy en Desacuerdo | M22: =IF(L22="Totalmente de Acuerdo",-1,IF(L22="Muy de Acuerdo",-0.66,IF(L22="Levemente de Acuerdo",-0.33,IF(L22="Levemente en Desacuerdo",0.33,IF(L22="Muy en Desacuerdo",0.66,IF(L22="Totalmente en Desacuerdo",1,"error")))))) -> 0.66 | N22: Levemente de Acuerdo | O22: =IF(N22="Totalmente de Acuerdo",1,IF(N22="Muy de Acuerdo",0.66,IF(N22="Levemente de Acuerdo",0.33,IF(N22="Levemente en Desacuerdo",-0.33,IF(N22="Muy en Desacuerdo",-0.66,IF(N22="Totalmente en Desacuerdo",-1,"error")))))) -> 0.33 | P22: Levemente en Desacuerdo | Q22: =IF(P22="Totalmente de Acuerdo",-1,IF(P22="Muy de Acuerdo",-0.66,IF(P22="Levemente de Acuerdo",-0.33,IF(P22="Levemente en Desacuerdo",0.33,IF(P22="Muy en Desacuerdo",0.66,IF(P22="Totalmente en Desacuerdo",1,"error")))))) -> 0.33 | R22: Muy de Acuerdo | S22: =IF(R22="Totalmente de Acuerdo",1,IF(R22="Muy de Acuerdo",0.66,IF(R22="Levemente de Acuerdo",0.33,IF(R22="Levemente en Desacuerdo",-0.33,IF(R22="Muy en Desacuerdo",-0.66,IF(R22="Totalmente en Desacuerdo",-1,"error")))))) -> 0.66 | T22: Levemente de Acuerdo | U22: =IF(T22="Totalmente de Acuerdo",-1,IF(T22="Muy de Acuerdo",-0.66,IF(T22="Levemente de Acuerdo",-0.33,IF(T22="Levemente en Desacuerdo",0.33,IF(T22="Muy en Desacuerdo",0.66,IF(T22="Totalmente en Desacuerdo",1,"error")))))) -> -0.33 | V22: Totalmente de Acuerdo | W22: =IF(V22="Totalmente de Acuerdo",1,IF(V22="Muy de Acuerdo",0.66,IF(V22="Levemente de Acuerdo",0.33,IF(V22="Levemente en Desacuerdo",-0.33,IF(V22="Muy en Desacuerdo",-0.66,IF(V22="Totalmente en Desacuerdo",-1,"error")))))) -> 1 | X22: Muy de Acuerdo | Y22: =IF(X22="Totalmente de Acuerdo",1,IF(X22="Muy de Acuerdo",0.66,IF(X22="Levemente de Acuerdo",0.33,IF(X22="Levemente en Desacuerdo",-0.33,IF(X22="Muy en Desacuerdo",-0.66,IF(X22="Totalmente en Desacuerdo",-1,"error")))))) -> 0.66 | Z22: Levemente en Acuerdo | AA22: =IF(Z22="Totalmente de Acuerdo",1,IF(Z22="Muy de Acuerdo",0.66,IF(Z22="Levemente en Acuerdo",0.33,IF(Z22="Levemente en Desacuerdo",-0.33,IF(Z22="Muy en Desacuerdo",-0.66,IF(Z22="Totalmente en Desacuerdo",-1,"error")))))) -> 0.33 | AB22: =+AA22+Y22+W22+U22+S22+Q22+O22+M22 -> 3.64 | AC22: =+AB22*AB$36 -> 4.095 | AD22: Totalmente en Desacuerdo | AE22: =IF(AD22="Totalmente de Acuerdo",1,IF(AD22="Muy de Acuerdo",0.66,IF(AD22="Levemente de Acuerdo",0.33,IF(AD22="Levemente en Desacuerdo",-0.33,IF(AD22="Muy en Desacuerdo",-0.66,IF(AD22="Totalmente en Desacuerdo",-1,"error")))))) -> -1 | AF22: Muy de Acuerdo | AG22: =IF(AF22="Totalmente de Acuerdo",-1,IF(AF22="Muy de Acuerdo",-0.66,IF(AF22="Levemente de Acuerdo",-0.33,IF(AF22="Levemente en Desacuerdo",0.33,IF(AF22="Muy en Desacuerdo",0.66,IF(AF22="Totalmente en Desacuerdo",1,"error")))))) -> -0.66 | AH22: Levemente de Acuerdo | AI22: =IF(AH22="Totalmente de Acuerdo",1,IF(AH22="Muy de Acuerdo",0.66,IF(AH22="Levemente de Acuerdo",0.33,IF(AH22="Levemente en Desacuerdo",-0.33,IF(AH22="Muy en Desacuerdo",-0.66,IF(AH22="Totalmente en Desacuerdo",-1,"error")))))) -> 0.33 | AJ22: Muy en Desacuerdo | AK22: =IF(AJ22="Totalmente de Acuerdo",1,IF(AJ22="Muy de Acuerdo",0.66,IF(AJ22="Levemente de Acuerdo",0.33,IF(AJ22="Levemente en Desacuerdo",-0.33,IF(AJ22="Muy en Desacuerdo",-0.66,IF(AJ22="Totalmente en Desacuerdo",-1,"error")))))) -> -0.66 | AL22: Levemente de Acuerdo | AM22: =IF(AL22="Totalmente de Acuerdo",-1,IF(AL22="Muy de Acuerdo",-0.66,IF(AL22="Levemente de Acuerdo",-0.33,IF(AL22="Levemente en Desacuerdo",0.33,IF(AL22="Muy en Desacuerdo",0.66,IF(AL22="Totalmente en Desacuerdo",1,"error")))))) -> -0.33 | AN22: Muy en Desacuerdo | AO22: =IF(AN22="Totalmente de Acuerdo",-1,IF(AN22="Muy de Acuerdo",-0.66,IF(AN22="Levemente de Acuerdo",-0.33,IF(AN22="Levemente en Desacuerdo",0.33,IF(AN22="Muy en Desacuerdo",0.66,IF(AN22="Totalmente en Desacuerdo",1,"error")))))) -> 0.66 | AP22: Levemente de Acuerdo | AQ22: =IF(AP22="Totalmente de Acuerdo",-1,IF(AP22="Muy de Acuerdo",-0.66,IF(AP22="Levemente de Acuerdo",-0.33,IF(AP22="Levemente en Desacuerdo",0.33,IF(AP22="Muy en Desacuerdo",0.66,IF(AP22="Totalmente en Desacuerdo",1,"error")))))) -> -0.33 | AR22: Totalmente de Acuerdo | AS22: =IF(AR22="Totalmente de Acuerdo",1,IF(AR22="Muy de Acuerdo",0.66,IF(AR22="Levemente de Acuerdo",0.33,IF(AR22="Levemente en Desacuerdo",-0.33,IF(AR22="Muy en Desacuerdo",-0.66,IF(AR22="Totalmente en Desacuerdo",-1,"error")))))) -> 1 | AT22: Totalmente en Desacuerdo | AU22: =IF(AT22="Totalmente de Acuerdo",-1,IF(AT22="Muy de Acuerdo",-0.66,IF(AT22="Levemente de Acuerdo",-0.33,IF(AT22="Levemente en Desacuerdo",0.33,IF(AT22="Muy en Desacuerdo",0.66,IF(AT22="Totalmente en Desacuerdo",1,"error")))))) -> 1 | AV22: =AU22+AS22+AQ22+AO22+AM22+AK22+AI22+AG22+AE22 -> 0.01 | AW22: Levemente de Acuerdo | AX22: Muy de Acuerdo | AY22: Levemente en Desacuerdo | AZ22: Totalmente en Desacuerdo | BA22: Totalmente en Desacuerdo | BB22: Totalmente de Acuerdo | BC22: Totalmente de Acuerdo | BD22: Totalmente de Acuerdo | BE22: Levemente en Desacuerdo | BF22: Muy en Desacuerdo | BG22: Muy en Desacuerdo | BH22: Me identifico | BX22: Javier Milei (La Libertad Avanza) | BY22: En blanco | BZ22: En blanco
A23: 45549.732 | B23: 005464198578260 | C23: 2002 | D23: Cuarto año | E23: Varón | F23: Universitario completo | G23: Universitario completo | H23: Clase Alta (ABC1): más de $2.850.000 mensuales | I23: Familia | J23: Ciudad de Córdoba | K23: . | L23: Totalmente en Desacuerdo | M23: =IF(L23="Totalmente de Acuerdo",-1,IF(L23="Muy de Acuerdo",-0.66,IF(L23="Levemente de Acuerdo",-0.33,IF(L23="Levemente en Desacuerdo",0.33,IF(L23="Muy en Desacuerdo",0.66,IF(L23="Totalmente en Desacuerdo",1,"error")))))) -> 1 | N23: Levemente de Acuerdo | O23: =IF(N23="Totalmente de Acuerdo",1,IF(N23="Muy de Acuerdo",0.66,IF(N23="Levemente de Acuerdo",0.33,IF(N23="Levemente en Desacuerdo",-0.33,IF(N23="Muy en Desacuerdo",-0.66,IF(N23="Totalmente en Desacuerdo",-1,"error")))))) -> 0.33 | P23: Muy de Acuerdo | Q23: =IF(P23="Totalmente de Acuerdo",-1,IF(P23="Muy de Acuerdo",-0.66,IF(P23="Levemente de Acuerdo",-0.33,IF(P23="Levemente en Desacuerdo",0.33,IF(P23="Muy en Desacuerdo",0.66,IF(P23="Totalmente en Desacuerdo",1,"error")))))) -> -0.66 | R23: Muy de Acuerdo | S23: =IF(R23="Totalmente de Acuerdo",1,IF(R23="Muy de Acuerdo",0.66,IF(R23="Levemente de Acuerdo",0.33,IF(R23="Levemente en Desacuerdo",-0.33,IF(R23="Muy en Desacuerdo",-0.66,IF(R23="Totalmente en Desacuerdo",-1,"error")))))) -> 0.66 | T23: Levemente en Desacuerdo | U23: =IF(T23="Totalmente de Acuerdo",-1,IF(T23="Muy de Acuerdo",-0.66,IF(T23="Levemente de Acuerdo",-0.33,IF(T23="Levemente en Desacuerdo",0.33,IF(T23="Muy en Desacuerdo",0.66,IF(T23="Totalmente en Desacuerdo",1,"error")))))) -> 0.33 | V23: Muy de Acuerdo | W23: =IF(V23="Totalmente de Acuerdo",1,IF(V23="Muy de Acuerdo",0.66,IF(V23="Levemente de Acuerdo",0.33,IF(V23="Levemente en Desacuerdo",-0.33,IF(V23="Muy en Desacuerdo",-0.66,IF(V23="Totalmente en Desacuerdo",-1,"error")))))) -> 0.66 | X23: Totalmente de Acuerdo | Y23: =IF(X23="Totalmente de Acuerdo",1,IF(X23="Muy de Acuerdo",0.66,IF(X23="Levemente de Acuerdo",0.33,IF(X23="Levemente en Desacuerdo",-0.33,IF(X23="Muy en Desacuerdo",-0.66,IF(X23="Totalmente en Desacuerdo",-1,"error")))))) -> 1 | Z23: Totalmente de Acuerdo | AA23: =IF(Z23="Totalmente de Acuerdo",1,IF(Z23="Muy de Acuerdo",0.66,IF(Z23="Levemente en Acuerdo",0.33,IF(Z23="Levemente en Desacuerdo",-0.33,IF(Z23="Muy en Desacuerdo",-0.66,IF(Z23="Totalmente en Desacuerdo",-1,"error")))))) -> 1 | AB23: =+AA23+Y23+W23+U23+S23+Q23+O23+M23 -> 4.32 | AC23: =+AB23*AB$36 -> 4.86 | AD23: Levemente en Desacuerdo | AE23: =IF(AD23="Totalmente de Acuerdo",1,IF(AD23="Muy de Acuerdo",0.66,IF(AD23="Levemente de Acuerdo",0.33,IF(AD23="Levemente en Desacuerdo",-0.33,IF(AD23="Muy en Desacuerdo",-0.66,IF(AD23="Totalmente en Desacuerdo",-1,"error")))))) -> -0.33 | AF23: Levemente en Desacuerdo | AG23: =IF(AF23="Totalmente de Acuerdo",-1,IF(AF23="Muy de Acuerdo",-0.66,IF(AF23="Levemente de Acuerdo",-0.33,IF(AF23="Levemente en Desacuerdo",0.33,IF(AF23="Muy en Desacuerdo",0.66,IF(AF23="Totalmente en Desacuerdo",1,"error")))))) -> 0.33 | AH23: Levemente en Desacuerdo | AI23: =IF(AH23="Totalmente de Acuerdo",1,IF(AH23="Muy de Acuerdo",0.66,IF(AH23="Levemente de Acuerdo",0.33,IF(AH23="Levemente en Desacuerdo",-0.33,IF(AH23="Muy en Desacuerdo",-0.66,IF(AH23="Totalmente en Desacuerdo",-1,"error")))))) -> -0.33 | AJ23: Levemente de Acuerdo | AK23: =IF(AJ23="Totalmente de Acuerdo",1,IF(AJ23="Muy de Acuerdo",0.66,IF(AJ23="Levemente de Acuerdo",0.33,IF(AJ23="Levemente en Desacuerdo",-0.33,IF(AJ23="Muy en Desacuerdo",-0.66,IF(AJ23="Totalmente en Desacuerdo",-1,"error")))))) -> 0.33 | AL23: Muy de Acuerdo | AM23: =IF(AL23="Totalmente de Acuerdo",-1,IF(AL23="Muy de Acuerdo",-0.66,IF(AL23="Levemente de Acuerdo",-0.33,IF(AL23="Levemente en Desacuerdo",0.33,IF(AL23="Muy en Desacuerdo",0.66,IF(AL23="Totalmente en Desacuerdo",1,"error")))))) -> -0.66 | AN23: Muy en Desacuerdo | AO23: =IF(AN23="Totalmente de Acuerdo",-1,IF(AN23="Muy de Acuerdo",-0.66,IF(AN23="Levemente de Acuerdo",-0.33,IF(AN23="Levemente en Desacuerdo",0.33,IF(AN23="Muy en Desacuerdo",0.66,IF(AN23="Totalmente en Desacuerdo",1,"error")))))) -> 0.66 | AP23: Totalmente de Acuerdo | AQ23: =IF(AP23="Totalmente de Acuerdo",-1,IF(AP23="Muy de Acuerdo",-0.66,IF(AP23="Levemente de Acuerdo",-0.33,IF(AP23="Levemente en Desacuerdo",0.33,IF(AP23="Muy en Desacuerdo",0.66,IF(AP23="Totalmente en Desacuerdo",1,"error")))))) -> -1 | AR23: Totalmente de Acuerdo | AS23: =IF(AR23="Totalmente de Acuerdo",1,IF(AR23="Muy de Acuerdo",0.66,IF(AR23="Levemente de Acuerdo",0.33,IF(AR23="Levemente en Desacuerdo",-0.33,IF(AR23="Muy en Desacuerdo",-0.66,IF(AR23="Totalmente en Desacuerdo",-1,"error")))))) -> 1 | AT23: Totalmente en Desacuerdo | AU23: =IF(AT23="Totalmente de Acuerdo",-1,IF(AT23="Muy de Acuerdo",-0.66,IF(AT23="Levemente de Acuerdo",-0.33,IF(AT23="Levemente en Desacuerdo",0.33,IF(AT23="Muy en Desacuerdo",0.66,IF(AT23="Totalmente en Desacuerdo",1,"error")))))) -> 1 | AV23: =AU23+AS23+AQ23+AO23+AM23+AK23+AI23+AG23+AE23 -> 1 | AW23: Levemente de Acuerdo | AX23: Muy de Acuerdo | AY23: Muy de Acuerdo | AZ23: Muy en Desacuerdo | BA23: Muy de Acuerdo | BB23: Totalmente en Desacuerdo | BC23: Totalmente en Desacuerdo | BD23: Muy en Desacuerdo | BE23: Muy de Acuerdo | BF23: Levemente de Acuerdo | BG23: Totalmente de Acuerdo | BH23: Me identifico | BO23: Me identifico | BX23: Patricia Bullrich (Juntos por el Cambio) | BY23: Patricia Bullrich (Juntos por el Cambio) | BZ23: Javier Milei (La Libertad Avanza)
A24: 45551.791 | B24: 00513759005 | C24: 2002 | D24: Cuarto año | E24: Varón | F24: Posgrado completo | G24: Posgrado completo | H24: Clase Media Alta (C2): entre $1.350.001 mensuales y $2.850.000 mensuales | I24: Familia | J24: Ciudad de Córdoba | K24: . | L24: Muy en Desacuerdo | M24: =IF(L24="Totalmente de Acuerdo",-1,IF(L24="Muy de Acuerdo",-0.66,IF(L24="Levemente de Acuerdo",-0.33,IF(L24="Levemente en Desacuerdo",0.33,IF(L24="Muy en Desacuerdo",0.66,IF(L24="Totalmente en Desacuerdo",1,"error")))))) -> 0.66 | N24: Levemente en Desacuerdo | O24: =IF(N24="Totalmente de Acuerdo",1,IF(N24="Muy de Acuerdo",0.66,IF(N24="Levemente de Acuerdo",0.33,IF(N24="Levemente en Desacuerdo",-0.33,IF(N24="Muy en Desacuerdo",-0.66,IF(N24="Totalmente en Desacuerdo",-1,"error")))))) -> -0.33 | P24: Totalmente de Acuerdo | Q24: =IF(P24="Totalmente de Acuerdo",-1,IF(P24="Muy de Acuerdo",-0.66,IF(P24="Levemente de Acuerdo",-0.33,IF(P24="Levemente en Desacuerdo",0.33,IF(P24="Muy en Desacuerdo",0.66,IF(P24="Totalmente en Desacuerdo",1,"error")))))) -> -1 | R24: Muy de Acuerdo | S24: =IF(R24="Totalmente de Acuerdo",1,IF(R24="Muy de Acuerdo",0.66,IF(R24="Levemente de Acuerdo",0.33,IF(R24="Levemente en Desacuerdo",-0.33,IF(R24="Muy en Desacuerdo",-0.66,IF(R24="Totalmente en Desacuerdo",-1,"error")))))) -> 0.66 | T24: Levemente de Acuerdo | U24: =IF(T24="Totalmente de Acuerdo",-1,IF(T24="Muy de Acuerdo",-0.66,IF(T24="Levemente de Acuerdo",-0.33,IF(T24="Levemente en Desacuerdo",0.33,IF(T24="Muy en Desacuerdo",0.66,IF(T24="Totalmente en Desacuerdo",1,"error")))))) -> -0.33 | V24: Levemente de Acuerdo | W24: =IF(V24="Totalmente de Acuerdo",1,IF(V24="Muy de Acuerdo",0.66,IF(V24="Levemente de Acuerdo",0.33,IF(V24="Levemente en Desacuerdo",-0.33,IF(V24="Muy en Desacuerdo",-0.66,IF(V24="Totalmente en Desacuerdo",-1,"error")))))) -> 0.33 | X24: Levemente en Desacuerdo | Y24: =IF(X24="Totalmente de Acuerdo",1,IF(X24="Muy de Acuerdo",0.66,IF(X24="Levemente de Acuerdo",0.33,IF(X24="Levemente en Desacuerdo",-0.33,IF(X24="Muy en Desacuerdo",-0.66,IF(X24="Totalmente en Desacuerdo",-1,"error")))))) -> -0.33 | Z24: Totalmente en Desacuerdo | AA24: =IF(Z24="Totalmente de Acuerdo",1,IF(Z24="Muy de Acuerdo",0.66,IF(Z24="Levemente en Acuerdo",0.33,IF(Z24="Levemente en Desacuerdo",-0.33,IF(Z24="Muy en Desacuerdo",-0.66,IF(Z24="Totalmente en Desacuerdo",-1,"error")))))) -> -1 | AB24: =+AA24+Y24+W24+U24+S24+Q24+O24+M24 -> -1.34 | AC24: =+AB24*AB$36 -> -1.5075 | AD24: Levemente de Acuerdo | AE24: =IF(AD24="Totalmente de Acuerdo",1,IF(AD24="Muy de Acuerdo",0.66,IF(AD24="Levemente de Acuerdo",0.33,IF(AD24="Levemente en Desacuerdo",-0.33,IF(AD24="Muy en Desacuerdo",-0.66,IF(AD24="Totalmente en Desacuerdo",-1,"error")))))) -> 0.33 | AF24: Muy de Acuerdo | AG24: =IF(AF24="Totalmente de Acuerdo",-1,IF(AF24="Muy de Acuerdo",-0.66,IF(AF24="Levemente de Acuerdo",-0.33,IF(AF24="Levemente en Desacuerdo",0.33,IF(AF24="Muy en Desacuerdo",0.66,IF(AF24="Totalmente en Desacuerdo",1,"error")))))) -> -0.66 | AH24: Muy de Acuerdo | AI24: =IF(AH24="Totalmente de Acuerdo",1,IF(AH24="Muy de Acuerdo",0.66,IF(AH24="Levemente de Acuerdo",0.33,IF(AH24="Levemente en Desacuerdo",-0.33,IF(AH24="Muy en Desacuerdo",-0.66,IF(AH24="Totalmente en Desacuerdo",-1,"error")))))) -> 0.66 | AJ24: Totalmente de Acuerdo | AK24: =IF(AJ24="Totalmente de Acuerdo",1,IF(AJ24="Muy de Acuerdo",0.66,IF(AJ24="Levemente de Acuerdo",0.33,IF(AJ24="Levemente en Desacuerdo",-0.33,IF(AJ24="Muy en Desacuerdo",-0.66,IF(AJ24="Totalmente en Desacuerdo",-1,"error")))))) -> 1 | AL24: Muy de Acuerdo | AM24: =IF(AL24="Totalmente de Acuerdo",-1,IF(AL24="Muy de Acuerdo",-0.66,IF(AL24="Levemente de Acuerdo",-0.33,IF(AL24="Levemente en Desacuerdo",0.33,IF(AL24="Muy en Desacuerdo",0.66,IF(AL24="Totalmente en Desacuerdo",1,"error")))))) -> -0.66 | AN24: Muy de Acuerdo | AO24: =IF(AN24="Totalmente de Acuerdo",-1,IF(AN24="Muy de Acuerdo",-0.66,IF(AN24="Levemente de Acuerdo",-0.33,IF(AN24="Levemente en Desacuerdo",0.33,IF(AN24="Muy en Desacuerdo",0.66,IF(AN24="Totalmente en Desacuerdo",1,"error")))))) -> -0.66 | AP24: Totalmente de Acuerdo | AQ24: =IF(AP24="Totalmente de Acuerdo",-1,IF(AP24="Muy de Acuerdo",-0.66,IF(AP24="Levemente de Acuerdo",-0.33,IF(AP24="Levemente en Desacuerdo",0.33,IF(AP24="Muy en Desacuerdo",0.66,IF(AP24="Totalmente en Desacuerdo",1,"error")))))) -> -1 | AR24: Muy de Acuerdo | AS24: =IF(AR24="Totalmente de Acuerdo",1,IF(AR24="Muy de Acuerdo",0.66,IF(AR24="Levemente de Acuerdo",0.33,IF(AR24="Levemente en Desacuerdo",-0.33,IF(AR24="Muy en Desacuerdo",-0.66,IF(AR24="Totalmente en Desacuerdo",-1,"error")))))) -> 0.66 | AT24: Muy en Desacuerdo | AU24: =IF(AT24="Totalmente de Acuerdo",-1,IF(AT24="Muy de Acuerdo",-0.66,IF(AT24="Levemente de Acuerdo",-0.33,IF(AT24="Levemente en Desacuerdo",0.33,IF(AT24="Muy en Desacuerdo",0.66,IF(AT24="Totalmente en Desacuerdo",1,"error")))))) -> 0.66 | AV24: =AU24+AS24+AQ24+AO24+AM24+AK24+AI24+AG24+AE24 -> 0.33 | AW24: Muy de Acuerdo | AX24: Muy de Acuerdo | AY24: Levemente de Acuerdo | AZ24: Levemente de Acuerdo | BA24: Muy en Desacuerdo | BB24: Levemente de Acuerdo | BC24: Levemente de Acuerdo | BD24: Levemente de Acuerdo | BE24: Muy en Desacuerdo | BF24: Muy de Acuerdo | BG24: Muy de Acuerdo | BL24: Me identifico | BX24: Javier Milei (La Libertad Avanza) | BY24: Patricia Bullrich (Juntos por el Cambio) | BZ24: Javier Milei (La Libertad Avanza)
A25: 45553.854 | B25: 00157138797 | C25: 1997 | D25: Quinto año | E25: Varón | F25: Universitario completo | G25: Universitario completo | H25: Clase Media Baja (C3): entre $850.001 mensuales y $1.350.000 mensuales | I25: Trabajo propio | J25: Ciudad de Córdoba | K25: . | L25: Levemente de Acuerdo | M25: =IF(L25="Totalmente de Acuerdo",-1,IF(L25="Muy de Acuerdo",-0.66,IF(L25="Levemente de Acuerdo",-0.33,IF(L25="Levemente en Desacuerdo",0.33,IF(L25="Muy en Desacuerdo",0.66,IF(L25="Totalmente en Desacuerdo",1,"error")))))) -> -0.33 | N25: Levemente en Desacuerdo | O25: =IF(N25="Totalmente de Acuerdo",1,IF(N25="Muy de Acuerdo",0.66,IF(N25="Levemente de Acuerdo",0.33,IF(N25="Levemente en Desacuerdo",-0.33,IF(N25="Muy en Desacuerdo",-0.66,IF(N25="Totalmente en Desacuerdo",-1,"error")))))) -> -0.33 | P25: Muy de Acuerdo | Q25: =IF(P25="Totalmente de Acuerdo",-1,IF(P25="Muy de Acuerdo",-0.66,IF(P25="Levemente de Acuerdo",-0.33,IF(P25="Levemente en Desacuerdo",0.33,IF(P25="Muy en Desacuerdo",0.66,IF(P25="Totalmente en Desacuerdo",1,"error")))))) -> -0.66 | R25: Muy de Acuerdo | S25: =IF(R25="Totalmente de Acuerdo",1,IF(R25="Muy de Acuerdo",0.66,IF(R25="Levemente de Acuerdo",0.33,IF(R25="Levemente en Desacuerdo",-0.33,IF(R25="Muy en Desacuerdo",-0.66,IF(R25="Totalmente en Desacuerdo",-1,"error")))))) -> 0.66 | T25: Levemente de Acuerdo | U25: =IF(T25="Totalmente de Acuerdo",-1,IF(T25="Muy de Acuerdo",-0.66,IF(T25="Levemente de Acuerdo",-0.33,IF(T25="Levemente en Desacuerdo",0.33,IF(T25="Muy en Desacuerdo",0.66,IF(T25="Totalmente en Desacuerdo",1,"error")))))) -> -0.33 | V25: Levemente en Desacuerdo | W25: =IF(V25="Totalmente de Acuerdo",1,IF(V25="Muy de Acuerdo",0.66,IF(V25="Levemente de Acuerdo",0.33,IF(V25="Levemente en Desacuerdo",-0.33,IF(V25="Muy en Desacuerdo",-0.66,IF(V25="Totalmente en Desacuerdo",-1,"error")))))) -> -0.33 | X25: Levemente en Desacuerdo | Y25: =IF(X25="Totalmente de Acuerdo",1,IF(X25="Muy de Acuerdo",0.66,IF(X25="Levemente de Acuerdo",0.33,IF(X25="Levemente en Desacuerdo",-0.33,IF(X25="Muy en Desacuerdo",-0.66,IF(X25="Totalmente en Desacuerdo",-1,"error")))))) -> -0.33 | Z25: Levemente en Desacuerdo | AA25: =IF(Z25="Totalmente de Acuerdo",1,IF(Z25="Muy de Acuerdo",0.66,IF(Z25="Levemente en Acuerdo",0.33,IF(Z25="Levemente en Desacuerdo",-0.33,IF(Z25="Muy en Desacuerdo",-0.66,IF(Z25="Totalmente en Desacuerdo",-1,"error")))))) -> -0.33 | AB25: =+AA25+Y25+W25+U25+S25+Q25+O25+M25 -> -1.98 | AC25: =+AB25*AB$36 -> -2.2275 | AD25: Muy de Acuerdo | AE25: =IF(AD25="Totalmente de Acuerdo",1,IF(AD25="Muy de Acuerdo",0.66,IF(AD25="Levemente de Acuerdo",0.33,IF(AD25="Levemente en Desacuerdo",-0.33,IF(AD25="Muy en Desacuerdo",-0.66,IF(AD25="Totalmente en Desacuerdo",-1,"error")))))) -> 0.66 | AF25: Levemente en Desacuerdo | AG25: =IF(AF25="Totalmente de Acuerdo",-1,IF(AF25="Muy de Acuerdo",-0.66,IF(AF25="Levemente de Acuerdo",-0.33,IF(AF25="Levemente en Desacuerdo",0.33,IF(AF25="Muy en Desacuerdo",0.66,IF(AF25="Totalmente en Desacuerdo",1,"error")))))) -> 0.33 | AH25: Totalmente en Desacuerdo | AI25: =IF(AH25="Totalmente de Acuerdo",1,IF(AH25="Muy de Acuerdo",0.66,IF(AH25="Levemente de Acuerdo",0.33,IF(AH25="Levemente en Desacuerdo",-0.33,IF(AH25="Muy en Desacuerdo",-0.66,IF(AH25="Totalmente en Desacuerdo",-1,"error")))))) -> -1 | AJ25: Totalmente en Desacuerdo | AK25: =IF(AJ25="Totalmente de Acuerdo",1,IF(AJ25="Muy de Acuerdo",0.66,IF(AJ25="Levemente de Acuerdo",0.33,IF(AJ25="Levemente en Desacuerdo",-0.33,IF(AJ25="Muy en Desacuerdo",-0.66,IF(AJ25="Totalmente en Desacuerdo",-1,"error")))))) -> -1 | AL25: Muy en Desacuerdo | AM25: =IF(AL25="Totalmente de Acuerdo",-1,IF(AL25="Muy de Acuerdo",-0.66,IF(AL25="Levemente de Acuerdo",-0.33,IF(AL25="Levemente en Desacuerdo",0.33,IF(AL25="Muy en Desacuerdo",0.66,IF(AL25="Totalmente en Desacuerdo",1,"error")))))) -> 0.66 | AN25: Levemente de Acuerdo | AO25: =IF(AN25="Totalmente de Acuerdo",-1,IF(AN25="Muy de Acuerdo",-0.66,IF(AN25="Levemente de Acuerdo",-0.33,IF(AN25="Levemente en Desacuerdo",0.33,IF(AN25="Muy en Desacuerdo",0.66,IF(AN25="Totalmente en Desacuerdo",1,"error")))))) -> -0.33 | AP25: Levemente en Desacuerdo | AQ25: =IF(AP25="Totalmente de Acuerdo",-1,IF(AP25="Muy de Acuerdo",-0.66,IF(AP25="Levemente de Acuerdo",-0.33,IF(AP25="Levemente en Desacuerdo",0.33,IF(AP25="Muy en Desacuerdo",0.66,IF(AP25="Totalmente en Desacuerdo",1,"error")))))) -> 0.33 | AR25: Levemente en Desacuerdo | AS25: =IF(AR25="Totalmente de Acuerdo",1,IF(AR25="Muy de Acuerdo",0.66,IF(AR25="Levemente de Acuerdo",0.33,IF(AR25="Levemente en Desacuerdo",-0.33,IF(AR25="Muy en Desacuerdo",-0.66,IF(AR25="Totalmente en Desacuerdo",-1,"error")))))) -> -0.33 | AT25: Totalmente en Desacuerdo | AU25: =IF(AT25="Totalmente de Acuerdo",-1,IF(AT25="Muy de Acuerdo",-0.66,IF(AT25="Levemente de Acuerdo",-0.33,IF(AT25="Levemente en Desacuerdo",0.33,IF(AT25="Muy en Desacuerdo",0.66,IF(AT25="Totalmente en Desacuerdo",1,"error")))))) -> 1 | AV25: =AU25+AS25+AQ25+AO25+AM25+AK25+AI25+AG25+AE25 -> 0.32 | AW25: Totalmente en Desacuerdo | AX25: Levemente de Acuerdo | AY25: Levemente de Acuerdo | AZ25: Levemente de Acuerdo | BA25: Totalmente de Acuerdo | BB25: Totalmente en Desacuerdo | BC25: Muy en Desacuerdo | BD25: Levemente en Desacuerdo | BE25: Totalmente en Desacuerdo | BF25: Levemente de Acuerdo | BG25: Totalmente de Acuerdo | BM25: Me identifico | BP25: Me identifico | BX25: Sergio Massa (Unión por la Patria) | BY25: Sergio Massa (Unión por la Patria) | BZ25: Sergio Massa (Unión por la Patria)
A26: 45553.863 | B26: 006400545666038 | C26: 2001 | D26: Cuarto año | E26: Mujer | F26: Posgrado completo | G26: Posgrado completo | H26: Clase Alta (ABC1): más de $2.850.000 mensuales | I26: Familia | J26: Otra localidad en otra Provincia | K26: . | L26: Totalmente de Acuerdo | M26: =IF(L26="Totalmente de Acuerdo",-1,IF(L26="Muy de Acuerdo",-0.66,IF(L26="Levemente de Acuerdo",-0.33,IF(L26="Levemente en Desacuerdo",0.33,IF(L26="Muy en Desacuerdo",0.66,IF(L26="Totalmente en Desacuerdo",1,"error")))))) -> -1 | N26: Muy en Desacuerdo | O26: =IF(N26="Totalmente de Acuerdo",1,IF(N26="Muy de Acuerdo",0.66,IF(N26="Levemente de Acuerdo",0.33,IF(N26="Levemente en Desacuerdo",-0.33,IF(N26="Muy en Desacuerdo",-0.66,IF(N26="Totalmente en Desacuerdo",-1,"error")))))) -> -0.66 | P26: Totalmente en Desacuerdo | Q26: =IF(P26="Totalmente de Acuerdo",-1,IF(P26="Muy de Acuerdo",-0.66,IF(P26="Levemente de Acuerdo",-0.33,IF(P26="Levemente en Desacuerdo",0.33,IF(P26="Muy en Desacuerdo",0.66,IF(P26="Totalmente en Desacuerdo",1,"error")))))) -> 1 | R26: Muy de Acuerdo | S26: =IF(R26="Totalmente de Acuerdo",1,IF(R26="Muy de Acuerdo",0.66,IF(R26="Levemente de Acuerdo",0.33,IF(R26="Levemente en Desacuerdo",-0.33,IF(R26="Muy en Desacuerdo",-0.66,IF(R26="Totalmente en Desacuerdo",-1,"error")))))) -> 0.66 | T26: Levemente de Acuerdo | U26: =IF(T26="Totalmente de Acuerdo",-1,IF(T26="Muy de Acuerdo",-0.66,IF(T26="Levemente de Acuerdo",-0.33,IF(T26="Levemente en Desacuerdo",0.33,IF(T26="Muy en Desacuerdo",0.66,IF(T26="Totalmente en Desacuerdo",1,"error")))))) -> -0.33 | V26: Levemente de Acuerdo | W26: =IF(V26="Totalmente de Acuerdo",1,IF(V26="Muy de Acuerdo",0.66,IF(V26="Levemente de Acuerdo",0.33,IF(V26="Levemente en Desacuerdo",-0.33,IF(V26="Muy en Desacuerdo",-0.66,IF(V26="Totalmente en Desacuerdo",-1,"error")))))) -> 0.33 | X26: Totalmente de Acuerdo | Y26: =IF(X26="Totalmente de Acuerdo",1,IF(X26="Muy de Acuerdo",0.66,IF(X26="Levemente de Acuerdo",0.33,IF(X26="Levemente en Desacuerdo",-0.33,IF(X26="Muy en Desacuerdo",-0.66,IF(X26="Totalmente en Desacuerdo",-1,"error")))))) -> 1 | Z26: Muy en Desacuerdo | AA26: =IF(Z26="Totalmente de Acuerdo",1,IF(Z26="Muy de Acuerdo",0.66,IF(Z26="Levemente en Acuerdo",0.33,IF(Z26="Levemente en Desacuerdo",-0.33,IF(Z26="Muy en Desacuerdo",-0.66,IF(Z26="Totalmente en Desacuerdo",-1,"error")))))) -> -0.66 | AB26: =+AA26+Y26+W26+U26+S26+Q26+O26+M26 -> 0.34 | AC26: =+AB26*AB$36 -> 0.3825 | AD26: Totalmente en Desacuerdo | AE26: =IF(AD26="Totalmente de Acuerdo",1,IF(AD26="Muy de Acuerdo",0.66,IF(AD26="Levemente de Acuerdo",0.33,IF(AD26="Levemente en Desacuerdo",-0.33,IF(AD26="Muy en Desacuerdo",-0.66,IF(AD26="Totalmente en Desacuerdo",-1,"error")))))) -> -1 | AF26: Totalmente de Acuerdo | AG26: =IF(AF26="Totalmente de Acuerdo",-1,IF(AF26="Muy de Acuerdo",-0.66,IF(AF26="Levemente de Acuerdo",-0.33,IF(AF26="Levemente en Desacuerdo",0.33,IF(AF26="Muy en Desacuerdo",0.66,IF(AF26="Totalmente en Desacuerdo",1,"error")))))) -> -1 | AH26: Levemente de Acuerdo | AI26: =IF(AH26="Totalmente de Acuerdo",1,IF(AH26="Muy de Acuerdo",0.66,IF(AH26="Levemente de Acuerdo",0.33,IF(AH26="Levemente en Desacuerdo",-0.33,IF(AH26="Muy en Desacuerdo",-0.66,IF(AH26="Totalmente en Desacuerdo",-1,"error")))))) -> 0.33 | AJ26: Totalmente en Desacuerdo | AK26: =IF(AJ26="Totalmente de Acuerdo",1,IF(AJ26="Muy de Acuerdo",0.66,IF(AJ26="Levemente de Acuerdo",0.33,IF(AJ26="Levemente en Desacuerdo",-0.33,IF(AJ26="Muy en Desacuerdo",-0.66,IF(AJ26="Totalmente en Desacuerdo",-1,"error")))))) -> -1 | AL26: Muy de Acuerdo | AM26: =IF(AL26="Totalmente de Acuerdo",-1,IF(AL26="Muy de Acuerdo",-0.66,IF(AL26="Levemente de Acuerdo",-0.33,IF(AL26="Levemente en Desacuerdo",0.33,IF(AL26="Muy en Desacuerdo",0.66,IF(AL26="Totalmente en Desacuerdo",1,"error")))))) -> -0.66 | AN26: Totalmente en Desacuerdo | AO26: =IF(AN26="Totalmente de Acuerdo",-1,IF(AN26="Muy de Acuerdo",-0.66,IF(AN26="Levemente de Acuerdo",-0.33,IF(AN26="Levemente en Desacuerdo",0.33,IF(AN26="Muy en Desacuerdo",0.66,IF(AN26="Totalmente en Desacuerdo",1,"error")))))) -> 1 | AP26: Levemente de Acuerdo | AQ26: =IF(AP26="Totalmente de Acuerdo",-1,IF(AP26="Muy de Acuerdo",-0.66,IF(AP26="Levemente de Acuerdo",-0.33,IF(AP26="Levemente en Desacuerdo",0.33,IF(AP26="Muy en Desacuerdo",0.66,IF(AP26="Totalmente en Desacuerdo",1,"error")))))) -> -0.33 | AR26: Totalmente de Acuerdo | AS26: =IF(AR26="Totalmente de Acuerdo",1,IF(AR26="Muy de Acuerdo",0.66,IF(AR26="Levemente de Acuerdo",0.33,IF(AR26="Levemente en Desacuerdo",-0.33,IF(AR26="Muy en Desacuerdo",-0.66,IF(AR26="Totalmente en Desacuerdo",-1,"error")))))) -> 1 | AT26: Totalmente en Desacuerdo | AU26: =IF(AT26="Totalmente de Acuerdo",-1,IF(AT26="Muy de Acuerdo",-0.66,IF(AT26="Levemente de Acuerdo",-0.33,IF(AT26="Levemente en Desacuerdo",0.33,IF(AT26="Muy en Desacuerdo",0.66,IF(AT26="Totalmente en Desacuerdo",1,"error")))))) -> 1 | AV26: =AU26+AS26+AQ26+AO26+AM26+AK26+AI26+AG26+AE26 -> -0.66 | AW26: Levemente de Acuerdo | AX26: Levemente de Acuerdo | AY26: Levemente en Desacuerdo | AZ26: Levemente de Acuerdo | BA26: Muy en Desacuerdo | BB26: Totalmente en Desacuerdo | BC26: Totalmente en Desacuerdo | BD26: Totalmente en Desacuerdo | BE26: Totalmente de Acuerdo | BF26: Muy de Acuerdo | BG26: Levemente en Desacuerdo | BH26: Me identifico | BR26: Me identifico | BX26: Javier Milei (La Libertad Avanza) | BY26: Javier Milei (La Libertad Avanza) | BZ26: Javier Milei (La Libertad Avanza)
A27: 45553.88 | B27: 003420609968086 | C27: 2000 | D27: Quinto año | E27: Varón | F27: Secundario completo | G27: Terciario completo | H27: Clase Media Baja (C3): entre $850.001 mensuales y $1.350.000 mensuales | I27: Beca|Pasantia|Familia | J27: Otra localidad en la Provincia de Córdoba | K27: . | L27: Muy de Acuerdo | M27: =IF(L27="Totalmente de Acuerdo",-1,IF(L27="Muy de Acuerdo",-0.66,IF(L27="Levemente de Acuerdo",-0.33,IF(L27="Levemente en Desacuerdo",0.33,IF(L27="Muy en Desacuerdo",0.66,IF(L27="Totalmente en Desacuerdo",1,"error")))))) -> -0.66 | N27: Levemente en Desacuerdo | O27: =IF(N27="Totalmente de Acuerdo",1,IF(N27="Muy de Acuerdo",0.66,IF(N27="Levemente de Acuerdo",0.33,IF(N27="Levemente en Desacuerdo",-0.33,IF(N27="Muy en Desacuerdo",-0.66,IF(N27="Totalmente en Desacuerdo",-1,"error")))))) -> -0.33 | P27: Muy de Acuerdo | Q27: =IF(P27="Totalmente de Acuerdo",-1,IF(P27="Muy de Acuerdo",-0.66,IF(P27="Levemente de Acuerdo",-0.33,IF(P27="Levemente en Desacuerdo",0.33,IF(P27="Muy en Desacuerdo",0.66,IF(P27="Totalmente en Desacuerdo",1,"error")))))) -> -0.66 | R27: Levemente de Acuerdo | S27: =IF(R27="Totalmente de Acuerdo",1,IF(R27="Muy de Acuerdo",0.66,IF(R27="Levemente de Acuerdo",0.33,IF(R27="Levemente en Desacuerdo",-0.33,IF(R27="Muy en Desacuerdo",-0.66,IF(R27="Totalmente en Desacuerdo",-1,"error")))))) -> 0.33 | T27: Muy de Acuerdo | U27: =IF(T27="Totalmente de Acuerdo",-1,IF(T27="Muy de Acuerdo",-0.66,IF(T27="Levemente de Acuerdo",-0.33,IF(T27="Levemente en Desacuerdo",0.33,IF(T27="Muy en Desacuerdo",0.66,IF(T27="Totalmente en Desacuerdo",1,"error")))))) -> -0.66 | V27: Muy de Acuerdo | W27: =IF(V27="Totalmente de Acuerdo",1,IF(V27="Muy de Acuerdo",0.66,IF(V27="Levemente de Acuerdo",0.33,IF(V27="Levemente en Desacuerdo",-0.33,IF(V27="Muy en Desacuerdo",-0.66,IF(V27="Totalmente en Desacuerdo",-1,"error")))))) -> 0.66 | X27: Levemente en Desacuerdo | Y27: =IF(X27="Totalmente de Acuerdo",1,IF(X27="Muy de Acuerdo",0.66,IF(X27="Levemente de Acuerdo",0.33,IF(X27="Levemente en Desacuerdo",-0.33,IF(X27="Muy en Desacuerdo",-0.66,IF(X27="Totalmente en Desacuerdo",-1,"error")))))) -> -0.33 | Z27: Muy en Desacuerdo | AA27: =IF(Z27="Totalmente de Acuerdo",1,IF(Z27="Muy de Acuerdo",0.66,IF(Z27="Levemente en Acuerdo",0.33,IF(Z27="Levemente en Desacuerdo",-0.33,IF(Z27="Muy en Desacuerdo",-0.66,IF(Z27="Totalmente en Desacuerdo",-1,"error")))))) -> -0.66 | AB27: =+AA27+Y27+W27+U27+S27+Q27+O27+M27 -> -2.31 | AC27: =+AB27*AB$36 -> -2.59875 | AD27: Levemente en Desacuerdo | AE27: =IF(AD27="Totalmente de Acuerdo",1,IF(AD27="Muy de Acuerdo",0.66,IF(AD27="Levemente de Acuerdo",0.33,IF(AD27="Levemente en Desacuerdo",-0.33,IF(AD27="Muy en Desacuerdo",-0.66,IF(AD27="Totalmente en Desacuerdo",-1,"error")))))) -> -0.33 | AF27: Muy de Acuerdo | AG27: =IF(AF27="Totalmente de Acuerdo",-1,IF(AF27="Muy de Acuerdo",-0.66,IF(AF27="Levemente de Acuerdo",-0.33,IF(AF27="Levemente en Desacuerdo",0.33,IF(AF27="Muy en Desacuerdo",0.66,IF(AF27="Totalmente en Desacuerdo",1,"error")))))) -> -0.66 | AH27: Muy en Desacuerdo | AI27: =IF(AH27="Totalmente de Acuerdo",1,IF(AH27="Muy de Acuerdo",0.66,IF(AH27="Levemente de Acuerdo",0.33,IF(AH27="Levemente en Desacuerdo",-0.33,IF(AH27="Muy en Desacuerdo",-0.66,IF(AH27="Totalmente en Desacuerdo",-1,"error")))))) -> -0.66 | AJ27: Muy en Desacuerdo | AK27: =IF(AJ27="Totalmente de Acuerdo",1,IF(AJ27="Muy de Acuerdo",0.66,IF(AJ27="Levemente de Acuerdo",0.33,IF(AJ27="Levemente en Desacuerdo",-0.33,IF(AJ27="Muy en Desacuerdo",-0.66,IF(AJ27="Totalmente en Desacuerdo",-1,"error")))))) -> -0.66 | AL27: Totalmente de Acuerdo | AM27: =IF(AL27="Totalmente de Acuerdo",-1,IF(AL27="Muy de Acuerdo",-0.66,IF(AL27="Levemente de Acuerdo",-0.33,IF(AL27="Levemente en Desacuerdo",0.33,IF(AL27="Muy en Desacuerdo",0.66,IF(AL27="Totalmente en Desacuerdo",1,"error")))))) -> -1 | AN27: Muy en Desacuerdo | AO27: =IF(AN27="Totalmente de Acuerdo",-1,IF(AN27="Muy de Acuerdo",-0.66,IF(AN27="Levemente de Acuerdo",-0.33,IF(AN27="Levemente en Desacuerdo",0.33,IF(AN27="Muy en Desacuerdo",0.66,IF(AN27="Totalmente en Desacuerdo",1,"error")))))) -> 0.66 | AP27: Muy de Acuerdo | AQ27: =IF(AP27="Totalmente de Acuerdo",-1,IF(AP27="Muy de Acuerdo",-0.66,IF(AP27="Levemente de Acuerdo",-0.33,IF(AP27="Levemente en Desacuerdo",0.33,IF(AP27="Muy en Desacuerdo",0.66,IF(AP27="Totalmente en Desacuerdo",1,"error")))))) -> -0.66 | AR27: Muy de Acuerdo | AS27: =IF(AR27="Totalmente de Acuerdo",1,IF(AR27="Muy de Acuerdo",0.66,IF(AR27="Levemente de Acuerdo",0.33,IF(AR27="Levemente en Desacuerdo",-0.33,IF(AR27="Muy en Desacuerdo",-0.66,IF(AR27="Totalmente en Desacuerdo",-1,"error")))))) -> 0.66 | AT27: Muy en Desacuerdo | AU27: =IF(AT27="Totalmente de Acuerdo",-1,IF(AT27="Muy de Acuerdo",-0.66,IF(AT27="Levemente de Acuerdo",-0.33,IF(AT27="Levemente en Desacuerdo",0.33,IF(AT27="Muy en Desacuerdo",0.66,IF(AT27="Totalmente en Desacuerdo",1,"error")))))) -> 0.66 | AV27: =AU27+AS27+AQ27+AO27+AM27+AK27+AI27+AG27+AE27 -> -1.99 | AW27: Muy de Acuerdo | AX27: Muy de Acuerdo | AY27: Muy en Desacuerdo | AZ27: Levemente en Desacuerdo | BA27: Levemente en Desacuerdo | BB27: Levemente en Desacuerdo | BC27: Levemente en Desacuerdo | BD27: Levemente en Desacuerdo | BE27: Muy de Acuerdo | BF27: Muy de Acuerdo | BG27: Muy de Acuerdo | BH27: Me identifico | BI27: Me identifico | BJ27: Me identifico | BK27: Me identifico | BL27: Me identifico | BM27: Me identifico | BN27: Me identifico | BO27: Me identifico | BP27: Me identifico | BQ27: Me identifico | BR27: Me identifico | BS27: Me identifico | BT27: Me identifico | BU27: Me identifico | BV27: Me identifico | BW27: Me identifico | BX27: No asistí | BY27: En blanco | BZ27: En blanco
A28: 45554.363 | B28: 00506717796 | C28: 2001 | D28: Cuarto año | E28: Mujer | F28: Universitario completo | G28: Universitario completo | H28: Clase Alta (ABC1): más de $2.850.000 mensuales | I28: Familia | J28: Ciudad de Córdoba | K28: . | L28: Levemente en Desacuerdo | M28: =IF(L28="Totalmente de Acuerdo",-1,IF(L28="Muy de Acuerdo",-0.66,IF(L28="Levemente de Acuerdo",-0.33,IF(L28="Levemente en Desacuerdo",0.33,IF(L28="Muy en Desacuerdo",0.66,IF(L28="Totalmente en Desacuerdo",1,"error")))))) -> 0.33 | N28: Levemente de Acuerdo | O28: =IF(N28="Totalmente de Acuerdo",1,IF(N28="Muy de Acuerdo",0.66,IF(N28="Levemente de Acuerdo",0.33,IF(N28="Levemente en Desacuerdo",-0.33,IF(N28="Muy en Desacuerdo",-0.66,IF(N28="Totalmente en Desacuerdo",-1,"error")))))) -> 0.33 | P28: Muy de Acuerdo | Q28: =IF(P28="Totalmente de Acuerdo",-1,IF(P28="Muy de Acuerdo",-0.66,IF(P28="Levemente de Acuerdo",-0.33,IF(P28="Levemente en Desacuerdo",0.33,IF(P28="Muy en Desacuerdo",0.66,IF(P28="Totalmente en Desacuerdo",1,"error")))))) -> -0.66 | R28: Levemente de Acuerdo | S28: =IF(R28="Totalmente de Acuerdo",1,IF(R28="Muy de Acuerdo",0.66,IF(R28="Levemente de Acuerdo",0.33,IF(R28="Levemente en Desacuerdo",-0.33,IF(R28="Muy en Desacuerdo",-0.66,IF(R28="Totalmente en Desacuerdo",-1,"error")))))) -> 0.33 | T28: Levemente en Desacuerdo | U28: =IF(T28="Totalmente de Acuerdo",-1,IF(T28="Muy de Acuerdo",-0.66,IF(T28="Levemente de Acuerdo",-0.33,IF(T28="Levemente en Desacuerdo",0.33,IF(T28="Muy en Desacuerdo",0.66,IF(T28="Totalmente en Desacuerdo",1,"error")))))) -> 0.33 | V28: Levemente en Desacuerdo | W28: =IF(V28="Totalmente de Acuerdo",1,IF(V28="Muy de Acuerdo",0.66,IF(V28="Levemente de Acuerdo",0.33,IF(V28="Levemente en Desacuerdo",-0.33,IF(V28="Muy en Desacuerdo",-0.66,IF(V28="Totalmente en Desacuerdo",-1,"error")))))) -> -0.33 | X28: Muy de Acuerdo | Y28: =IF(X28="Totalmente de Acuerdo",1,IF(X28="Muy de Acuerdo",0.66,IF(X28="Levemente de Acuerdo",0.33,IF(X28="Levemente en Desacuerdo",-0.33,IF(X28="Muy en Desacuerdo",-0.66,IF(X28="Totalmente en Desacuerdo",-1,"error")))))) -> 0.66 | Z28: Muy en Desacuerdo | AA28: =IF(Z28="Totalmente de Acuerdo",1,IF(Z28="Muy de Acuerdo",0.66,IF(Z28="Levemente en Acuerdo",0.33,IF(Z28="Levemente en Desacuerdo",-0.33,IF(Z28="Muy en Desacuerdo",-0.66,IF(Z28="Totalmente en Desacuerdo",-1,"error")))))) -> -0.66 | AB28: =+AA28+Y28+W28+U28+S28+Q28+O28+M28 -> 0.33 | AC28: =+AB28*AB$36 -> 0.37125 | AD28: Levemente en Desacuerdo | AE28: =IF(AD28="Totalmente de Acuerdo",1,IF(AD28="Muy de Acuerdo",0.66,IF(AD28="Levemente de Acuerdo",0.33,IF(AD28="Levemente en Desacuerdo",-0.33,IF(AD28="Muy en Desacuerdo",-0.66,IF(AD28="Totalmente en Desacuerdo",-1,"error")))))) -> -0.33 | AF28: Muy de Acuerdo | AG28: =IF(AF28="Totalmente de Acuerdo",-1,IF(AF28="Muy de Acuerdo",-0.66,IF(AF28="Levemente de Acuerdo",-0.33,IF(AF28="Levemente en Desacuerdo",0.33,IF(AF28="Muy en Desacuerdo",0.66,IF(AF28="Totalmente en Desacuerdo",1,"error")))))) -> -0.66 | AH28: Muy en Desacuerdo | AI28: =IF(AH28="Totalmente de Acuerdo",1,IF(AH28="Muy de Acuerdo",0.66,IF(AH28="Levemente de Acuerdo",0.33,IF(AH28="Levemente en Desacuerdo",-0.33,IF(AH28="Muy en Desacuerdo",-0.66,IF(AH28="Totalmente en Desacuerdo",-1,"error")))))) -> -0.66 | AJ28: Totalmente en Desacuerdo | AK28: =IF(AJ28="Totalmente de Acuerdo",1,IF(AJ28="Muy de Acuerdo",0.66,IF(AJ28="Levemente de Acuerdo",0.33,IF(AJ28="Levemente en Desacuerdo",-0.33,IF(AJ28="Muy en Desacuerdo",-0.66,IF(AJ28="Totalmente en Desacuerdo",-1,"error")))))) -> -1 | AL28: Levemente de Acuerdo | AM28: =IF(AL28="Totalmente de Acuerdo",-1,IF(AL28="Muy de Acuerdo",-0.66,IF(AL28="Levemente de Acuerdo",-0.33,IF(AL28="Levemente en Desacuerdo",0.33,IF(AL28="Muy en Desacuerdo",0.66,IF(AL28="Totalmente en Desacuerdo",1,"error")))))) -> -0.33 | AN28: Muy en Desacuerdo | AO28: =IF(AN28="Totalmente de Acuerdo",-1,IF(AN28="Muy de Acuerdo",-0.66,IF(AN28="Levemente de Acuerdo",-0.33,IF(AN28="Levemente en Desacuerdo",0.33,IF(AN28="Muy en Desacuerdo",0.66,IF(AN28="Totalmente en Desacuerdo",1,"error")))))) -> 0.66 | AP28: Levemente de Acuerdo | AQ28: =IF(AP28="Totalmente de Acuerdo",-1,IF(AP28="Muy de Acuerdo",-0.66,IF(AP28="Levemente de Acuerdo",-0.33,IF(AP28="Levemente en Desacuerdo",0.33,IF(AP28="Muy en Desacuerdo",0.66,IF(AP28="Totalmente en Desacuerdo",1,"error")))))) -> -0.33 | AR28: Muy de Acuerdo | AS28: =IF(AR28="Totalmente de Acuerdo",1,IF(AR28="Muy de Acuerdo",0.66,IF(AR28="Levemente de Acuerdo",0.33,IF(AR28="Levemente en Desacuerdo",-0.33,IF(AR28="Muy en Desacuerdo",-0.66,IF(AR28="Totalmente en Desacuerdo",-1,"error")))))) -> 0.66 | AT28: Totalmente en Desacuerdo | AU28: =IF(AT28="Totalmente de Acuerdo",-1,IF(AT28="Muy de Acuerdo",-0.66,IF(AT28="Levemente de Acuerdo",-0.33,IF(AT28="Levemente en Desacuerdo",0.33,IF(AT28="Muy en Desacuerdo",0.66,IF(AT28="Totalmente en Desacuerdo",1,"error")))))) -> 1 | AV28: =AU28+AS28+AQ28+AO28+AM28+AK28+AI28+AG28+AE28 -> -0.99 | AW28: Muy de Acuerdo | AX28: Levemente de Acuerdo | AY28: Totalmente en Desacuerdo | AZ28: Muy en Desacuerdo | BA28: Totalmente en Desacuerdo | BB28: Levemente de Acuerdo | BC28: Levemente en Desacuerdo | BD28: Muy de Acuerdo | BE28: Totalmente de Acuerdo | BF28: Levemente en Desacuerdo | BG28: Levemente en Desacuerdo | BH28: Me identifico | BL28: Me identifico | BM28: Me identifico | BO28: Me identifico | BR28: Me identifico | BX28: Patricia Bullrich (Juntos por el Cambio) | BY28: Javier Milei (La Libertad Avanza) | BZ28: Javier Milei (La Libertad Avanza)
A29: 45554.668 | B29: 00516733809 | C29: 2002 | D29: Cuarto año | E29: Mujer | F29: Universitario incompleto | G29: Universitario incompleto | H29: Clase Media Alta (C2): entre $1.350.001 mensuales y $2.850.000 mensuales | I29: Familia | J29: Otra localidad en la Provincia de Córdoba | K29: . | L29: Muy en Desacuerdo | M29: =IF(L29="Totalmente de Acuerdo",-1,IF(L29="Muy de Acuerdo",-0.66,IF(L29="Levemente de Acuerdo",-0.33,IF(L29="Levemente en Desacuerdo",0.33,IF(L29="Muy en Desacuerdo",0.66,IF(L29="Totalmente en Desacuerdo",1,"error")))))) -> 0.66 | N29: Totalmente de Acuerdo | O29: =IF(N29="Totalmente de Acuerdo",1,IF(N29="Muy de Acuerdo",0.66,IF(N29="Levemente de Acuerdo",0.33,IF(N29="Levemente en Desacuerdo",-0.33,IF(N29="Muy en Desacuerdo",-0.66,IF(N29="Totalmente en Desacuerdo",-1,"error")))))) -> 1 | P29: Totalmente en Desacuerdo | Q29: =IF(P29="Totalmente de Acuerdo",-1,IF(P29="Muy de Acuerdo",-0.66,IF(P29="Levemente de Acuerdo",-0.33,IF(P29="Levemente en Desacuerdo",0.33,IF(P29="Muy en Desacuerdo",0.66,IF(P29="Totalmente en Desacuerdo",1,"error")))))) -> 1 | R29: Muy de Acuerdo | S29: =IF(R29="Totalmente de Acuerdo",1,IF(R29="Muy de Acuerdo",0.66,IF(R29="Levemente de Acuerdo",0.33,IF(R29="Levemente en Desacuerdo",-0.33,IF(R29="Muy en Desacuerdo",-0.66,IF(R29="Totalmente en Desacuerdo",-1,"error")))))) -> 0.66 | T29: Muy en Desacuerdo | U29: =IF(T29="Totalmente de Acuerdo",-1,IF(T29="Muy de Acuerdo",-0.66,IF(T29="Levemente de Acuerdo",-0.33,IF(T29="Levemente en Desacuerdo",0.33,IF(T29="Muy en Desacuerdo",0.66,IF(T29="Totalmente en Desacuerdo",1,"error")))))) -> 0.66 | V29: Muy en Desacuerdo | W29: =IF(V29="Totalmente de Acuerdo",1,IF(V29="Muy de Acuerdo",0.66,IF(V29="Levemente de Acuerdo",0.33,IF(V29="Levemente en Desacuerdo",-0.33,IF(V29="Muy en Desacuerdo",-0.66,IF(V29="Totalmente en Desacuerdo",-1,"error")))))) -> -0.66 | X29: Muy de Acuerdo | Y29: =IF(X29="Totalmente de Acuerdo",1,IF(X29="Muy de Acuerdo",0.66,IF(X29="Levemente de Acuerdo",0.33,IF(X29="Levemente en Desacuerdo",-0.33,IF(X29="Muy en Desacuerdo",-0.66,IF(X29="Totalmente en Desacuerdo",-1,"error")))))) -> 0.66 | Z29: Muy en Desacuerdo | AA29: =IF(Z29="Totalmente de Acuerdo",1,IF(Z29="Muy de Acuerdo",0.66,IF(Z29="Levemente en Acuerdo",0.33,IF(Z29="Levemente en Desacuerdo",-0.33,IF(Z29="Muy en Desacuerdo",-0.66,IF(Z29="Totalmente en Desacuerdo",-1,"error")))))) -> -0.66 | AB29: =+AA29+Y29+W29+U29+S29+Q29+O29+M29 -> 3.32 | AC29: =+AB29*AB$36 -> 3.735 | AD29: Muy en Desacuerdo | AE29: =IF(AD29="Totalmente de Acuerdo",1,IF(AD29="Muy de Acuerdo",0.66,IF(AD29="Levemente de Acuerdo",0.33,IF(AD29="Levemente en Desacuerdo",-0.33,IF(AD29="Muy en Desacuerdo",-0.66,IF(AD29="Totalmente en Desacuerdo",-1,"error")))))) -> -0.66 | AF29: Totalmente de Acuerdo | AG29: =IF(AF29="Totalmente de Acuerdo",-1,IF(AF29="Muy de Acuerdo",-0.66,IF(AF29="Levemente de Acuerdo",-0.33,IF(AF29="Levemente en Desacuerdo",0.33,IF(AF29="Muy en Desacuerdo",0.66,IF(AF29="Totalmente en Desacuerdo",1,"error")))))) -> -1 | AH29: Levemente de Acuerdo | AI29: =IF(AH29="Totalmente de Acuerdo",1,IF(AH29="Muy de Acuerdo",0.66,IF(AH29="Levemente de Acuerdo",0.33,IF(AH29="Levemente en Desacuerdo",-0.33,IF(AH29="Muy en Desacuerdo",-0.66,IF(AH29="Totalmente en Desacuerdo",-1,"error")))))) -> 0.33 | AJ29: Levemente de Acuerdo | AK29: =IF(AJ29="Totalmente de Acuerdo",1,IF(AJ29="Muy de Acuerdo",0.66,IF(AJ29="Levemente de Acuerdo",0.33,IF(AJ29="Levemente en Desacuerdo",-0.33,IF(AJ29="Muy en Desacuerdo",-0.66,IF(AJ29="Totalmente en Desacuerdo",-1,"error")))))) -> 0.33 | AL29: Totalmente de Acuerdo | AM29: =IF(AL29="Totalmente de Acuerdo",-1,IF(AL29="Muy de Acuerdo",-0.66,IF(AL29="Levemente de Acuerdo",-0.33,IF(AL29="Levemente en Desacuerdo",0.33,IF(AL29="Muy en Desacuerdo",0.66,IF(AL29="Totalmente en Desacuerdo",1,"error")))))) -> -1 | AN29: Totalmente en Desacuerdo | AO29: =IF(AN29="Totalmente de Acuerdo",-1,IF(AN29="Muy de Acuerdo",-0.66,IF(AN29="Levemente de Acuerdo",-0.33,IF(AN29="Levemente en Desacuerdo",0.33,IF(AN29="Muy en Desacuerdo",0.66,IF(AN29="Totalmente en Desacuerdo",1,"error")))))) -> 1 | AP29: Muy en Desacuerdo | AQ29: =IF(AP29="Totalmente de Acuerdo",-1,IF(AP29="Muy de Acuerdo",-0.66,IF(AP29="Levemente de Acuerdo",-0.33,IF(AP29="Levemente en Desacuerdo",0.33,IF(AP29="Muy en Desacuerdo",0.66,IF(AP29="Totalmente en Desacuerdo",1,"error")))))) -> 0.66 | AR29: Totalmente de Acuerdo | AS29: =IF(AR29="Totalmente de Acuerdo",1,IF(AR29="Muy de Acuerdo",0.66,IF(AR29="Levemente de Acuerdo",0.33,IF(AR29="Levemente en Desacuerdo",-0.33,IF(AR29="Muy en Desacuerdo",-0.66,IF(AR29="Totalmente en Desacuerdo",-1,"error")))))) -> 1 | AT29: Muy de Acuerdo | AU29: =IF(AT29="Totalmente de Acuerdo",-1,IF(AT29="Muy de Acuerdo",-0.66,IF(AT29="Levemente de Acuerdo",-0.33,IF(AT29="Levemente en Desacuerdo",0.33,IF(AT29="Muy en Desacuerdo",0.66,IF(AT29="Totalmente en Desacuerdo",1,"error")))))) -> -0.66 | AV29: =AU29+AS29+AQ29+AO29+AM29+AK29+AI29+AG29+AE29 -> 0 | AW29: Muy de Acuerdo | AX29: Levemente de Acuerdo | AY29: Levemente en Desacuerdo | AZ29: Levemente en Desacuerdo | BA29: Levemente de Acuerdo | BB29: Levemente en Desacuerdo | BC29: Levemente en Desacuerdo | BD29: Muy en Desacuerdo | BE29: Muy en Desacuerdo | BF29: Muy de Acuerdo | BG29: Levemente en Desacuerdo | BH29: Me identifico | BM29: Me identifico | BR29: Me identifico | BX29: Patricia Bullrich (Juntos por el Cambio) | BY29: Javier Milei (La Libertad Avanza) | BZ29: Javier Milei (La Libertad Avanza)
A30: 45554.826 | B30: 005316712496717 | C30: 2002 | D30: Tercer año | E30: Varón | F30: Terciario completo | G30: Terciario completo | H30: Clase Media Baja (C3): entre $850.001 mensuales y $1.350.000 mensuales | I30: Trabajo propio | J30: Ciudad de Córdoba | K30: . | L30: Levemente en Desacuerdo | M30: =IF(L30="Totalmente de Acuerdo",-1,IF(L30="Muy de Acuerdo",-0.66,IF(L30="Levemente de Acuerdo",-0.33,IF(L30="Levemente en Desacuerdo",0.33,IF(L30="Muy en Desacuerdo",0.66,IF(L30="Totalmente en Desacuerdo",1,"error")))))) -> 0.33 | N30: Levemente en Desacuerdo | O30: =IF(N30="Totalmente de Acuerdo",1,IF(N30="Muy de Acuerdo",0.66,IF(N30="Levemente de Acuerdo",0.33,IF(N30="Levemente en Desacuerdo",-0.33,IF(N30="Muy en Desacuerdo",-0.66,IF(N30="Totalmente en Desacuerdo",-1,"error")))))) -> -0.33 | P30: Totalmente de Acuerdo | Q30: =IF(P30="Totalmente de Acuerdo",-1,IF(P30="Muy de Acuerdo",-0.66,IF(P30="Levemente de Acuerdo",-0.33,IF(P30="Levemente en Desacuerdo",0.33,IF(P30="Muy en Desacuerdo",0.66,IF(P30="Totalmente en Desacuerdo",1,"error")))))) -> -1 | R30: Muy de Acuerdo | S30: =IF(R30="Totalmente de Acuerdo",1,IF(R30="Muy de Acuerdo",0.66,IF(R30="Levemente de Acuerdo",0.33,IF(R30="Levemente en Desacuerdo",-0.33,IF(R30="Muy en Desacuerdo",-0.66,IF(R30="Totalmente en Desacuerdo",-1,"error")))))) -> 0.66 | T30: Levemente en Desacuerdo | U30: =IF(T30="Totalmente de Acuerdo",-1,IF(T30="Muy de Acuerdo",-0.66,IF(T30="Levemente de Acuerdo",-0.33,IF(T30="Levemente en Desacuerdo",0.33,IF(T30="Muy en Desacuerdo",0.66,IF(T30="Totalmente en Desacuerdo",1,"error")))))) -> 0.33 | V30: Levemente en Desacuerdo | W30: =IF(V30="Totalmente de Acuerdo",1,IF(V30="Muy de Acuerdo",0.66,IF(V30="Levemente de Acuerdo",0.33,IF(V30="Levemente en Desacuerdo",-0.33,IF(V30="Muy en Desacuerdo",-0.66,IF(V30="Totalmente en Desacuerdo",-1,"error")))))) -> -0.33 | X30: Levemente de Acuerdo | Y30: =IF(X30="Totalmente de Acuerdo",1,IF(X30="Muy de Acuerdo",0.66,IF(X30="Levemente de Acuerdo",0.33,IF(X30="Levemente en Desacuerdo",-0.33,IF(X30="Muy en Desacuerdo",-0.66,IF(X30="Totalmente en Desacuerdo",-1,"error")))))) -> 0.33 | Z30: Muy en Desacuerdo | AA30: =IF(Z30="Totalmente de Acuerdo",1,IF(Z30="Muy de Acuerdo",0.66,IF(Z30="Levemente en Acuerdo",0.33,IF(Z30="Levemente en Desacuerdo",-0.33,IF(Z30="Muy en Desacuerdo",-0.66,IF(Z30="Totalmente en Desacuerdo",-1,"error")))))) -> -0.66 | AB30: =+AA30+Y30+W30+U30+S30+Q30+O30+M30 -> -0.67 | AC30: =+AB30*AB$36 -> -0.75375 | AD30: Levemente de Acuerdo | AE30: =IF(AD30="Totalmente de Acuerdo",1,IF(AD30="Muy de Acuerdo",0.66,IF(AD30="Levemente de Acuerdo",0.33,IF(AD30="Levemente en Desacuerdo",-0.33,IF(AD30="Muy en Desacuerdo",-0.66,IF(AD30="Totalmente en Desacuerdo",-1,"error")))))) -> 0.33 | AF30: Muy de Acuerdo | AG30: =IF(AF30="Totalmente de Acuerdo",-1,IF(AF30="Muy de Acuerdo",-0.66,IF(AF30="Levemente de Acuerdo",-0.33,IF(AF30="Levemente en Desacuerdo",0.33,IF(AF30="Muy en Desacuerdo",0.66,IF(AF30="Totalmente en Desacuerdo",1,"error")))))) -> -0.66 | AH30: Totalmente en Desacuerdo | AI30: =IF(AH30="Totalmente de Acuerdo",1,IF(AH30="Muy de Acuerdo",0.66,IF(AH30="Levemente de Acuerdo",0.33,IF(AH30="Levemente en Desacuerdo",-0.33,IF(AH30="Muy en Desacuerdo",-0.66,IF(AH30="Totalmente en Desacuerdo",-1,"error")))))) -> -1 | AJ30: Totalmente en Desacuerdo | AK30: =IF(AJ30="Totalmente de Acuerdo",1,IF(AJ30="Muy de Acuerdo",0.66,IF(AJ30="Levemente de Acuerdo",0.33,IF(AJ30="Levemente en Desacuerdo",-0.33,IF(AJ30="Muy en Desacuerdo",-0.66,IF(AJ30="Totalmente en Desacuerdo",-1,"error")))))) -> -1 | AL30: Levemente en Desacuerdo | AM30: =IF(AL30="Totalmente de Acuerdo",-1,IF(AL30="Muy de Acuerdo",-0.66,IF(AL30="Levemente de Acuerdo",-0.33,IF(AL30="Levemente en Desacuerdo",0.33,IF(AL30="Muy en Desacuerdo",0.66,IF(AL30="Totalmente en Desacuerdo",1,"error")))))) -> 0.33 | AN30: Levemente en Desacuerdo | AO30: =IF(AN30="Totalmente de Acuerdo",-1,IF(AN30="Muy de Acuerdo",-0.66,IF(AN30="Levemente de Acuerdo",-0.33,IF(AN30="Levemente en Desacuerdo",0.33,IF(AN30="Muy en Desacuerdo",0.66,IF(AN30="Totalmente en Desacuerdo",1,"error")))))) -> 0.33 | AP30: Levemente de Acuerdo | AQ30: =IF(AP30="Totalmente de Acuerdo",-1,IF(AP30="Muy de Acuerdo",-0.66,IF(AP30="Levemente de Acuerdo",-0.33,IF(AP30="Levemente en Desacuerdo",0.33,IF(AP30="Muy en Desacuerdo",0.66,IF(AP30="Totalmente en Desacuerdo",1,"error")))))) -> -0.33 | AR30: Levemente en Desacuerdo | AS30: =IF(AR30="Totalmente de Acuerdo",1,IF(AR30="Muy de Acuerdo",0.66,IF(AR30="Levemente de Acuerdo",0.33,IF(AR30="Levemente en Desacuerdo",-0.33,IF(AR30="Muy en Desacuerdo",-0.66,IF(AR30="Totalmente en Desacuerdo",-1,"error")))))) -> -0.33 | AT30: Totalmente en Desacuerdo | AU30: =IF(AT30="Totalmente de Acuerdo",-1,IF(AT30="Muy de Acuerdo",-0.66,IF(AT30="Levemente de Acuerdo",-0.33,IF(AT30="Levemente en Desacuerdo",0.33,IF(AT30="Muy en Desacuerdo",0.66,IF(AT30="Totalmente en Desacuerdo",1,"error")))))) -> 1 | AV30: =AU30+AS30+AQ30+AO30+AM30+AK30+AI30+AG30+AE30 -> -1.33 | AW30: Muy de Acuerdo | AX30: Muy de Acuerdo | AY30: Levemente en Desacuerdo | AZ30: Levemente en Desacuerdo | BA30: Totalmente en Desacuerdo | BB30: Levemente en Desacuerdo | BC30: Muy en Desacuerdo | BD30: Levemente en Desacuerdo | BE30: Muy en Desacuerdo | BF30: Muy de Acuerdo | BG30: Levemente de Acuerdo | BK30: Me identifico | BM30: Me identifico | BX30: Patricia Bullrich (Juntos por el Cambio) | BY30: Patricia Bullrich (Juntos por el Cambio) | BZ30: Javier Milei (La Libertad Avanza)
A31: 45556.73 | B31: 003856132397521 | C31: 2000 | D31: Quinto año | E31: Mujer | F31: Posgrado completo | G31: Universitario completo | H31: Clase Media Alta (C2): entre $1.350.001 mensuales y $2.850.000 mensuales | I31: Beca | J31: Ciudad de Córdoba | K31: . | L31: Totalmente de Acuerdo | M31: =IF(L31="Totalmente de Acuerdo",-1,IF(L31="Muy de Acuerdo",-0.66,IF(L31="Levemente de Acuerdo",-0.33,IF(L31="Levemente en Desacuerdo",0.33,IF(L31="Muy en Desacuerdo",0.66,IF(L31="Totalmente en Desacuerdo",1,"error")))))) -> -1 | N31: Totalmente en Desacuerdo | O31: =IF(N31="Totalmente de Acuerdo",1,IF(N31="Muy de Acuerdo",0.66,IF(N31="Levemente de Acuerdo",0.33,IF(N31="Levemente en Desacuerdo",-0.33,IF(N31="Muy en Desacuerdo",-0.66,IF(N31="Totalmente en Desacuerdo",-1,"error")))))) -> -1 | P31: Totalmente de Acuerdo | Q31: =IF(P31="Totalmente de Acuerdo",-1,IF(P31="Muy de Acuerdo",-0.66,IF(P31="Levemente de Acuerdo",-0.33,IF(P31="Levemente en Desacuerdo",0.33,IF(P31="Muy en Desacuerdo",0.66,IF(P31="Totalmente en Desacuerdo",1,"error")))))) -> -1 | R31: Muy en Desacuerdo | S31: =IF(R31="Totalmente de Acuerdo",1,IF(R31="Muy de Acuerdo",0.66,IF(R31="Levemente de Acuerdo",0.33,IF(R31="Levemente en Desacuerdo",-0.33,IF(R31="Muy en Desacuerdo",-0.66,IF(R31="Totalmente en Desacuerdo",-1,"error")))))) -> -0.66 | T31: Totalmente de Acuerdo | U31: =IF(T31="Totalmente de Acuerdo",-1,IF(T31="Muy de Acuerdo",-0.66,IF(T31="Levemente de Acuerdo",-0.33,IF(T31="Levemente en Desacuerdo",0.33,IF(T31="Muy en Desacuerdo",0.66,IF(T31="Totalmente en Desacuerdo",1,"error")))))) -> -1 | V31: Levemente en Desacuerdo | W31: =IF(V31="Totalmente de Acuerdo",1,IF(V31="Muy de Acuerdo",0.66,IF(V31="Levemente de Acuerdo",0.33,IF(V31="Levemente en Desacuerdo",-0.33,IF(V31="Muy en Desacuerdo",-0.66,IF(V31="Totalmente en Desacuerdo",-1,"error")))))) -> -0.33 | X31: Muy en Desacuerdo | Y31: =IF(X31="Totalmente de Acuerdo",1,IF(X31="Muy de Acuerdo",0.66,IF(X31="Levemente de Acuerdo",0.33,IF(X31="Levemente en Desacuerdo",-0.33,IF(X31="Muy en Desacuerdo",-0.66,IF(X31="Totalmente en Desacuerdo",-1,"error")))))) -> -0.66 | Z31: Totalmente en Desacuerdo | AA31: =IF(Z31="Totalmente de Acuerdo",1,IF(Z31="Muy de Acuerdo",0.66,IF(Z31="Levemente en Acuerdo",0.33,IF(Z31="Levemente en Desacuerdo",-0.33,IF(Z31="Muy en Desacuerdo",-0.66,IF(Z31="Totalmente en Desacuerdo",-1,"error")))))) -> -1 | AB31: =+AA31+Y31+W31+U31+S31+Q31+O31+M31 -> -6.65 | AC31: =+AB31*AB$36 -> -7.48125 | AD31: Muy de Acuerdo | AE31: =IF(AD31="Totalmente de Acuerdo",1,IF(AD31="Muy de Acuerdo",0.66,IF(AD31="Levemente de Acuerdo",0.33,IF(AD31="Levemente en Desacuerdo",-0.33,IF(AD31="Muy en Desacuerdo",-0.66,IF(AD31="Totalmente en Desacuerdo",-1,"error")))))) -> 0.66 | AF31: Levemente en Desacuerdo | AG31: =IF(AF31="Totalmente de Acuerdo",-1,IF(AF31="Muy de Acuerdo",-0.66,IF(AF31="Levemente de Acuerdo",-0.33,IF(AF31="Levemente en Desacuerdo",0.33,IF(AF31="Muy en Desacuerdo",0.66,IF(AF31="Totalmente en Desacuerdo",1,"error")))))) -> 0.33 | AH31: Totalmente en Desacuerdo | AI31: =IF(AH31="Totalmente de Acuerdo",1,IF(AH31="Muy de Acuerdo",0.66,IF(AH31="Levemente de Acuerdo",0.33,IF(AH31="Levemente en Desacuerdo",-0.33,IF(AH31="Muy en Desacuerdo",-0.66,IF(AH31="Totalmente en Desacuerdo",-1,"error")))))) -> -1 | AJ31: Totalmente en Desacuerdo | AK31: =IF(AJ31="Totalmente de Acuerdo",1,IF(AJ31="Muy de Acuerdo",0.66,IF(AJ31="Levemente de Acuerdo",0.33,IF(AJ31="Levemente en Desacuerdo",-0.33,IF(AJ31="Muy en Desacuerdo",-0.66,IF(AJ31="Totalmente en Desacuerdo",-1,"error")))))) -> -1 | AL31: Totalmente de Acuerdo | AM31: =IF(AL31="Totalmente de Acuerdo",-1,IF(AL31="Muy de Acuerdo",-0.66,IF(AL31="Levemente de Acuerdo",-0.33,IF(AL31="Levemente en Desacuerdo",0.33,IF(AL31="Muy en Desacuerdo",0.66,IF(AL31="Totalmente en Desacuerdo",1,"error")))))) -> -1 | AN31: Levemente de Acuerdo | AO31: =IF(AN31="Totalmente de Acuerdo",-1,IF(AN31="Muy de Acuerdo",-0.66,IF(AN31="Levemente de Acuerdo",-0.33,IF(AN31="Levemente en Desacuerdo",0.33,IF(AN31="Muy en Desacuerdo",0.66,IF(AN31="Totalmente en Desacuerdo",1,"error")))))) -> -0.33 | AP31: Muy de Acuerdo | AQ31: =IF(AP31="Totalmente de Acuerdo",-1,IF(AP31="Muy de Acuerdo",-0.66,IF(AP31="Levemente de Acuerdo",-0.33,IF(AP31="Levemente en Desacuerdo",0.33,IF(AP31="Muy en Desacuerdo",0.66,IF(AP31="Totalmente en Desacuerdo",1,"error")))))) -> -0.66 | AR31: Totalmente en Desacuerdo | AS31: =IF(AR31="Totalmente de Acuerdo",1,IF(AR31="Muy de Acuerdo",0.66,IF(AR31="Levemente de Acuerdo",0.33,IF(AR31="Levemente en Desacuerdo",-0.33,IF(AR31="Muy en Desacuerdo",-0.66,IF(AR31="Totalmente en Desacuerdo",-1,"error")))))) -> -1 | AT31: Totalmente en Desacuerdo | AU31: =IF(AT31="Totalmente de Acuerdo",-1,IF(AT31="Muy de Acuerdo",-0.66,IF(AT31="Levemente de Acuerdo",-0.33,IF(AT31="Levemente en Desacuerdo",0.33,IF(AT31="Muy en Desacuerdo",0.66,IF(AT31="Totalmente en Desacuerdo",1,"error")))))) -> 1 | AV31: =AU31+AS31+AQ31+AO31+AM31+AK31+AI31+AG31+AE31 -> -3 | AW31: Totalmente en Desacuerdo | AX31: Levemente en Desacuerdo | AY31: Totalmente de Acuerdo | AZ31: Muy en Desacuerdo | BA31: Muy de Acuerdo | BB31: Totalmente en Desacuerdo | BC31: Totalmente en Desacuerdo | BD31: Totalmente en Desacuerdo | BE31: Totalmente en Desacuerdo | BF31: Totalmente de Acuerdo | BG31: Muy en Desacuerdo | BJ31: Me identifico | BK31: Me identifico | BP31: Me identifico | BQ31: Me identifico | BU31: Me identifico | BV31: Me identifico | BX31: Juan Grabois (Unión por la Patria) | BY31: Sergio Massa (Unión por la Patria) | BZ31: Sergio Massa (Unión por la Patria)
A32: 45560.553 | B32: 00284397411 | C32: 1999 | D32: Cuarto año | E32: Otra | F32: Universitario completo | G32: Posgrado completo | H32: Clase Media Alta (C2): entre $1.350.001 mensuales y $2.850.000 mensuales | I32: Trabajo propio | J32: Otra localidad en otra Provincia | K32: . | L32: Muy de Acuerdo | M32: =IF(L32="Totalmente de Acuerdo",-1,IF(L32="Muy de Acuerdo",-0.66,IF(L32="Levemente de Acuerdo",-0.33,IF(L32="Levemente en Desacuerdo",0.33,IF(L32="Muy en Desacuerdo",0.66,IF(L32="Totalmente en Desacuerdo",1,"error")))))) -> -0.66 | N32: Muy en Desacuerdo | O32: =IF(N32="Totalmente de Acuerdo",1,IF(N32="Muy de Acuerdo",0.66,IF(N32="Levemente de Acuerdo",0.33,IF(N32="Levemente en Desacuerdo",-0.33,IF(N32="Muy en Desacuerdo",-0.66,IF(N32="Totalmente en Desacuerdo",-1,"error")))))) -> -0.66 | P32: Totalmente de Acuerdo | Q32: =IF(P32="Totalmente de Acuerdo",-1,IF(P32="Muy de Acuerdo",-0.66,IF(P32="Levemente de Acuerdo",-0.33,IF(P32="Levemente en Desacuerdo",0.33,IF(P32="Muy en Desacuerdo",0.66,IF(P32="Totalmente en Desacuerdo",1,"error")))))) -> -1 | R32: Totalmente en Desacuerdo | S32: =IF(R32="Totalmente de Acuerdo",1,IF(R32="Muy de Acuerdo",0.66,IF(R32="Levemente de Acuerdo",0.33,IF(R32="Levemente en Desacuerdo",-0.33,IF(R32="Muy en Desacuerdo",-0.66,IF(R32="Totalmente en Desacuerdo",-1,"error")))))) -> -1 | T32: Muy de Acuerdo | U32: =IF(T32="Totalmente de Acuerdo",-1,IF(T32="Muy de Acuerdo",-0.66,IF(T32="Levemente de Acuerdo",-0.33,IF(T32="Levemente en Desacuerdo",0.33,IF(T32="Muy en Desacuerdo",0.66,IF(T32="Totalmente en Desacuerdo",1,"error")))))) -> -0.66 | V32: Levemente de Acuerdo | W32: =IF(V32="Totalmente de Acuerdo",1,IF(V32="Muy de Acuerdo",0.66,IF(V32="Levemente de Acuerdo",0.33,IF(V32="Levemente en Desacuerdo",-0.33,IF(V32="Muy en Desacuerdo",-0.66,IF(V32="Totalmente en Desacuerdo",-1,"error")))))) -> 0.33 | X32: Levemente en Desacuerdo | Y32: =IF(X32="Totalmente de Acuerdo",1,IF(X32="Muy de Acuerdo",0.66,IF(X32="Levemente de Acuerdo",0.33,IF(X32="Levemente en Desacuerdo",-0.33,IF(X32="Muy en Desacuerdo",-0.66,IF(X32="Totalmente en Desacuerdo",-1,"error")))))) -> -0.33 | Z32: Totalmente en Desacuerdo | AA32: =IF(Z32="Totalmente de Acuerdo",1,IF(Z32="Muy de Acuerdo",0.66,IF(Z32="Levemente en Acuerdo",0.33,IF(Z32="Levemente en Desacuerdo",-0.33,IF(Z32="Muy en Desacuerdo",-0.66,IF(Z32="Totalmente en Desacuerdo",-1,"error")))))) -> -1 | AB32: =+AA32+Y32+W32+U32+S32+Q32+O32+M32 -> -4.98 | AC32: =+AB32*AB$36 -> -5.6025 | AD32: Muy en Desacuerdo | AE32: =IF(AD32="Totalmente de Acuerdo",1,IF(AD32="Muy de Acuerdo",0.66,IF(AD32="Levemente de Acuerdo",0.33,IF(AD32="Levemente en Desacuerdo",-0.33,IF(AD32="Muy en Desacuerdo",-0.66,IF(AD32="Totalmente en Desacuerdo",-1,"error")))))) -> -0.66 | AF32: Muy en Desacuerdo | AG32: =IF(AF32="Totalmente de Acuerdo",-1,IF(AF32="Muy de Acuerdo",-0.66,IF(AF32="Levemente de Acuerdo",-0.33,IF(AF32="Levemente en Desacuerdo",0.33,IF(AF32="Muy en Desacuerdo",0.66,IF(AF32="Totalmente en Desacuerdo",1,"error")))))) -> 0.66 | AH32: Totalmente en Desacuerdo | AI32: =IF(AH32="Totalmente de Acuerdo",1,IF(AH32="Muy de Acuerdo",0.66,IF(AH32="Levemente de Acuerdo",0.33,IF(AH32="Levemente en Desacuerdo",-0.33,IF(AH32="Muy en Desacuerdo",-0.66,IF(AH32="Totalmente en Desacuerdo",-1,"error")))))) -> -1 | AJ32: Totalmente en Desacuerdo | AK32: =IF(AJ32="Totalmente de Acuerdo",1,IF(AJ32="Muy de Acuerdo",0.66,IF(AJ32="Levemente de Acuerdo",0.33,IF(AJ32="Levemente en Desacuerdo",-0.33,IF(AJ32="Muy en Desacuerdo",-0.66,IF(AJ32="Totalmente en Desacuerdo",-1,"error")))))) -> -1 | AL32: Totalmente de Acuerdo | AM32: =IF(AL32="Totalmente de Acuerdo",-1,IF(AL32="Muy de Acuerdo",-0.66,IF(AL32="Levemente de Acuerdo",-0.33,IF(AL32="Levemente en Desacuerdo",0.33,IF(AL32="Muy en Desacuerdo",0.66,IF(AL32="Totalmente en Desacuerdo",1,"error")))))) -> -1 | AN32: Levemente de Acuerdo | AO32: =IF(AN32="Totalmente de Acuerdo",-1,IF(AN32="Muy de Acuerdo",-0.66,IF(AN32="Levemente de Acuerdo",-0.33,IF(AN32="Levemente en Desacuerdo",0.33,IF(AN32="Muy en Desacuerdo",0.66,IF(AN32="Totalmente en Desacuerdo",1,"error")))))) -> -0.33 | AP32: Muy de Acuerdo | AQ32: =IF(AP32="Totalmente de Acuerdo",-1,IF(AP32="Muy de Acuerdo",-0.66,IF(AP32="Levemente de Acuerdo",-0.33,IF(AP32="Levemente en Desacuerdo",0.33,IF(AP32="Muy en Desacuerdo",0.66,IF(AP32="Totalmente en Desacuerdo",1,"error")))))) -> -0.66 | AR32: Totalmente en Desacuerdo | AS32: =IF(AR32="Totalmente de Acuerdo",1,IF(AR32="Muy de Acuerdo",0.66,IF(AR32="Levemente de Acuerdo",0.33,IF(AR32="Levemente en Desacuerdo",-0.33,IF(AR32="Muy en Desacuerdo",-0.66,IF(AR32="Totalmente en Desacuerdo",-1,"error")))))) -> -1 | AT32: Levemente en Desacuerdo | AU32: =IF(AT32="Totalmente de Acuerdo",-1,IF(AT32="Muy de Acuerdo",-0.66,IF(AT32="Levemente de Acuerdo",-0.33,IF(AT32="Levemente en Desacuerdo",0.33,IF(AT32="Muy en Desacuerdo",0.66,IF(AT32="Totalmente en Desacuerdo",1,"error")))))) -> 0.33 | AV32: =AU32+AS32+AQ32+AO32+AM32+AK32+AI32+AG32+AE32 -> -4.66 | AW32: Totalmente en Desacuerdo | AX32: Levemente en Desacuerdo | AY32: Muy de Acuerdo | AZ32: Levemente de Acuerdo | BA32: Muy en Desacuerdo | BB32: Totalmente en Desacuerdo | BC32: Totalmente en Desacuerdo | BD32: Totalmente en Desacuerdo | BE32: Totalmente en Desacuerdo | BF32: Muy de Acuerdo | BG32: Totalmente en Desacuerdo | BP32: Me identifico | BQ32: Me identifico | BU32: Me identifico | BX32: Sergio Massa (Unión por la Patria) | BY32: Sergio Massa (Unión por la Patria) | BZ32: Sergio Massa (Unión por la Patria)
L33: promedio | M33: =+AVERAGE(M3:M32) -> 0.078 | O33: =+AVERAGE(O3:O32) -> -0.033 | Q33: =+AVERAGE(Q3:Q32) -> -0.58533333 | S33: =+AVERAGE(S3:S32) -> 0.463 | U33: =+AVERAGE(U3:U32) -> -0.033333333 | W33: =+AVERAGE(W3:W32) -> 0.321 | Y33: =+AVERAGE(Y3:Y32) -> 0.288 | AA33: =+AVERAGE(AA3:AA32) -> -0.47466667 | AB33: =+AVERAGE(M33:AA33) -> 0.0029583333 | AC33: =+AB33*AB$36 -> 0.003328125 | AE33: =+AVERAGE(AE3:AE32) -> -0.24333333 | AG33: =+AVERAGE(AG3:AG32) -> -0.442 | AI33: =+AVERAGE(AI3:AI32) -> -0.311 | AK33: =+AVERAGE(AK3:AK32) -> -0.57766667 | AM33: =+AVERAGE(AM3:AM32) -> -0.443 | AO33: =+AVERAGE(AO3:AO32) -> 0.35466667 | AQ33: =+AVERAGE(AQ3:AQ32) -> -0.199 | AS33: =+AVERAGE(AS3:AS32) -> 0.32066667 | AU33: =+AVERAGE(AU3:AU32) -> 0.68733333 | AV33: =AU33+AS33+AQ33+AO33+AM33+AK33+AI33+AG33+AE33 -> -0.85333333
